Workbook
Name Ops: 'Ops Team'!$A$1:$C$30
Name Slicer_Date_of_this_request: #N/A
Name Slicer_New_Rental_or_Extension: #N/A
Name Slicer_Rental_Approved: #N/A
Name Slicer_Truck_Breakdown_or_New_Hire: #N/A
Name Slicer_Unit_Number: #N/A
Name TPMSLU: #REF!

Sheet Addresses
A1: TRIM ENT ID | B1: Emplid | C1: Name | D1: Enterprise ID | E1: Status as of 2025-09-30 | F1: Job Code | G1: Job Title | H1: Tech Type | I1: Company | J1: Region | K1: District | L1: Location | M1: Loc City | N1: Loc State | O1: Orig Hire Dt | P1: Last Hire Dt | Q1: Service Dt | R1: Days of Svc | S1: Yrs of Svc | T1: Svc Category | U1: Empl Address1 | V1: Empl Address2 | W1: Empl City | X1: Empl State | Y1: Empl Postal
A2: =TRIM(D2) | B2: 11024630301 | C2: SPRADLING,RYAN T | E2: T | F2: HS2003 | G2: Service Technician 1, In-Home | H2: In Home Tech | I2: TSH | J2: 58890 | K2: 08184 | L2: 28081 | M2: Sacramento | N2: CA | O2: 45662 | P2: 45662 | Q2: 45662 | R2: 267 | S2: 0 | T2: 6 Mo - 1 Year | U2: 720 SHELL AVE APT 101 | W2: MARTINEZ | X2: CA | Y2: 94553
A3: =TRIM(D3) | B3: 11024631201 | C3: LACEY,ANTHONY | E3: A | F3: HS2023 | G3: Service Technician 2, In-Home | H3: In Home Tech | I3: TSH | J3: 58890 | K3: 08184 | L3: 28045 | M3: Sacramento | N3: CA | O3: 45928 | P3: 45928 | Q3: 45928 | R3: 1 | S3: 0 | T3: 0-30 Days | U3: 769 CAPRICE WAY | W3: CHICO | X3: CA | Y3: 95973
A4: =TRIM(D4) | B4: 31024630673 | C4: RAMOS,DION | E4: T | F4: HS2003 | G4: Service Technician 1, In-Home | H4: In Home Tech | I4: TSH | J4: 58850 | K4: 07435 | L4: 28094 | M4: Winter Park | N4: FL | O4: 45795 | P4: 45795 | Q4: 45795 | R4: 134 | S4: 0 | T4: 91 Days - 6 Months | U4: 1304 SW 22ND PL | W4: CAPE CORAL | X4: FL | Y4: 33991
A5: =TRIM(D5) | B5: 81024630418 | C5: MORRIS,SHAWN | E5: T | F5: UHS018 | G5: Service Technician HV, In-Home | H5: In Home Tech | I5: TSH | J5: 58850 | K5: 08309 | L5: 24042 | M5: Sterling Heights | N5: MI | O5: 45697 | P5: 45697 | Q5: 45697 | R5: 232 | S5: 0 | T5: 6 Mo - 1 Year | U5: 2525 IVY PL. | W5: TOLEDO | X5: OH | Y5: 43613
A6: =TRIM(D6) -> aacuna | B6: 91022642419 | C6: ACUNA JR,ARTURO | D6: aacuna | E6: A | F6: HS2018 | G6: Service Tech - Modified Duty | H6: In Home Tech | I6: TSH | J6: 58890 | K6: 07108 | L6: 28042 | M6: Fontana | N6: CA | O6: 38783 | P6: 45123 | Q6: 45123 | R6: 806 | S6: 2 | T6: 1-3 Years | U6: 867 N 2nd St | V6: Unit 2293 | W6: El Cajon | X6: CA | Y6: 92021
A7: =TRIM(D7) -> aadamow | B7: 91024630879 | C7: ADAMOWSKI,AUSTIN T | D7: aadamow | E7: A | F7: HS9661 | G7: Service Technician 3, In-Home | H7: In Home Tech | I7: TSH | J7: 58890 | K7: 08555 | L7: 08220 | M7: New Berlin | N7: WI | O7: 45858 | P7: 45858 | Q7: 45858 | R7: 71 | S7: 0 | T7: 61-90 Days | U7: 525 KELVINGTON DRIVE #2 | W7: SUN PRAIRIE | X7: WI | Y7: 53590
A8: =TRIM(D8) -> aaguil0 | B8: 21024624182 | C8: AGUILAR,ANTHONY I | D8: aaguil0 | E8: A | F8: HS1782 | G8: HVAC Lead Installer | H8: HVAC Tech | I8: TSH | J8: 58890 | K8: 07108 | L8: 28042 | M8: Fontana | N8: CA | O8: 44770 | P8: 44770 | Q8: 44770 | R8: 1159 | S8: 3 | T8: 3-6 Years | U8: 4126 village dr | V8: Apt C | W8: Chino Hills | X8: CA | Y8: 91709
A9: =TRIM(D9) -> aalbarr | B9: 41024626464 | C9: ALBARRAN,ARTURO | D9: aalbarr | E9: T | F9: HS2305 | G9: HVAC Svc Tech II, Break/Fix | H9: HVAC Tech | I9: TSH | J9: 58890 | K9: 08555 | L9: 28037 | M9: Hoffman Estates | N9: IL | O9: 45032 | P9: 45032 | Q9: 45032 | R9: 897 | S9: 2 | T9: 1-3 Years | U9: 214 EVOLUTION | W9: HIGHWOOD | X9: IL | Y9: 60040
A10: =TRIM(D10) -> aalexa5 | B10: 11024064791 | C10: ALEXANDER,andy E | D10: aalexa5 | E10: A | F10: HS2003 | G10: Service Technician 1, In-Home | H10: In Home Tech | I10: TSH | J10: 58890 | K10: 07088 | L10: 28056 | M10: El Cajon | N10: CA | O10: 41736 | P10: 41736 | Q10: 41736 | R10: 4193 | S10: 11 | T10: 6-15 Years | U10: 4026 camino paz | W10: Spring Valley | X10: CA | Y10: 91977
A11: =TRIM(D11) -> aalnajj | B11: 81024627928 | C11: ALNAJJAR,ABDELRAHMAN | D11: aalnajj | E11: L | F11: HS2003 | G11: Service Technician 1, In-Home | H11: In Home Tech | I11: TSH | J11: 58850 | K11: 07435 | L11: 28240 | M11: Hialeah | N11: FL | O11: 45221 | P11: 45221 | Q11: 45221 | R11: 708 | S11: 1 | T11: 1-3 Years | U11: 6495 SHORELINE DRIVE | V11: APT8502 | W11: SAINT PETERSBURG | X11: FL | Y11: 33708
A12: =TRIM(D12) -> AALVARA | B12: 01021240600 | C12: ALVARADO,AUGUSTINE | D12: AALVARA | E12: A | F12: HS2003 | G12: Service Technician 1, In-Home | H12: In Home Tech | I12: TSH | J12: 58890 | K12: 07995 | L12: 28224 | M12: Farmers Branch | N12: TX | O12: 32656 | P12: 32656 | Q12: 32656 | R12: 13273 | S12: 36 | T12: 16+ Years | U12: 804 NORTH CR 1450 | W12: LUBBOCK | X12: TX | Y12: 79416
A13: =TRIM(D13) -> aanacle | B13: 81024627258 | C13: ANACLETO,ANTONIO N | D13: aanacle | E13: T | F13: HS2023 | G13: Service Technician 2, In-Home | H13: In Home Tech | I13: TSH | J13: 58850 | K13: 07435 | L13: 28240 | M13: Hialeah | N13: FL | O13: 45144 | P13: 45144 | Q13: 45144 | R13: 785 | S13: 2 | T13: 1-3 Years | U13: 4306 GINGER COVE DR | V13: APARTMENT F | W13: TAMPA | X13: FL | Y13: 33634
A14: =TRIM(D14) -> aander2 | B14: 41024630294 | C14: ANDERSON,ANGELO | D14: aander2 | E14: A | F14: HS2308 | G14: HVAC Svc Tech I, Break/Fix | H14: HVAC Tech | I14: TSH | J14: 58850 | K14: 08175 | L14: 28121 | M14: Richmond | N14: VA | O14: 45676 | P14: 45676 | Q14: 45676 | R14: 253 | S14: 0 | T14: 6 Mo - 1 Year | U14: 25 Kyle Dr | W14: Garner | X14: NC | Y14: 27529
A15: =TRIM(D15) -> aaprim | B15: 51024631145 | C15: APRIM,ADAM L | D15: aaprim | E15: A | F15: HS1782 | G15: HVAC Lead Installer | H15: HVAC Tech | I15: TSH | J15: 58890 | K15: 08555 | L15: 28037 | M15: Hoffman Estates | N15: IL | O15: 45914 | P15: 45914 | Q15: 45914 | R15: 15 | S15: 0 | T15: 0-30 Days | U15: 183 N EAST RIVER RD | V15: C1 | W15: DES PLAINES | X15: IL | Y15: 60016
A16: =TRIM(D16) -> AARELLA | B16: 91023308459 | C16: ARELLANO,ANTHONY R | D16: AARELLA | E16: A | F16: HS2014 | G16: Team Lead Technician | H16: In Home Tech | I16: TSH | J16: 58890 | K16: 08184 | L16: 28081 | M16: Sacramento | N16: CA | O16: 40018 | P16: 40018 | Q16: 40018 | R16: 5911 | S16: 16 | T16: 16+ Years | U16: 27492 ORLANDO AVE | W16: HAYWARD | X16: CA | Y16: 94545
A17: =TRIM(D17) -> aarnold | B17: 91024631259 | C17: ARNOLD,ANTHONY J | D17: aarnold | E17: A | O17: 45935 | Q17: 45935 | U17: 7326 KENSINGTON DR. W | W17: NORTHWEST FORT WAYNE | X17: IN | Y17: 46818
A18: =TRIM(D18) -> aasghar | B18: 71024627287 | C18: ASGHARI,AHMAD OMAID | D18: aasghar | E18: A | F18: HS9661 | G18: Service Technician 3, In-Home | H18: In Home Tech | I18: TSH | J18: 58850 | K18: 03132 | L18: 28003 | M18: Linthicum Hts | N18: MD | O18: 45165 | P18: 45165 | Q18: 45165 | R18: 764 | S18: 2 | T18: 1-3 Years | U18: 8900 golden oak dr | V18: Apt J | W18: MANASSAS | X18: VA | Y18: 20109
A19: =TRIM(D19) -> aash0 | B19: 21024627192 | C19: ASH,AUSTIN | D19: aash0 | E19: T | F19: HS9661 | G19: Service Technician 3, In-Home | H19: In Home Tech | I19: TSH | J19: 58890 | K19: 08169 | L19: 28059 | M19: Salt Lake Cty | N19: UT | O19: 45130 | P19: 45130 | Q19: 45130 | R19: 799 | S19: 2 | T19: 1-3 Years | U19: 433 S 1210 E | W19: PLEASANT GROVE | X19: UT | Y19: 84062
A20: =TRIM(D20) -> AATRISC | B20: 71021845617 | C20: ATRISCO,ANGEL | D20: AATRISC | E20: A | F20: HS2003 | G20: Service Technician 1, In-Home | H20: In Home Tech | I20: TSH | J20: 58890 | K20: 08366 | L20: 28049 | M20: Fresno | N20: CA | O20: 36836 | P20: 36836 | Q20: 36836 | R20: 9093 | S20: 24 | T20: 16+ Years | U20: 996 San Gabriel | W20: Soledad | X20: CA | Y20: 93960
A21: =TRIM(D21) -> aatta | B21: 01024614750 | C21: Atta,Abdul M | D21: aatta | E21: A | F21: HS2003 | G21: Service Technician 1, In-Home | H21: In Home Tech | I21: TSH | J21: 58850 | K21: 03132 | L21: 28003 | M21: Linthicum Hts | N21: MD | O21: 44111 | P21: 44111 | Q21: 44111 | R21: 1818 | S21: 4 | T21: 3-6 Years | U21: 1961 Gableridge Turn | V21: Apt 301 | W21: Woodbridge | X21: VA | Y21: 22191
A22: =TRIM(D22) -> aayubi | B22: 01024561620 | C22: Ayubi,Amir E | D22: aayubi | E22: L | F22: HS2305 | G22: HVAC Svc Tech II, Break/Fix | H22: HVAC Tech | I22: TSH | J22: 58890 | K22: 07088 | L22: 28205 | M22: Mesa | N22: AZ | O22: 43409 | P22: 43409 | Q22: 43409 | R22: 2520 | S22: 6 | T22: 6-15 Years | U22: 1116 N 11TH AVE | W22: TUCSON | X22: AZ | Y22: 85705
A23: =TRIM(D23) -> abalice | B23: 11024624121 | C23: BALICE,ANTHONY | D23: abalice | E23: A | F23: HS2305 | G23: HVAC Svc Tech II, Break/Fix | H23: HVAC Tech | I23: TSH | J23: 58890 | K23: 08555 | L23: 28037 | M23: Hoffman Estates | N23: IL | O23: 44785 | P23: 44785 | Q23: 44785 | R23: 1144 | S23: 3 | T23: 3-6 Years | U23: 13619 ASPLAND DRIVE | W23: ROCKTON | X23: IL | Y23: 61072
A24: =TRIM(D24) -> abautis | B24: 71024622537 | C24: BAUTISTA VILLANUEVA,ALEX | D24: abautis | E24: A | F24: HS2003 | G24: Service Technician 1, In-Home | H24: In Home Tech | I24: TSH | J24: 58890 | K24: 07108 | L24: 28042 | M24: Fontana | N24: CA | O24: 44609 | P24: 44609 | Q24: 44609 | R24: 1320 | S24: 3 | T24: 3-6 Years | U24: 12913 RAMSEY DR. | W24: LA MIRADA | X24: CA | Y24: 90638
A25: =TRIM(D25) -> ABECKLE | B25: 31023010323 | C25: BECKLES,ANTON C | D25: ABECKLE | E25: T | F25: HS2023 | G25: Service Technician 2, In-Home | H25: In Home Tech | I25: TSH | J25: 58850 | K25: 04766 | L25: 28125 | M25: Louisville | N25: KY | O25: 39433 | P25: 39433 | Q25: 39433 | R25: 6496 | S25: 17 | T25: 16+ Years | U25: 2011 maple view lane | W25: Indian trail | X25: NC | Y25: 28079
A26: =TRIM(D26) -> ABEHLE | B26: 61021971066 | C26: BEHLER,ADAM C | D26: ABEHLE | E26: A | F26: HS2306 | G26: HVAC Technician Supervisor | H26: HVAC Tech | I26: TSH | J26: 58890 | K26: 08184 | L26: 28045 | M26: Sacramento | N26: CA | O26: 37137 | P26: 37137 | Q26: 37137 | R26: 8792 | S26: 24 | T26: 16+ Years | U26: 2695 Hopi Ct | W26: Cameron Park | X26: CA | Y26: 95682
A27: =TRIM(D27) -> abejte | B27: 11023930111 | C27: Bejte,Arben | D27: abejte | E27: A | F27: HS2023 | G27: Service Technician 2, In-Home | H27: In Home Tech | I27: TSH | J27: 58850 | K27: 07670 | L27: 28009 | M27: Danvers | N27: MA | O27: 41396 | P27: 41396 | Q27: 41396 | R27: 4533 | S27: 12 | T27: 6-15 Years | U27: 440 north ave | V27: apt 90 | W27: haverhill | X27: MA | Y27: 01830
A28: =TRIM(D28) -> aberik | B28: 11024631171 | C28: BERIK,ASKHAT | D28: aberik | E28: A | F28: HS2023 | G28: Service Technician 2, In-Home | H28: In Home Tech | I28: TSH | J28: 58890 | K28: 08555 | L28: 28037 | M28: Hoffman Estates | N28: IL | O28: 45914 | P28: 45914 | Q28: 45914 | R28: 15 | S28: 0 | T28: 0-30 Days | U28: 2335 SEDGFIELD CT | W28: SCHAUMBURG | X28: IL | Y28: 60194
A29: =TRIM(D29) -> abiblej | B29: 71024198517 | C29: BIBLE JR,ARTHUR L | D29: abiblej | E29: A | F29: HS9661 | G29: Service Technician 3, In-Home | H29: In Home Tech | I29: TSH | J29: 58890 | K29: 08228 | L29: 28040 | M29: Portland | N29: OR | O29: 42038 | P29: 42038 | Q29: 42038 | R29: 3891 | S29: 10 | T29: 6-15 Years | U29: 1771 Myrtle Street | W29: Baker City | X29: OR | Y29: 97814
A30: =TRIM(D30) -> ablake0 | B30: 11024335191 | C30: BLAKE Sr.,AARON R | D30: ablake0 | E30: T | F30: HS2305 | G30: HVAC Svc Tech II, Break/Fix | H30: HVAC Tech | I30: TSH | J30: 58850 | K30: 03132 | L30: 28003 | M30: Linthicum Hts | N30: MD | O30: 42432 | P30: 42432 | Q30: 42432 | R30: 3497 | S30: 9 | T30: 6-15 Years | U30: 3907 BURNS COURT S.E | W30: WASHINGTON | X30: DC | Y30: 20019
A31: =TRIM(D31) -> abland | B31: 81004652898 | C31: BLAND,AMIR | D31: abland | E31: A | F31: HS1022 | G31: Service Tech 2 Trainee, IH | H31: In Home Tech | I31: TSH | J31: 58850 | K31: 08035 | L31: 28085 | M31: College Park | N31: GA | O31: 39032 | P31: 45851 | Q31: 45851 | R31: 78 | S31: 0 | T31: 61-90 Days | U31: 1075 Chapman Circle | W31: Stone Mountain | X31: GA | Y31: 30088
A32: =TRIM(D32) -> abrady | B32: 11024628021 | C32: Brady,Andrew Mitchel | D32: abrady | E32: T | F32: HS2063 | G32: Service Technician HV, In-Home | H32: In Home Tech | I32: TSH | J32: 58850 | K32: 08175 | L32: 28121 | M32: Richmond | N32: VA | O32: 45235 | P32: 45235 | Q32: 45235 | R32: 694 | S32: 1 | T32: 1-3 Years | U32: 924 Tiffany ln | W32: Conway | X32: SC | Y32: 29526
A33: =TRIM(D33) -> ABRANTL | B33: 81021017628 | C33: BRANTLEY,AARON | D33: ABRANTL | E33: A | F33: HS1992 | G33: Service Tech 1, IH | H33: In Home Tech | I33: TSH | J33: 58850 | K33: 08035 | L33: 28085 | M33: College Park | N33: GA | O33: 26742 | P33: 26742 | Q33: 26742 | R33: 19187 | S33: 52 | T33: 16+ Years | U33: 3810 CLEARWATER DR | W33: COLLEGE PARK | X33: GA | Y33: 30349
A34: =TRIM(D34) -> abravar | B34: 11024201831 | C34: BRAVAR,ALEX | D34: abravar | E34: A | F34: HS2023 | G34: Service Technician 2, In-Home | H34: In Home Tech | I34: TSH | J34: 58850 | K34: 08175 | L34: 28121 | M34: Richmond | N34: VA | O34: 42065 | P34: 44250 | Q34: 44250 | R34: 1679 | S34: 4 | T34: 3-6 Years | U34: 5902 Riviera Arch | W34: VIRGINIA BEACH | X34: VA | Y34: 23464
A35: =TRIM(D35) -> abrook0 | B35: 41024626434 | C35: BROOKS,ADONIS | D35: abrook0 | E35: A | F35: UHS003 | G35: Service Technician 2, In-Home | H35: In Home Tech | I35: TSH | J35: 58850 | K35: 08309 | L35: 08309 | M35: Clinton Township | N35: MI | O35: 45032 | P35: 45032 | Q35: 45032 | R35: 897 | S35: 2 | T35: 1-3 Years | U35: 2679 HARDING | W35: DETROIT | X35: MI | Y35: 48214
A36: =TRIM(D36) -> abrown0 | B36: 61024630746 | C36: BROWN,ADRIELLE | D36: abrown0 | E36: A | F36: HS2003 | G36: Service Technician 1, In-Home | H36: In Home Tech | I36: TSH | J36: 58890 | K36: 08206 | L36: 28129 | M36: Nashville | N36: TN | O36: 45823 | P36: 45823 | Q36: 45823 | R36: 106 | S36: 0 | T36: 91 Days - 6 Months | U36: 16255 Rio Grande St | W36: GULFPORT | X36: MS | Y36: 39501
A37: =TRIM(D37) -> abroyle | B37: 81024630488 | C37: BROYLES,ANDREW J | D37: abroyle | E37: T | F37: HS9661 | G37: Service Technician 3, In-Home | H37: In Home Tech | I37: TSH | J37: 58890 | K37: 08206 | L37: 28129 | M37: Nashville | N37: TN | O37: 45718 | P37: 45718 | Q37: 45718 | R37: 211 | S37: 0 | T37: 6 Mo - 1 Year | U37: 910 ROBIN HOOD DR. NW | W37: CLEVELAND | X37: TN | Y37: 37312
A38: =TRIM(D38) -> abyrd0 | B38: 61024631076 | C38: BYRD,ALFONSO E | D38: abyrd0 | E38: A | F38: HS2308 | G38: HVAC Svc Tech I, Break/Fix | H38: HVAC Tech | I38: TSH | J38: 58850 | K38: 08035 | L38: 28085 | M38: College Park | N38: GA | O38: 45914 | P38: 45914 | Q38: 45914 | R38: 15 | S38: 0 | T38: 0-30 Days | U38: 1048 FLAT SHOALS RD APT#1504 | V38: 1504 | W38: COLLEGE PARK | X38: GA | Y38: 30349
A39: =TRIM(D39) -> acadet | B39: 81024631128 | C39: Cadet,Adler | D39: acadet | E39: A | F39: HS2305 | G39: HVAC Svc Tech II, Break/Fix | H39: HVAC Tech | I39: TSH | J39: 58850 | K39: 07744 | L39: 28012 | M39: Melville | N39: NY | O39: 45907 | P39: 45907 | Q39: 45907 | R39: 22 | S39: 0 | T39: 0-30 Days | U39: 174-11 142nd | W39: Jamaica | X39: NY | Y39: 11434
A40: =TRIM(D40) -> ACANAL2 | B40: 01021063760 | C40: CANALES REYES,ADRIAN | D40: ACANAL2 | E40: A | F40: HS2023 | G40: Service Technician 2, In-Home | H40: In Home Tech | I40: PST | J40: 58850 | K40: 08935 | L40: 08935 | M40: San Juan | N40: PR | O40: 32560 | P40: 32560 | Q40: 32560 | R40: 13369 | S40: 36 | T40: 16+ Years | U40: #11 ANTONIO RODRIGUEZ ST. | W40: CATANO | X40: PR | Y40: 00962
A41: =TRIM(D41) -> ACHANEY | B41: 91023313599 | C41: CHANEY,ANTHONY C | D41: ACHANEY | E41: A | F41: HS2003 | G41: Service Technician 1, In-Home | H41: In Home Tech | I41: TSH | J41: 58890 | K41: 07088 | L41: 28056 | M41: El Cajon | N41: CA | O41: 40028 | P41: 40028 | Q41: 40028 | R41: 5901 | S41: 16 | T41: 16+ Years | U41: 6015 Edgewater Street | W41: San Diego | X41: CA | Y41: 92139
A42: =TRIM(D42) -> achavi0 | B42: 21024616842 | C42: CHAVIRA,ALONSO | D42: achavi0 | E42: A | F42: HS9661 | G42: Service Technician 3, In-Home | H42: In Home Tech | I42: TSH | J42: 58890 | K42: 08147 | L42: 28212 | M42: San Antonio | N42: TX | O42: 44230 | P42: 44230 | Q42: 44230 | R42: 1699 | S42: 4 | T42: 3-6 Years | U42: 546 ORLANDO STREET | W42: CHAPARRAL | X42: NM | Y42: 88081
A43: =TRIM(D43) -> ACHRI10 | B43: 11021299591 | C43: CHRISTIAN,ALEX J | D43: ACHRI10 | E43: A | F43: HS1992 | G43: Service Tech 1, IH | H43: In Home Tech | I43: TSH | J43: 58850 | K43: 08035 | L43: 28085 | M43: College Park | N43: GA | O43: 35723 | P43: 35723 | Q43: 35723 | R43: 10206 | S43: 27 | T43: 16+ Years | U43: 308 TEAKWOOD TERRACE | W43: STOCKBRIDGE | X43: GA | Y43: 30281
A44: =TRIM(D44) -> aclark | B44: 31024630753 | C44: CLARK,AUSTIN | D44: aclark | E44: A | F44: HS2003 | G44: Service Technician 1, In-Home | H44: In Home Tech | I44: TSH | J44: 58890 | K44: 08206 | L44: 28129 | M44: Nashville | N44: TN | O44: 45837 | P44: 45837 | Q44: 45837 | R44: 92 | S44: 0 | T44: 91 Days - 6 Months | U44: 5702 FOXHAVEN DR | W44: NUNNELLY | X44: TN | Y44: 37137
A45: =TRIM(D45) -> aclayto | B45: 41024630984 | C45: CLAYTON,ANTHONY D | D45: aclayto | E45: T | F45: HS9661 | G45: Service Technician 3, In-Home | H45: In Home Tech | I45: TSH | J45: 58850 | K45: 04766 | L45: 28124 | M45: Louisville | N45: KY | O45: 45872 | P45: 45872 | Q45: 45872 | R45: 57 | S45: 0 | T45: 31-60 Days | U45: 364 KEENER RD | W45: SEYMOUR | X45: TN | Y45: 37865
A46: =TRIM(D46) -> acobb | B46: 71024622037 | C46: COBB,ANTHONY P | D46: acobb | E46: L | F46: HS2023 | G46: Service Technician 2, In-Home | H46: In Home Tech | I46: TSH | J46: 58890 | K46: 08158 | L46: 28234 | M46: Honolulu | N46: HI | O46: 44560 | P46: 44560 | Q46: 44560 | R46: 1369 | S46: 3 | T46: 3-6 Years | U46: 95-154 Kauopae Place | W46: Mililani | X46: HI | Y46: 96789
A47: =TRIM(D47) -> acolind | B47: 41024618854 | C47: COLINDREZ,ALEXANDER | D47: acolind | E47: A | F47: HS2003 | G47: Service Technician 1, In-Home | H47: In Home Tech | I47: TSH | J47: 58850 | K47: 07744 | L47: 28012 | M47: Melville | N47: NY | O47: 44327 | P47: 44478 | Q47: 44327 | R47: 1602 | S47: 4 | T47: 3-6 Years | U47: 60 E MAPLE ST | W47: CENTRAL ISLIP | X47: NY | Y47: 11722
A48: =TRIM(D48) -> acook14 | B48: 81024211138 | C48: COOK,ANTHONY N | D48: acook14 | E48: A | F48: HS2014 | G48: Team Lead Technician | H48: In Home Tech | I48: TSH | J48: 58850 | K48: 04766 | L48: 28114 | M48: Columbus | N48: OH | O48: 42093 | P48: 42093 | Q48: 42093 | R48: 3836 | S48: 10 | T48: 6-15 Years | U48: 1098 KEATHLEY BRANCH | W48: HAROLD | X48: KY | Y48: 41635
A49: =TRIM(D49) -> ACORRE | B49: 51021076145 | C49: CORREA SR,ANGEL L | D49: ACORRE | E49: A | F49: HS2014 | G49: Team Lead Technician | H49: In Home Tech | I49: TSH | J49: 58850 | K49: 08380 | L49: 28270 | M49: Allentown | N49: PA | O49: 33122 | P49: 33122 | Q49: 33122 | R49: 12807 | S49: 35 | T49: 16+ Years | U49: 2640 TOMIC PLACE | W49: BATH | X49: PA | Y49: 18014
A50: =TRIM(D50) -> acovas | B50: 61024620216 | C50: COVAS,ANTHONY | D50: acovas | E50: A | F50: HS2023 | G50: Service Technician 2, In-Home | H50: In Home Tech | I50: TSH | J50: 58850 | K50: 04766 | L50: 28114 | M50: Columbus | N50: OH | O50: 44425 | P50: 44425 | Q50: 44425 | R50: 1504 | S50: 4 | T50: 3-6 Years | U50: 4188 MILL TRACE RD | W50: YOUNGSTOWN | X50: OH | Y50: 44511
... A52: =TRIM(D52) -> adavalo | B52: 01024618030 | C52: DAVALOS,ARMANDO | D52: adavalo | E52: A | F52: HS2305 | G52: HVAC Svc Tech II, Break/Fix | H52: HVAC Tech | I52: TSH | J52: 58890 | K52: 08555 | L52: 28037 | M52: Hoffman Estates | N52: IL | O52: 44279 | P52: 44279 | Q52: 44279 | R52: 1650 | S52: 4 | T52: 3-6 Years | U52: 1705 highland ave | W52: Crest hill | X52: IL | Y52: 60403
A53: =TRIM(D53) -> adavis4 | B53: 01024630990 | C53: DAVIS,AVERY | D53: adavis4 | E53: T | F53: HS1022 | G53: Service Tech 2 Trainee, IH | H53: In Home Tech | I53: TSH | J53: 58850 | K53: 08035 | L53: 09246 | M53: Homewood | N53: AL | O53: 45879 | P53: 45879 | Q53: 45879 | R53: 50 | S53: 0 | T53: 31-60 Days | U53: 300 APACHE DRIVE | V53: UNIT 7B | W53: ENTERPRISE | X53: AL | Y53: 36330
A54: =TRIM(D54) -> adeguz0 | B54: 41024279314 | C54: DE GUZMAN,ANTONIO B | D54: adeguz0 | E54: A | F54: HS2023 | G54: Service Technician 2, In-Home | H54: In Home Tech | I54: TSH | J54: 58890 | K54: 08184 | L54: 28081 | M54: Sacramento | N54: CA | O54: 42291 | P54: 42291 | Q54: 42291 | R54: 3638 | S54: 9 | T54: 6-15 Years | U54: 7000 E SAMUEL CT | W54: VACAVILLE | X54: CA | Y54: 95687
A55: =TRIM(D55) -> adelac1 | B55: 31024537283 | C55: DELA CRUZ,AMBROCIO A | D55: adelac1 | E55: A | F55: HS2003 | G55: Service Technician 1, In-Home | H55: In Home Tech | I55: TSH | J55: 58890 | K55: 08184 | L55: 28081 | M55: Sacramento | N55: CA | O55: 43257 | P55: 43257 | Q55: 43257 | R55: 2672 | S55: 7 | T55: 6-15 Years | U55: 6404 CONLON AVENUE | W55: EL CERRITO | X55: CA | Y55: 94530
A56: =TRIM(D56) -> adelafu | B56: 11024629061 | C56: DELAFUENTE,ADRIAN | D56: adelafu | E56: A | F56: HS2305 | G56: HVAC Svc Tech II, Break/Fix | H56: HVAC Tech | I56: TSH | J56: 58890 | K56: 08366 | L56: 28048 | M56: Fresno | N56: CA | O56: 45410 | P56: 45410 | Q56: 45410 | R56: 519 | S56: 1 | T56: 1-3 Years | U56: 1445 PEACH ST. | V56: 205 | W56: SELMA | X56: CA | Y56: 93662
A57: =TRIM(D57) -> ADEVENT | B57: 91023424799 | C57: DE VENT,ALVIN L | D57: ADEVENT | E57: A | F57: HS2023 | G57: Service Technician 2, In-Home | H57: In Home Tech | I57: TSH | J57: 58890 | K57: 08184 | L57: 28081 | M57: Sacramento | N57: CA | O57: 40283 | P57: 40850 | Q57: 40283 | R57: 5646 | S57: 15 | T57: 6-15 Years | U57: 2719 San Gregorio Ct | W57: Antioch | X57: CA | Y57: 94531
A58: =TRIM(D58) -> adiaz2 | B58: 31024620163 | C58: DIAZ,ABIB | D58: adiaz2 | E58: A | F58: HS2023 | G58: Service Technician 2, In-Home | H58: In Home Tech | I58: TSH | J58: 58890 | K58: 08096 | L58: 28023 | M58: Indianapolis | N58: IN | O58: 44427 | P58: 44427 | Q58: 44427 | R58: 1502 | S58: 4 | T58: 3-6 Years | U58: 6046 Meadowview Dr | W58: Whitestown | X58: IN | Y58: 46075
A59: =TRIM(D59) -> ADITTA1 | B59: 31021349743 | C59: DITTA,ANTHONY J | D59: ADITTA1 | E59: L | F59: HS2023 | G59: Service Technician 2, In-Home | H59: In Home Tech | I59: TSH | J59: 58850 | K59: 03132 | L59: 28003 | M59: Linthicum Hts | N59: MD | O59: 35898 | P59: 35898 | Q59: 35898 | R59: 10031 | S59: 27 | T59: 16+ Years | U59: 9 GENEVIEVE COURT | W59: STEVENSVILLE | X59: MD | Y59: 21666
A60: =TRIM(D60) -> ADORSE3 | B60: 81021054948 | C60: DORSEY,ARCHIE L | D60: ADORSE3 | E60: L | F60: HS2003 | G60: Service Technician 1, In-Home | H60: In Home Tech | I60: TSH | J60: 58850 | K60: 07435 | L60: 28098 | M60: Winter Park | N60: FL | O60: 32028 | P60: 32028 | Q60: 32028 | R60: 13901 | S60: 38 | T60: 16+ Years | U60: 3861 13TH AVE S | W60: ST PETERSBURG | X60: FL | Y60: 33711
A61: =TRIM(D61) -> adougla | B61: 21024630372 | C61: DOUGLAS,AARON | D61: adougla | E61: T | F61: HS2003 | G61: Service Technician 1, In-Home | H61: In Home Tech | I61: TSH | J61: 58890 | K61: 08158 | L61: 28234 | M61: Honolulu | N61: HI | O61: 45662 | P61: 45662 | Q61: 45662 | R61: 267 | S61: 0 | T61: 6 Mo - 1 Year | U61: 98-1250 KUAWA ST | V61: DWLFT | W61: AIEA | X61: HI | Y61: 96701
A62: =TRIM(D62) -> aekwelu | B62: 11023926121 | C62: EKWELUM,ANNY A | D62: aekwelu | E62: T | F62: HS2023 | G62: Service Technician 2, In-Home | H62: In Home Tech | I62: TSH | J62: 58890 | K62: 07995 | L62: 28224 | M62: Farmers Branch | N62: TX | O62: 41386 | P62: 41386 | Q62: 41386 | R62: 4543 | S62: 12 | T62: 6-15 Years | U62: P.O. Box 740142 | W62: Dallas | X62: TX | Y62: 75374
A63: =TRIM(D63) -> AELSER | B63: 21023626742 | C63: ELSER,ALBERT J | D63: AELSER | E63: A | F63: HS2023 | G63: Service Technician 2, In-Home | H63: In Home Tech | I63: TSH | J63: 58850 | K63: 07670 | L63: 28062 | M63: College Point | N63: NY | O63: 40757 | P63: 40757 | Q63: 40757 | R63: 5172 | S63: 14 | T63: 6-15 Years | U63: 22 ROBBINS RD. | V63: 0 | W63: MIDDLETOWN | X63: NY | Y63: 10940
A64: =TRIM(D64) -> aemerso | B64: 91024621859 | C64: EMERSON,ALLAN G | D64: aemerso | E64: A | F64: HS2003 | G64: Service Technician 1, In-Home | H64: In Home Tech | I64: TSH | J64: 58850 | K64: 04766 | L64: 28125 | M64: Louisville | N64: KY | O64: 44539 | P64: 44539 | Q64: 44539 | R64: 1390 | S64: 3 | T64: 3-6 Years | U64: 3829 HANOVER DRIVE | W64: MASON | X64: OH | Y64: 45040
A65: =TRIM(D65) -> aengen | B65: 81024350508 | C65: ENGEN,ALLEN | D65: aengen | E65: A | F65: HS2003 | G65: Service Technician 1, In-Home | H65: In Home Tech | I65: TSH | J65: 58890 | K65: 08184 | L65: 28081 | M65: Sacramento | N65: CA | O65: 42499 | P65: 42499 | Q65: 42499 | R65: 3430 | S65: 9 | T65: 6-15 Years | U65: 1421 Loeffler Lane | V65: #2 | W65: Concord | X65: CA | Y65: 94521
A66: =TRIM(D66) -> AESPOSI | B66: 81022839208 | C66: ESPOSITO,ANTHONY J | D66: AESPOSI | E66: A | F66: HS2023 | G66: Service Technician 2, In-Home | H66: In Home Tech | I66: TSH | J66: 58850 | K66: 08175 | L66: 28121 | M66: Richmond | N66: VA | O66: 39181 | P66: 39181 | Q66: 39181 | R66: 6748 | S66: 18 | T66: 16+ Years | U66: 106 HEATHERWOOD LN | W66: YORKTOWN | X66: VA | Y66: 23692
A67: =TRIM(D67) -> aestrad | B67: 61024631216 | C67: ESTRADA,ASHLEY L | D67: aestrad | E67: A | F67: HS2023 | G67: Service Technician 2, In-Home | H67: In Home Tech | I67: TSH | J67: 58850 | K67: 07670 | L67: 28009 | M67: Danvers | N67: MA | O67: 45928 | P67: 45928 | Q67: 45928 | R67: 1 | S67: 0 | T67: 0-30 Days | U67: 710 WEEDEN ST | W67: PAWTUCKET | X67: RI | Y67: 02860
A68: =TRIM(D68) -> AFALCO1 | B68: 51021159845 | C68: FALCON,ARNALDO | D68: AFALCO1 | E68: A | F68: HS2032 | G68: Service Technician LG, In-Home | H68: In Home Tech | I68: PST | J68: 58850 | K68: 08935 | L68: 08935 | M68: San Juan | N68: PR | O68: 35005 | P68: 35005 | Q68: 35005 | R68: 10924 | S68: 29 | T68: 16+ Years | U68: OR88 VIA 20 | V68: VILLA FONTANA | W68: CAROLINA | X68: PR | Y68: 00983
A69: =TRIM(D69) -> afavazz | B69: 11023951251 | C69: FAVAZZA,ANDREW | D69: afavazz | E69: A | F69: UHS003 | G69: Service Technician 2, In-Home | H69: In Home Tech | I69: TSH | J69: 58890 | K69: 03580 | L69: 03580 | M69: Fenton | N69: MO | O69: 41451 | P69: 44931 | Q69: 44931 | R69: 998 | S69: 2 | T69: 1-3 Years | U69: 15276 CLAYTON RD | W69: BALLWIN | X69: MO | Y69: 63011
A70: =TRIM(D70) -> afelix | B70: 01024630880 | C70: FELIX,ASCHBEA | D70: afelix | E70: A | F70: HS9661 | G70: Service Technician 3, In-Home | H70: In Home Tech | I70: TSH | J70: 58850 | K70: 07744 | L70: 28012 | M70: Melville | N70: NY | O70: 45865 | P70: 45865 | Q70: 45865 | R70: 64 | S70: 0 | T70: 61-90 Days | U70: 1191 PARK PLACE | V70: 11D | W70: BROOKLYN | X70: NY | Y70: 11213
A71: =TRIM(D71) -> afergu0 | B71: 21024630722 | C71: FERGUSON,ANTHONY | D71: afergu0 | E71: T | F71: HS2003 | G71: Service Technician 1, In-Home | H71: In Home Tech | I71: TSH | J71: 58850 | K71: 04766 | L71: 28114 | M71: Columbus | N71: OH | O71: 45816 | P71: 45816 | Q71: 45816 | R71: 113 | S71: 0 | T71: 91 Days - 6 Months | U71: 214 BANNISTER ST | W71: FOSTORIA | X71: OH | Y71: 44830
A72: =TRIM(D72) -> afergus | B72: 61024630656 | C72: FERGUSON,ANTONIO | D72: afergus | E72: T | F72: HS2305 | G72: HVAC Svc Tech II, Break/Fix | H72: HVAC Tech | I72: TSH | J72: 58850 | K72: 08175 | L72: 28121 | M72: Richmond | N72: VA | O72: 45795 | P72: 45795 | Q72: 45795 | R72: 134 | S72: 0 | T72: 91 Days - 6 Months | U72: 3501 SKIPPING ROCK PL | W72: RICHMOND | X72: VA | Y72: 23234
A73: =TRIM(D73) -> aferna4 | B73: 91024616409 | C73: FERNANDEZ,ANIBAL | D73: aferna4 | E73: T | F73: HS2023 | G73: Service Technician 2, In-Home | H73: In Home Tech | I73: TSH | J73: 58850 | K73: 03132 | L73: 28003 | M73: Linthicum Hts | N73: MD | O73: 44202 | P73: 44202 | Q73: 44202 | R73: 1727 | S73: 4 | T73: 3-6 Years | U73: 4008 SHARILYN DRIVE | W73: ABINGDON | X73: MD | Y73: 21009
A74: =TRIM(D74) -> AFERRAR | B74: 11021036031 | C74: FERRARA,ANTHONY S | D74: AFERRAR | E74: A | F74: HS2003 | G74: Service Technician 1, In-Home | H74: In Home Tech | I74: TSH | J74: 58890 | K74: 08096 | L74: 28023 | M74: Indianapolis | N74: IN | O74: 29698 | P74: 29698 | Q74: 29698 | R74: 16231 | S74: 44 | T74: 16+ Years | U74: 710 NORTH SCHOOL STREET | W74: NORMAL | X74: IL | Y74: 61761
A75: =TRIM(D75) -> aferrei | B75: 91024618109 | C75: FERREIRA,ADAIR | D75: aferrei | E75: A | F75: HS2023 | G75: Service Technician 2, In-Home | H75: In Home Tech | I75: TSH | J75: 58850 | K75: 07670 | L75: 28009 | M75: Danvers | N75: MA | O75: 44277 | P75: 44277 | Q75: 44277 | R75: 1652 | S75: 4 | T75: 3-6 Years | U75: 116 SCHOOL ST. | W75: LOWELL | X75: MA | Y75: 01854
A76: =TRIM(D76) -> afickes | B76: 01024591450 | C76: FICKES,ANDREW C | D76: afickes | E76: T | F76: HS2014 | G76: Team Lead Technician | H76: In Home Tech | I76: TSH | J76: 58890 | K76: 08096 | L76: 28023 | M76: Indianapolis | N76: IN | O76: 43712 | P76: 43712 | Q76: 43712 | R76: 2217 | S76: 6 | T76: 6-15 Years | U76: 709 n limestone ln | W76: PEORIA | X76: IL | Y76: 61604
A77: =TRIM(D77) -> afiglio | B77: 91024631169 | C77: FIGLIOLI,ANTHONY C | D77: afiglio | E77: A | F77: HS2023 | G77: Service Technician 2, In-Home | H77: In Home Tech | I77: TSH | J77: 58850 | K77: 07670 | L77: 28009 | M77: Danvers | N77: MA | O77: 45914 | P77: 45914 | Q77: 45914 | R77: 15 | S77: 0 | T77: 0-30 Days | U77: 6 BENHAM ST | W77: PLYMOUTH | X77: MA | Y77: 02360
A78: =TRIM(D78) -> afiguer | B78: 71024630407 | C78: FIGUERAS,ANDRES A | D78: afiguer | E78: T | F78: HS2003 | G78: Service Technician 1, In-Home | H78: In Home Tech | I78: TSH | J78: 58850 | K78: 08035 | L78: 28085 | M78: College Park | N78: GA | O78: 45690 | P78: 45690 | Q78: 45690 | R78: 239 | S78: 0 | T78: 6 Mo - 1 Year | U78: 235 BJ LN | W78: ODUM | X78: GA | Y78: 31555
A79: =TRIM(D79) -> afoster | B79: 21024630672 | C79: FOSTER,ANDRES | D79: afoster | E79: T | F79: HS1021 | G79: Service Tech 1 Trainee, IH | H79: In Home Tech | I79: TSH | J79: 58850 | K79: 08035 | L79: 09246 | M79: Homewood | N79: AL | O79: 45795 | P79: 45795 | Q79: 45795 | R79: 134 | S79: 0 | T79: 91 Days - 6 Months | U79: 1971 CHANCELLOR RIDGE RD | W79: PRATTVILLE | X79: AL | Y79: 36066
A80: =TRIM(D80) -> afrelic | B80: 11024594391 | C80: Frelick,Adam P | D80: afrelic | E80: A | F80: HS9661 | G80: Service Technician 3, In-Home | H80: In Home Tech | I80: TSH | J80: 58850 | K80: 08175 | L80: 28121 | M80: Richmond | N80: VA | O80: 43747 | P80: 43747 | Q80: 43747 | R80: 2182 | S80: 5 | T80: 3-6 Years | U80: 1562 Gordon Avenue Southeast | W80: Roanoke | X80: VA | Y80: 24014
A81: =TRIM(D81) -> afruche | B81: 71024626227 | C81: FRUCHEY,AARON G | D81: afruche | E81: A | F81: HS9661 | G81: Service Technician 3, In-Home | H81: In Home Tech | I81: TSH | J81: 58890 | K81: 08184 | L81: 28081 | M81: Sacramento | N81: CA | O81: 45008 | P81: 45008 | Q81: 45008 | R81: 921 | S81: 2 | T81: 1-3 Years | U81: 9344 Jessica dr | W81: Windsor | X81: CA | Y81: 95492
A82: =TRIM(D82) -> AFRYE1 | B82: 71023762517 | C82: FRYE,ANTONIO | D82: AFRYE1 | E82: A | F82: HS2003 | G82: Service Technician 1, In-Home | H82: In Home Tech | I82: TSH | J82: 58890 | K82: 08147 | L82: 28212 | M82: San Antonio | N82: TX | O82: 41036 | P82: 41036 | Q82: 41036 | R82: 4893 | S82: 13 | T82: 6-15 Years | U82: 8238 GRISSOM CIR | W82: SAN ANTONIO | X82: TX | Y82: 78251-2829
... A84: =TRIM(D84) -> agambl0 | B84: 31024206303 | C84: GAMBLE,ADAM Truman | D84: agambl0 | E84: A | F84: HS1022 | G84: Service Tech 2 Trainee, IH | H84: In Home Tech | I84: TSH | J84: 58850 | K84: 08035 | L84: 28085 | M84: College Park | N84: GA | O84: 42079 | P84: 45914 | Q84: 45914 | R84: 15 | S84: 0 | T84: 0-30 Days | U84: 36 AMBERTON COURT | W84: DEATSVILLE | X84: AL | Y84: 36022
A85: =TRIM(D85) -> AGAME05 | B85: 81022499608 | C85: GAMEZ,ALDO R | D85: AGAME05 | E85: A | F85: HS2003 | G85: Service Technician 1, In-Home | H85: In Home Tech | I85: TSH | J85: 58890 | K85: 08147 | L85: 28212 | M85: San Antonio | N85: TX | O85: 38481 | P85: 38481 | Q85: 38481 | R85: 7448 | S85: 20 | T85: 16+ Years | U85: 2901 Central Blvd. | V85: 305 | W85: BROWNSVILLE | X85: TX | Y85: 78520
A86: =TRIM(D86) -> agary | B86: 41024630904 | C86: GARY,ANDREW P | D86: agary | E86: A | F86: HS9661 | G86: Service Technician 3, In-Home | H86: In Home Tech | I86: TSH | J86: 58890 | K86: 08206 | L86: 28129 | M86: Nashville | N86: TN | O86: 45865 | P86: 45865 | Q86: 45865 | R86: 64 | S86: 0 | T86: 61-90 Days | U86: 1901 OVERTON DR. | W86: COLUMBIA | X86: TN | Y86: 38401
A87: =TRIM(D87) -> agarza | B87: 91024625759 | C87: GARZA,ANDREW | D87: agarza | E87: A | F87: HS2003 | G87: Service Technician 1, In-Home | H87: In Home Tech | I87: TSH | J87: 58890 | K87: 08147 | L87: 28212 | M87: San Antonio | N87: TX | O87: 44952 | P87: 44952 | Q87: 44952 | R87: 977 | S87: 2 | T87: 1-3 Years | U87: 15607 Mint Patch Meadow | W87: Von ormy | X87: TX | Y87: 78073
A88: =TRIM(D88) -> aghulam | B88: 41024631154 | C88: GHULAMI,ALI REZA | D88: aghulam | E88: A | F88: HS2003 | G88: Service Technician 1, In-Home | H88: In Home Tech | I88: TSH | J88: 58850 | K88: 03132 | L88: 28003 | M88: Linthicum Hts | N88: MD | O88: 45914 | P88: 45914 | Q88: 45914 | R88: 15 | S88: 0 | T88: 0-30 Days | U88: 810 WILSON POINT RD, APT D | W88: BALTIMORE | X88: MD | Y88: 21220
A89: =TRIM(D89) -> agiles | B89: 31024627343 | C89: GILES,ANTHONY J | D89: agiles | E89: T | F89: HS2003 | G89: Service Technician 1, In-Home | H89: In Home Tech | I89: TSH | J89: 58890 | K89: 08555 | L89: 28037 | M89: Hoffman Estates | N89: IL | O89: 45158 | P89: 45158 | Q89: 45158 | R89: 771 | S89: 2 | T89: 1-3 Years | U89: 1901 S. Harlem | V89: 2R | W89: BERWYN | X89: IL | Y89: 60402
A90: =TRIM(D90) -> agill | B90: 31024624873 | C90: GILL,ALBERT | D90: agill | E90: L | F90: HS2003 | G90: Service Technician 1, In-Home | H90: In Home Tech | I90: TSH | J90: 58890 | K90: 08158 | L90: 28234 | M90: Honolulu | N90: HI | O90: 44861 | P90: 44861 | Q90: 44861 | R90: 1068 | S90: 2 | T90: 1-3 Years | U90: 120 PUUEO ST | V90: B509 | W90: HILO | X90: HI | Y90: 96720
A91: =TRIM(D91) -> agillis | B91: 31022331753 | C91: GILLIS,ANTHONY | D91: agillis | E91: A | F91: HS1992 | G91: Service Tech 1, IH | H91: In Home Tech | I91: TSH | J91: 58850 | K91: 08035 | L91: 28085 | M91: College Park | N91: GA | O91: 38075 | P91: 45704 | Q91: 45704 | R91: 225 | S91: 0 | T91: 6 Mo - 1 Year | U91: 2527 bonds lake rd nw | W91: Conyers | X91: GA | Y91: 30012
A92: =TRIM(D92) -> AGON248 | B92: 41021056954 | C92: GONZALEZ,ALFREDO V | D92: AGON248 | E92: A | F92: HS2003 | G92: Service Technician 1, In-Home | H92: In Home Tech | I92: TSH | J92: 58890 | K92: 07088 | L92: 28056 | M92: El Cajon | N92: CA | O92: 32161 | P92: 32161 | Q92: 32161 | R92: 13768 | S92: 37 | T92: 16+ Years | U92: 2109 N. SPRUCE | W92: SANTA ANA | X92: CA | Y92: 92706
A93: =TRIM(D93) -> AGONZA1 | B93: 71021141677 | C93: GONZALEZ,ALONZO | D93: AGONZA1 | E93: L | F93: HS2023 | G93: Service Technician 2, In-Home | H93: In Home Tech | I93: TSH | J93: 58890 | K93: 08366 | L93: 28048 | M93: Fresno | N93: CA | O93: 34872 | P93: 34872 | Q93: 34872 | R93: 11057 | S93: 30 | T93: 16+ Years | U93: 14467 WEST KEARNEY BLVD | W93: KERMAN | X93: CA | Y93: 93630
A94: =TRIM(D94) -> AGONZA4 | B94: 91021544619 | C94: GONZALEZ,ALBERTO A | D94: AGONZA4 | E94: A | F94: HS2023 | G94: Service Technician 2, In-Home | H94: In Home Tech | I94: TSH | J94: 58890 | K94: 07995 | L94: 28224 | M94: Farmers Branch | N94: TX | O94: 36283 | P94: 36283 | Q94: 36283 | R94: 9646 | S94: 26 | T94: 16+ Years | U94: 5901 SYCAMORE CREEK RD | W94: FORTH WORTH | X94: TX | Y94: 76134
A95: =TRIM(D95) -> AGOSNE1 | B95: 71023018417 | C95: GOSNELL,ANDREW W | D95: AGOSNE1 | E95: A | F95: HS2023 | G95: Service Technician 2, In-Home | H95: In Home Tech | I95: TSH | J95: 58890 | K95: 07995 | L95: 28224 | M95: Farmers Branch | N95: TX | O95: 39468 | P95: 39468 | Q95: 39468 | R95: 6461 | S95: 17 | T95: 16+ Years | U95: 523 N GREEN ST. | W95: Grand saline | X95: TX | Y95: 75140
A96: =TRIM(D96) -> agulley | B96: 41024630994 | C96: GULLEY,AUNDRAY | D96: agulley | E96: A | F96: HS2023 | G96: Service Technician 2, In-Home | H96: In Home Tech | I96: TSH | J96: 58890 | K96: 08206 | L96: 28129 | M96: Nashville | N96: TN | O96: 45872 | P96: 45872 | Q96: 45872 | R96: 57 | S96: 0 | T96: 31-60 Days | U96: 1640 SOUTHERN HILLS DRIVE | W96: CONWAY | X96: AR | Y96: 72034
A97: =TRIM(D97) -> AHARDE | B97: 11021041401 | C97: HARDEN,ANDREW | D97: AHARDE | E97: A | F97: HS2014 | G97: Team Lead Technician | H97: In Home Tech | I97: TSH | J97: 58890 | K97: 08096 | L97: 28023 | M97: Indianapolis | N97: IN | O97: 30664 | P97: 44905 | Q97: 30664 | R97: 15265 | S97: 41 | T97: 16+ Years | U97: 16495 STATE ROAD 159 | W97: LEWIS | X97: IN | Y97: 47858
A98: =TRIM(D98) -> AHARPE | B98: 51021096585 | C98: HARPER JR,ARGUSTUS | D98: AHARPE | E98: R | F98: HS2003 | G98: Service Technician 1, In-Home | H98: In Home Tech | I98: TSH | J98: 58890 | K98: 08107 | L98: 28207 | M98: Houston | N98: TX | O98: 33981 | P98: 33981 | Q98: 33981 | R98: 11948 | S98: 32 | T98: 16+ Years | U98: 1318 AUBURN VIEW LN. | W98: FRESNO | X98: TX | Y98: 77545
A99: =TRIM(D99) -> aharri0 | B99: 51024630995 | C99: HARRIS,ANTRON J | D99: aharri0 | E99: A | F99: HS1022 | G99: Service Tech 2 Trainee, IH | H99: In Home Tech | I99: TSH | J99: 58850 | K99: 08035 | L99: 28085 | M99: College Park | N99: GA | O99: 45886 | P99: 45886 | Q99: 45886 | R99: 43 | S99: 0 | T99: 31-60 Days | U99: 407 COBBLESTONE BLVD, STOCKBRIDGE | W99: STOCKBRIDGE | X99: GA | Y99: 30281
A100: =TRIM(D100) -> aharris | B100: 61024630896 | C100: HARRIS,ARTHUR C | D100: aharris | E100: A | F100: HS2305 | G100: HVAC Svc Tech II, Break/Fix | H100: HVAC Tech | I100: TSH | J100: 58850 | K100: 07744 | L100: 28012 | M100: Melville | N100: NY | O100: 45858 | P100: 45858 | Q100: 45858 | R100: 71 | S100: 0 | T100: 61-90 Days | U100: 2136 HONEYWELL AVE | V100: APT 4K | W100: BRONX | X100: NY | Y100: 10460
A101: =TRIM(D101) -> ahartwe | B101: 01024620930 | C101: HARTWECK,AARON | D101: ahartwe | E101: A | F101: HS2003 | G101: Service Technician 1, In-Home | H101: In Home Tech | I101: TSH | J101: 58850 | K101: 08175 | L101: 28121 | M101: Richmond | N101: VA | O101: 44469 | P101: 44469 | Q101: 44469 | R101: 1460 | S101: 4 | T101: 3-6 Years | U101: 305 KUWICKI RD | W101: PIKEVILLE | X101: NC | Y101: 27863
A102: =TRIM(D102) -> aherbs | B102: 91021100579 | C102: HERBST,ANDREW | D102: aherbs | E102: A | F102: HS2023 | G102: Service Technician 2, In-Home | H102: In Home Tech | I102: TSH | J102: 58850 | K102: 07435 | L102: 28094 | M102: Winter Park | N102: FL | O102: 34127 | P102: 44041 | Q102: 44041 | R102: 1888 | S102: 5 | T102: 3-6 Years | U102: 3027 DUNHILL DRIVE | W102: COCOA | X102: FL | Y102: 32926
...

Sheet TEST
A1: Date of this request | B1: Van Rental PO is opened up on in Holman | C1: Name | D1: Enterprise ID | E1: Trim Van Num | F1: Tech Ph Num | G1: Van assigned in TPMS | H1: Start Rental Date | I1: Repair Location | J1: ISSUE: | K1: Permanent Solution in place: | L1: AMS updated:
A2: 46090 | B2: 61263 | C2: MORGAN, TYLER | D2: JMORGA1 | E2: =TRIM(B2) -> 61263 | F2: 9106029707 | G2: =IFERROR(VLOOKUP(D2,'TPMS-auto'!A:J,6,0),"Not-in-TPMS") -> 088047 | H2: New Rental | I2: FIRESTONE, 7717 STATE AVE, KANSAS CITY, KS 66112 | J2: CHECK ENGINE LIGHT IS ON | K2: Repair van | L2: Yes

Sheet Rental Approvals 
A1: Date of this request | B1: Van Rental PO is opened up on in Holman | C1: Name | D1: Enterprise ID | E1: Trim Van Num | F1: Tech Ph Num | G1: Van assigned in TPMS | H1: Start Rental Date | I1: Repair Location | J1: ISSUE: | K1: Permanent Solution in place: | L1: AMS updated: | M1: Fleet Tracker Updated | N1: Rental Approved | O1: Approved in Holman | P1: Unit Number | Q1: Team Members | R1: Existing RENTAL opened on truck # | S1: New Rental or Extension | T1: Truck Breakdown or New Hire | U1: Existing Rental open for How long? | V1: Tech Service Date
A2: 45918 | B2: 46634 | C2: MCKENZIE, ANTHONY | D2: AMCKENZ | E2: =TRIM(B2) -> 46634 | F2: =IFERROR(VLOOKUP(D2,'TPMS-auto'!A:J, 10,0), "Not-in-TPMS") -> Not-in-TPMS | G2: =IFERROR(VLOOKUP(D2,'TPMS-auto'!A:J,6,0),"Not-in-TPMS") -> Not-in-TPMS | H2: 45887 | I2: Van 46634 looks like it is ready to go - located at: NH A MCKENZIE JR PEP BOYS 17050 NW 57TH AVE | J2: No van assigned in TPMS; Tech is in rental | K2: Assign van in TPMS - | L2: Yes | N2: No | O2: Yes | P2: =IFERROR(VLOOKUP(D2,'TPMS-auto'!A:D, 4,0),"Not-in-TPMS") -> Not-in-TPMS | Q2: =IFERROR(VLOOKUP(Table2[[#This Row],[Unit Number]],Ops,3,0),"Not-in-TPMS") -> Not-in-TPMS | R2: =IFERROR(VLOOKUP(Table2[[#This Row],[Enterprise ID]], 'ExistingRental-12.11'!A:H, 3, 0), "Not Open On 12.11") -> Not Open On 12.11 | S2: =IF(Table2[[#This Row],[Start Rental Date]]="New Rental", "New Rental", "Rental Extension Request") -> Rental Extension Request | T2: =IFERROR(IF(Table2[[#This Row],[Date of this request]]-Table2[[#This Row],[Tech Service Date]]<60, "New Hire Rental", "Truck Breakdown"), "New Hire Rental") -> New Hire Rental | U2: =IFERROR(VLOOKUP(Table2[[#This Row],[Enterprise ID]], 'ExistingRental-12.11'!A:H, 7, 0), "Not Open On 12.11") -> Not Open On 12.11 | V2: =IFERROR(VLOOKUP(Table2[[#This Row],[Enterprise ID]],'Tech-ServiceDate'!A:B,2,0), "EitherNewHire or Termed") -> EitherNewHire or Termed
A3: 45918 | B3: 46146 | C3: Dilan Abreu | D3: DABREU | E3: =TRIM(B3) -> 46146 | F3: =IFERROR(VLOOKUP(D3,'TPMS-auto'!A:J, 10,0), "Not-in-TPMS") -> 7735520093 | G3: =IFERROR(VLOOKUP(D3,'TPMS-auto'!A:J,6,0),"Not-in-TPMS") -> 021159 | H3: 45911 | I3: New hire - Truck is assigned in TPMS - was moved to Tulsa Ok - 907 NORTH F STREET, MUSKOGEE, OK, 74403 - this is RFARRO house - Samsara shows this van is there also | K3: 46146 has been moved to OK - need another van for this new hire tech | L3: Yes | N3: Yes | O3: Yes | P3: =IFERROR(VLOOKUP(D3,'TPMS-auto'!A:D, 4,0),"Not-in-TPMS") -> 0008555 | Q3: =IFERROR(VLOOKUP(Table2[[#This Row],[Unit Number]],Ops,3,0),"Not-in-TPMS") -> Monica, Cheryl & Machell | R3: =IFERROR(VLOOKUP(Table2[[#This Row],[Enterprise ID]], 'ExistingRental-12.11'!A:H, 3, 0), "Not Open On 12.11") -> Not Open On 12.11 | S3: =IF(Table2[[#This Row],[Start Rental Date]]="New Rental", "New Rental", "Rental Extension Request") -> Rental Extension Request | T3: =IFERROR(IF(Table2[[#This Row],[Date of this request]]-Table2[[#This Row],[Tech Service Date]]<60, "New Hire Rental", "Truck Breakdown"), "New Hire Rental") -> New Hire Rental | U3: =IFERROR(VLOOKUP(Table2[[#This Row],[Enterprise ID]], 'ExistingRental-12.11'!A:H, 7, 0), "Not Open On 12.11") -> Not Open On 12.11 | V3: =IFERROR(VLOOKUP(Table2[[#This Row],[Enterprise ID]],'Tech-ServiceDate'!A:B,2,0), "EitherNewHire or Termed") -> 45900
A4: 45918 | B4: 61679 | C4: JUAREZ, ELIJAH | D4: EJUAREZ | E4: =TRIM(B4) -> 61679 | F4: =IFERROR(VLOOKUP(D4,'TPMS-auto'!A:J, 10,0), "Not-in-TPMS") -> 9154330595 | G4: =IFERROR(VLOOKUP(D4,'TPMS-auto'!A:J,6,0),"Not-in-TPMS") -> 061679 | H4: 45898 | I4: AAMCO TOTAL CAR CARE 1407 LOMALAND DR #102 EL PASO TX 79935 | J4: Rear Diff on order will arrive 10/28 | K4: Rob Anderson: WHY is tech in a rental when van was approved for repair 8/29. Transmission slipping PO was voided - is this actually a declined repair?? this is actually a rear diff that is on order expected delivery date is 10/28 | L4: Yes | N4: Yes | O4: Yes | P4: =IFERROR(VLOOKUP(D4,'TPMS-auto'!A:D, 4,0),"Not-in-TPMS") -> 0008147 | Q4: =IFERROR(VLOOKUP(Table2[[#This Row],[Unit Number]],Ops,3,0),"Not-in-TPMS") -> Carol & Tasha | R4: =IFERROR(VLOOKUP(Table2[[#This Row],[Enterprise ID]], 'ExistingRental-12.11'!A:H, 3, 0), "Not Open On 12.11") -> 45993 | S4: =IF(Table2[[#This Row],[Start Rental Date]]="New Rental", "New Rental", "Rental Extension Request") -> Rental Extension Request | T4: =IFERROR(IF(Table2[[#This Row],[Date of this request]]-Table2[[#This Row],[Tech Service Date]]<60, "New Hire Rental", "Truck Breakdown"), "New Hire Rental") -> Truck Breakdown | U4: =IFERROR(VLOOKUP(Table2[[#This Row],[Enterprise ID]], 'ExistingRental-12.11'!A:H, 7, 0), "Not Open On 12.11") -> ELIJAH JUAREZ | V4: =IFERROR(VLOOKUP(Table2[[#This Row],[Enterprise ID]],'Tech-ServiceDate'!A:B,2,0), "EitherNewHire or Termed") -> 44805
A5: 45918 | B5: 36108 | C5: GOMEZ, JOHN | D5: JGOMEZ | E5: =TRIM(B5) -> 36108 | F5: =IFERROR(VLOOKUP(D5,'TPMS-auto'!A:J, 10,0), "Not-in-TPMS") -> Not-in-TPMS | G5: =IFERROR(VLOOKUP(D5,'TPMS-auto'!A:J,6,0),"Not-in-TPMS") -> Not-in-TPMS | H5: New Rental | I5: Rental - JGOMEZ in rental - Van location is unknown - need to find out where this van is - no PO open in Holman except for the rental PO (Last known location is: 12392 EASTLINE ROAD, TRENTON, TX, 75490) | J5: Tech does not have a permanent van assignment - this truck was used as a random truck assignment- Tech needs a permanent van | K5: Find a permanent van for this tech | L5: Yes | N5: Yes | O5: Yes | P5: =IFERROR(VLOOKUP(D5,'TPMS-auto'!A:D, 4,0),"Not-in-TPMS") -> Not-in-TPMS | Q5: =IFERROR(VLOOKUP(Table2[[#This Row],[Unit Number]],Ops,3,0),"Not-in-TPMS") -> Not-in-TPMS | R5: =IFERROR(VLOOKUP(Table2[[#This Row],[Enterprise ID]], 'ExistingRental-12.11'!A:H, 3, 0), "Not Open On 12.11") -> Not Open On 12.11 | S5: =IF(Table2[[#This Row],[Start Rental Date]]="New Rental", "New Rental", "Rental Extension Request") -> New Rental | T5: =IFERROR(IF(Table2[[#This Row],[Date of this request]]-Table2[[#This Row],[Tech Service Date]]<60, "New Hire Rental", "Truck Breakdown"), "New Hire Rental") -> New Hire Rental | U5: =IFERROR(VLOOKUP(Table2[[#This Row],[Enterprise ID]], 'ExistingRental-12.11'!A:H, 7, 0), "Not Open On 12.11") -> Not Open On 12.11 | V5: =IFERROR(VLOOKUP(Table2[[#This Row],[Enterprise ID]],'Tech-ServiceDate'!A:B,2,0), "EitherNewHire or Termed") -> EitherNewHire or Termed
A6: 45918 | B6: 21091 | C6: JOHNNY QUACH | D6: JQUACH | E6: =TRIM(B6) -> 21091 | F6: =IFERROR(VLOOKUP(D6,'TPMS-auto'!A:J, 10,0), "Not-in-TPMS") -> 6262032405 | G6: =IFERROR(VLOOKUP(D6,'TPMS-auto'!A:J,6,0),"Not-in-TPMS") -> 021091 | I6: PEP BOYS 11937 E VALLEY BLVD EL MONTE CA 91732 | J6: PO approved on 9/16 - | K6: Tech JQUACH in rental 9/16 - PO approved 9/17 - rental extended 9/18 - tire only repair - get out of the shop asap | L6: Yes | N6: Yes | O6: Yes | P6: =IFERROR(VLOOKUP(D6,'TPMS-auto'!A:D, 4,0),"Not-in-TPMS") -> 0007108 | Q6: =IFERROR(VLOOKUP(Table2[[#This Row],[Unit Number]],Ops,3,0),"Not-in-TPMS") -> Carol & Tasha | R6: =IFERROR(VLOOKUP(Table2[[#This Row],[Enterprise ID]], 'ExistingRental-12.11'!A:H, 3, 0), "Not Open On 12.11") -> Not Open On 12.11 | S6: =IF(Table2[[#This Row],[Start Rental Date]]="New Rental", "New Rental", "Rental Extension Request") -> Rental Extension Request | T6: =IFERROR(IF(Table2[[#This Row],[Date of this request]]-Table2[[#This Row],[Tech Service Date]]<60, "New Hire Rental", "Truck Breakdown"), "New Hire Rental") -> Truck Breakdown | U6: =IFERROR(VLOOKUP(Table2[[#This Row],[Enterprise ID]], 'ExistingRental-12.11'!A:H, 7, 0), "Not Open On 12.11") -> Not Open On 12.11 | V6: =IFERROR(VLOOKUP(Table2[[#This Row],[Enterprise ID]],'Tech-ServiceDate'!A:B,2,0), "EitherNewHire or Termed") -> 40785
A7: 45918 | B7: 46835 | C7: HARTLEY, JONATHAN | D7: JHARTLE | E7: =TRIM(B7) -> 46835 | F7: =IFERROR(VLOOKUP(D7,'TPMS-auto'!A:J, 10,0), "Not-in-TPMS") -> 8287230074 | G7: =IFERROR(VLOOKUP(D7,'TPMS-auto'!A:J,6,0),"Not-in-TPMS") -> 046835 | I7: DALE EARNHART CHEVROLET, PO BOX 1250, NEWTON NC 28658 - no estimate since 8/27 | J7: Tech in rental - repair at Chevrolet - has no estimate to approve | K7: Get van repaired and tech out of rental | L7: Yes | N7: Yes | O7: Yes | P7: =IFERROR(VLOOKUP(D7,'TPMS-auto'!A:D, 4,0),"Not-in-TPMS") -> 0004766 | Q7: =IFERROR(VLOOKUP(Table2[[#This Row],[Unit Number]],Ops,3,0),"Not-in-TPMS") -> Rob & Andrea | R7: =IFERROR(VLOOKUP(Table2[[#This Row],[Enterprise ID]], 'ExistingRental-12.11'!A:H, 3, 0), "Not Open On 12.11") -> Not Open On 12.11 | S7: =IF(Table2[[#This Row],[Start Rental Date]]="New Rental", "New Rental", "Rental Extension Request") -> Rental Extension Request | T7: =IFERROR(IF(Table2[[#This Row],[Date of this request]]-Table2[[#This Row],[Tech Service Date]]<60, "New Hire Rental", "Truck Breakdown"), "New Hire Rental") -> Truck Breakdown | U7: =IFERROR(VLOOKUP(Table2[[#This Row],[Enterprise ID]], 'ExistingRental-12.11'!A:H, 7, 0), "Not Open On 12.11") -> Not Open On 12.11 | V7: =IFERROR(VLOOKUP(Table2[[#This Row],[Enterprise ID]],'Tech-ServiceDate'!A:B,2,0), "EitherNewHire or Termed") -> 45501
A8: 45918 | B8: 36161 | C8: GREGORY, KENTREL | D8: KGREGOR | E8: =TRIM(B8) -> 36161 | F8: =IFERROR(VLOOKUP(D8,'TPMS-auto'!A:J, 10,0), "Not-in-TPMS") -> 5028302709 | G8: =IFERROR(VLOOKUP(D8,'TPMS-auto'!A:J,6,0),"Not-in-TPMS") -> 036161 | H8: 45909 | I8: Rental extension request - van is repaired and is at: PEP BOYS, 1001 BRECKENRIDGE LN, LOUISVILLE KY 40207 | K8: 36161 needs to be assigned to this tech and he needs to pick up the van | L8: Yes | N8: No - go get the van at PEP BOYS, 1001 BRECKENRIDGE LN, LOUISVILLE KY 40207 | O8: Yes | P8: =IFERROR(VLOOKUP(D8,'TPMS-auto'!A:D, 4,0),"Not-in-TPMS") -> 0004766 | Q8: =IFERROR(VLOOKUP(Table2[[#This Row],[Unit Number]],Ops,3,0),"Not-in-TPMS") -> Rob & Andrea | R8: =IFERROR(VLOOKUP(Table2[[#This Row],[Enterprise ID]], 'ExistingRental-12.11'!A:H, 3, 0), "Not Open On 12.11") -> Not Open On 12.11 | S8: =IF(Table2[[#This Row],[Start Rental Date]]="New Rental", "New Rental", "Rental Extension Request") -> Rental Extension Request | T8: =IFERROR(IF(Table2[[#This Row],[Date of this request]]-Table2[[#This Row],[Tech Service Date]]<60, "New Hire Rental", "Truck Breakdown"), "New Hire Rental") -> New Hire Rental | U8: =IFERROR(VLOOKUP(Table2[[#This Row],[Enterprise ID]], 'ExistingRental-12.11'!A:H, 7, 0), "Not Open On 12.11") -> Not Open On 12.11 | V8: =IFERROR(VLOOKUP(Table2[[#This Row],[Enterprise ID]],'Tech-ServiceDate'!A:B,2,0), "EitherNewHire or Termed") -> 45893
A9: 45918 | B9: 36003 | C9: Fazil Hamza | D9: FHAMZA | E9: =TRIM(B9) -> 36003 | F9: =IFERROR(VLOOKUP(D9,'TPMS-auto'!A:J, 10,0), "Not-in-TPMS") -> 7323185436 | G9: =IFERROR(VLOOKUP(D9,'TPMS-auto'!A:J,6,0),"Not-in-TPMS") -> 046509 | H9: 45838 | I9: Van was approved for major repair on 2.20.2025. Need repair status LINDSAY CHEVROLET INC, 15605 JEFFERSON DAVIS HWY, WOODBRIDGE VA 22191 | J9: Last PO approval was 4687.45 on 8/28 0 need final repair status | K9: Tech to get 46509 back to him and release 36003 for another tech | L9: Yes | N9: Yes | O9: Yes | P9: =IFERROR(VLOOKUP(D9,'TPMS-auto'!A:D, 4,0),"Not-in-TPMS") -> 0007084 | Q9: =IFERROR(VLOOKUP(Table2[[#This Row],[Unit Number]],Ops,3,0),"Not-in-TPMS") -> Monica, Cheryl & Machell | R9: =IFERROR(VLOOKUP(Table2[[#This Row],[Enterprise ID]], 'ExistingRental-12.11'!A:H, 3, 0), "Not Open On 12.11") -> 45992 | S9: =IF(Table2[[#This Row],[Start Rental Date]]="New Rental", "New Rental", "Rental Extension Request") -> Rental Extension Request | T9: =IFERROR(IF(Table2[[#This Row],[Date of this request]]-Table2[[#This Row],[Tech Service Date]]<60, "New Hire Rental", "Truck Breakdown"), "New Hire Rental") -> Truck Breakdown | U9: =IFERROR(VLOOKUP(Table2[[#This Row],[Enterprise ID]], 'ExistingRental-12.11'!A:H, 7, 0), "Not Open On 12.11") -> FAZIL HAMZA | V9: =IFERROR(VLOOKUP(Table2[[#This Row],[Enterprise ID]],'Tech-ServiceDate'!A:B,2,0), "EitherNewHire or Termed") -> 44209
A10: 45918 | B10: 47164 | C10: Alan Hollis | D10: AHOLLIS | E10: =TRIM(B10) -> 47164 | F10: =IFERROR(VLOOKUP(D10,'TPMS-auto'!A:J, 10,0), "Not-in-TPMS") -> 7064020229 | G10: =IFERROR(VLOOKUP(D10,'TPMS-auto'!A:J,6,0),"Not-in-TPMS") -> 046702 | H10: 45849 | I10: This is not assigned to this tech - he's getting 46702? | J10: Last service PO is in Pepboys - repaired on 5/30 | K10: Assign truck 46702 in TPMS | L10: Yes | N10: No | O10: Yes | P10: =IFERROR(VLOOKUP(D10,'TPMS-auto'!A:D, 4,0),"Not-in-TPMS") -> 0008035 | Q10: =IFERROR(VLOOKUP(Table2[[#This Row],[Unit Number]],Ops,3,0),"Not-in-TPMS") -> Rob & Andrea | R10: =IFERROR(VLOOKUP(Table2[[#This Row],[Enterprise ID]], 'ExistingRental-12.11'!A:H, 3, 0), "Not Open On 12.11") -> Not Open On 12.11 | S10: =IF(Table2[[#This Row],[Start Rental Date]]="New Rental", "New Rental", "Rental Extension Request") -> Rental Extension Request | T10: =IFERROR(IF(Table2[[#This Row],[Date of this request]]-Table2[[#This Row],[Tech Service Date]]<60, "New Hire Rental", "Truck Breakdown"), "New Hire Rental") -> Truck Breakdown | U10: =IFERROR(VLOOKUP(Table2[[#This Row],[Enterprise ID]], 'ExistingRental-12.11'!A:H, 7, 0), "Not Open On 12.11") -> Not Open On 12.11 | V10: =IFERROR(VLOOKUP(Table2[[#This Row],[Enterprise ID]],'Tech-ServiceDate'!A:B,2,0), "EitherNewHire or Termed") -> 45844
A11: 45918 | B11: 21187 | C11: London Williams | D11: LWILLI3 | E11: =TRIM(B11) -> 21187 | F11: =IFERROR(VLOOKUP(D11,'TPMS-auto'!A:J, 10,0), "Not-in-TPMS") -> 2253371244 | G11: =IFERROR(VLOOKUP(D11,'TPMS-auto'!A:J,6,0),"Not-in-TPMS") -> 023686 | H11: New Rental | I11: AMS showed van was at PEP BOYS 12200 I-10 SERVICE RD , NEW ORLEANS, LA, 70128 for 2nd opinion- Banner Chevrolet kept the van for a long time and didn't repair - New info says van is at Otter Self Storage - 9425 Burbank Dr, Baton Rouge, LA 70810 | J11: Tech assigned van 23686, but has 21187 listed as rental. 21187 is at Pep Boys for 2nd opinion - | K11: No - needs a permanent van replacement - neither van is a good option (21187 nor 23686) | L11: Yes | N11: Yes | O11: Yes | P11: =IFERROR(VLOOKUP(D11,'TPMS-auto'!A:D, 4,0),"Not-in-TPMS") -> 0008206 | Q11: =IFERROR(VLOOKUP(Table2[[#This Row],[Unit Number]],Ops,3,0),"Not-in-TPMS") -> Monica, Cheryl & Machell | R11: =IFERROR(VLOOKUP(Table2[[#This Row],[Enterprise ID]], 'ExistingRental-12.11'!A:H, 3, 0), "Not Open On 12.11") -> Not Open On 12.11 | S11: =IF(Table2[[#This Row],[Start Rental Date]]="New Rental", "New Rental", "Rental Extension Request") -> New Rental | T11: =IFERROR(IF(Table2[[#This Row],[Date of this request]]-Table2[[#This Row],[Tech Service Date]]<60, "New Hire Rental", "Truck Breakdown"), "New Hire Rental") -> Truck Breakdown | U11: =IFERROR(VLOOKUP(Table2[[#This Row],[Enterprise ID]], 'ExistingRental-12.11'!A:H, 7, 0), "Not Open On 12.11") -> Not Open On 12.11 | V11: =IFERROR(VLOOKUP(Table2[[#This Row],[Enterprise ID]],'Tech-ServiceDate'!A:B,2,0), "EitherNewHire or Termed") -> 45816
A12: 45918 | B12: 22234 | C12: Jonathan Washabaugh | D12: JWASHAB | E12: =TRIM(B12) -> 22234 | F12: =IFERROR(VLOOKUP(D12,'TPMS-auto'!A:J, 10,0), "Not-in-TPMS") -> 8599131963 | G12: =IFERROR(VLOOKUP(D12,'TPMS-auto'!A:J,6,0),"Not-in-TPMS") -> 037176 | H12: 45915 | I12: Tech in rental - 9/12 - at AAMCO - needs repair and get back to the tech | K12: Get estimate and get repaired at AAMCO | L12: Yes | N12: Yes | O12: Yes | P12: =IFERROR(VLOOKUP(D12,'TPMS-auto'!A:D, 4,0),"Not-in-TPMS") -> 0004766 | Q12: =IFERROR(VLOOKUP(Table2[[#This Row],[Unit Number]],Ops,3,0),"Not-in-TPMS") -> Rob & Andrea | R12: =IFERROR(VLOOKUP(Table2[[#This Row],[Enterprise ID]], 'ExistingRental-12.11'!A:H, 3, 0), "Not Open On 12.11") -> Not Open On 12.11 | S12: =IF(Table2[[#This Row],[Start Rental Date]]="New Rental", "New Rental", "Rental Extension Request") -> Rental Extension Request | T12: =IFERROR(IF(Table2[[#This Row],[Date of this request]]-Table2[[#This Row],[Tech Service Date]]<60, "New Hire Rental", "Truck Breakdown"), "New Hire Rental") -> Truck Breakdown | U12: =IFERROR(VLOOKUP(Table2[[#This Row],[Enterprise ID]], 'ExistingRental-12.11'!A:H, 7, 0), "Not Open On 12.11") -> Not Open On 12.11 | V12: =IFERROR(VLOOKUP(Table2[[#This Row],[Enterprise ID]],'Tech-ServiceDate'!A:B,2,0), "EitherNewHire or Termed") -> 44686
A13: 45918 | B13: 37125 | C13: Kareem Williams | D13: KWILLI1 | E13: =TRIM(B13) -> 37125 | F13: =IFERROR(VLOOKUP(D13,'TPMS-auto'!A:J, 10,0), "Not-in-TPMS") -> 2287602794 | G13: =IFERROR(VLOOKUP(D13,'TPMS-auto'!A:J,6,0),"Not-in-TPMS") -> 037125 | H13: 45910 | I13: New hire - 9/2 start, 9/23 on route - need to set up transportation to get the tech and van connected - no OPEN pos on 37125 | J13: No van assigned in TPMS; Tech is in rental | K13: Get him a permanent van asap - van is in Laurel, MS - going to Gulfport, MS - | L13: Yes | N13: Yes | O13: Yes | P13: =IFERROR(VLOOKUP(D13,'TPMS-auto'!A:D, 4,0),"Not-in-TPMS") -> 0008206 | Q13: =IFERROR(VLOOKUP(Table2[[#This Row],[Unit Number]],Ops,3,0),"Not-in-TPMS") -> Monica, Cheryl & Machell | R13: =IFERROR(VLOOKUP(Table2[[#This Row],[Enterprise ID]], 'ExistingRental-12.11'!A:H, 3, 0), "Not Open On 12.11") -> 45971 | S13: =IF(Table2[[#This Row],[Start Rental Date]]="New Rental", "New Rental", "Rental Extension Request") -> Rental Extension Request | T13: =IFERROR(IF(Table2[[#This Row],[Date of this request]]-Table2[[#This Row],[Tech Service Date]]<60, "New Hire Rental", "Truck Breakdown"), "New Hire Rental") -> New Hire Rental | U13: =IFERROR(VLOOKUP(Table2[[#This Row],[Enterprise ID]], 'ExistingRental-12.11'!A:H, 7, 0), "Not Open On 12.11") -> KAREEM WILLIAMS | V13: =IFERROR(VLOOKUP(Table2[[#This Row],[Enterprise ID]],'Tech-ServiceDate'!A:B,2,0), "EitherNewHire or Termed") -> 45900
A14: 45918 | B14: 61470 | C14: LARSON, CHRISTOPHER | D14: CLARSON | E14: =TRIM(B14) -> 61470 | F14: =IFERROR(VLOOKUP(D14,'TPMS-auto'!A:J, 10,0), "Not-in-TPMS") -> 6605001207 | G14: =IFERROR(VLOOKUP(D14,'TPMS-auto'!A:J,6,0),"Not-in-TPMS") -> 046161 | H14: 45896 | I14: Declined repair - after 2nd estimate - $9,794.76 - need permanent van assignment | K14: Van will be declined repair $9,794.76 - need a permanent van assignment | L14: Yes | N14: Yes | O14: Yes | P14: =IFERROR(VLOOKUP(D14,'TPMS-auto'!A:D, 4,0),"Not-in-TPMS") -> 0008420 | Q14: =IFERROR(VLOOKUP(Table2[[#This Row],[Unit Number]],Ops,3,0),"Not-in-TPMS") -> Rob & Andrea | R14: =IFERROR(VLOOKUP(Table2[[#This Row],[Enterprise ID]], 'ExistingRental-12.11'!A:H, 3, 0), "Not Open On 12.11") -> Not Open On 12.11 | S14: =IF(Table2[[#This Row],[Start Rental Date]]="New Rental", "New Rental", "Rental Extension Request") -> Rental Extension Request | T14: =IFERROR(IF(Table2[[#This Row],[Date of this request]]-Table2[[#This Row],[Tech Service Date]]<60, "New Hire Rental", "Truck Breakdown"), "New Hire Rental") -> Truck Breakdown | U14: =IFERROR(VLOOKUP(Table2[[#This Row],[Enterprise ID]], 'ExistingRental-12.11'!A:H, 7, 0), "Not Open On 12.11") -> Not Open On 12.11 | V14: =IFERROR(VLOOKUP(Table2[[#This Row],[Enterprise ID]],'Tech-ServiceDate'!A:B,2,0), "EitherNewHire or Termed") -> 44307
A15: 45918 | B15: 61015 | C15: SOKOLOWSKI, BERNARD | D15: BSOKOLO | E15: =TRIM(B15) -> 61015 | F15: =IFERROR(VLOOKUP(D15,'TPMS-auto'!A:J, 10,0), "Not-in-TPMS") -> 7249536540 | G15: =IFERROR(VLOOKUP(D15,'TPMS-auto'!A:J,6,0),"Not-in-TPMS") -> 061016 | H15: 45862 | I15: Tech in rental since 7/24 - is the van here: PEP BOYS 20229 ROUTE 19, CRANBERRY TWP, PA, 16066 | J15: Where is this van? Tech rental on 7/24 but no repair scheduled | K15: Find van, get repair estimate | L15: Yes | N15: Yes | O15: Yes | P15: =IFERROR(VLOOKUP(D15,'TPMS-auto'!A:D, 4,0),"Not-in-TPMS") -> 0004766 | Q15: =IFERROR(VLOOKUP(Table2[[#This Row],[Unit Number]],Ops,3,0),"Not-in-TPMS") -> Rob & Andrea | R15: =IFERROR(VLOOKUP(Table2[[#This Row],[Enterprise ID]], 'ExistingRental-12.11'!A:H, 3, 0), "Not Open On 12.11") -> Not Open On 12.11 | S15: =IF(Table2[[#This Row],[Start Rental Date]]="New Rental", "New Rental", "Rental Extension Request") -> Rental Extension Request | T15: =IFERROR(IF(Table2[[#This Row],[Date of this request]]-Table2[[#This Row],[Tech Service Date]]<60, "New Hire Rental", "Truck Breakdown"), "New Hire Rental") -> Truck Breakdown | U15: =IFERROR(VLOOKUP(Table2[[#This Row],[Enterprise ID]], 'ExistingRental-12.11'!A:H, 7, 0), "Not Open On 12.11") -> Not Open On 12.11 | V15: =IFERROR(VLOOKUP(Table2[[#This Row],[Enterprise ID]],'Tech-ServiceDate'!A:B,2,0), "EitherNewHire or Termed") -> 37255
A16: 45918 | B16: 36222 | C16: COMBS, GRANT | D16: GCOMBS | E16: =TRIM(B16) -> 36222 | F16: =IFERROR(VLOOKUP(D16,'TPMS-auto'!A:J, 10,0), "Not-in-TPMS") -> Not-in-TPMS | G16: =IFERROR(VLOOKUP(D16,'TPMS-auto'!A:J,6,0),"Not-in-TPMS") -> Not-in-TPMS | H16: 45828 | I16: Needs a windshield - approved on 9/15 in Holman - Safelite | J16: Tech in rental since 6/20; What is the scheduled date for the windshield? | K16: Tech in rental since 6/20- getting 61354 - just need windshield replaced and get tech out of rental into the van | L16: Yes | N16: Yes | O16: Yes | P16: =IFERROR(VLOOKUP(D16,'TPMS-auto'!A:D, 4,0),"Not-in-TPMS") -> Not-in-TPMS | Q16: =IFERROR(VLOOKUP(Table2[[#This Row],[Unit Number]],Ops,3,0),"Not-in-TPMS") -> Not-in-TPMS | R16: =IFERROR(VLOOKUP(Table2[[#This Row],[Enterprise ID]], 'ExistingRental-12.11'!A:H, 3, 0), "Not Open On 12.11") -> Not Open On 12.11 | S16: =IF(Table2[[#This Row],[Start Rental Date]]="New Rental", "New Rental", "Rental Extension Request") -> Rental Extension Request | T16: =IFERROR(IF(Table2[[#This Row],[Date of this request]]-Table2[[#This Row],[Tech Service Date]]<60, "New Hire Rental", "Truck Breakdown"), "New Hire Rental") -> New Hire Rental | U16: =IFERROR(VLOOKUP(Table2[[#This Row],[Enterprise ID]], 'ExistingRental-12.11'!A:H, 7, 0), "Not Open On 12.11") -> Not Open On 12.11 | V16: =IFERROR(VLOOKUP(Table2[[#This Row],[Enterprise ID]],'Tech-ServiceDate'!A:B,2,0), "EitherNewHire or Termed") -> EitherNewHire or Termed
A17: 45918 | B17: 36305 | C17: Francis Grejdus | D17: FGREJDU | E17: =TRIM(B17) -> 36305 | F17: =IFERROR(VLOOKUP(D17,'TPMS-auto'!A:J, 10,0), "Not-in-TPMS") -> 8655009637 | G17: =IFERROR(VLOOKUP(D17,'TPMS-auto'!A:J,6,0),"Not-in-TPMS") -> 036305 | H17: 45918 | K17: Get van repaired and tech out of rental | L17: Yes | N17: Yes | O17: Yes | P17: =IFERROR(VLOOKUP(D17,'TPMS-auto'!A:D, 4,0),"Not-in-TPMS") -> 0004766 | Q17: =IFERROR(VLOOKUP(Table2[[#This Row],[Unit Number]],Ops,3,0),"Not-in-TPMS") -> Rob & Andrea | R17: =IFERROR(VLOOKUP(Table2[[#This Row],[Enterprise ID]], 'ExistingRental-12.11'!A:H, 3, 0), "Not Open On 12.11") -> Not Open On 12.11 | S17: =IF(Table2[[#This Row],[Start Rental Date]]="New Rental", "New Rental", "Rental Extension Request") -> Rental Extension Request | T17: =IFERROR(IF(Table2[[#This Row],[Date of this request]]-Table2[[#This Row],[Tech Service Date]]<60, "New Hire Rental", "Truck Breakdown"), "New Hire Rental") -> Truck Breakdown | U17: =IFERROR(VLOOKUP(Table2[[#This Row],[Enterprise ID]], 'ExistingRental-12.11'!A:H, 7, 0), "Not Open On 12.11") -> Not Open On 12.11 | V17: =IFERROR(VLOOKUP(Table2[[#This Row],[Enterprise ID]],'Tech-ServiceDate'!A:B,2,0), "EitherNewHire or Termed") -> 38744
A18: 45918 | B18: 23394 | C18: VELEZ, SUAMYS | D18: SVELEZ4 | E18: =TRIM(B18) -> 23394 | F18: =IFERROR(VLOOKUP(D18,'TPMS-auto'!A:J, 10,0), "Not-in-TPMS") -> Not-in-TPMS | G18: =IFERROR(VLOOKUP(D18,'TPMS-auto'!A:J,6,0),"Not-in-TPMS") -> Not-in-TPMS | H18: 45825 | I18: PEP BOYS, 1490 US 70 W, GARNER NC 27529 | K18: Get van repaired and tech out of rental | L18: Yes | N18: Yes | O18: Yes | P18: =IFERROR(VLOOKUP(D18,'TPMS-auto'!A:D, 4,0),"Not-in-TPMS") -> Not-in-TPMS | Q18: =IFERROR(VLOOKUP(Table2[[#This Row],[Unit Number]],Ops,3,0),"Not-in-TPMS") -> Not-in-TPMS | R18: =IFERROR(VLOOKUP(Table2[[#This Row],[Enterprise ID]], 'ExistingRental-12.11'!A:H, 3, 0), "Not Open On 12.11") -> Not Open On 12.11 | S18: =IF(Table2[[#This Row],[Start Rental Date]]="New Rental", "New Rental", "Rental Extension Request") -> Rental Extension Request | T18: =IFERROR(IF(Table2[[#This Row],[Date of this request]]-Table2[[#This Row],[Tech Service Date]]<60, "New Hire Rental", "Truck Breakdown"), "New Hire Rental") -> Truck Breakdown | U18: =IFERROR(VLOOKUP(Table2[[#This Row],[Enterprise ID]], 'ExistingRental-12.11'!A:H, 7, 0), "Not Open On 12.11") -> Not Open On 12.11 | V18: =IFERROR(VLOOKUP(Table2[[#This Row],[Enterprise ID]],'Tech-ServiceDate'!A:B,2,0), "EitherNewHire or Termed") -> 43263
A19: 45918 | B19: 46837 | C19: SAMMONS, ALEX | D19: ASAMMON | E19: =TRIM(B19) -> 46837 | F19: =IFERROR(VLOOKUP(D19,'TPMS-auto'!A:J, 10,0), "Not-in-TPMS") -> Not-in-TPMS | G19: =IFERROR(VLOOKUP(D19,'TPMS-auto'!A:J,6,0),"Not-in-TPMS") -> Not-in-TPMS | H19: 45903 | I19: New Hire - no permanent van assignement - Move van from: PEP BOYS, 215 BOARDMAN POLAND RD, BOARDMAN OH 44512 - to 5844 E. P Ridge Road Apt 6 Huntington, WV | J19: No van assigned in TPMS; Tech is in rental - van is in | K19: Assign this van to ASAMMON and schedule transportation to get the van to him | L19: Yes | N19: Yes | O19: Yes | P19: =IFERROR(VLOOKUP(D19,'TPMS-auto'!A:D, 4,0),"Not-in-TPMS") -> Not-in-TPMS | Q19: =IFERROR(VLOOKUP(Table2[[#This Row],[Unit Number]],Ops,3,0),"Not-in-TPMS") -> Not-in-TPMS | R19: =IFERROR(VLOOKUP(Table2[[#This Row],[Enterprise ID]], 'ExistingRental-12.11'!A:H, 3, 0), "Not Open On 12.11") -> Not Open On 12.11 | S19: =IF(Table2[[#This Row],[Start Rental Date]]="New Rental", "New Rental", "Rental Extension Request") -> Rental Extension Request | T19: =IFERROR(IF(Table2[[#This Row],[Date of this request]]-Table2[[#This Row],[Tech Service Date]]<60, "New Hire Rental", "Truck Breakdown"), "New Hire Rental") -> New Hire Rental | U19: =IFERROR(VLOOKUP(Table2[[#This Row],[Enterprise ID]], 'ExistingRental-12.11'!A:H, 7, 0), "Not Open On 12.11") -> Not Open On 12.11 | V19: =IFERROR(VLOOKUP(Table2[[#This Row],[Enterprise ID]],'Tech-ServiceDate'!A:B,2,0), "EitherNewHire or Termed") -> EitherNewHire or Termed
A20: 45918 | B20: 46209 | C20: Jorge Pena | D20: JPENA1 | E20: =TRIM(B20) -> 46209 | F20: =IFERROR(VLOOKUP(D20,'TPMS-auto'!A:J, 10,0), "Not-in-TPMS") -> 2109150317 | G20: =IFERROR(VLOOKUP(D20,'TPMS-auto'!A:J,6,0),"Not-in-TPMS") -> 046209 | H20: New Rental | I20: Tech in rental - JPENA1 - PO approved on 8/29 for AC repair - why is it still there? | J20: PO approved 8/29, tech asking for rental extension | K20: Get van repaired and tech out of rental | L20: Yes | N20: Yes | O20: Yes | P20: =IFERROR(VLOOKUP(D20,'TPMS-auto'!A:D, 4,0),"Not-in-TPMS") -> 0008147 | Q20: =IFERROR(VLOOKUP(Table2[[#This Row],[Unit Number]],Ops,3,0),"Not-in-TPMS") -> Carol & Tasha | R20: =IFERROR(VLOOKUP(Table2[[#This Row],[Enterprise ID]], 'ExistingRental-12.11'!A:H, 3, 0), "Not Open On 12.11") -> 45960 | S20: =IF(Table2[[#This Row],[Start Rental Date]]="New Rental", "New Rental", "Rental Extension Request") -> New Rental | T20: =IFERROR(IF(Table2[[#This Row],[Date of this request]]-Table2[[#This Row],[Tech Service Date]]<60, "New Hire Rental", "Truck Breakdown"), "New Hire Rental") -> Truck Breakdown | U20: =IFERROR(VLOOKUP(Table2[[#This Row],[Enterprise ID]], 'ExistingRental-12.11'!A:H, 7, 0), "Not Open On 12.11") -> JORGE PENA | V20: =IFERROR(VLOOKUP(Table2[[#This Row],[Enterprise ID]],'Tech-ServiceDate'!A:B,2,0), "EitherNewHire or Termed") -> 44980
A21: 45918 | B21: 61320 | C21: LE, SHYHEIM | D21: SPELLE | E21: =TRIM(B21) -> 61320 | F21: =IFERROR(VLOOKUP(D21,'TPMS-auto'!A:J, 10,0), "Not-in-TPMS") -> 4109821742 | G21: =IFERROR(VLOOKUP(D21,'TPMS-auto'!A:J,6,0),"Not-in-TPMS") -> 061320 | I21: Accident - truck is at: CHESAPEAKE SERVICE CENTER LLC, 895B NOTTINGHAM RD, ELKTON MD 21921 | K21: Send to body shop to get fixed | L21: Yes | N21: Yes | O21: Yes | P21: =IFERROR(VLOOKUP(D21,'TPMS-auto'!A:D, 4,0),"Not-in-TPMS") -> 0007084 | Q21: =IFERROR(VLOOKUP(Table2[[#This Row],[Unit Number]],Ops,3,0),"Not-in-TPMS") -> Monica, Cheryl & Machell | R21: =IFERROR(VLOOKUP(Table2[[#This Row],[Enterprise ID]], 'ExistingRental-12.11'!A:H, 3, 0), "Not Open On 12.11") -> 45877 | S21: =IF(Table2[[#This Row],[Start Rental Date]]="New Rental", "New Rental", "Rental Extension Request") -> Rental Extension Request | T21: =IFERROR(IF(Table2[[#This Row],[Date of this request]]-Table2[[#This Row],[Tech Service Date]]<60, "New Hire Rental", "Truck Breakdown"), "New Hire Rental") -> Truck Breakdown | U21: =IFERROR(VLOOKUP(Table2[[#This Row],[Enterprise ID]], 'ExistingRental-12.11'!A:H, 7, 0), "Not Open On 12.11") -> SHYHEIM PELLE | V21: =IFERROR(VLOOKUP(Table2[[#This Row],[Enterprise ID]],'Tech-ServiceDate'!A:B,2,0), "EitherNewHire or Termed") -> 45256
A22: 45918 | B22: 21689 | C22: Tyler Carnahan | D22: TCARNAH | E22: =TRIM(B22) -> 21689 | F22: =IFERROR(VLOOKUP(D22,'TPMS-auto'!A:J, 10,0), "Not-in-TPMS") -> 8136480860 | G22: =IFERROR(VLOOKUP(D22,'TPMS-auto'!A:J,6,0),"Not-in-TPMS") -> 021207 | H22: 45905 | I22: Van is at Expert Car Care - last location - 3016 ALAFAYA TRAIL, OVIEDO FL 32765 - Van is being driven daily | K22: Assign in TPMS - Van is at Expert Car Care or find the van where it is. | L22: Yes | N22: No | O22: Yes | P22: =IFERROR(VLOOKUP(D22,'TPMS-auto'!A:D, 4,0),"Not-in-TPMS") -> 0007435 | Q22: =IFERROR(VLOOKUP(Table2[[#This Row],[Unit Number]],Ops,3,0),"Not-in-TPMS") -> Rob & Andrea | R22: =IFERROR(VLOOKUP(Table2[[#This Row],[Enterprise ID]], 'ExistingRental-12.11'!A:H, 3, 0), "Not Open On 12.11") -> 45861 | S22: =IF(Table2[[#This Row],[Start Rental Date]]="New Rental", "New Rental", "Rental Extension Request") -> Rental Extension Request | T22: =IFERROR(IF(Table2[[#This Row],[Date of this request]]-Table2[[#This Row],[Tech Service Date]]<60, "New Hire Rental", "Truck Breakdown"), "New Hire Rental") -> New Hire Rental | U22: =IFERROR(VLOOKUP(Table2[[#This Row],[Enterprise ID]], 'ExistingRental-12.11'!A:H, 7, 0), "Not Open On 12.11") -> TYLER CARNAHAN | V22: =IFERROR(VLOOKUP(Table2[[#This Row],[Enterprise ID]],'Tech-ServiceDate'!A:B,2,0), "EitherNewHire or Termed") -> 45893
A23: 45918 | B23: 23862 | C23: COUCH, VAN | D23: VCOUCH | E23: =TRIM(B23) -> 23862 | F23: =IFERROR(VLOOKUP(D23,'TPMS-auto'!A:J, 10,0), "Not-in-TPMS") -> 3312407987 | G23: =IFERROR(VLOOKUP(D23,'TPMS-auto'!A:J,6,0),"Not-in-TPMS") -> 023862 | H23: 45876 | I23: Tech picked up and brought back on 9/5 - AC repair was at PEP BOYS, 17015 TORRENCE AVE, LANSING IL 60438 | K23: Went back in the shop on 9/5 - no purchase order - we don't know where this is / Reached out to Van Couch to understand his rental situation - 10/3 / Van reports that Pep Boys states they havent had time for someone to look at it. Calling Pep Boy's / 10/16 - Spoke to Pep Boy's earlier today and they should be getting inside today to look over it. Spoke with Tech prior so Pep Boys knows what the problems are. jchild2 | L23: Yes | N23: Yes | O23: Yes | P23: =IFERROR(VLOOKUP(D23,'TPMS-auto'!A:D, 4,0),"Not-in-TPMS") -> 0008555 | Q23: =IFERROR(VLOOKUP(Table2[[#This Row],[Unit Number]],Ops,3,0),"Not-in-TPMS") -> Monica, Cheryl & Machell | R23: =IFERROR(VLOOKUP(Table2[[#This Row],[Enterprise ID]], 'ExistingRental-12.11'!A:H, 3, 0), "Not Open On 12.11") -> 45905 | S23: =IF(Table2[[#This Row],[Start Rental Date]]="New Rental", "New Rental", "Rental Extension Request") -> Rental Extension Request | T23: =IFERROR(IF(Table2[[#This Row],[Date of this request]]-Table2[[#This Row],[Tech Service Date]]<60, "New Hire Rental", "Truck Breakdown"), "New Hire Rental") -> Truck Breakdown | U23: =IFERROR(VLOOKUP(Table2[[#This Row],[Enterprise ID]], 'ExistingRental-12.11'!A:H, 7, 0), "Not Open On 12.11") -> VAN COUCH | V23: =IFERROR(VLOOKUP(Table2[[#This Row],[Enterprise ID]],'Tech-ServiceDate'!A:B,2,0), "EitherNewHire or Termed") -> 44273
A24: 45919 | B24: 46044 | C24: Aaron Fruchey | D24: AFRUCHE | E24: =TRIM(B24) -> 46044 | F24: =IFERROR(VLOOKUP(D24,'TPMS-auto'!A:J, 10,0), "Not-in-TPMS") -> 9167076508 | G24: =IFERROR(VLOOKUP(D24,'TPMS-auto'!A:J,6,0),"Not-in-TPMS") -> 046044 | H24: 45918 | I24: 520 CONTRA COSTA BLVD, PLEASANT HILL, CA 94523 | J24: Engine made popping noise | K24: Get van repaired and tech out of rental | L24: Yes | N24: Yes | O24: Yes | P24: =IFERROR(VLOOKUP(D24,'TPMS-auto'!A:D, 4,0),"Not-in-TPMS") -> 0008184 | Q24: =IFERROR(VLOOKUP(Table2[[#This Row],[Unit Number]],Ops,3,0),"Not-in-TPMS") -> Carol & Tasha | R24: =IFERROR(VLOOKUP(Table2[[#This Row],[Enterprise ID]], 'ExistingRental-12.11'!A:H, 3, 0), "Not Open On 12.11") -> 45918 | S24: =IF(Table2[[#This Row],[Start Rental Date]]="New Rental", "New Rental", "Rental Extension Request") -> Rental Extension Request | T24: =IFERROR(IF(Table2[[#This Row],[Date of this request]]-Table2[[#This Row],[Tech Service Date]]<60, "New Hire Rental", "Truck Breakdown"), "New Hire Rental") -> Truck Breakdown | U24: =IFERROR(VLOOKUP(Table2[[#This Row],[Enterprise ID]], 'ExistingRental-12.11'!A:H, 7, 0), "Not Open On 12.11") -> AARON FRUCHEY | V24: =IFERROR(VLOOKUP(Table2[[#This Row],[Enterprise ID]],'Tech-ServiceDate'!A:B,2,0), "EitherNewHire or Termed") -> 45008
A25: 45919 | B25: 36516 | C25: Lloyd, George | D25: GLLOYD0 | E25: =TRIM(B25) -> 36516 | F25: =IFERROR(VLOOKUP(D25,'TPMS-auto'!A:J, 10,0), "Not-in-TPMS") -> 6895008458 | G25: =IFERROR(VLOOKUP(D25,'TPMS-auto'!A:J,6,0),"Not-in-TPMS") -> 036516 | H25: 45919 | I25: EXPERT CAR CARE INC., 3016 ALAFAYA TRAIL, OVIEDO FL 32765 | J25: no AC, sliding door in-op and load noise while driving | K25: Get van repaired and tech out of rental | L25: Yes | N25: Yes | O25: Yes | P25: =IFERROR(VLOOKUP(D25,'TPMS-auto'!A:D, 4,0),"Not-in-TPMS") -> 0007435 | Q25: =IFERROR(VLOOKUP(Table2[[#This Row],[Unit Number]],Ops,3,0),"Not-in-TPMS") -> Rob & Andrea | R25: =IFERROR(VLOOKUP(Table2[[#This Row],[Enterprise ID]], 'ExistingRental-12.11'!A:H, 3, 0), "Not Open On 12.11") -> 45986 | S25: =IF(Table2[[#This Row],[Start Rental Date]]="New Rental", "New Rental", "Rental Extension Request") -> Rental Extension Request | T25: =IFERROR(IF(Table2[[#This Row],[Date of this request]]-Table2[[#This Row],[Tech Service Date]]<60, "New Hire Rental", "Truck Breakdown"), "New Hire Rental") -> Truck Breakdown | U25: =IFERROR(VLOOKUP(Table2[[#This Row],[Enterprise ID]], 'ExistingRental-12.11'!A:H, 7, 0), "Not Open On 12.11") -> GEORGE LLOYD | V25: =IFERROR(VLOOKUP(Table2[[#This Row],[Enterprise ID]],'Tech-ServiceDate'!A:B,2,0), "EitherNewHire or Termed") -> 44258
A26: 45919 | B26: 23598 | C26: James Shaub | D26: JSHAUB0 | E26: =TRIM(B26) -> 23598 | F26: =IFERROR(VLOOKUP(D26,'TPMS-auto'!A:J, 10,0), "Not-in-TPMS") -> 7179167608 | G26: =IFERROR(VLOOKUP(D26,'TPMS-auto'!A:J,6,0),"Not-in-TPMS") -> 023598 | H26: 45919 | I26: PEP BOYS 1700 FRUITVILLE PIKE LANCASTER PA 17601 | J26: AC issue | K26: Get van repaired and tech out of rental | L26: Yes | N26: Yes | O26: Yes | P26: =IFERROR(VLOOKUP(D26,'TPMS-auto'!A:D, 4,0),"Not-in-TPMS") -> 0006141 | Q26: =IFERROR(VLOOKUP(Table2[[#This Row],[Unit Number]],Ops,3,0),"Not-in-TPMS") -> Monica, Cheryl & Machell | R26: =IFERROR(VLOOKUP(Table2[[#This Row],[Enterprise ID]], 'ExistingRental-12.11'!A:H, 3, 0), "Not Open On 12.11") -> Not Open On 12.11 | S26: =IF(Table2[[#This Row],[Start Rental Date]]="New Rental", "New Rental", "Rental Extension Request") -> Rental Extension Request | T26: =IFERROR(IF(Table2[[#This Row],[Date of this request]]-Table2[[#This Row],[Tech Service Date]]<60, "New Hire Rental", "Truck Breakdown"), "New Hire Rental") -> Truck Breakdown | U26: =IFERROR(VLOOKUP(Table2[[#This Row],[Enterprise ID]], 'ExistingRental-12.11'!A:H, 7, 0), "Not Open On 12.11") -> Not Open On 12.11 | V26: =IFERROR(VLOOKUP(Table2[[#This Row],[Enterprise ID]],'Tech-ServiceDate'!A:B,2,0), "EitherNewHire or Termed") -> 40583
A27: 45919 | B27: 47109 | C27: JORDAN BARTLET | D27: JBARTLE | E27: =TRIM(B27) -> 47109 | F27: =IFERROR(VLOOKUP(D27,'TPMS-auto'!A:J, 10,0), "Not-in-TPMS") -> 7189082409 | G27: =IFERROR(VLOOKUP(D27,'TPMS-auto'!A:J,6,0),"Not-in-TPMS") -> 047109 | H27: 45882 | I27: Hertz rental since 8/6 - van is repaired and paid vendor: RICHIES CITGO, 1153 WALT WHITMAN RD, MELVILLE NY 11747 | J27: New hire, Not in TPMS | K27: Assign van # 47109 to this tech and move him into it - get him out of the rental by 9/22 | L27: Yes | N27: Yes | O27: Yes | P27: =IFERROR(VLOOKUP(D27,'TPMS-auto'!A:D, 4,0),"Not-in-TPMS") -> 0007744 | Q27: =IFERROR(VLOOKUP(Table2[[#This Row],[Unit Number]],Ops,3,0),"Not-in-TPMS") -> Rob & Andrea | R27: =IFERROR(VLOOKUP(Table2[[#This Row],[Enterprise ID]], 'ExistingRental-12.11'!A:H, 3, 0), "Not Open On 12.11") -> Not Open On 12.11 | S27: =IF(Table2[[#This Row],[Start Rental Date]]="New Rental", "New Rental", "Rental Extension Request") -> Rental Extension Request | T27: =IFERROR(IF(Table2[[#This Row],[Date of this request]]-Table2[[#This Row],[Tech Service Date]]<60, "New Hire Rental", "Truck Breakdown"), "New Hire Rental") -> New Hire Rental | U27: =IFERROR(VLOOKUP(Table2[[#This Row],[Enterprise ID]], 'ExistingRental-12.11'!A:H, 7, 0), "Not Open On 12.11") -> Not Open On 12.11 | V27: =IFERROR(VLOOKUP(Table2[[#This Row],[Enterprise ID]],'Tech-ServiceDate'!A:B,2,0), "EitherNewHire or Termed") -> 45865
A28: 45919 | B28: 46838 | C28: KURTIS ELLINGER | D28: KELLIN | E28: =TRIM(B28) -> 46838 | F28: =IFERROR(VLOOKUP(D28,'TPMS-auto'!A:J, 10,0), "Not-in-TPMS") -> 7403241033 | G28: =IFERROR(VLOOKUP(D28,'TPMS-auto'!A:J,6,0),"Not-in-TPMS") -> 046838 | H28: 45878 | I28: JEFF WYLER COLUMBUS INC, 5885 GENDER RD, CANAL WINCHESTER OH 43110 | J28: Declined repair - reversing decision - will repair | K28: Repair his truck and get him back in it asap | L28: Yes | N28: Yes | O28: Yes | P28: =IFERROR(VLOOKUP(D28,'TPMS-auto'!A:D, 4,0),"Not-in-TPMS") -> 0004766 | Q28: =IFERROR(VLOOKUP(Table2[[#This Row],[Unit Number]],Ops,3,0),"Not-in-TPMS") -> Rob & Andrea | R28: =IFERROR(VLOOKUP(Table2[[#This Row],[Enterprise ID]], 'ExistingRental-12.11'!A:H, 3, 0), "Not Open On 12.11") -> 45916 | S28: =IF(Table2[[#This Row],[Start Rental Date]]="New Rental", "New Rental", "Rental Extension Request") -> Rental Extension Request | T28: =IFERROR(IF(Table2[[#This Row],[Date of this request]]-Table2[[#This Row],[Tech Service Date]]<60, "New Hire Rental", "Truck Breakdown"), "New Hire Rental") -> Truck Breakdown | U28: =IFERROR(VLOOKUP(Table2[[#This Row],[Enterprise ID]], 'ExistingRental-12.11'!A:H, 7, 0), "Not Open On 12.11") -> KURTIS ELLINGER | V28: =IFERROR(VLOOKUP(Table2[[#This Row],[Enterprise ID]],'Tech-ServiceDate'!A:B,2,0), "EitherNewHire or Termed") -> 35957
A29: 45919 | B29: 37424 | C29: PEREZ, JOSEPH | D29: JPEREZ3 | E29: =TRIM(B29) -> 37424 | F29: =IFERROR(VLOOKUP(D29,'TPMS-auto'!A:J, 10,0), "Not-in-TPMS") -> Not-in-TPMS | G29: =IFERROR(VLOOKUP(D29,'TPMS-auto'!A:J,6,0),"Not-in-TPMS") -> Not-in-TPMS | H29: 45849 | I29: Rental is on 37424 but tech is assigned 21192 - 21192 is in the shop | K29: 21192 needs to have decision reversed - install transmission and get it back to the tech asap | L29: Yes | N29: Yes | O29: Yes | P29: =IFERROR(VLOOKUP(D29,'TPMS-auto'!A:D, 4,0),"Not-in-TPMS") -> Not-in-TPMS | Q29: =IFERROR(VLOOKUP(Table2[[#This Row],[Unit Number]],Ops,3,0),"Not-in-TPMS") -> Not-in-TPMS | R29: =IFERROR(VLOOKUP(Table2[[#This Row],[Enterprise ID]], 'ExistingRental-12.11'!A:H, 3, 0), "Not Open On 12.11") -> Not Open On 12.11 | S29: =IF(Table2[[#This Row],[Start Rental Date]]="New Rental", "New Rental", "Rental Extension Request") -> Rental Extension Request | T29: =IFERROR(IF(Table2[[#This Row],[Date of this request]]-Table2[[#This Row],[Tech Service Date]]<60, "New Hire Rental", "Truck Breakdown"), "New Hire Rental") -> New Hire Rental | U29: =IFERROR(VLOOKUP(Table2[[#This Row],[Enterprise ID]], 'ExistingRental-12.11'!A:H, 7, 0), "Not Open On 12.11") -> Not Open On 12.11 | V29: =IFERROR(VLOOKUP(Table2[[#This Row],[Enterprise ID]],'Tech-ServiceDate'!A:B,2,0), "EitherNewHire or Termed") -> EitherNewHire or Termed
A30: 45919 | B30: 36780 | C30: ROBINSON, WALTER | D30: WROBINS | E30: =TRIM(B30) -> 36780 | F30: =IFERROR(VLOOKUP(D30,'TPMS-auto'!A:J, 10,0), "Not-in-TPMS") -> Not-in-TPMS | G30: =IFERROR(VLOOKUP(D30,'TPMS-auto'!A:J,6,0),"Not-in-TPMS") -> Not-in-TPMS | H30: 45849 | I30: In rental - van is in Houston, tech is in Houston - he needs to get out of rental and into the van | J30: AAMCO TOTAL CAR CARE, 10030 VETERANS MEMORIAL, HOUSTON TX 77038 | K30: Assign the van to the tech 36780 - give him time to move into the van asap | L30: Yes | N30: Yes | O30: Yes | P30: =IFERROR(VLOOKUP(D30,'TPMS-auto'!A:D, 4,0),"Not-in-TPMS") -> Not-in-TPMS | Q30: =IFERROR(VLOOKUP(Table2[[#This Row],[Unit Number]],Ops,3,0),"Not-in-TPMS") -> Not-in-TPMS | R30: =IFERROR(VLOOKUP(Table2[[#This Row],[Enterprise ID]], 'ExistingRental-12.11'!A:H, 3, 0), "Not Open On 12.11") -> Not Open On 12.11 | S30: =IF(Table2[[#This Row],[Start Rental Date]]="New Rental", "New Rental", "Rental Extension Request") -> Rental Extension Request | T30: =IFERROR(IF(Table2[[#This Row],[Date of this request]]-Table2[[#This Row],[Tech Service Date]]<60, "New Hire Rental", "Truck Breakdown"), "New Hire Rental") -> New Hire Rental | U30: =IFERROR(VLOOKUP(Table2[[#This Row],[Enterprise ID]], 'ExistingRental-12.11'!A:H, 7, 0), "Not Open On 12.11") -> Not Open On 12.11 | V30: =IFERROR(VLOOKUP(Table2[[#This Row],[Enterprise ID]],'Tech-ServiceDate'!A:B,2,0), "EitherNewHire or Termed") -> EitherNewHire or Termed
A31: 45919 | B31: 22610 | C31: Justin Setlif | D31: JSETLIF | E31: =TRIM(B31) -> 22610 | F31: =IFERROR(VLOOKUP(D31,'TPMS-auto'!A:J, 10,0), "Not-in-TPMS") -> 3367065348 | G31: =IFERROR(VLOOKUP(D31,'TPMS-auto'!A:J,6,0),"Not-in-TPMS") -> 088119 | H31: 45919 | J31: Part time new hire needs rental starting Monday | K31: Needs a permanent van | L31: Yes | N31: Yes | O31: Yes | P31: =IFERROR(VLOOKUP(D31,'TPMS-auto'!A:D, 4,0),"Not-in-TPMS") -> 0008175 | Q31: =IFERROR(VLOOKUP(Table2[[#This Row],[Unit Number]],Ops,3,0),"Not-in-TPMS") -> Rob & Andrea | R31: =IFERROR(VLOOKUP(Table2[[#This Row],[Enterprise ID]], 'ExistingRental-12.11'!A:H, 3, 0), "Not Open On 12.11") -> Not Open On 12.11 | S31: =IF(Table2[[#This Row],[Start Rental Date]]="New Rental", "New Rental", "Rental Extension Request") -> Rental Extension Request | T31: =IFERROR(IF(Table2[[#This Row],[Date of this request]]-Table2[[#This Row],[Tech Service Date]]<60, "New Hire Rental", "Truck Breakdown"), "New Hire Rental") -> New Hire Rental | U31: =IFERROR(VLOOKUP(Table2[[#This Row],[Enterprise ID]], 'ExistingRental-12.11'!A:H, 7, 0), "Not Open On 12.11") -> Not Open On 12.11 | V31: =IFERROR(VLOOKUP(Table2[[#This Row],[Enterprise ID]],'Tech-ServiceDate'!A:B,2,0), "EitherNewHire or Termed") -> 45872
A32: 45919 | B32: 61243 | C32: Fidel Magallanes | D32: FMAGA01 | E32: =TRIM(B32) -> 61243 | F32: =IFERROR(VLOOKUP(D32,'TPMS-auto'!A:J, 10,0), "Not-in-TPMS") -> 8312108140 | G32: =IFERROR(VLOOKUP(D32,'TPMS-auto'!A:J,6,0),"Not-in-TPMS") -> 061243 | H32: 45909 | I32: SALINAS VALLEY FORD/ISUZU, 1100 AUTO CENTER CIR, SALINAS CA 93907 | J32: Trans warranty | K32: Waiting for Dahmer to respond to the warranty request. That was sent off today. NO eta at this time | L32: Yes | N32: Yes | O32: Yes | P32: =IFERROR(VLOOKUP(D32,'TPMS-auto'!A:D, 4,0),"Not-in-TPMS") -> 0008366 | Q32: =IFERROR(VLOOKUP(Table2[[#This Row],[Unit Number]],Ops,3,0),"Not-in-TPMS") -> Carol & Tasha | R32: =IFERROR(VLOOKUP(Table2[[#This Row],[Enterprise ID]], 'ExistingRental-12.11'!A:H, 3, 0), "Not Open On 12.11") -> Not Open On 12.11 | S32: =IF(Table2[[#This Row],[Start Rental Date]]="New Rental", "New Rental", "Rental Extension Request") -> Rental Extension Request | T32: =IFERROR(IF(Table2[[#This Row],[Date of this request]]-Table2[[#This Row],[Tech Service Date]]<60, "New Hire Rental", "Truck Breakdown"), "New Hire Rental") -> Truck Breakdown | U32: =IFERROR(VLOOKUP(Table2[[#This Row],[Enterprise ID]], 'ExistingRental-12.11'!A:H, 7, 0), "Not Open On 12.11") -> Not Open On 12.11 | V32: =IFERROR(VLOOKUP(Table2[[#This Row],[Enterprise ID]],'Tech-ServiceDate'!A:B,2,0), "EitherNewHire or Termed") -> 37903
A33: 45919 | B33: 21207 | C33: Corey Newell | D33: CNEWELL | E33: =TRIM(B33) -> 21207 | F33: =IFERROR(VLOOKUP(D33,'TPMS-auto'!A:J, 10,0), "Not-in-TPMS") -> 2514960693 | G33: =IFERROR(VLOOKUP(D33,'TPMS-auto'!A:J,6,0),"Not-in-TPMS") -> 0 | H33: 45860 | I33: 21207 was updated to MHOWSON on 9/19 | J33: No van assigned in TPMS; Tech is in rental Not seeing tech on New hire sheet | K33: Find a van for this tech | L33: Yes | N33: Yes | O33: Yes | P33: =IFERROR(VLOOKUP(D33,'TPMS-auto'!A:D, 4,0),"Not-in-TPMS") -> 0008035 | Q33: =IFERROR(VLOOKUP(Table2[[#This Row],[Unit Number]],Ops,3,0),"Not-in-TPMS") -> Rob & Andrea | R33: =IFERROR(VLOOKUP(Table2[[#This Row],[Enterprise ID]], 'ExistingRental-12.11'!A:H, 3, 0), "Not Open On 12.11") -> Not Open On 12.11 | S33: =IF(Table2[[#This Row],[Start Rental Date]]="New Rental", "New Rental", "Rental Extension Request") -> Rental Extension Request | T33: =IFERROR(IF(Table2[[#This Row],[Date of this request]]-Table2[[#This Row],[Tech Service Date]]<60, "New Hire Rental", "Truck Breakdown"), "New Hire Rental") -> Truck Breakdown | U33: =IFERROR(VLOOKUP(Table2[[#This Row],[Enterprise ID]], 'ExistingRental-12.11'!A:H, 7, 0), "Not Open On 12.11") -> Not Open On 12.11 | V33: =IFERROR(VLOOKUP(Table2[[#This Row],[Enterprise ID]],'Tech-ServiceDate'!A:B,2,0), "EitherNewHire or Termed") -> 45851
A34: 45919 | B34: 22183 | C34: Robert Mcelwain | D34: RMCELWA | E34: =TRIM(B34) -> 22183 | F34: =IFERROR(VLOOKUP(D34,'TPMS-auto'!A:J, 10,0), "Not-in-TPMS") -> 6622195968 | G34: =IFERROR(VLOOKUP(D34,'TPMS-auto'!A:J,6,0),"Not-in-TPMS") -> 022183 | H34: 45911 | I34: D&S SERVICE CENTER, 5464 CLIFF GOOKIN BLVD, TUPELO MS 38801 | J34: Vas has fuel injector issues, to be repaired under warranty. | K34: ETA 9/26 | L34: Yes | N34: Yes | O34: Yes | P34: =IFERROR(VLOOKUP(D34,'TPMS-auto'!A:D, 4,0),"Not-in-TPMS") -> 0008206 | Q34: =IFERROR(VLOOKUP(Table2[[#This Row],[Unit Number]],Ops,3,0),"Not-in-TPMS") -> Monica, Cheryl & Machell | R34: =IFERROR(VLOOKUP(Table2[[#This Row],[Enterprise ID]], 'ExistingRental-12.11'!A:H, 3, 0), "Not Open On 12.11") -> Not Open On 12.11 | S34: =IF(Table2[[#This Row],[Start Rental Date]]="New Rental", "New Rental", "Rental Extension Request") -> Rental Extension Request | T34: =IFERROR(IF(Table2[[#This Row],[Date of this request]]-Table2[[#This Row],[Tech Service Date]]<60, "New Hire Rental", "Truck Breakdown"), "New Hire Rental") -> Truck Breakdown | U34: =IFERROR(VLOOKUP(Table2[[#This Row],[Enterprise ID]], 'ExistingRental-12.11'!A:H, 7, 0), "Not Open On 12.11") -> Not Open On 12.11 | V34: =IFERROR(VLOOKUP(Table2[[#This Row],[Enterprise ID]],'Tech-ServiceDate'!A:B,2,0), "EitherNewHire or Termed") -> 42457
A35: 45919 | B35: 23945 | C35: COSTELLO, MARSHALL | D35: MCOSTEL | E35: =TRIM(B35) -> 23945 | F35: =IFERROR(VLOOKUP(D35,'TPMS-auto'!A:J, 10,0), "Not-in-TPMS") -> 3028974391 | G35: =IFERROR(VLOOKUP(D35,'TPMS-auto'!A:J,6,0),"Not-in-TPMS") -> 046465 | H35: 45882 | I35: Tech does not have a permanent van assignement - using this van for rental approval | K35: Assign a van to MCOSTEL asap | L35: Yes | N35: Yes | O35: Yes | P35: =IFERROR(VLOOKUP(D35,'TPMS-auto'!A:D, 4,0),"Not-in-TPMS") -> 0007084 | Q35: =IFERROR(VLOOKUP(Table2[[#This Row],[Unit Number]],Ops,3,0),"Not-in-TPMS") -> Monica, Cheryl & Machell | R35: =IFERROR(VLOOKUP(Table2[[#This Row],[Enterprise ID]], 'ExistingRental-12.11'!A:H, 3, 0), "Not Open On 12.11") -> 46000 | S35: =IF(Table2[[#This Row],[Start Rental Date]]="New Rental", "New Rental", "Rental Extension Request") -> Rental Extension Request | T35: =IFERROR(IF(Table2[[#This Row],[Date of this request]]-Table2[[#This Row],[Tech Service Date]]<60, "New Hire Rental", "Truck Breakdown"), "New Hire Rental") -> New Hire Rental | U35: =IFERROR(VLOOKUP(Table2[[#This Row],[Enterprise ID]], 'ExistingRental-12.11'!A:H, 7, 0), "Not Open On 12.11") -> MARSHALL COSTELLO | V35: =IFERROR(VLOOKUP(Table2[[#This Row],[Enterprise ID]],'Tech-ServiceDate'!A:B,2,0), "EitherNewHire or Termed") -> 45886
A36: 45919 | B36: 23022 | C36: BARBA, CHRISTOPHE | D36: CBARBA2 | E36: =TRIM(B36) -> 23022 | F36: =IFERROR(VLOOKUP(D36,'TPMS-auto'!A:J, 10,0), "Not-in-TPMS") -> 9098466848 | G36: =IFERROR(VLOOKUP(D36,'TPMS-auto'!A:J,6,0),"Not-in-TPMS") -> 023022 | H36: 45915 | I36: Tech broke down - just received the van - needs brakes and has been approved | K36: CBARBA2 - rental started 9/15 - van needs brakes - at Pep Boys - estimate approved - | L36: Yes | N36: Yes | O36: Yes | P36: =IFERROR(VLOOKUP(D36,'TPMS-auto'!A:D, 4,0),"Not-in-TPMS") -> 0007108 | Q36: =IFERROR(VLOOKUP(Table2[[#This Row],[Unit Number]],Ops,3,0),"Not-in-TPMS") -> Carol & Tasha | R36: =IFERROR(VLOOKUP(Table2[[#This Row],[Enterprise ID]], 'ExistingRental-12.11'!A:H, 3, 0), "Not Open On 12.11") -> Not Open On 12.11 | S36: =IF(Table2[[#This Row],[Start Rental Date]]="New Rental", "New Rental", "Rental Extension Request") -> Rental Extension Request | T36: =IFERROR(IF(Table2[[#This Row],[Date of this request]]-Table2[[#This Row],[Tech Service Date]]<60, "New Hire Rental", "Truck Breakdown"), "New Hire Rental") -> Truck Breakdown | U36: =IFERROR(VLOOKUP(Table2[[#This Row],[Enterprise ID]], 'ExistingRental-12.11'!A:H, 7, 0), "Not Open On 12.11") -> Not Open On 12.11 | V36: =IFERROR(VLOOKUP(Table2[[#This Row],[Enterprise ID]],'Tech-ServiceDate'!A:B,2,0), "EitherNewHire or Termed") -> 31979
A37: 45919 | B37: 36222 | C37: Roberto Ayala | D37: RAYALA1 | E37: =TRIM(B37) -> 36222 | F37: =IFERROR(VLOOKUP(D37,'TPMS-auto'!A:J, 10,0), "Not-in-TPMS") -> Not-in-TPMS | G37: =IFERROR(VLOOKUP(D37,'TPMS-auto'!A:J,6,0),"Not-in-TPMS") -> Not-in-TPMS | H37: 45828 | I37: Tech is assigned to 61513 - that was the van he was driving when the engine blew - no oil. $9200 repair was declined in June | J37: Tech had a declined repair and no solution for a new van - we must find a solution before a repair is declined. | K37: Find a van for RAYALA1 and get him out of the rental | L37: Yes | N37: Yes | O37: Yes | P37: =IFERROR(VLOOKUP(D37,'TPMS-auto'!A:D, 4,0),"Not-in-TPMS") -> Not-in-TPMS | Q37: =IFERROR(VLOOKUP(Table2[[#This Row],[Unit Number]],Ops,3,0),"Not-in-TPMS") -> Not-in-TPMS | R37: =IFERROR(VLOOKUP(Table2[[#This Row],[Enterprise ID]], 'ExistingRental-12.11'!A:H, 3, 0), "Not Open On 12.11") -> Not Open On 12.11 | S37: =IF(Table2[[#This Row],[Start Rental Date]]="New Rental", "New Rental", "Rental Extension Request") -> Rental Extension Request | T37: =IFERROR(IF(Table2[[#This Row],[Date of this request]]-Table2[[#This Row],[Tech Service Date]]<60, "New Hire Rental", "Truck Breakdown"), "New Hire Rental") -> New Hire Rental | U37: =IFERROR(VLOOKUP(Table2[[#This Row],[Enterprise ID]], 'ExistingRental-12.11'!A:H, 7, 0), "Not Open On 12.11") -> Not Open On 12.11 | V37: =IFERROR(VLOOKUP(Table2[[#This Row],[Enterprise ID]],'Tech-ServiceDate'!A:B,2,0), "EitherNewHire or Termed") -> EitherNewHire or Termed
A38: 45922 | B38: 61208 | C38: Alberto Gonzalez | D38: AGONZA4 | E38: =TRIM(B38) -> 61208 | F38: =IFERROR(VLOOKUP(D38,'TPMS-auto'!A:J, 10,0), "Not-in-TPMS") -> 8167249181 | G38: =IFERROR(VLOOKUP(D38,'TPMS-auto'!A:J,6,0),"Not-in-TPMS") -> 061208 | H38: 45856 | I38: PEP BOYS 6725 MCCART ST FORT WORTH TX 76133 | J38: Declined repair | K38: John - Jen: Declined repair on 7/23 - need a new truck assignment. AGONZA4 is in rental as of 7/18 - needs a permanent truck assigned asap | L38: Yes | N38: Yes | O38: Yes | P38: =IFERROR(VLOOKUP(D38,'TPMS-auto'!A:D, 4,0),"Not-in-TPMS") -> 0007995 | Q38: =IFERROR(VLOOKUP(Table2[[#This Row],[Unit Number]],Ops,3,0),"Not-in-TPMS") -> Carol & Tasha | R38: =IFERROR(VLOOKUP(Table2[[#This Row],[Enterprise ID]], 'ExistingRental-12.11'!A:H, 3, 0), "Not Open On 12.11") -> 45887 | S38: =IF(Table2[[#This Row],[Start Rental Date]]="New Rental", "New Rental", "Rental Extension Request") -> Rental Extension Request | T38: =IFERROR(IF(Table2[[#This Row],[Date of this request]]-Table2[[#This Row],[Tech Service Date]]<60, "New Hire Rental", "Truck Breakdown"), "New Hire Rental") -> Truck Breakdown | U38: =IFERROR(VLOOKUP(Table2[[#This Row],[Enterprise ID]], 'ExistingRental-12.11'!A:H, 7, 0), "Not Open On 12.11") -> ALBERTO GONZALEZ | V38: =IFERROR(VLOOKUP(Table2[[#This Row],[Enterprise ID]],'Tech-ServiceDate'!A:B,2,0), "EitherNewHire or Termed") -> 36283
A39: 45922 | B39: 36295 | C39: EMERSON, ALLAN | D39: AEMERSO | E39: =TRIM(B39) -> 36295 | F39: =IFERROR(VLOOKUP(D39,'TPMS-auto'!A:J, 10,0), "Not-in-TPMS") -> 5139570009 | G39: =IFERROR(VLOOKUP(D39,'TPMS-auto'!A:J,6,0),"Not-in-TPMS") -> 036295 | H39: 45908 | I39: FIRESTONE COMPLETE AUTO CARE, 8045 ARBOR SQUARE DR, MASON OH 45040 | J39: Van picked up, rental still open | K39: Decline rental renewal until technician reports why they haven't gotten back in their new van | L39: Yes | N39: Yes | O39: Yes | P39: =IFERROR(VLOOKUP(D39,'TPMS-auto'!A:D, 4,0),"Not-in-TPMS") -> 0004766 | Q39: =IFERROR(VLOOKUP(Table2[[#This Row],[Unit Number]],Ops,3,0),"Not-in-TPMS") -> Rob & Andrea | R39: =IFERROR(VLOOKUP(Table2[[#This Row],[Enterprise ID]], 'ExistingRental-12.11'!A:H, 3, 0), "Not Open On 12.11") -> 45908 | S39: =IF(Table2[[#This Row],[Start Rental Date]]="New Rental", "New Rental", "Rental Extension Request") -> Rental Extension Request | T39: =IFERROR(IF(Table2[[#This Row],[Date of this request]]-Table2[[#This Row],[Tech Service Date]]<60, "New Hire Rental", "Truck Breakdown"), "New Hire Rental") -> Truck Breakdown | U39: =IFERROR(VLOOKUP(Table2[[#This Row],[Enterprise ID]], 'ExistingRental-12.11'!A:H, 7, 0), "Not Open On 12.11") -> ALLAN EMERSON | V39: =IFERROR(VLOOKUP(Table2[[#This Row],[Enterprise ID]],'Tech-ServiceDate'!A:B,2,0), "EitherNewHire or Termed") -> 44539
A40: 45922 | B40: 37139 | C40: Anthony Parson | D40: APARSO0 | E40: =TRIM(B40) -> 37139 | F40: =IFERROR(VLOOKUP(D40,'TPMS-auto'!A:J, 10,0), "Not-in-TPMS") -> 3042209563 | G40: =IFERROR(VLOOKUP(D40,'TPMS-auto'!A:J,6,0),"Not-in-TPMS") -> 037139 | H40: 45846 | I40: EATON CHEVROLET BUICK & GMC, 527 W MADISON ST, HOUSTON MS 38851 | J40: Trans warrranty - APARSO0 - in rental since 7/8 - van is tat Eaton Chevrolet - warranty transmission repair - they have taken 2 months and still not approved by GM for replacement of the transmission under warranty.. | K40: Move the van to another shop - repair it and ask Holman to get our money back from Eaton Chevrolet | L40: Yes | N40: Yes | O40: Yes | P40: =IFERROR(VLOOKUP(D40,'TPMS-auto'!A:D, 4,0),"Not-in-TPMS") -> 0008206 | Q40: =IFERROR(VLOOKUP(Table2[[#This Row],[Unit Number]],Ops,3,0),"Not-in-TPMS") -> Monica, Cheryl & Machell | R40: =IFERROR(VLOOKUP(Table2[[#This Row],[Enterprise ID]], 'ExistingRental-12.11'!A:H, 3, 0), "Not Open On 12.11") -> 45846 | S40: =IF(Table2[[#This Row],[Start Rental Date]]="New Rental", "New Rental", "Rental Extension Request") -> Rental Extension Request | T40: =IFERROR(IF(Table2[[#This Row],[Date of this request]]-Table2[[#This Row],[Tech Service Date]]<60, "New Hire Rental", "Truck Breakdown"), "New Hire Rental") -> Truck Breakdown | U40: =IFERROR(VLOOKUP(Table2[[#This Row],[Enterprise ID]], 'ExistingRental-12.11'!A:H, 7, 0), "Not Open On 12.11") -> ANTHONY PARSON | V40: =IFERROR(VLOOKUP(Table2[[#This Row],[Enterprise ID]],'Tech-ServiceDate'!A:B,2,0), "EitherNewHire or Termed") -> 43782
A41: 45922 | B41: 46775 | C41: Cedric Thomas | D41: CTHOMAS | E41: =TRIM(B41) -> 46775 | F41: =IFERROR(VLOOKUP(D41,'TPMS-auto'!A:J, 10,0), "Not-in-TPMS") -> 9105391963 | G41: =IFERROR(VLOOKUP(D41,'TPMS-auto'!A:J,6,0),"Not-in-TPMS") -> 046775 | H41: 45860 | I41: PEP BOYS 1490 US HWY 70 W GARNER NC 27529 | J41: Van is not in TPMS | K41: New hire - on route on 8/4 with no van assignment - Jen and John : Need a van assigned asap | L41: Yes | N41: Yes | O41: Yes | P41: =IFERROR(VLOOKUP(D41,'TPMS-auto'!A:D, 4,0),"Not-in-TPMS") -> 0008175 | Q41: =IFERROR(VLOOKUP(Table2[[#This Row],[Unit Number]],Ops,3,0),"Not-in-TPMS") -> Rob & Andrea | R41: =IFERROR(VLOOKUP(Table2[[#This Row],[Enterprise ID]], 'ExistingRental-12.11'!A:H, 3, 0), "Not Open On 12.11") -> 45861 | S41: =IF(Table2[[#This Row],[Start Rental Date]]="New Rental", "New Rental", "Rental Extension Request") -> Rental Extension Request | T41: =IFERROR(IF(Table2[[#This Row],[Date of this request]]-Table2[[#This Row],[Tech Service Date]]<60, "New Hire Rental", "Truck Breakdown"), "New Hire Rental") -> Truck Breakdown | U41: =IFERROR(VLOOKUP(Table2[[#This Row],[Enterprise ID]], 'ExistingRental-12.11'!A:H, 7, 0), "Not Open On 12.11") -> CEDRIC THOMAS | V41: =IFERROR(VLOOKUP(Table2[[#This Row],[Enterprise ID]],'Tech-ServiceDate'!A:B,2,0), "EitherNewHire or Termed") -> 45851
A42: 45922 | B42: 23150 | C42: JACKSON, DAVIDW | D42: DJACKS2 | E42: =TRIM(B42) -> 23150 | F42: =IFERROR(VLOOKUP(D42,'TPMS-auto'!A:J, 10,0), "Not-in-TPMS") -> 6019780048 | G42: =IFERROR(VLOOKUP(D42,'TPMS-auto'!A:J,6,0),"Not-in-TPMS") -> 047164 | H42: 45883 | J42: Van is not in TPMS | K42: DJACKS2 - new hire in rental since 8/14/2025 - tech needs a permanent van assignment asap - Tech on Route 8/25 | L42: Yes | N42: Yes | O42: Yes | P42: =IFERROR(VLOOKUP(D42,'TPMS-auto'!A:D, 4,0),"Not-in-TPMS") -> 0008206 | Q42: =IFERROR(VLOOKUP(Table2[[#This Row],[Unit Number]],Ops,3,0),"Not-in-TPMS") -> Monica, Cheryl & Machell | R42: =IFERROR(VLOOKUP(Table2[[#This Row],[Enterprise ID]], 'ExistingRental-12.11'!A:H, 3, 0), "Not Open On 12.11") -> 45867 | S42: =IF(Table2[[#This Row],[Start Rental Date]]="New Rental", "New Rental", "Rental Extension Request") -> Rental Extension Request | T42: =IFERROR(IF(Table2[[#This Row],[Date of this request]]-Table2[[#This Row],[Tech Service Date]]<60, "New Hire Rental", "Truck Breakdown"), "New Hire Rental") -> New Hire Rental | U42: =IFERROR(VLOOKUP(Table2[[#This Row],[Enterprise ID]], 'ExistingRental-12.11'!A:H, 7, 0), "Not Open On 12.11") -> DAVID JACKSON | V42: =IFERROR(VLOOKUP(Table2[[#This Row],[Enterprise ID]],'Tech-ServiceDate'!A:B,2,0), "EitherNewHire or Termed") -> 45872
A43: 45922 | B43: 21537 | C43: BANKSTON, DONNIE | D43: DBANKST | E43: =TRIM(B43) -> 21537 | F43: =IFERROR(VLOOKUP(D43,'TPMS-auto'!A:J, 10,0), "Not-in-TPMS") -> 9854033640 | G43: =IFERROR(VLOOKUP(D43,'TPMS-auto'!A:J,6,0),"Not-in-TPMS") -> 037167 | H43: 45859 | K43: DBANKST - in rental since 7/21/2025 - Van repair was declined - tech needs a replacement van assignment asap | L43: Yes | N43: Yes | O43: Yes | P43: =IFERROR(VLOOKUP(D43,'TPMS-auto'!A:D, 4,0),"Not-in-TPMS") -> 0008206 | Q43: =IFERROR(VLOOKUP(Table2[[#This Row],[Unit Number]],Ops,3,0),"Not-in-TPMS") -> Monica, Cheryl & Machell | R43: =IFERROR(VLOOKUP(Table2[[#This Row],[Enterprise ID]], 'ExistingRental-12.11'!A:H, 3, 0), "Not Open On 12.11") -> Not Open On 12.11 | S43: =IF(Table2[[#This Row],[Start Rental Date]]="New Rental", "New Rental", "Rental Extension Request") -> Rental Extension Request | T43: =IFERROR(IF(Table2[[#This Row],[Date of this request]]-Table2[[#This Row],[Tech Service Date]]<60, "New Hire Rental", "Truck Breakdown"), "New Hire Rental") -> Truck Breakdown | U43: =IFERROR(VLOOKUP(Table2[[#This Row],[Enterprise ID]], 'ExistingRental-12.11'!A:H, 7, 0), "Not Open On 12.11") -> Not Open On 12.11 | V43: =IFERROR(VLOOKUP(Table2[[#This Row],[Enterprise ID]],'Tech-ServiceDate'!A:B,2,0), "EitherNewHire or Termed") -> 36976
A44: 45922 | B44: 46677 | C44: PINK, DWIGHT | D44: DPINK2 | E44: =TRIM(B44) -> 46677 | F44: =IFERROR(VLOOKUP(D44,'TPMS-auto'!A:J, 10,0), "Not-in-TPMS") -> 5619005962 | G44: =IFERROR(VLOOKUP(D44,'TPMS-auto'!A:J,6,0),"Not-in-TPMS") -> 046677 | H44: 45908 | I44: PEP BOYS 800 N MILITARY TRAIL WEST PALM BEACH FL 33415 | J44: Additional work approved on 9/15 | K44: DPINK2 - in rental since 9/8 - PO approved for Pep Boys to repair on 9/15 - need to get it repaired (Rob Anderson) | L44: Yes | N44: Yes | O44: Yes | P44: =IFERROR(VLOOKUP(D44,'TPMS-auto'!A:D, 4,0),"Not-in-TPMS") -> 0007435 | Q44: =IFERROR(VLOOKUP(Table2[[#This Row],[Unit Number]],Ops,3,0),"Not-in-TPMS") -> Rob & Andrea | R44: =IFERROR(VLOOKUP(Table2[[#This Row],[Enterprise ID]], 'ExistingRental-12.11'!A:H, 3, 0), "Not Open On 12.11") -> 45975 | S44: =IF(Table2[[#This Row],[Start Rental Date]]="New Rental", "New Rental", "Rental Extension Request") -> Rental Extension Request | T44: =IFERROR(IF(Table2[[#This Row],[Date of this request]]-Table2[[#This Row],[Tech Service Date]]<60, "New Hire Rental", "Truck Breakdown"), "New Hire Rental") -> Truck Breakdown | U44: =IFERROR(VLOOKUP(Table2[[#This Row],[Enterprise ID]], 'ExistingRental-12.11'!A:H, 7, 0), "Not Open On 12.11") -> DWIGHT PINK | V44: =IFERROR(VLOOKUP(Table2[[#This Row],[Enterprise ID]],'Tech-ServiceDate'!A:B,2,0), "EitherNewHire or Termed") -> 36983
A45: 45922 | B45: 21252 | C45: Gary Riggins | D45: GRIGGI1 | E45: =TRIM(B45) -> 21252 | F45: =IFERROR(VLOOKUP(D45,'TPMS-auto'!A:J, 10,0), "Not-in-TPMS") -> 4083090972 | G45: =IFERROR(VLOOKUP(D45,'TPMS-auto'!A:J,6,0),"Not-in-TPMS") -> 021252 | H45: 45895 | I45: CAPITOL CHEVROLET INC, 905 CAPITOL EXPY AUTO MALL, SAN JOSE CA 95136 | J45: Rob has issues with this dealership - it is there because of warranty on prior transmission replacement | K45: Get van repaired or moved - discuss with Holman - first repair was on 8/23, never completed, new PO on 9/22 - shop is unresponsive | L45: Yes | N45: Yes | O45: Yes | P45: =IFERROR(VLOOKUP(D45,'TPMS-auto'!A:D, 4,0),"Not-in-TPMS") -> 0008184 | Q45: =IFERROR(VLOOKUP(Table2[[#This Row],[Unit Number]],Ops,3,0),"Not-in-TPMS") -> Carol & Tasha | R45: =IFERROR(VLOOKUP(Table2[[#This Row],[Enterprise ID]], 'ExistingRental-12.11'!A:H, 3, 0), "Not Open On 12.11") -> Not Open On 12.11 | S45: =IF(Table2[[#This Row],[Start Rental Date]]="New Rental", "New Rental", "Rental Extension Request") -> Rental Extension Request | T45: =IFERROR(IF(Table2[[#This Row],[Date of this request]]-Table2[[#This Row],[Tech Service Date]]<60, "New Hire Rental", "Truck Breakdown"), "New Hire Rental") -> Truck Breakdown | U45: =IFERROR(VLOOKUP(Table2[[#This Row],[Enterprise ID]], 'ExistingRental-12.11'!A:H, 7, 0), "Not Open On 12.11") -> Not Open On 12.11 | V45: =IFERROR(VLOOKUP(Table2[[#This Row],[Enterprise ID]],'Tech-ServiceDate'!A:B,2,0), "EitherNewHire or Termed") -> 43241
A46: 45922 | B46: 61308 | C46: Hamayoon Azimi | D46: HAZIMI | E46: =TRIM(B46) -> 61308 | F46: =IFERROR(VLOOKUP(D46,'TPMS-auto'!A:J, 10,0), "Not-in-TPMS") -> 3013791012 | G46: =IFERROR(VLOOKUP(D46,'TPMS-auto'!A:J,6,0),"Not-in-TPMS") -> 061308 | H46: 45875 | I46: PEP BOYS, 1641 WIGGLESWORTH WAY, WOODBRIDGE VA 22191 | J46: Sliding door handle is broken eta 9/25 all other repairs have been completed | K46: Get van repaired - can he use it without the handle? | L46: Yes | N46: Yes | O46: Yes | P46: =IFERROR(VLOOKUP(D46,'TPMS-auto'!A:D, 4,0),"Not-in-TPMS") -> 0007084 | Q46: =IFERROR(VLOOKUP(Table2[[#This Row],[Unit Number]],Ops,3,0),"Not-in-TPMS") -> Monica, Cheryl & Machell | R46: =IFERROR(VLOOKUP(Table2[[#This Row],[Enterprise ID]], 'ExistingRental-12.11'!A:H, 3, 0), "Not Open On 12.11") -> 45964 | S46: =IF(Table2[[#This Row],[Start Rental Date]]="New Rental", "New Rental", "Rental Extension Request") -> Rental Extension Request | T46: =IFERROR(IF(Table2[[#This Row],[Date of this request]]-Table2[[#This Row],[Tech Service Date]]<60, "New Hire Rental", "Truck Breakdown"), "New Hire Rental") -> Truck Breakdown | U46: =IFERROR(VLOOKUP(Table2[[#This Row],[Enterprise ID]], 'ExistingRental-12.11'!A:H, 7, 0), "Not Open On 12.11") -> HAMAYOON AZIMI | V46: =IFERROR(VLOOKUP(Table2[[#This Row],[Enterprise ID]],'Tech-ServiceDate'!A:B,2,0), "EitherNewHire or Termed") -> 42772
A47: 45922 | B47: 61705 | C47: GONZALEZ, HUGO | D47: HGONZA2 | E47: =TRIM(B47) -> 61705 | F47: =IFERROR(VLOOKUP(D47,'TPMS-auto'!A:J, 10,0), "Not-in-TPMS") -> 9158614306 | G47: =IFERROR(VLOOKUP(D47,'TPMS-auto'!A:J,6,0),"Not-in-TPMS") -> 061705 | H47: 45896 | I47: AAMCO TOTAL CAR CARE, 1407 LOMALAND DR, #102, EL PASO TX 79935 | J47: AAMCO repair approved on 9/5/2025 - is van ready? | K47: Van needs to be repaired and picked up - Rob to follow up with shop | L47: Yes | N47: No | O47: Yes | P47: =IFERROR(VLOOKUP(D47,'TPMS-auto'!A:D, 4,0),"Not-in-TPMS") -> 0008147 | Q47: =IFERROR(VLOOKUP(Table2[[#This Row],[Unit Number]],Ops,3,0),"Not-in-TPMS") -> Carol & Tasha | R47: =IFERROR(VLOOKUP(Table2[[#This Row],[Enterprise ID]], 'ExistingRental-12.11'!A:H, 3, 0), "Not Open On 12.11") -> Not Open On 12.11 | S47: =IF(Table2[[#This Row],[Start Rental Date]]="New Rental", "New Rental", "Rental Extension Request") -> Rental Extension Request | T47: =IFERROR(IF(Table2[[#This Row],[Date of this request]]-Table2[[#This Row],[Tech Service Date]]<60, "New Hire Rental", "Truck Breakdown"), "New Hire Rental") -> Truck Breakdown | U47: =IFERROR(VLOOKUP(Table2[[#This Row],[Enterprise ID]], 'ExistingRental-12.11'!A:H, 7, 0), "Not Open On 12.11") -> Not Open On 12.11 | V47: =IFERROR(VLOOKUP(Table2[[#This Row],[Enterprise ID]],'Tech-ServiceDate'!A:B,2,0), "EitherNewHire or Termed") -> 44812
A48: 45922 | B48: 47330 | C48: James Juhasz | D48: JJUHASZ | E48: =TRIM(B48) -> 47330 | F48: =IFERROR(VLOOKUP(D48,'TPMS-auto'!A:J, 10,0), "Not-in-TPMS") -> 7326195164 | G48: =IFERROR(VLOOKUP(D48,'TPMS-auto'!A:J,6,0),"Not-in-TPMS") -> 047330 | H48: 45920 | I48: AAMCO 545 ST HWY 18 , EAST BRUNSWICK, NJ. | J48: Trans issue, trans is under warranty | K48: JJUHAZ - in rental since 9/22 - no estimate pending, towed on 9/20 - what is the repair needed and where is the van? | L48: Yes | N48: Yes | O48: Yes | P48: =IFERROR(VLOOKUP(D48,'TPMS-auto'!A:D, 4,0),"Not-in-TPMS") -> 0008380 | Q48: =IFERROR(VLOOKUP(Table2[[#This Row],[Unit Number]],Ops,3,0),"Not-in-TPMS") -> Rob & Andrea | R48: =IFERROR(VLOOKUP(Table2[[#This Row],[Enterprise ID]], 'ExistingRental-12.11'!A:H, 3, 0), "Not Open On 12.11") -> Not Open On 12.11 | S48: =IF(Table2[[#This Row],[Start Rental Date]]="New Rental", "New Rental", "Rental Extension Request") -> Rental Extension Request | T48: =IFERROR(IF(Table2[[#This Row],[Date of this request]]-Table2[[#This Row],[Tech Service Date]]<60, "New Hire Rental", "Truck Breakdown"), "New Hire Rental") -> Truck Breakdown | U48: =IFERROR(VLOOKUP(Table2[[#This Row],[Enterprise ID]], 'ExistingRental-12.11'!A:H, 7, 0), "Not Open On 12.11") -> Not Open On 12.11 | V48: =IFERROR(VLOOKUP(Table2[[#This Row],[Enterprise ID]],'Tech-ServiceDate'!A:B,2,0), "EitherNewHire or Termed") -> 40840
A49: 45922 | B49: 21264 | C49: Jose Lopez | D49: JLOPEZ0 | E49: =TRIM(B49) -> 21264 | F49: =IFERROR(VLOOKUP(D49,'TPMS-auto'!A:J, 10,0), "Not-in-TPMS") -> 2108753317 | G49: =IFERROR(VLOOKUP(D49,'TPMS-auto'!A:J,6,0),"Not-in-TPMS") -> 021264 | H49: 45875 | I49: MIDAS #2279, 16337 SAN PEDRO AVE, SAN ANTONIO TX 78232 | J49: Repair was approved on 8/6 - why hasn't the tech picked up the van? | K49: Tech pick up the van asap | L49: Yes | N49: No | O49: Yes | P49: =IFERROR(VLOOKUP(D49,'TPMS-auto'!A:D, 4,0),"Not-in-TPMS") -> 0008147 | Q49: =IFERROR(VLOOKUP(Table2[[#This Row],[Unit Number]],Ops,3,0),"Not-in-TPMS") -> Carol & Tasha | R49: =IFERROR(VLOOKUP(Table2[[#This Row],[Enterprise ID]], 'ExistingRental-12.11'!A:H, 3, 0), "Not Open On 12.11") -> 45875 | S49: =IF(Table2[[#This Row],[Start Rental Date]]="New Rental", "New Rental", "Rental Extension Request") -> Rental Extension Request | T49: =IFERROR(IF(Table2[[#This Row],[Date of this request]]-Table2[[#This Row],[Tech Service Date]]<60, "New Hire Rental", "Truck Breakdown"), "New Hire Rental") -> Truck Breakdown | U49: =IFERROR(VLOOKUP(Table2[[#This Row],[Enterprise ID]], 'ExistingRental-12.11'!A:H, 7, 0), "Not Open On 12.11") -> JOSE LOPEZ | V49: =IFERROR(VLOOKUP(Table2[[#This Row],[Enterprise ID]],'Tech-ServiceDate'!A:B,2,0), "EitherNewHire or Termed") -> 45592
A50: 45922 | B50: 36605 | C50: MUDGETT, JOSHUA | D50: JMUDGET | E50: =TRIM(B50) -> 36605 | F50: =IFERROR(VLOOKUP(D50,'TPMS-auto'!A:J, 10,0), "Not-in-TPMS") -> 7156062268 | G50: =IFERROR(VLOOKUP(D50,'TPMS-auto'!A:J,6,0),"Not-in-TPMS") -> 036605 | H50: 45897 | J50: JMUDGET - in rental since 8/28 - van repair was approved for $2969 on 9/19 - need van repaired and tech out of rental | K50: Check on van repair status | L50: Yes | N50: Yes | O50: Yes | P50: =IFERROR(VLOOKUP(D50,'TPMS-auto'!A:D, 4,0),"Not-in-TPMS") -> 0008555 | Q50: =IFERROR(VLOOKUP(Table2[[#This Row],[Unit Number]],Ops,3,0),"Not-in-TPMS") -> Monica, Cheryl & Machell | R50: =IFERROR(VLOOKUP(Table2[[#This Row],[Enterprise ID]], 'ExistingRental-12.11'!A:H, 3, 0), "Not Open On 12.11") -> Not Open On 12.11 | S50: =IF(Table2[[#This Row],[Start Rental Date]]="New Rental", "New Rental", "Rental Extension Request") -> Rental Extension Request | T50: =IFERROR(IF(Table2[[#This Row],[Date of this request]]-Table2[[#This Row],[Tech Service Date]]<60, "New Hire Rental", "Truck Breakdown"), "New Hire Rental") -> Truck Breakdown | U50: =IFERROR(VLOOKUP(Table2[[#This Row],[Enterprise ID]], 'ExistingRental-12.11'!A:H, 7, 0), "Not Open On 12.11") -> Not Open On 12.11 | V50: =IFERROR(VLOOKUP(Table2[[#This Row],[Enterprise ID]],'Tech-ServiceDate'!A:B,2,0), "EitherNewHire or Termed") -> 45001
A51: 45922 | B51: 61212 | C51: Latargi Fowler | D51: LFOWLER | E51: =TRIM(B51) -> 61212 | F51: =IFERROR(VLOOKUP(D51,'TPMS-auto'!A:J, 10,0), "Not-in-TPMS") -> 4698822214 | G51: =IFERROR(VLOOKUP(D51,'TPMS-auto'!A:J,6,0),"Not-in-TPMS") -> 061212 | H51: 45854 | J51: Declined repair | K51: Tech needs a replacement van assigned to him and moved to his location (Jennifer Dyer, John Childres)? | L51: Yes | N51: Yes | O51: Yes | P51: =IFERROR(VLOOKUP(D51,'TPMS-auto'!A:D, 4,0),"Not-in-TPMS") -> 0007995 | Q51: =IFERROR(VLOOKUP(Table2[[#This Row],[Unit Number]],Ops,3,0),"Not-in-TPMS") -> Carol & Tasha | R51: =IFERROR(VLOOKUP(Table2[[#This Row],[Enterprise ID]], 'ExistingRental-12.11'!A:H, 3, 0), "Not Open On 12.11") -> Not Open On 12.11 | S51: =IF(Table2[[#This Row],[Start Rental Date]]="New Rental", "New Rental", "Rental Extension Request") -> Rental Extension Request | T51: =IFERROR(IF(Table2[[#This Row],[Date of this request]]-Table2[[#This Row],[Tech Service Date]]<60, "New Hire Rental", "Truck Breakdown"), "New Hire Rental") -> Truck Breakdown | U51: =IFERROR(VLOOKUP(Table2[[#This Row],[Enterprise ID]], 'ExistingRental-12.11'!A:H, 7, 0), "Not Open On 12.11") -> Not Open On 12.11 | V51: =IFERROR(VLOOKUP(Table2[[#This Row],[Enterprise ID]],'Tech-ServiceDate'!A:B,2,0), "EitherNewHire or Termed") -> 45438
A52: 45922 | B52: 6588 | C52: ADAMS, MARK | D52: MADAMS0 | E52: =TRIM(B52) -> 6588 | F52: =IFERROR(VLOOKUP(D52,'TPMS-auto'!A:J, 10,0), "Not-in-TPMS") -> 8654040116 | G52: =IFERROR(VLOOKUP(D52,'TPMS-auto'!A:J,6,0),"Not-in-TPMS") -> 022161 | H52: 45875 | J52: Declined repair | K52: MADAMS0 - in rental since 8/6 - needs a replacement van asap - John / Jen - get the tech a replacement asap | L52: Yes | N52: Yes | O52: Yes | P52: =IFERROR(VLOOKUP(D52,'TPMS-auto'!A:D, 4,0),"Not-in-TPMS") -> 0004766 | Q52: =IFERROR(VLOOKUP(Table2[[#This Row],[Unit Number]],Ops,3,0),"Not-in-TPMS") -> Rob & Andrea | R52: =IFERROR(VLOOKUP(Table2[[#This Row],[Enterprise ID]], 'ExistingRental-12.11'!A:H, 3, 0), "Not Open On 12.11") -> 45938 | S52: =IF(Table2[[#This Row],[Start Rental Date]]="New Rental", "New Rental", "Rental Extension Request") -> Rental Extension Request | T52: =IFERROR(IF(Table2[[#This Row],[Date of this request]]-Table2[[#This Row],[Tech Service Date]]<60, "New Hire Rental", "Truck Breakdown"), "New Hire Rental") -> Truck Breakdown | U52: =IFERROR(VLOOKUP(Table2[[#This Row],[Enterprise ID]], 'ExistingRental-12.11'!A:H, 7, 0), "Not Open On 12.11") -> MARK ADAMS JR | V52: =IFERROR(VLOOKUP(Table2[[#This Row],[Enterprise ID]],'Tech-ServiceDate'!A:B,2,0), "EitherNewHire or Termed") -> 45655
A53: 45922 | B53: 22368 | C53: Mark Polite | D53: MPOLITE | E53: =TRIM(B53) -> 22368 | F53: =IFERROR(VLOOKUP(D53,'TPMS-auto'!A:J, 10,0), "Not-in-TPMS") -> 5746214542 | G53: =IFERROR(VLOOKUP(D53,'TPMS-auto'!A:J,6,0),"Not-in-TPMS") -> 022368 | H53: 45911 | I53: New hire in rental - started 9/2 - on route 9/23 - | J53: Rental should not be assigned to this truck | K53: John - Jen - what is the status of getting the van to the tech? | L53: Yes | N53: Yes | O53: Yes | P53: =IFERROR(VLOOKUP(D53,'TPMS-auto'!A:D, 4,0),"Not-in-TPMS") -> 0008096 | Q53: =IFERROR(VLOOKUP(Table2[[#This Row],[Unit Number]],Ops,3,0),"Not-in-TPMS") -> Monica, Cheryl & Machell | R53: =IFERROR(VLOOKUP(Table2[[#This Row],[Enterprise ID]], 'ExistingRental-12.11'!A:H, 3, 0), "Not Open On 12.11") -> 45999 | S53: =IF(Table2[[#This Row],[Start Rental Date]]="New Rental", "New Rental", "Rental Extension Request") -> Rental Extension Request | T53: =IFERROR(IF(Table2[[#This Row],[Date of this request]]-Table2[[#This Row],[Tech Service Date]]<60, "New Hire Rental", "Truck Breakdown"), "New Hire Rental") -> New Hire Rental | U53: =IFERROR(VLOOKUP(Table2[[#This Row],[Enterprise ID]], 'ExistingRental-12.11'!A:H, 7, 0), "Not Open On 12.11") -> MARK POLITE | V53: =IFERROR(VLOOKUP(Table2[[#This Row],[Enterprise ID]],'Tech-ServiceDate'!A:B,2,0), "EitherNewHire or Termed") -> 45900
A54: 45922 | B54: 46205 | C54: ALMARAZ, NICHOLAS | D54: NALMARA | E54: =TRIM(B54) -> 46205 | F54: =IFERROR(VLOOKUP(D54,'TPMS-auto'!A:J, 10,0), "Not-in-TPMS") -> 3613433095 | G54: =IFERROR(VLOOKUP(D54,'TPMS-auto'!A:J,6,0),"Not-in-TPMS") -> 046205 | H54: 45884 | I54: MIDAS #5126 (National Account) 6407 N NAVARRO ST VICTORIA TX 77904 | J54: PO was paid on 9/13 and most likely done | K54: NALMARA in rental since 8/15 - repair in process at Midas - Holman PO needs followup (ROB) Rob Anderson to investigate - need more information on this, PO in Holman is incomplete - only shows Jasper Engines approval request - rob will follow up | L54: Yes | N54: No | O54: No | P54: =IFERROR(VLOOKUP(D54,'TPMS-auto'!A:D, 4,0),"Not-in-TPMS") -> 0008147 | Q54: =IFERROR(VLOOKUP(Table2[[#This Row],[Unit Number]],Ops,3,0),"Not-in-TPMS") -> Carol & Tasha | R54: =IFERROR(VLOOKUP(Table2[[#This Row],[Enterprise ID]], 'ExistingRental-12.11'!A:H, 3, 0), "Not Open On 12.11") -> 45884 | S54: =IF(Table2[[#This Row],[Start Rental Date]]="New Rental", "New Rental", "Rental Extension Request") -> Rental Extension Request | T54: =IFERROR(IF(Table2[[#This Row],[Date of this request]]-Table2[[#This Row],[Tech Service Date]]<60, "New Hire Rental", "Truck Breakdown"), "New Hire Rental") -> Truck Breakdown | U54: =IFERROR(VLOOKUP(Table2[[#This Row],[Enterprise ID]], 'ExistingRental-12.11'!A:H, 7, 0), "Not Open On 12.11") -> NICHOLAS ALMARAZ | V54: =IFERROR(VLOOKUP(Table2[[#This Row],[Enterprise ID]],'Tech-ServiceDate'!A:B,2,0), "EitherNewHire or Termed") -> 45067
A55: 45922 | B55: 21312 | C55: SWISHER, NICK | D55: NSWISHE | E55: =TRIM(B55) -> 21312 | F55: =IFERROR(VLOOKUP(D55,'TPMS-auto'!A:J, 10,0), "Not-in-TPMS") -> 6146780095 | G55: =IFERROR(VLOOKUP(D55,'TPMS-auto'!A:J,6,0),"Not-in-TPMS") -> 021312 | H55: 45919 | I55: MIDAS #5126 (National Account) 6407 N NAVARRO ST VICTORIA TX 77904 | J55: Tech is in van and was at a valveline on 9/18 wanting the flushes to be done. | K55: NSWISHE - in rental since 9/9 - need followup with the shop - tech took van from Valvoline to another shop? Rob Anderson to investigate - NO PO in Holman | L55: Yes | N55: No | O55: No | P55: =IFERROR(VLOOKUP(D55,'TPMS-auto'!A:D, 4,0),"Not-in-TPMS") -> 0004766 | Q55: =IFERROR(VLOOKUP(Table2[[#This Row],[Unit Number]],Ops,3,0),"Not-in-TPMS") -> Rob & Andrea | R55: =IFERROR(VLOOKUP(Table2[[#This Row],[Enterprise ID]], 'ExistingRental-12.11'!A:H, 3, 0), "Not Open On 12.11") -> Not Open On 12.11 | S55: =IF(Table2[[#This Row],[Start Rental Date]]="New Rental", "New Rental", "Rental Extension Request") -> Rental Extension Request | T55: =IFERROR(IF(Table2[[#This Row],[Date of this request]]-Table2[[#This Row],[Tech Service Date]]<60, "New Hire Rental", "Truck Breakdown"), "New Hire Rental") -> Truck Breakdown | U55: =IFERROR(VLOOKUP(Table2[[#This Row],[Enterprise ID]], 'ExistingRental-12.11'!A:H, 7, 0), "Not Open On 12.11") -> Not Open On 12.11 | V55: =IFERROR(VLOOKUP(Table2[[#This Row],[Enterprise ID]],'Tech-ServiceDate'!A:B,2,0), "EitherNewHire or Termed") -> 43201
A56: 45922 | B56: 61436 | C56: Patrick Allen Robertson JR | D56: PROBERT | E56: =TRIM(B56) -> 61436 | F56: =IFERROR(VLOOKUP(D56,'TPMS-auto'!A:J, 10,0), "Not-in-TPMS") -> 9164771778 | G56: =IFERROR(VLOOKUP(D56,'TPMS-auto'!A:J,6,0),"Not-in-TPMS") -> 061436 | H56: New Rental | I56: New hire PROBERT - started 9/15, on route 10/6 | J56: Van is not in TPMS | K56: New hire that needs a permanent van identified and assigned - John and Jen asap! | L56: Yes | N56: Yes | O56: Yes | P56: =IFERROR(VLOOKUP(D56,'TPMS-auto'!A:D, 4,0),"Not-in-TPMS") -> 0007108 | Q56: =IFERROR(VLOOKUP(Table2[[#This Row],[Unit Number]],Ops,3,0),"Not-in-TPMS") -> Carol & Tasha | R56: =IFERROR(VLOOKUP(Table2[[#This Row],[Enterprise ID]], 'ExistingRental-12.11'!A:H, 3, 0), "Not Open On 12.11") -> Not Open On 12.11 | S56: =IF(Table2[[#This Row],[Start Rental Date]]="New Rental", "New Rental", "Rental Extension Request") -> New Rental | T56: =IFERROR(IF(Table2[[#This Row],[Date of this request]]-Table2[[#This Row],[Tech Service Date]]<60, "New Hire Rental", "Truck Breakdown"), "New Hire Rental") -> New Hire Rental | U56: =IFERROR(VLOOKUP(Table2[[#This Row],[Enterprise ID]], 'ExistingRental-12.11'!A:H, 7, 0), "Not Open On 12.11") -> Not Open On 12.11 | V56: =IFERROR(VLOOKUP(Table2[[#This Row],[Enterprise ID]],'Tech-ServiceDate'!A:B,2,0), "EitherNewHire or Termed") -> 45914
A57: 45922 | B57: 36243 | C57: Philllip Hassel | D57: PHASSE0 | E57: =TRIM(B57) -> 36243 | F57: =IFERROR(VLOOKUP(D57,'TPMS-auto'!A:J, 10,0), "Not-in-TPMS") -> 9108765642 | G57: =IFERROR(VLOOKUP(D57,'TPMS-auto'!A:J,6,0),"Not-in-TPMS") -> 037035 | H57: 45907 | I57: AAMCO TOTAL CAR CARE, 1047 BRAGG BLVD, FAYETTEVILLE NC 28301 | J57: Trans warranty | K57: Repair van - Holman approval was on 9/15 for $2694 - when will repair be completed? | L57: Yes | N57: Yes | O57: Yes | P57: =IFERROR(VLOOKUP(D57,'TPMS-auto'!A:D, 4,0),"Not-in-TPMS") -> 0008175 | Q57: =IFERROR(VLOOKUP(Table2[[#This Row],[Unit Number]],Ops,3,0),"Not-in-TPMS") -> Rob & Andrea | R57: =IFERROR(VLOOKUP(Table2[[#This Row],[Enterprise ID]], 'ExistingRental-12.11'!A:H, 3, 0), "Not Open On 12.11") -> Not Open On 12.11 | S57: =IF(Table2[[#This Row],[Start Rental Date]]="New Rental", "New Rental", "Rental Extension Request") -> Rental Extension Request | T57: =IFERROR(IF(Table2[[#This Row],[Date of this request]]-Table2[[#This Row],[Tech Service Date]]<60, "New Hire Rental", "Truck Breakdown"), "New Hire Rental") -> Truck Breakdown | U57: =IFERROR(VLOOKUP(Table2[[#This Row],[Enterprise ID]], 'ExistingRental-12.11'!A:H, 7, 0), "Not Open On 12.11") -> Not Open On 12.11 | V57: =IFERROR(VLOOKUP(Table2[[#This Row],[Enterprise ID]],'Tech-ServiceDate'!A:B,2,0), "EitherNewHire or Termed") -> 41176
A58: 45922 | B58: 37275 | C58: COOPER, LUTHER | D58: LERBYCO | E58: =TRIM(B58) -> 37275 | F58: =IFERROR(VLOOKUP(D58,'TPMS-auto'!A:J, 10,0), "Not-in-TPMS") -> 2058642855 | G58: =IFERROR(VLOOKUP(D58,'TPMS-auto'!A:J,6,0),"Not-in-TPMS") -> 037275 | H58: 45868 | I58: PEP BOYS, 3019 ALLISON BONNETT DR, HUEYTOWN AL 35023 | J58: Van repair was approved on 8/5 - knock sensor - last notes were on 8/14 - we need the van out of the shop and back to the tech | K58: Get van repair status - tech needs to get out of the rental | L58: Yes | N58: Yes | O58: Yes | P58: =IFERROR(VLOOKUP(D58,'TPMS-auto'!A:D, 4,0),"Not-in-TPMS") -> 0008035 | Q58: =IFERROR(VLOOKUP(Table2[[#This Row],[Unit Number]],Ops,3,0),"Not-in-TPMS") -> Rob & Andrea | R58: =IFERROR(VLOOKUP(Table2[[#This Row],[Enterprise ID]], 'ExistingRental-12.11'!A:H, 3, 0), "Not Open On 12.11") -> 45974 | S58: =IF(Table2[[#This Row],[Start Rental Date]]="New Rental", "New Rental", "Rental Extension Request") -> Rental Extension Request | T58: =IFERROR(IF(Table2[[#This Row],[Date of this request]]-Table2[[#This Row],[Tech Service Date]]<60, "New Hire Rental", "Truck Breakdown"), "New Hire Rental") -> Truck Breakdown | U58: =IFERROR(VLOOKUP(Table2[[#This Row],[Enterprise ID]], 'ExistingRental-12.11'!A:H, 7, 0), "Not Open On 12.11") -> LUTHER ERBY COOPER | V58: =IFERROR(VLOOKUP(Table2[[#This Row],[Enterprise ID]],'Tech-ServiceDate'!A:B,2,0), "EitherNewHire or Termed") -> 45032
A59: 45922 | B59: 46802 | C59: ANDREW VASQUEZ | D59: AVASQU3 | E59: =TRIM(B59) -> 46802 | F59: =IFERROR(VLOOKUP(D59,'TPMS-auto'!A:J, 10,0), "Not-in-TPMS") -> 7048340147 | G59: =IFERROR(VLOOKUP(D59,'TPMS-auto'!A:J,6,0),"Not-in-TPMS") -> 046802 | H59: New Rental | J59: Trans issue | K59: AVASQU3 - in rental since 9/22 - repair estimate of $3823.88 waiting for approval - AAMCO TOTAL CAR CARE 225 E GARRISON BLVD GASTONIA NC 28052 | L59: Yes | N59: Yes | O59: Yes | P59: =IFERROR(VLOOKUP(D59,'TPMS-auto'!A:D, 4,0),"Not-in-TPMS") -> 0004766 | Q59: =IFERROR(VLOOKUP(Table2[[#This Row],[Unit Number]],Ops,3,0),"Not-in-TPMS") -> Rob & Andrea | R59: =IFERROR(VLOOKUP(Table2[[#This Row],[Enterprise ID]], 'ExistingRental-12.11'!A:H, 3, 0), "Not Open On 12.11") -> Not Open On 12.11 | S59: =IF(Table2[[#This Row],[Start Rental Date]]="New Rental", "New Rental", "Rental Extension Request") -> New Rental | T59: =IFERROR(IF(Table2[[#This Row],[Date of this request]]-Table2[[#This Row],[Tech Service Date]]<60, "New Hire Rental", "Truck Breakdown"), "New Hire Rental") -> Truck Breakdown | U59: =IFERROR(VLOOKUP(Table2[[#This Row],[Enterprise ID]], 'ExistingRental-12.11'!A:H, 7, 0), "Not Open On 12.11") -> Not Open On 12.11 | V59: =IFERROR(VLOOKUP(Table2[[#This Row],[Enterprise ID]],'Tech-ServiceDate'!A:B,2,0), "EitherNewHire or Termed") -> 44118
A60: 45922 | B60: 46445 | C60: Jose Nunez | D60: JNUNEZ | E60: =TRIM(B60) -> 46445 | F60: =IFERROR(VLOOKUP(D60,'TPMS-auto'!A:J, 10,0), "Not-in-TPMS") -> 9098488012 | G60: =IFERROR(VLOOKUP(D60,'TPMS-auto'!A:J,6,0),"Not-in-TPMS") -> 046445 | H60: New Rental | I60: PEP BOYS 1650 W REDLANDS BLVD REDLANDS CA 92373 | J60: Oil leak and check engine light - JNUNEZ in rental on 9/22 - Holman approved 3 days. Tech broke down due to no oil in the van! - Fortunately, the shop has added oil, checked out the van and it should be repaired on 9/23 and ready for pickup | K60: New rental request; Holman shows auto approved - tech needs to return the rental on 9/23 and pick up his van. Also need to initiate an EPV for allowing the truck to run without oil - he risked a major engine failure and is fortunate this only required a tow and oil. | L60: Yes | N60: No | O60: Yes | P60: =IFERROR(VLOOKUP(D60,'TPMS-auto'!A:D, 4,0),"Not-in-TPMS") -> 0007108 | Q60: =IFERROR(VLOOKUP(Table2[[#This Row],[Unit Number]],Ops,3,0),"Not-in-TPMS") -> Carol & Tasha | R60: =IFERROR(VLOOKUP(Table2[[#This Row],[Enterprise ID]], 'ExistingRental-12.11'!A:H, 3, 0), "Not Open On 12.11") -> Not Open On 12.11 | S60: =IF(Table2[[#This Row],[Start Rental Date]]="New Rental", "New Rental", "Rental Extension Request") -> New Rental | T60: =IFERROR(IF(Table2[[#This Row],[Date of this request]]-Table2[[#This Row],[Tech Service Date]]<60, "New Hire Rental", "Truck Breakdown"), "New Hire Rental") -> Truck Breakdown | U60: =IFERROR(VLOOKUP(Table2[[#This Row],[Enterprise ID]], 'ExistingRental-12.11'!A:H, 7, 0), "Not Open On 12.11") -> Not Open On 12.11 | V60: =IFERROR(VLOOKUP(Table2[[#This Row],[Enterprise ID]],'Tech-ServiceDate'!A:B,2,0), "EitherNewHire or Termed") -> 44763
A61: 45922 | B61: 46663 | C61: RONALD TASSIN | D61: RTASSIN | E61: =TRIM(B61) -> 46663 | F61: =IFERROR(VLOOKUP(D61,'TPMS-auto'!A:J, 10,0), "Not-in-TPMS") -> 9855494860 | G61: =IFERROR(VLOOKUP(D61,'TPMS-auto'!A:J,6,0),"Not-in-TPMS") -> 046663 | H61: New Rental | I61: 600 S MORRISON BLVD, HAMMOND, LA 70403 | J61: Radiator burst open | K61: New rental request - need repair estimate | L61: Yes | N61: Yes | O61: Yes | P61: =IFERROR(VLOOKUP(D61,'TPMS-auto'!A:D, 4,0),"Not-in-TPMS") -> 0008206 | Q61: =IFERROR(VLOOKUP(Table2[[#This Row],[Unit Number]],Ops,3,0),"Not-in-TPMS") -> Monica, Cheryl & Machell | R61: =IFERROR(VLOOKUP(Table2[[#This Row],[Enterprise ID]], 'ExistingRental-12.11'!A:H, 3, 0), "Not Open On 12.11") -> Not Open On 12.11 | S61: =IF(Table2[[#This Row],[Start Rental Date]]="New Rental", "New Rental", "Rental Extension Request") -> New Rental | T61: =IFERROR(IF(Table2[[#This Row],[Date of this request]]-Table2[[#This Row],[Tech Service Date]]<60, "New Hire Rental", "Truck Breakdown"), "New Hire Rental") -> Truck Breakdown | U61: =IFERROR(VLOOKUP(Table2[[#This Row],[Enterprise ID]], 'ExistingRental-12.11'!A:H, 7, 0), "Not Open On 12.11") -> Not Open On 12.11 | V61: =IFERROR(VLOOKUP(Table2[[#This Row],[Enterprise ID]],'Tech-ServiceDate'!A:B,2,0), "EitherNewHire or Termed") -> 42394
A62: 45922 | B62: 23310 | C62: Martin Wohlford | D62: MWOHLFO | E62: =TRIM(B62) -> 23310 | F62: =IFERROR(VLOOKUP(D62,'TPMS-auto'!A:J, 10,0), "Not-in-TPMS") -> 2108510351 | G62: =IFERROR(VLOOKUP(D62,'TPMS-auto'!A:J,6,0),"Not-in-TPMS") -> 023310 | H62: 45917 | I62: Insights is down | J62: Tech is sick and can't pick up vehicle | K62: Van is ready for pickup - tech will return rental 9/23 | L62: Yes | N62: Yes | O62: Yes | P62: =IFERROR(VLOOKUP(D62,'TPMS-auto'!A:D, 4,0),"Not-in-TPMS") -> 0008147 | Q62: =IFERROR(VLOOKUP(Table2[[#This Row],[Unit Number]],Ops,3,0),"Not-in-TPMS") -> Carol & Tasha | R62: =IFERROR(VLOOKUP(Table2[[#This Row],[Enterprise ID]], 'ExistingRental-12.11'!A:H, 3, 0), "Not Open On 12.11") -> Not Open On 12.11 | S62: =IF(Table2[[#This Row],[Start Rental Date]]="New Rental", "New Rental", "Rental Extension Request") -> Rental Extension Request | T62: =IFERROR(IF(Table2[[#This Row],[Date of this request]]-Table2[[#This Row],[Tech Service Date]]<60, "New Hire Rental", "Truck Breakdown"), "New Hire Rental") -> Truck Breakdown | U62: =IFERROR(VLOOKUP(Table2[[#This Row],[Enterprise ID]], 'ExistingRental-12.11'!A:H, 7, 0), "Not Open On 12.11") -> Not Open On 12.11 | V62: =IFERROR(VLOOKUP(Table2[[#This Row],[Enterprise ID]],'Tech-ServiceDate'!A:B,2,0), "EitherNewHire or Termed") -> 44167
A63: 45922 | B63: 46961 | C63: CRAWFORD, LAVER | D63: LCRAWFO | E63: =TRIM(B63) -> 46961 | F63: =IFERROR(VLOOKUP(D63,'TPMS-auto'!A:J, 10,0), "Not-in-TPMS") -> 9482233344 | G63: =IFERROR(VLOOKUP(D63,'TPMS-auto'!A:J,6,0),"Not-in-TPMS") -> 046961 | H63: 45825 | I63: van 46961 was assigned to the tech previously - | J63: Declined repair | K63: Rob Anderson - van repair shows declined on 6/26, but the amount declined is unclear in the Holman PO - should this be reconsidered since the tech is STILL IN A RENTAL? Tech needs a permanent van assignment asap! | L63: Yes | N63: Yes | O63: Yes | P63: =IFERROR(VLOOKUP(D63,'TPMS-auto'!A:D, 4,0),"Not-in-TPMS") -> 0008175 | Q63: =IFERROR(VLOOKUP(Table2[[#This Row],[Unit Number]],Ops,3,0),"Not-in-TPMS") -> Rob & Andrea | R63: =IFERROR(VLOOKUP(Table2[[#This Row],[Enterprise ID]], 'ExistingRental-12.11'!A:H, 3, 0), "Not Open On 12.11") -> 45827 | S63: =IF(Table2[[#This Row],[Start Rental Date]]="New Rental", "New Rental", "Rental Extension Request") -> Rental Extension Request | T63: =IFERROR(IF(Table2[[#This Row],[Date of this request]]-Table2[[#This Row],[Tech Service Date]]<60, "New Hire Rental", "Truck Breakdown"), "New Hire Rental") -> Truck Breakdown | U63: =IFERROR(VLOOKUP(Table2[[#This Row],[Enterprise ID]], 'ExistingRental-12.11'!A:H, 7, 0), "Not Open On 12.11") -> LAVER CRAWFORD | V63: =IFERROR(VLOOKUP(Table2[[#This Row],[Enterprise ID]],'Tech-ServiceDate'!A:B,2,0), "EitherNewHire or Termed") -> 45760
A64: 45922 | B64: 61369 | C64: Carolyn Barnett | D64: CBARNET | E64: =TRIM(B64) -> 61369 | F64: =IFERROR(VLOOKUP(D64,'TPMS-auto'!A:J, 10,0), "Not-in-TPMS") -> 2569217517 | G64: =IFERROR(VLOOKUP(D64,'TPMS-auto'!A:J,6,0),"Not-in-TPMS") -> 061369 | H64: 45916 | I64: AAMCO TOTAL CAR CARE, 1109 S QUINTARD AVE, ANNISTON AL 36201 | J64: CBARNET - tech in rental since 9/16 - AAMCO TOTAL CAR CARE, 1109 S QUINTARD AVE, ANNISTON AL 36201 get van repaired | K64: Get van repaired | L64: Yes | N64: Yes | O64: Yes | P64: =IFERROR(VLOOKUP(D64,'TPMS-auto'!A:D, 4,0),"Not-in-TPMS") -> 0008035 | Q64: =IFERROR(VLOOKUP(Table2[[#This Row],[Unit Number]],Ops,3,0),"Not-in-TPMS") -> Rob & Andrea | R64: =IFERROR(VLOOKUP(Table2[[#This Row],[Enterprise ID]], 'ExistingRental-12.11'!A:H, 3, 0), "Not Open On 12.11") -> Not Open On 12.11 | S64: =IF(Table2[[#This Row],[Start Rental Date]]="New Rental", "New Rental", "Rental Extension Request") -> Rental Extension Request | T64: =IFERROR(IF(Table2[[#This Row],[Date of this request]]-Table2[[#This Row],[Tech Service Date]]<60, "New Hire Rental", "Truck Breakdown"), "New Hire Rental") -> Truck Breakdown | U64: =IFERROR(VLOOKUP(Table2[[#This Row],[Enterprise ID]], 'ExistingRental-12.11'!A:H, 7, 0), "Not Open On 12.11") -> Not Open On 12.11 | V64: =IFERROR(VLOOKUP(Table2[[#This Row],[Enterprise ID]],'Tech-ServiceDate'!A:B,2,0), "EitherNewHire or Termed") -> 45354
A65: 45922 | B65: 36636 | C65: BALDARAS, ROBERTO | D65: RBALDER | E65: =TRIM(B65) -> 36636 | F65: =IFERROR(VLOOKUP(D65,'TPMS-auto'!A:J, 10,0), "Not-in-TPMS") -> Not-in-TPMS | G65: =IFERROR(VLOOKUP(D65,'TPMS-auto'!A:J,6,0),"Not-in-TPMS") -> Not-in-TPMS | H65: 45887 | I65: New hire - no van assigned - in rental since 8/18 - no truck assigned | J65: Van is not in TPMS | K65: Van 36636 has been assigned to the tech / Will be transported / TPMS and AMS are being updated / Will update with Transport ETA once we have it / jchild2 | L65: Yes | N65: Yes | O65: Yes | P65: =IFERROR(VLOOKUP(D65,'TPMS-auto'!A:D, 4,0),"Not-in-TPMS") -> Not-in-TPMS | Q65: =IFERROR(VLOOKUP(Table2[[#This Row],[Unit Number]],Ops,3,0),"Not-in-TPMS") -> Not-in-TPMS | R65: =IFERROR(VLOOKUP(Table2[[#This Row],[Enterprise ID]], 'ExistingRental-12.11'!A:H, 3, 0), "Not Open On 12.11") -> Not Open On 12.11 | S65: =IF(Table2[[#This Row],[Start Rental Date]]="New Rental", "New Rental", "Rental Extension Request") -> Rental Extension Request | T65: =IFERROR(IF(Table2[[#This Row],[Date of this request]]-Table2[[#This Row],[Tech Service Date]]<60, "New Hire Rental", "Truck Breakdown"), "New Hire Rental") -> New Hire Rental | U65: =IFERROR(VLOOKUP(Table2[[#This Row],[Enterprise ID]], 'ExistingRental-12.11'!A:H, 7, 0), "Not Open On 12.11") -> Not Open On 12.11 | V65: =IFERROR(VLOOKUP(Table2[[#This Row],[Enterprise ID]],'Tech-ServiceDate'!A:B,2,0), "EitherNewHire or Termed") -> EitherNewHire or Termed
A66: 45922 | B66: 46983 | C66: Luis Merced | D66: LMERCED | E66: =TRIM(B66) -> 46983 | F66: =IFERROR(VLOOKUP(D66,'TPMS-auto'!A:J, 10,0), "Not-in-TPMS") -> 7577252358 | G66: =IFERROR(VLOOKUP(D66,'TPMS-auto'!A:J,6,0),"Not-in-TPMS") -> 046983 | H66: New Rental | I66: New rental | J66: Van in repair - tires - waiting for approval in Holman | K66: New rental request | L66: Yes | N66: Yes | O66: Yes | P66: =IFERROR(VLOOKUP(D66,'TPMS-auto'!A:D, 4,0),"Not-in-TPMS") -> 0008175 | Q66: =IFERROR(VLOOKUP(Table2[[#This Row],[Unit Number]],Ops,3,0),"Not-in-TPMS") -> Rob & Andrea | R66: =IFERROR(VLOOKUP(Table2[[#This Row],[Enterprise ID]], 'ExistingRental-12.11'!A:H, 3, 0), "Not Open On 12.11") -> Not Open On 12.11 | S66: =IF(Table2[[#This Row],[Start Rental Date]]="New Rental", "New Rental", "Rental Extension Request") -> New Rental | T66: =IFERROR(IF(Table2[[#This Row],[Date of this request]]-Table2[[#This Row],[Tech Service Date]]<60, "New Hire Rental", "Truck Breakdown"), "New Hire Rental") -> Truck Breakdown | U66: =IFERROR(VLOOKUP(Table2[[#This Row],[Enterprise ID]], 'ExistingRental-12.11'!A:H, 7, 0), "Not Open On 12.11") -> Not Open On 12.11 | V66: =IFERROR(VLOOKUP(Table2[[#This Row],[Enterprise ID]],'Tech-ServiceDate'!A:B,2,0), "EitherNewHire or Termed") -> 43262
A67: 45922 | B67: 61045 | C67: Andy Kempf | D67: AKEMPF1 | E67: =TRIM(B67) -> 61045 | F67: =IFERROR(VLOOKUP(D67,'TPMS-auto'!A:J, 10,0), "Not-in-TPMS") -> 5174209644 | G67: =IFERROR(VLOOKUP(D67,'TPMS-auto'!A:J,6,0),"Not-in-TPMS") -> 061045 | H67: New Rental | I67: 6615 SOUTH PENNSYLVANIA AVENUE LANSING,MICHIGAN | J67: Van does not crank or start | K67: New rental request - for oil change and tire rotation - technician should schedule this and WAIT for the repair to be completed - this should NOT require a rental vehicle | L67: Yes | N67: No | O67: Yes | P67: =IFERROR(VLOOKUP(D67,'TPMS-auto'!A:D, 4,0),"Not-in-TPMS") -> 0008220 | Q67: =IFERROR(VLOOKUP(Table2[[#This Row],[Unit Number]],Ops,3,0),"Not-in-TPMS") -> Monica, Cheryl & Machell | R67: =IFERROR(VLOOKUP(Table2[[#This Row],[Enterprise ID]], 'ExistingRental-12.11'!A:H, 3, 0), "Not Open On 12.11") -> Not Open On 12.11 | S67: =IF(Table2[[#This Row],[Start Rental Date]]="New Rental", "New Rental", "Rental Extension Request") -> New Rental | T67: =IFERROR(IF(Table2[[#This Row],[Date of this request]]-Table2[[#This Row],[Tech Service Date]]<60, "New Hire Rental", "Truck Breakdown"), "New Hire Rental") -> Truck Breakdown | U67: =IFERROR(VLOOKUP(Table2[[#This Row],[Enterprise ID]], 'ExistingRental-12.11'!A:H, 7, 0), "Not Open On 12.11") -> Not Open On 12.11 | V67: =IFERROR(VLOOKUP(Table2[[#This Row],[Enterprise ID]],'Tech-ServiceDate'!A:B,2,0), "EitherNewHire or Termed") -> 32616
A68: 45922 | B68: 36488 | C68: Mathew Roelke | D68: MROELKE | E68: =TRIM(B68) -> 36488 | F68: =IFERROR(VLOOKUP(D68,'TPMS-auto'!A:J, 10,0), "Not-in-TPMS") -> 8508241426 | G68: =IFERROR(VLOOKUP(D68,'TPMS-auto'!A:J,6,0),"Not-in-TPMS") -> 036488 | H68: New Rental | I68: MROELKE - in rental since 9/22 - van repair at ARKANSAS AUTOMOTIVE & TRUCK MA, 129 SHADY GROVE RD, HOT SPRINGS AR 71901 waiting on estimate from shop - since 9/16 - no estimate in HOLMAN? | J68: Need estimate from Shop asap - get van repaired - truck was taken to the shop on 9/16 - no estimate in Holman on 9/22 | K68: New rental request | L68: Yes | N68: Yes | O68: Yes | P68: =IFERROR(VLOOKUP(D68,'TPMS-auto'!A:D, 4,0),"Not-in-TPMS") -> 0008206 | Q68: =IFERROR(VLOOKUP(Table2[[#This Row],[Unit Number]],Ops,3,0),"Not-in-TPMS") -> Monica, Cheryl & Machell | R68: =IFERROR(VLOOKUP(Table2[[#This Row],[Enterprise ID]], 'ExistingRental-12.11'!A:H, 3, 0), "Not Open On 12.11") -> Not Open On 12.11 | S68: =IF(Table2[[#This Row],[Start Rental Date]]="New Rental", "New Rental", "Rental Extension Request") -> New Rental | T68: =IFERROR(IF(Table2[[#This Row],[Date of this request]]-Table2[[#This Row],[Tech Service Date]]<60, "New Hire Rental", "Truck Breakdown"), "New Hire Rental") -> Truck Breakdown | U68: =IFERROR(VLOOKUP(Table2[[#This Row],[Enterprise ID]], 'ExistingRental-12.11'!A:H, 7, 0), "Not Open On 12.11") -> Not Open On 12.11 | V68: =IFERROR(VLOOKUP(Table2[[#This Row],[Enterprise ID]],'Tech-ServiceDate'!A:B,2,0), "EitherNewHire or Termed") -> 45123
A69: 45922 | B69: 21317 | C69: Yakerial Judah | D69: YJUDAH | E69: =TRIM(B69) -> 21317 | F69: =IFERROR(VLOOKUP(D69,'TPMS-auto'!A:J, 10,0), "Not-in-TPMS") -> Not-in-TPMS | G69: =IFERROR(VLOOKUP(D69,'TPMS-auto'!A:J,6,0),"Not-in-TPMS") -> Not-in-TPMS | H69: New Rental | I69: FIRESTONE COMPLETE AUTO CARE, 1014 E INNES ST, SALISBURY NC 28144 | J69: Van does not crank or start tech assigned to 46801 | K69: New rental request - YJUDAH is assigned this van - he has been in a rental since 9/22 - the rental is opened on truck #21317 - this van, 46801 appears to be repaired - it was assigned to this tech since 2/7/2025 - where is van #46801?? | L69: Yes | N69: Yes | O69: Yes | P69: =IFERROR(VLOOKUP(D69,'TPMS-auto'!A:D, 4,0),"Not-in-TPMS") -> Not-in-TPMS | Q69: =IFERROR(VLOOKUP(Table2[[#This Row],[Unit Number]],Ops,3,0),"Not-in-TPMS") -> Not-in-TPMS | R69: =IFERROR(VLOOKUP(Table2[[#This Row],[Enterprise ID]], 'ExistingRental-12.11'!A:H, 3, 0), "Not Open On 12.11") -> Not Open On 12.11 | S69: =IF(Table2[[#This Row],[Start Rental Date]]="New Rental", "New Rental", "Rental Extension Request") -> New Rental | T69: =IFERROR(IF(Table2[[#This Row],[Date of this request]]-Table2[[#This Row],[Tech Service Date]]<60, "New Hire Rental", "Truck Breakdown"), "New Hire Rental") -> Truck Breakdown | U69: =IFERROR(VLOOKUP(Table2[[#This Row],[Enterprise ID]], 'ExistingRental-12.11'!A:H, 7, 0), "Not Open On 12.11") -> Not Open On 12.11 | V69: =IFERROR(VLOOKUP(Table2[[#This Row],[Enterprise ID]],'Tech-ServiceDate'!A:B,2,0), "EitherNewHire or Termed") -> 45557
A70: 45922 | B70: 37365 | C70: Rafi Abassi | D70: RABASSI | E70: =TRIM(B70) -> 37365 | F70: =IFERROR(VLOOKUP(D70,'TPMS-auto'!A:J, 10,0), "Not-in-TPMS") -> 2098890779 | G70: =IFERROR(VLOOKUP(D70,'TPMS-auto'!A:J,6,0),"Not-in-TPMS") -> 037365 | H70: New Rental | I70: 711 KANSAS AVE EXT, MODESTO, CA 95351 | J70: Van overheated | K70: New rental request - MWOHLFO - tehc in rental since 9/17 - J+L COMPLETE AUTO RPR INC 711 N FRANKLIN ST MODESTO CA 95351 - repair is approved | L70: Yes | N70: Yes | O70: Yes | P70: =IFERROR(VLOOKUP(D70,'TPMS-auto'!A:D, 4,0),"Not-in-TPMS") -> 0008366 | Q70: =IFERROR(VLOOKUP(Table2[[#This Row],[Unit Number]],Ops,3,0),"Not-in-TPMS") -> Carol & Tasha | R70: =IFERROR(VLOOKUP(Table2[[#This Row],[Enterprise ID]], 'ExistingRental-12.11'!A:H, 3, 0), "Not Open On 12.11") -> Not Open On 12.11 | S70: =IF(Table2[[#This Row],[Start Rental Date]]="New Rental", "New Rental", "Rental Extension Request") -> New Rental | T70: =IFERROR(IF(Table2[[#This Row],[Date of this request]]-Table2[[#This Row],[Tech Service Date]]<60, "New Hire Rental", "Truck Breakdown"), "New Hire Rental") -> Truck Breakdown | U70: =IFERROR(VLOOKUP(Table2[[#This Row],[Enterprise ID]], 'ExistingRental-12.11'!A:H, 7, 0), "Not Open On 12.11") -> Not Open On 12.11 | V70: =IFERROR(VLOOKUP(Table2[[#This Row],[Enterprise ID]],'Tech-ServiceDate'!A:B,2,0), "EitherNewHire or Termed") -> 43014
A71: 45922 | B71: 46490 | C71: MCLIECHEY, DANIEL | D71: DMCLIEC | E71: =TRIM(B71) -> 46490 | F71: =IFERROR(VLOOKUP(D71,'TPMS-auto'!A:J, 10,0), "Not-in-TPMS") -> 7578310437 | G71: =IFERROR(VLOOKUP(D71,'TPMS-auto'!A:J,6,0),"Not-in-TPMS") -> 046986 | H71: 45915 | I71: New hire - started on 8/25, on route 9/15 no van assignment | J71: Van is not in TPMS | K71: John - Jen - Need a permanent van assignment | L71: Yes | N71: Yes | O71: Yes | P71: =IFERROR(VLOOKUP(D71,'TPMS-auto'!A:D, 4,0),"Not-in-TPMS") -> 0008175 | Q71: =IFERROR(VLOOKUP(Table2[[#This Row],[Unit Number]],Ops,3,0),"Not-in-TPMS") -> Rob & Andrea | R71: =IFERROR(VLOOKUP(Table2[[#This Row],[Enterprise ID]], 'ExistingRental-12.11'!A:H, 3, 0), "Not Open On 12.11") -> Not Open On 12.11 | S71: =IF(Table2[[#This Row],[Start Rental Date]]="New Rental", "New Rental", "Rental Extension Request") -> Rental Extension Request | T71: =IFERROR(IF(Table2[[#This Row],[Date of this request]]-Table2[[#This Row],[Tech Service Date]]<60, "New Hire Rental", "Truck Breakdown"), "New Hire Rental") -> New Hire Rental | U71: =IFERROR(VLOOKUP(Table2[[#This Row],[Enterprise ID]], 'ExistingRental-12.11'!A:H, 7, 0), "Not Open On 12.11") -> Not Open On 12.11 | V71: =IFERROR(VLOOKUP(Table2[[#This Row],[Enterprise ID]],'Tech-ServiceDate'!A:B,2,0), "EitherNewHire or Termed") -> 45893
A72: 45922 | B72: 23153 | C72: MCGHEE, EISHA | E72: =TRIM(B72) -> 23153 | F72: =IFERROR(VLOOKUP(D72,'TPMS-auto'!A:J, 10,0), "Not-in-TPMS") -> Not-in-TPMS | G72: =IFERROR(VLOOKUP(D72,'TPMS-auto'!A:J,6,0),"Not-in-TPMS") -> Not-in-TPMS | H72: 45846 | I72: Tech was terminated 8/30 - rental is not approved | J72: Van is not in TPMS - Tech was terminated on 8/30 - Segno still shows active and rental is still open with Enterprise | K72: Rental extension is not approved - this person owes us for 22 days rental | L72: Yes | N72: NO | O72: Yes | P72: =IFERROR(VLOOKUP(D72,'TPMS-auto'!A:D, 4,0),"Not-in-TPMS") -> Not-in-TPMS | Q72: =IFERROR(VLOOKUP(Table2[[#This Row],[Unit Number]],Ops,3,0),"Not-in-TPMS") -> Not-in-TPMS | R72: =IFERROR(VLOOKUP(Table2[[#This Row],[Enterprise ID]], 'ExistingRental-12.11'!A:H, 3, 0), "Not Open On 12.11") -> Not Open On 12.11 | S72: =IF(Table2[[#This Row],[Start Rental Date]]="New Rental", "New Rental", "Rental Extension Request") -> Rental Extension Request | T72: =IFERROR(IF(Table2[[#This Row],[Date of this request]]-Table2[[#This Row],[Tech Service Date]]<60, "New Hire Rental", "Truck Breakdown"), "New Hire Rental") -> New Hire Rental | U72: =IFERROR(VLOOKUP(Table2[[#This Row],[Enterprise ID]], 'ExistingRental-12.11'!A:H, 7, 0), "Not Open On 12.11") -> Not Open On 12.11 | V72: =IFERROR(VLOOKUP(Table2[[#This Row],[Enterprise ID]],'Tech-ServiceDate'!A:B,2,0), "EitherNewHire or Termed") -> EitherNewHire or Termed
A73: 45922 | B73: 46499 | C73: Mohammed Haidari | D73: MHAIDAR | E73: =TRIM(B73) -> 46499 | F73: =IFERROR(VLOOKUP(D73,'TPMS-auto'!A:J, 10,0), "Not-in-TPMS") -> 5716825085 | G73: =IFERROR(VLOOKUP(D73,'TPMS-auto'!A:J,6,0),"Not-in-TPMS") -> 0 | H73: 45909 | I73: FITZGERALD AUTO MALL INC, 114 BAUGHMANS LANE, FREDERICK MD 21702 | J73: New hire, TPMS shows JHARRIS - this truck is being used for rental approval but tech does not have a permanent van assignment | K73: John - Jen: Get tech assigned to a permanent van | L73: Yes | N73: Yes | O73: Yes | P73: =IFERROR(VLOOKUP(D73,'TPMS-auto'!A:D, 4,0),"Not-in-TPMS") -> 0007084 | Q73: =IFERROR(VLOOKUP(Table2[[#This Row],[Unit Number]],Ops,3,0),"Not-in-TPMS") -> Monica, Cheryl & Machell | R73: =IFERROR(VLOOKUP(Table2[[#This Row],[Enterprise ID]], 'ExistingRental-12.11'!A:H, 3, 0), "Not Open On 12.11") -> Not Open On 12.11 | S73: =IF(Table2[[#This Row],[Start Rental Date]]="New Rental", "New Rental", "Rental Extension Request") -> Rental Extension Request | T73: =IFERROR(IF(Table2[[#This Row],[Date of this request]]-Table2[[#This Row],[Tech Service Date]]<60, "New Hire Rental", "Truck Breakdown"), "New Hire Rental") -> Truck Breakdown | U73: =IFERROR(VLOOKUP(Table2[[#This Row],[Enterprise ID]], 'ExistingRental-12.11'!A:H, 7, 0), "Not Open On 12.11") -> Not Open On 12.11 | V73: =IFERROR(VLOOKUP(Table2[[#This Row],[Enterprise ID]],'Tech-ServiceDate'!A:B,2,0), "EitherNewHire or Termed") -> 45837
A74: 45922 | B74: 36770 | C74: Louis Smith | D74: LSMI314 | E74: =TRIM(B74) -> 36770 | F74: =IFERROR(VLOOKUP(D74,'TPMS-auto'!A:J, 10,0), "Not-in-TPMS") -> 3468483248 | G74: =IFERROR(VLOOKUP(D74,'TPMS-auto'!A:J,6,0),"Not-in-TPMS") -> 036770 | H74: New Rental | I74: PEP BOYS 845 S FRY ROAD KATY TX 77450 | J74: Check Engine light on and ABS light on - repair is approved - tech can get a rental for 2 days max | K74: Van is at Pep Boys - tech waited hours for repair to be completed, asked for rental at 5PM | L74: Yes | N74: Yes | O74: Yes | P74: =IFERROR(VLOOKUP(D74,'TPMS-auto'!A:D, 4,0),"Not-in-TPMS") -> 0008107 | Q74: =IFERROR(VLOOKUP(Table2[[#This Row],[Unit Number]],Ops,3,0),"Not-in-TPMS") -> Carol & Tasha | R74: =IFERROR(VLOOKUP(Table2[[#This Row],[Enterprise ID]], 'ExistingRental-12.11'!A:H, 3, 0), "Not Open On 12.11") -> 45980 | S74: =IF(Table2[[#This Row],[Start Rental Date]]="New Rental", "New Rental", "Rental Extension Request") -> New Rental | T74: =IFERROR(IF(Table2[[#This Row],[Date of this request]]-Table2[[#This Row],[Tech Service Date]]<60, "New Hire Rental", "Truck Breakdown"), "New Hire Rental") -> Truck Breakdown | U74: =IFERROR(VLOOKUP(Table2[[#This Row],[Enterprise ID]], 'ExistingRental-12.11'!A:H, 7, 0), "Not Open On 12.11") -> LOUIS SMITH | V74: =IFERROR(VLOOKUP(Table2[[#This Row],[Enterprise ID]],'Tech-ServiceDate'!A:B,2,0), "EitherNewHire or Termed") -> 39052
A75: 45922 | B75: 37417 | C75: HER, KENEDY | D75: KHER0 | E75: =TRIM(B75) -> 37417 | F75: =IFERROR(VLOOKUP(D75,'TPMS-auto'!A:J, 10,0), "Not-in-TPMS") -> Not-in-TPMS | G75: =IFERROR(VLOOKUP(D75,'TPMS-auto'!A:J,6,0),"Not-in-TPMS") -> Not-in-TPMS | H75: 45918 | I75: BERGSTROM CHEVY OF MADISON, 1225 APPLEGATE RD, MADISON WI 53713 | J75: Possible transmission warranty - | K75: Get van repaired and tech out of rental | L75: Yes | N75: Yes | O75: Yes | P75: =IFERROR(VLOOKUP(D75,'TPMS-auto'!A:D, 4,0),"Not-in-TPMS") -> Not-in-TPMS | Q75: =IFERROR(VLOOKUP(Table2[[#This Row],[Unit Number]],Ops,3,0),"Not-in-TPMS") -> Not-in-TPMS | R75: =IFERROR(VLOOKUP(Table2[[#This Row],[Enterprise ID]], 'ExistingRental-12.11'!A:H, 3, 0), "Not Open On 12.11") -> Not Open On 12.11 | S75: =IF(Table2[[#This Row],[Start Rental Date]]="New Rental", "New Rental", "Rental Extension Request") -> Rental Extension Request | T75: =IFERROR(IF(Table2[[#This Row],[Date of this request]]-Table2[[#This Row],[Tech Service Date]]<60, "New Hire Rental", "Truck Breakdown"), "New Hire Rental") -> New Hire Rental | U75: =IFERROR(VLOOKUP(Table2[[#This Row],[Enterprise ID]], 'ExistingRental-12.11'!A:H, 7, 0), "Not Open On 12.11") -> Not Open On 12.11 | V75: =IFERROR(VLOOKUP(Table2[[#This Row],[Enterprise ID]],'Tech-ServiceDate'!A:B,2,0), "EitherNewHire or Termed") -> EitherNewHire or Termed
A76: 45922 | B76: 21633 | C76: Anthony Clayton | D76: ACLAYTO | E76: =TRIM(B76) -> 21633 | F76: =IFERROR(VLOOKUP(D76,'TPMS-auto'!A:J, 10,0), "Not-in-TPMS") -> Not-in-TPMS | G76: =IFERROR(VLOOKUP(D76,'TPMS-auto'!A:J,6,0),"Not-in-TPMS") -> Not-in-TPMS | H76: 45881 | I76: PEP BOYS 1001 BRECKENVILLE LN, LOUISVILLE, KY, 40207 | J76: Van is not in TPMS - ACLAYTO - in rental on 8/12 - van was originally declined, switched from sell to keep on 9/16 - towed from storage lot to Pep Boys - no estimate from Holman or Pep as of 9/22 | K76: Get tech Van #37386 - asap - 37386 does not have a PO in Holman - ROB A call Holman about this one - find out why it doesn't have a PO | L76: Yes | N76: Yes | O76: Yes | P76: =IFERROR(VLOOKUP(D76,'TPMS-auto'!A:D, 4,0),"Not-in-TPMS") -> Not-in-TPMS | Q76: =IFERROR(VLOOKUP(Table2[[#This Row],[Unit Number]],Ops,3,0),"Not-in-TPMS") -> Not-in-TPMS | R76: =IFERROR(VLOOKUP(Table2[[#This Row],[Enterprise ID]], 'ExistingRental-12.11'!A:H, 3, 0), "Not Open On 12.11") -> Not Open On 12.11 | S76: =IF(Table2[[#This Row],[Start Rental Date]]="New Rental", "New Rental", "Rental Extension Request") -> Rental Extension Request | T76: =IFERROR(IF(Table2[[#This Row],[Date of this request]]-Table2[[#This Row],[Tech Service Date]]<60, "New Hire Rental", "Truck Breakdown"), "New Hire Rental") -> New Hire Rental | U76: =IFERROR(VLOOKUP(Table2[[#This Row],[Enterprise ID]], 'ExistingRental-12.11'!A:H, 7, 0), "Not Open On 12.11") -> Not Open On 12.11 | V76: =IFERROR(VLOOKUP(Table2[[#This Row],[Enterprise ID]],'Tech-ServiceDate'!A:B,2,0), "EitherNewHire or Termed") -> EitherNewHire or Termed
A77: 45922 | B77: 46007 | C77: Steven Bailey | D77: SBAILE7 | E77: =TRIM(B77) -> 46007 | F77: =IFERROR(VLOOKUP(D77,'TPMS-auto'!A:J, 10,0), "Not-in-TPMS") -> 2089700407 | G77: =IFERROR(VLOOKUP(D77,'TPMS-auto'!A:J,6,0),"Not-in-TPMS") -> 046007 | H77: New Rental | I77: ALL THINGS AUTOMOTIVE & DIESEL, 1509 CHAFFIN LN, IDAHO FALLS ID 83401 | J77: No AC | K77: Waiting for estimate from shop - | L77: Yes | N77: Yes | O77: Yes | P77: =IFERROR(VLOOKUP(D77,'TPMS-auto'!A:D, 4,0),"Not-in-TPMS") -> 0008228 | Q77: =IFERROR(VLOOKUP(Table2[[#This Row],[Unit Number]],Ops,3,0),"Not-in-TPMS") -> Carol & Tasha | R77: =IFERROR(VLOOKUP(Table2[[#This Row],[Enterprise ID]], 'ExistingRental-12.11'!A:H, 3, 0), "Not Open On 12.11") -> Not Open On 12.11 | S77: =IF(Table2[[#This Row],[Start Rental Date]]="New Rental", "New Rental", "Rental Extension Request") -> New Rental | T77: =IFERROR(IF(Table2[[#This Row],[Date of this request]]-Table2[[#This Row],[Tech Service Date]]<60, "New Hire Rental", "Truck Breakdown"), "New Hire Rental") -> Truck Breakdown | U77: =IFERROR(VLOOKUP(Table2[[#This Row],[Enterprise ID]], 'ExistingRental-12.11'!A:H, 7, 0), "Not Open On 12.11") -> Not Open On 12.11 | V77: =IFERROR(VLOOKUP(Table2[[#This Row],[Enterprise ID]],'Tech-ServiceDate'!A:B,2,0), "EitherNewHire or Termed") -> 43446
A78: 45922 | B78: 23028 | C78: Ron Jones | D78: RJONES2 | E78: =TRIM(B78) -> 23028 | F78: =IFERROR(VLOOKUP(D78,'TPMS-auto'!A:J, 10,0), "Not-in-TPMS") -> 9168834798 | G78: =IFERROR(VLOOKUP(D78,'TPMS-auto'!A:J,6,0),"Not-in-TPMS") -> 047352 | H78: New Rental | I78: FIRESTONE COMPLETE AUTO CARE, 760 IKEA COURT, WEST SACRAMENTO CA 95605 | J78: Just now in TPMS today - tech is assigned truck #47352. The rental should be opened on the correct truck assigned to the technician 47352 | K78: Truck 47352 assigned to the technician in TPMS, but it appears to be needing repair - shows an estimate was declined on 8/22 for $6,196.11 -- was it declined or was it repaired? Remove the TPMS truck assignment IF the tech is getting a new van, when will it be in his possession? John Childres-Jen Dyer?? | L78: Yes | N78: Yes | O78: Yes | P78: =IFERROR(VLOOKUP(D78,'TPMS-auto'!A:D, 4,0),"Not-in-TPMS") -> 0008184 | Q78: =IFERROR(VLOOKUP(Table2[[#This Row],[Unit Number]],Ops,3,0),"Not-in-TPMS") -> Carol & Tasha | R78: =IFERROR(VLOOKUP(Table2[[#This Row],[Enterprise ID]], 'ExistingRental-12.11'!A:H, 3, 0), "Not Open On 12.11") -> Not Open On 12.11 | S78: =IF(Table2[[#This Row],[Start Rental Date]]="New Rental", "New Rental", "Rental Extension Request") -> New Rental | T78: =IFERROR(IF(Table2[[#This Row],[Date of this request]]-Table2[[#This Row],[Tech Service Date]]<60, "New Hire Rental", "Truck Breakdown"), "New Hire Rental") -> Truck Breakdown | U78: =IFERROR(VLOOKUP(Table2[[#This Row],[Enterprise ID]], 'ExistingRental-12.11'!A:H, 7, 0), "Not Open On 12.11") -> Not Open On 12.11 | V78: =IFERROR(VLOOKUP(Table2[[#This Row],[Enterprise ID]],'Tech-ServiceDate'!A:B,2,0), "EitherNewHire or Termed") -> 44742
A79: 45922 | B79: 22258 | C79: RAFAEL ROBERT | D79: RROBERT | E79: =TRIM(B79) -> 22258 | F79: =IFERROR(VLOOKUP(D79,'TPMS-auto'!A:J, 10,0), "Not-in-TPMS") -> 3214295314 | G79: =IFERROR(VLOOKUP(D79,'TPMS-auto'!A:J,6,0),"Not-in-TPMS") -> 022258 | H79: New Rental | I79: Unknown | J79: No AC - tech didn't say where he was taking the van | K79: Need to know where the tech is taking the van prior to approving rental | L79: Yes | N79: No | O79: Yes | P79: =IFERROR(VLOOKUP(D79,'TPMS-auto'!A:D, 4,0),"Not-in-TPMS") -> 0007435 | Q79: =IFERROR(VLOOKUP(Table2[[#This Row],[Unit Number]],Ops,3,0),"Not-in-TPMS") -> Rob & Andrea | R79: =IFERROR(VLOOKUP(Table2[[#This Row],[Enterprise ID]], 'ExistingRental-12.11'!A:H, 3, 0), "Not Open On 12.11") -> Not Open On 12.11 | S79: =IF(Table2[[#This Row],[Start Rental Date]]="New Rental", "New Rental", "Rental Extension Request") -> New Rental | T79: =IFERROR(IF(Table2[[#This Row],[Date of this request]]-Table2[[#This Row],[Tech Service Date]]<60, "New Hire Rental", "Truck Breakdown"), "New Hire Rental") -> Truck Breakdown | U79: =IFERROR(VLOOKUP(Table2[[#This Row],[Enterprise ID]], 'ExistingRental-12.11'!A:H, 7, 0), "Not Open On 12.11") -> Not Open On 12.11 | V79: =IFERROR(VLOOKUP(Table2[[#This Row],[Enterprise ID]],'Tech-ServiceDate'!A:B,2,0), "EitherNewHire or Termed") -> 44798
A80: 45922 | B80: 46884 | C80: FULLER, ROOSEVELT | D80: RFULLER | E80: =TRIM(B80) -> 46884 | F80: =IFERROR(VLOOKUP(D80,'TPMS-auto'!A:J, 10,0), "Not-in-TPMS") -> Not-in-TPMS | G80: =IFERROR(VLOOKUP(D80,'TPMS-auto'!A:J,6,0),"Not-in-TPMS") -> Not-in-TPMS | H80: 45908 | I80: CHEV-BUICK-GMC-CAD OF MURFREES, 960 JOHN R RICE BLVD, MURFREESBORO TN 37129 | J80: Warranty Trans | K80: RFULLER - in rental since 9/8 - transmission is IN WARRANTY with GM - stuck waiting for repairs - Rob to discuss with Holman about getting another shop to repair and bill GM | L80: Yes | N80: Yes | O80: Yes | P80: =IFERROR(VLOOKUP(D80,'TPMS-auto'!A:D, 4,0),"Not-in-TPMS") -> Not-in-TPMS | Q80: =IFERROR(VLOOKUP(Table2[[#This Row],[Unit Number]],Ops,3,0),"Not-in-TPMS") -> Not-in-TPMS | R80: =IFERROR(VLOOKUP(Table2[[#This Row],[Enterprise ID]], 'ExistingRental-12.11'!A:H, 3, 0), "Not Open On 12.11") -> Not Open On 12.11 | S80: =IF(Table2[[#This Row],[Start Rental Date]]="New Rental", "New Rental", "Rental Extension Request") -> Rental Extension Request | T80: =IFERROR(IF(Table2[[#This Row],[Date of this request]]-Table2[[#This Row],[Tech Service Date]]<60, "New Hire Rental", "Truck Breakdown"), "New Hire Rental") -> New Hire Rental | U80: =IFERROR(VLOOKUP(Table2[[#This Row],[Enterprise ID]], 'ExistingRental-12.11'!A:H, 7, 0), "Not Open On 12.11") -> Not Open On 12.11 | V80: =IFERROR(VLOOKUP(Table2[[#This Row],[Enterprise ID]],'Tech-ServiceDate'!A:B,2,0), "EitherNewHire or Termed") -> EitherNewHire or Termed
A81: 45922 | B81: 36026 | C81: RAMZ, SEEAR | D81: SRAMZ | E81: =TRIM(B81) -> 36026 | F81: =IFERROR(VLOOKUP(D81,'TPMS-auto'!A:J, 10,0), "Not-in-TPMS") -> 5406307000 | G81: =IFERROR(VLOOKUP(D81,'TPMS-auto'!A:J,6,0),"Not-in-TPMS") -> 036026 | H81: 45909 | I81: PEP BOYS, 8000 STREAM WALK LN, MANASSAS VA 22110 | J81: Van running rough CEL on | K81: Tech refuses to pick up van, he was told it was done over a week ago, he showed up today and said the AC was not working (it is) and the brakes were bad (they're not) curently driving a 2024 Suburban rental - Tim Michael called tech, he will return the rental today. | L81: Yes | N81: No | O81: No | P81: =IFERROR(VLOOKUP(D81,'TPMS-auto'!A:D, 4,0),"Not-in-TPMS") -> 0007084 | Q81: =IFERROR(VLOOKUP(Table2[[#This Row],[Unit Number]],Ops,3,0),"Not-in-TPMS") -> Monica, Cheryl & Machell | R81: =IFERROR(VLOOKUP(Table2[[#This Row],[Enterprise ID]], 'ExistingRental-12.11'!A:H, 3, 0), "Not Open On 12.11") -> Not Open On 12.11 | S81: =IF(Table2[[#This Row],[Start Rental Date]]="New Rental", "New Rental", "Rental Extension Request") -> Rental Extension Request | T81: =IFERROR(IF(Table2[[#This Row],[Date of this request]]-Table2[[#This Row],[Tech Service Date]]<60, "New Hire Rental", "Truck Breakdown"), "New Hire Rental") -> Truck Breakdown | U81: =IFERROR(VLOOKUP(Table2[[#This Row],[Enterprise ID]], 'ExistingRental-12.11'!A:H, 7, 0), "Not Open On 12.11") -> Not Open On 12.11 | V81: =IFERROR(VLOOKUP(Table2[[#This Row],[Enterprise ID]],'Tech-ServiceDate'!A:B,2,0), "EitherNewHire or Termed") -> 44973
A82: 45922 | B82: 47218 | C82: Dale Meyer | D82: DMEYE1 | E82: =TRIM(B82) -> 47218 | F82: =IFERROR(VLOOKUP(D82,'TPMS-auto'!A:J, 10,0), "Not-in-TPMS") -> 5035191664 | G82: =IFERROR(VLOOKUP(D82,'TPMS-auto'!A:J,6,0),"Not-in-TPMS") -> 047218 | H82: New Rental | I82: LES SCHWAB TIRE CENTER 390 NE BURNSIDE RD GRESHAM OR 97030 | J82: New rental 2 days max | K82: Brake repair - DMEYE1 - since 9/22 - at Les Schwab Tire Repair - repair approved - 2 days rental max per Rob | L82: Yes | N82: Yes | O82: Yes | P82: =IFERROR(VLOOKUP(D82,'TPMS-auto'!A:D, 4,0),"Not-in-TPMS") -> 0008228 | Q82: =IFERROR(VLOOKUP(Table2[[#This Row],[Unit Number]],Ops,3,0),"Not-in-TPMS") -> Carol & Tasha | R82: =IFERROR(VLOOKUP(Table2[[#This Row],[Enterprise ID]], 'ExistingRental-12.11'!A:H, 3, 0), "Not Open On 12.11") -> Not Open On 12.11 | S82: =IF(Table2[[#This Row],[Start Rental Date]]="New Rental", "New Rental", "Rental Extension Request") -> New Rental | T82: =IFERROR(IF(Table2[[#This Row],[Date of this request]]-Table2[[#This Row],[Tech Service Date]]<60, "New Hire Rental", "Truck Breakdown"), "New Hire Rental") -> Truck Breakdown | U82: =IFERROR(VLOOKUP(Table2[[#This Row],[Enterprise ID]], 'ExistingRental-12.11'!A:H, 7, 0), "Not Open On 12.11") -> Not Open On 12.11 | V82: =IFERROR(VLOOKUP(Table2[[#This Row],[Enterprise ID]],'Tech-ServiceDate'!A:B,2,0), "EitherNewHire or Termed") -> 36927
A83: 45922 | B83: 46473 | C83: Paul Thibodo | D83: PTHIBOD | E83: =TRIM(B83) -> 46473 | F83: =IFERROR(VLOOKUP(D83,'TPMS-auto'!A:J, 10,0), "Not-in-TPMS") -> Not-in-TPMS | G83: =IFERROR(VLOOKUP(D83,'TPMS-auto'!A:J,6,0),"Not-in-TPMS") -> Not-in-TPMS | H83: 45874 | I83: PEP BOYS 1641 WIGGLESWORTH WAY WOODBRIDGE VA 22191 | J83: Repair estimate for $433 - Holman was "reminding" Pep Boys from 8/13 through 9/22 -- no answer from Pep Boys - they ended up calling Pep Boys, received the PO and approved it on 9/22 | K83: Van will be repaired by 9/25. | L83: Yes | N83: Yes | O83: Yes | P83: =IFERROR(VLOOKUP(D83,'TPMS-auto'!A:D, 4,0),"Not-in-TPMS") -> Not-in-TPMS | Q83: =IFERROR(VLOOKUP(Table2[[#This Row],[Unit Number]],Ops,3,0),"Not-in-TPMS") -> Not-in-TPMS | R83: =IFERROR(VLOOKUP(Table2[[#This Row],[Enterprise ID]], 'ExistingRental-12.11'!A:H, 3, 0), "Not Open On 12.11") -> Not Open On 12.11 | S83: =IF(Table2[[#This Row],[Start Rental Date]]="New Rental", "New Rental", "Rental Extension Request") -> Rental Extension Request | T83: =IFERROR(IF(Table2[[#This Row],[Date of this request]]-Table2[[#This Row],[Tech Service Date]]<60, "New Hire Rental", "Truck Breakdown"), "New Hire Rental") -> New Hire Rental | U83: =IFERROR(VLOOKUP(Table2[[#This Row],[Enterprise ID]], 'ExistingRental-12.11'!A:H, 7, 0), "Not Open On 12.11") -> Not Open On 12.11 | V83: =IFERROR(VLOOKUP(Table2[[#This Row],[Enterprise ID]],'Tech-ServiceDate'!A:B,2,0), "EitherNewHire or Termed") -> EitherNewHire or Termed
A84: 45922 | B84: 46159 | C84: YURAN, RUDY | D84: RYURANL | E84: =TRIM(B84) -> 46159 | F84: =IFERROR(VLOOKUP(D84,'TPMS-auto'!A:J, 10,0), "Not-in-TPMS") -> Not-in-TPMS | G84: =IFERROR(VLOOKUP(D84,'TPMS-auto'!A:J,6,0),"Not-in-TPMS") -> Not-in-TPMS | H84: 45867 | J84: Van was picked up and driver was to bring van back for further repairs | K84: Rob A Follow up with the driver | N84: No | O84: No | P84: =IFERROR(VLOOKUP(D84,'TPMS-auto'!A:D, 4,0),"Not-in-TPMS") -> Not-in-TPMS | Q84: =IFERROR(VLOOKUP(Table2[[#This Row],[Unit Number]],Ops,3,0),"Not-in-TPMS") -> Not-in-TPMS | R84: =IFERROR(VLOOKUP(Table2[[#This Row],[Enterprise ID]], 'ExistingRental-12.11'!A:H, 3, 0), "Not Open On 12.11") -> Not Open On 12.11 | S84: =IF(Table2[[#This Row],[Start Rental Date]]="New Rental", "New Rental", "Rental Extension Request") -> Rental Extension Request | T84: =IFERROR(IF(Table2[[#This Row],[Date of this request]]-Table2[[#This Row],[Tech Service Date]]<60, "New Hire Rental", "Truck Breakdown"), "New Hire Rental") -> Truck Breakdown | U84: =IFERROR(VLOOKUP(Table2[[#This Row],[Enterprise ID]], 'ExistingRental-12.11'!A:H, 7, 0), "Not Open On 12.11") -> Not Open On 12.11 | V84: =IFERROR(VLOOKUP(Table2[[#This Row],[Enterprise ID]],'Tech-ServiceDate'!A:B,2,0), "EitherNewHire or Termed") -> 44686
A85: 45922 | B85: 47291 | C85: Sean Wicklander | D85: SWICKLA | E85: =TRIM(B85) -> 47291 | F85: =IFERROR(VLOOKUP(D85,'TPMS-auto'!A:J, 10,0), "Not-in-TPMS") -> 7154922473 | G85: =IFERROR(VLOOKUP(D85,'TPMS-auto'!A:J,6,0),"Not-in-TPMS") -> 047291 | H85: 45894 | I85: Declined repair - ADVANCED TRANSMISSION SVC LLC, 1233 W. CLAIREMONT AVE., EAU CLAIRE WI 54301 | J85: Declined in JUNE - no solution in place? | K85: John - Jen - what is the status of getting the van to the tech? | L85: Yes | N85: Yes | O85: Yes | P85: =IFERROR(VLOOKUP(D85,'TPMS-auto'!A:D, 4,0),"Not-in-TPMS") -> 0008162 | Q85: =IFERROR(VLOOKUP(Table2[[#This Row],[Unit Number]],Ops,3,0),"Not-in-TPMS") -> Monica, Cheryl & Machell | R85: =IFERROR(VLOOKUP(Table2[[#This Row],[Enterprise ID]], 'ExistingRental-12.11'!A:H, 3, 0), "Not Open On 12.11") -> 45895 | S85: =IF(Table2[[#This Row],[Start Rental Date]]="New Rental", "New Rental", "Rental Extension Request") -> Rental Extension Request | T85: =IFERROR(IF(Table2[[#This Row],[Date of this request]]-Table2[[#This Row],[Tech Service Date]]<60, "New Hire Rental", "Truck Breakdown"), "New Hire Rental") -> Truck Breakdown | U85: =IFERROR(VLOOKUP(Table2[[#This Row],[Enterprise ID]], 'ExistingRental-12.11'!A:H, 7, 0), "Not Open On 12.11") -> SEAN WICKLANDER | V85: =IFERROR(VLOOKUP(Table2[[#This Row],[Enterprise ID]],'Tech-ServiceDate'!A:B,2,0), "EitherNewHire or Termed") -> 44896
A86: 45922 | B86: 61842 | C86: William Every | D86: WEVERY1 | E86: =TRIM(B86) -> 61842 | F86: =IFERROR(VLOOKUP(D86,'TPMS-auto'!A:J, 10,0), "Not-in-TPMS") -> 5855539662 | G86: =IFERROR(VLOOKUP(D86,'TPMS-auto'!A:J,6,0),"Not-in-TPMS") -> 061842 | H86: 45915 | I86: PEP BOYS, 1375 MARKET PLACE DR, HENRIETTA NY 14623 | J86: Approved on 9/19 no eta at this time - tech got rental on 9/15, had a wreck on 9/17 - rear ended by another driver | K86: Repair finally approved at Pep Boys on 9/19 - multiple issues | L86: Yes | N86: Yes | O86: Yes | P86: =IFERROR(VLOOKUP(D86,'TPMS-auto'!A:D, 4,0),"Not-in-TPMS") -> 0007670 | Q86: =IFERROR(VLOOKUP(Table2[[#This Row],[Unit Number]],Ops,3,0),"Not-in-TPMS") -> Rob & Andrea | R86: =IFERROR(VLOOKUP(Table2[[#This Row],[Enterprise ID]], 'ExistingRental-12.11'!A:H, 3, 0), "Not Open On 12.11") -> Not Open On 12.11 | S86: =IF(Table2[[#This Row],[Start Rental Date]]="New Rental", "New Rental", "Rental Extension Request") -> Rental Extension Request | T86: =IFERROR(IF(Table2[[#This Row],[Date of this request]]-Table2[[#This Row],[Tech Service Date]]<60, "New Hire Rental", "Truck Breakdown"), "New Hire Rental") -> Truck Breakdown | U86: =IFERROR(VLOOKUP(Table2[[#This Row],[Enterprise ID]], 'ExistingRental-12.11'!A:H, 7, 0), "Not Open On 12.11") -> Not Open On 12.11 | V86: =IFERROR(VLOOKUP(Table2[[#This Row],[Enterprise ID]],'Tech-ServiceDate'!A:B,2,0), "EitherNewHire or Termed") -> 34260
A87: 45923 | B87: 36876 | C87: HUTCHINSON, ADAM | D87: AHUTCHI | E87: =TRIM(B87) -> 36876 | F87: =IFERROR(VLOOKUP(D87,'TPMS-auto'!A:J, 10,0), "Not-in-TPMS") -> 3619051148 | G87: =IFERROR(VLOOKUP(D87,'TPMS-auto'!A:J,6,0),"Not-in-TPMS") -> 036876 | H87: 45881 | I87: NEESSEN CHEVROLET INC., 2007 S US HWY 77, PO BOX 1573, KINGSVILLE TX 78363 | J87: Rob Anderson declined on 8/12 - $5,677.60 Van is at NEESSEN CHEVROLET INC., 2007 S US HWY 77, PO BOX 1573, KINGSVILLE TX 78363 - tech AHUTCHI needs a permanent van assignment | K87: Get the tech another van assigned asap - John Childres and Jen Dyer | L87: Yes | N87: Yes | O87: Yes | P87: =IFERROR(VLOOKUP(D87,'TPMS-auto'!A:D, 4,0),"Not-in-TPMS") -> 0008147 | Q87: =IFERROR(VLOOKUP(Table2[[#This Row],[Unit Number]],Ops,3,0),"Not-in-TPMS") -> Carol & Tasha | R87: =IFERROR(VLOOKUP(Table2[[#This Row],[Enterprise ID]], 'ExistingRental-12.11'!A:H, 3, 0), "Not Open On 12.11") -> Not Open On 12.11 | S87: =IF(Table2[[#This Row],[Start Rental Date]]="New Rental", "New Rental", "Rental Extension Request") -> Rental Extension Request | T87: =IFERROR(IF(Table2[[#This Row],[Date of this request]]-Table2[[#This Row],[Tech Service Date]]<60, "New Hire Rental", "Truck Breakdown"), "New Hire Rental") -> Truck Breakdown | U87: =IFERROR(VLOOKUP(Table2[[#This Row],[Enterprise ID]], 'ExistingRental-12.11'!A:H, 7, 0), "Not Open On 12.11") -> Not Open On 12.11 | V87: =IFERROR(VLOOKUP(Table2[[#This Row],[Enterprise ID]],'Tech-ServiceDate'!A:B,2,0), "EitherNewHire or Termed") -> 45718
A88: 45923 | B88: 46315 | C88: ALEXANDER STURNS | D88: ASTURNS | E88: =TRIM(B88) -> 46315 | F88: =IFERROR(VLOOKUP(D88,'TPMS-auto'!A:J, 10,0), "Not-in-TPMS") -> 2819350549 | G88: =IFERROR(VLOOKUP(D88,'TPMS-auto'!A:J,6,0),"Not-in-TPMS") -> 046315 | H88: 45873 | I88: AAMCO TOTAL CAR CARE, 1377 SOUTH LOOP WEST, HOUSTON TX 77054 | J88: ASTURNS - in rental since 8/4 - Declined repair $7609 - need to get the tech a van | K88: Needs permenant van assigned - John C and Jen - tech needs a van assignment | L88: Yes | N88: Yes | O88: Yes | P88: =IFERROR(VLOOKUP(D88,'TPMS-auto'!A:D, 4,0),"Not-in-TPMS") -> 0008107 | Q88: =IFERROR(VLOOKUP(Table2[[#This Row],[Unit Number]],Ops,3,0),"Not-in-TPMS") -> Carol & Tasha | R88: =IFERROR(VLOOKUP(Table2[[#This Row],[Enterprise ID]], 'ExistingRental-12.11'!A:H, 3, 0), "Not Open On 12.11") -> Not Open On 12.11 | S88: =IF(Table2[[#This Row],[Start Rental Date]]="New Rental", "New Rental", "Rental Extension Request") -> Rental Extension Request | T88: =IFERROR(IF(Table2[[#This Row],[Date of this request]]-Table2[[#This Row],[Tech Service Date]]<60, "New Hire Rental", "Truck Breakdown"), "New Hire Rental") -> Truck Breakdown | U88: =IFERROR(VLOOKUP(Table2[[#This Row],[Enterprise ID]], 'ExistingRental-12.11'!A:H, 7, 0), "Not Open On 12.11") -> Not Open On 12.11 | V88: =IFERROR(VLOOKUP(Table2[[#This Row],[Enterprise ID]],'Tech-ServiceDate'!A:B,2,0), "EitherNewHire or Termed") -> 40623
A89: 45923 | B89: 46598 | C89: FELIX, ASCHBEA | D89: AFELIX | E89: =TRIM(B89) -> 46598 | F89: =IFERROR(VLOOKUP(D89,'TPMS-auto'!A:J, 10,0), "Not-in-TPMS") -> 7186904729 | G89: =IFERROR(VLOOKUP(D89,'TPMS-auto'!A:J,6,0),"Not-in-TPMS") -> 046598 | L89: Yes | N89: Yes | O89: Yes | P89: =IFERROR(VLOOKUP(D89,'TPMS-auto'!A:D, 4,0),"Not-in-TPMS") -> 0007744 | Q89: =IFERROR(VLOOKUP(Table2[[#This Row],[Unit Number]],Ops,3,0),"Not-in-TPMS") -> Rob & Andrea | R89: =IFERROR(VLOOKUP(Table2[[#This Row],[Enterprise ID]], 'ExistingRental-12.11'!A:H, 3, 0), "Not Open On 12.11") -> 45880 | S89: =IF(Table2[[#This Row],[Start Rental Date]]="New Rental", "New Rental", "Rental Extension Request") -> Rental Extension Request | T89: =IFERROR(IF(Table2[[#This Row],[Date of this request]]-Table2[[#This Row],[Tech Service Date]]<60, "New Hire Rental", "Truck Breakdown"), "New Hire Rental") -> New Hire Rental | U89: =IFERROR(VLOOKUP(Table2[[#This Row],[Enterprise ID]], 'ExistingRental-12.11'!A:H, 7, 0), "Not Open On 12.11") -> ASCHBEA FELIX | V89: =IFERROR(VLOOKUP(Table2[[#This Row],[Enterprise ID]],'Tech-ServiceDate'!A:B,2,0), "EitherNewHire or Termed") -> 45865
A90: 45923 | B90: 46431 | C90: Ashely Orozco | D90: AOROZCO | E90: =TRIM(B90) -> 46431 | F90: =IFERROR(VLOOKUP(D90,'TPMS-auto'!A:J, 10,0), "Not-in-TPMS") -> 8189411387 | G90: =IFERROR(VLOOKUP(D90,'TPMS-auto'!A:J,6,0),"Not-in-TPMS") -> 046431 | H90: New Rental | I90: PEP BOYS, 1231 SAN FERNANDO RD, SAN FERNANDO CA 91340 | J90: CEL on loss of power | K90: New Rental - what is the ETA on repair? Rob Anderson | L90: Yes | N90: Yes | O90: Yes | P90: =IFERROR(VLOOKUP(D90,'TPMS-auto'!A:D, 4,0),"Not-in-TPMS") -> 0007108 | Q90: =IFERROR(VLOOKUP(Table2[[#This Row],[Unit Number]],Ops,3,0),"Not-in-TPMS") -> Carol & Tasha | R90: =IFERROR(VLOOKUP(Table2[[#This Row],[Enterprise ID]], 'ExistingRental-12.11'!A:H, 3, 0), "Not Open On 12.11") -> 45981 | S90: =IF(Table2[[#This Row],[Start Rental Date]]="New Rental", "New Rental", "Rental Extension Request") -> New Rental | T90: =IFERROR(IF(Table2[[#This Row],[Date of this request]]-Table2[[#This Row],[Tech Service Date]]<60, "New Hire Rental", "Truck Breakdown"), "New Hire Rental") -> Truck Breakdown | U90: =IFERROR(VLOOKUP(Table2[[#This Row],[Enterprise ID]], 'ExistingRental-12.11'!A:H, 7, 0), "Not Open On 12.11") -> ASHLEY OROZCO | V90: =IFERROR(VLOOKUP(Table2[[#This Row],[Enterprise ID]],'Tech-ServiceDate'!A:B,2,0), "EitherNewHire or Termed") -> 45802
A91: 45923 | B91: 37051 | C91: HANSEN, DAVID | D91: DHANSE9 | E91: =TRIM(B91) -> 37051 | F91: =IFERROR(VLOOKUP(D91,'TPMS-auto'!A:J, 10,0), "Not-in-TPMS") -> 4343635938 | G91: =IFERROR(VLOOKUP(D91,'TPMS-auto'!A:J,6,0),"Not-in-TPMS") -> 037051 | H91: 45859 | I91: PINKERTON CHEVROLET- LYNCHBURG, 801 GRAVES MILL RD., LYNCHBURG VA 24502 | J91: 9/4: DVR DAVID HANSEN CALLED STATING VEH NEEDS TO BE TOWED TO DEALER BECAUSE THIS VENDOR FOUND IN LIMP ,ODE AND 11 DTC'S AND MORE THAN TECH CAN HANDLE. I CALLED F/A ROB ANDERSON AND HE ADVISED TO HAVE VEH TOWED TO LYNCHBURG CHEVROLET PER DVR REQUEST . I CALLED DEALER AND ANNOUNCED THE VEHICLE . | K91: Get the van repaired - at PINKERTON CHEVROLET- LYNCHBURG 801 GRAVES MILL RD. LYNCHBURG VA 24502 - PO approved on 9/10 - for $874 - tech has been in rental since 7/21 - Rob Anderson | L91: Yes | N91: Yes | O91: Yes | P91: =IFERROR(VLOOKUP(D91,'TPMS-auto'!A:D, 4,0),"Not-in-TPMS") -> 0008175 | Q91: =IFERROR(VLOOKUP(Table2[[#This Row],[Unit Number]],Ops,3,0),"Not-in-TPMS") -> Rob & Andrea | R91: =IFERROR(VLOOKUP(Table2[[#This Row],[Enterprise ID]], 'ExistingRental-12.11'!A:H, 3, 0), "Not Open On 12.11") -> Not Open On 12.11 | S91: =IF(Table2[[#This Row],[Start Rental Date]]="New Rental", "New Rental", "Rental Extension Request") -> Rental Extension Request | T91: =IFERROR(IF(Table2[[#This Row],[Date of this request]]-Table2[[#This Row],[Tech Service Date]]<60, "New Hire Rental", "Truck Breakdown"), "New Hire Rental") -> Truck Breakdown | U91: =IFERROR(VLOOKUP(Table2[[#This Row],[Enterprise ID]], 'ExistingRental-12.11'!A:H, 7, 0), "Not Open On 12.11") -> Not Open On 12.11 | V91: =IFERROR(VLOOKUP(Table2[[#This Row],[Enterprise ID]],'Tech-ServiceDate'!A:B,2,0), "EitherNewHire or Termed") -> 42107
A92: 45923 | B92: 46585 | C92: Hector Fernadez | D92: HFERNAN | E92: =TRIM(B92) -> 46585 | F92: =IFERROR(VLOOKUP(D92,'TPMS-auto'!A:J, 10,0), "Not-in-TPMS") -> 9736260994 | G92: =IFERROR(VLOOKUP(D92,'TPMS-auto'!A:J,6,0),"Not-in-TPMS") -> 046585 | H92: New Rental | I92: AAA 3478 US-9, FREEHOLD, NJ 07728 | J92: Van will not start | K92: New rental - | L92: Yes | N92: Yes | O92: Yes | P92: =IFERROR(VLOOKUP(D92,'TPMS-auto'!A:D, 4,0),"Not-in-TPMS") -> 0008380 | Q92: =IFERROR(VLOOKUP(Table2[[#This Row],[Unit Number]],Ops,3,0),"Not-in-TPMS") -> Rob & Andrea | R92: =IFERROR(VLOOKUP(Table2[[#This Row],[Enterprise ID]], 'ExistingRental-12.11'!A:H, 3, 0), "Not Open On 12.11") -> Not Open On 12.11 | S92: =IF(Table2[[#This Row],[Start Rental Date]]="New Rental", "New Rental", "Rental Extension Request") -> New Rental | T92: =IFERROR(IF(Table2[[#This Row],[Date of this request]]-Table2[[#This Row],[Tech Service Date]]<60, "New Hire Rental", "Truck Breakdown"), "New Hire Rental") -> New Hire Rental | U92: =IFERROR(VLOOKUP(Table2[[#This Row],[Enterprise ID]], 'ExistingRental-12.11'!A:H, 7, 0), "Not Open On 12.11") -> Not Open On 12.11 | V92: =IFERROR(VLOOKUP(Table2[[#This Row],[Enterprise ID]],'Tech-ServiceDate'!A:B,2,0), "EitherNewHire or Termed") -> 45886
A93: 45923 | B93: 37402 | C93: Jamie Adachi | D93: JADACHI | E93: =TRIM(B93) -> 37402 | F93: =IFERROR(VLOOKUP(D93,'TPMS-auto'!A:J, 10,0), "Not-in-TPMS") -> Not-in-TPMS | G93: =IFERROR(VLOOKUP(D93,'TPMS-auto'!A:J,6,0),"Not-in-TPMS") -> Not-in-TPMS | H93: New Rental | I93: LA QUINTA CHEVROLET, 79-225 HIGHWAY 111, LA QUINTA CA 92253 | J93: No AC, CEL on, loss of power | K93: New Rental - what is the ETA on repair? Rob Anderson | L93: Yes | N93: Yes | O93: Yes | P93: =IFERROR(VLOOKUP(D93,'TPMS-auto'!A:D, 4,0),"Not-in-TPMS") -> Not-in-TPMS | Q93: =IFERROR(VLOOKUP(Table2[[#This Row],[Unit Number]],Ops,3,0),"Not-in-TPMS") -> Not-in-TPMS | R93: =IFERROR(VLOOKUP(Table2[[#This Row],[Enterprise ID]], 'ExistingRental-12.11'!A:H, 3, 0), "Not Open On 12.11") -> Not Open On 12.11 | S93: =IF(Table2[[#This Row],[Start Rental Date]]="New Rental", "New Rental", "Rental Extension Request") -> New Rental | T93: =IFERROR(IF(Table2[[#This Row],[Date of this request]]-Table2[[#This Row],[Tech Service Date]]<60, "New Hire Rental", "Truck Breakdown"), "New Hire Rental") -> New Hire Rental | U93: =IFERROR(VLOOKUP(Table2[[#This Row],[Enterprise ID]], 'ExistingRental-12.11'!A:H, 7, 0), "Not Open On 12.11") -> Not Open On 12.11 | V93: =IFERROR(VLOOKUP(Table2[[#This Row],[Enterprise ID]],'Tech-ServiceDate'!A:B,2,0), "EitherNewHire or Termed") -> EitherNewHire or Termed
A94: 45923 | B94: 36903 | C94: JONATHAN HUDNALL | D94: JHUDNA1 | E94: =TRIM(B94) -> 36903 | F94: =IFERROR(VLOOKUP(D94,'TPMS-auto'!A:J, 10,0), "Not-in-TPMS") -> 2109541809 | G94: =IFERROR(VLOOKUP(D94,'TPMS-auto'!A:J,6,0),"Not-in-TPMS") -> 036903 | H94: 45923 | I94: Was in Transit | J94: Tech moving from San Antonio to Corpus Cristi | K94: Tech picked up the van and is good to go / Address updated in TPMS/AMS/Holman / jchild2 | L94: Yes | N94: No | O94: No | P94: =IFERROR(VLOOKUP(D94,'TPMS-auto'!A:D, 4,0),"Not-in-TPMS") -> 0008147 | Q94: =IFERROR(VLOOKUP(Table2[[#This Row],[Unit Number]],Ops,3,0),"Not-in-TPMS") -> Carol & Tasha | R94: =IFERROR(VLOOKUP(Table2[[#This Row],[Enterprise ID]], 'ExistingRental-12.11'!A:H, 3, 0), "Not Open On 12.11") -> Not Open On 12.11 | S94: =IF(Table2[[#This Row],[Start Rental Date]]="New Rental", "New Rental", "Rental Extension Request") -> Rental Extension Request | T94: =IFERROR(IF(Table2[[#This Row],[Date of this request]]-Table2[[#This Row],[Tech Service Date]]<60, "New Hire Rental", "Truck Breakdown"), "New Hire Rental") -> Truck Breakdown | U94: =IFERROR(VLOOKUP(Table2[[#This Row],[Enterprise ID]], 'ExistingRental-12.11'!A:H, 7, 0), "Not Open On 12.11") -> Not Open On 12.11 | V94: =IFERROR(VLOOKUP(Table2[[#This Row],[Enterprise ID]],'Tech-ServiceDate'!A:B,2,0), "EitherNewHire or Termed") -> 44200
A95: 45923 | B95: 61746 | C95: JARRETT, KEVIN | D95: KJARRET | E95: =TRIM(B95) -> 61746 | F95: =IFERROR(VLOOKUP(D95,'TPMS-auto'!A:J, 10,0), "Not-in-TPMS") -> 5855539663 | G95: =IFERROR(VLOOKUP(D95,'TPMS-auto'!A:J,6,0),"Not-in-TPMS") -> 061746 | H95: 45845 | I95: PEP BOYS, 1375 MARKET PLACE DR, HENRIETTA NY 14623 | J95: Declined repair in July - no solution in place, we are spending more on rental than the repair declined | K95: KJARRET - in rental since 7/7 - Declined repair was $4,622.33 at Pep Boys - why haven't we solved this? Rob Anderson - get repair reconsidered asap Van is very Rusty and shop does not recommend repairing the van | L95: Yes | N95: Yes | O95: Yes | P95: =IFERROR(VLOOKUP(D95,'TPMS-auto'!A:D, 4,0),"Not-in-TPMS") -> 0007670 | Q95: =IFERROR(VLOOKUP(Table2[[#This Row],[Unit Number]],Ops,3,0),"Not-in-TPMS") -> Rob & Andrea | R95: =IFERROR(VLOOKUP(Table2[[#This Row],[Enterprise ID]], 'ExistingRental-12.11'!A:H, 3, 0), "Not Open On 12.11") -> 45954 | S95: =IF(Table2[[#This Row],[Start Rental Date]]="New Rental", "New Rental", "Rental Extension Request") -> Rental Extension Request | T95: =IFERROR(IF(Table2[[#This Row],[Date of this request]]-Table2[[#This Row],[Tech Service Date]]<60, "New Hire Rental", "Truck Breakdown"), "New Hire Rental") -> Truck Breakdown | U95: =IFERROR(VLOOKUP(Table2[[#This Row],[Enterprise ID]], 'ExistingRental-12.11'!A:H, 7, 0), "Not Open On 12.11") -> KEVIN JARRETT | V95: =IFERROR(VLOOKUP(Table2[[#This Row],[Enterprise ID]],'Tech-ServiceDate'!A:B,2,0), "EitherNewHire or Termed") -> 35572
A96: 45923 | B96: 47273 | C96: Mark Higgins | D96: MHIGGI0 | E96: =TRIM(B96) -> 47273 | F96: =IFERROR(VLOOKUP(D96,'TPMS-auto'!A:J, 10,0), "Not-in-TPMS") -> 2085803354 | G96: =IFERROR(VLOOKUP(D96,'TPMS-auto'!A:J,6,0),"Not-in-TPMS") -> 047273 | H96: New Rental | I96: BLUE WRENCH, 265 N BALTIC PL, MERIDIAN ID 83642 | J96: Probably broken shiift cable | K96: New Rental - what is the ETA on repair? Rob Anderson | L96: Yes | N96: Yes | O96: Yes | P96: =IFERROR(VLOOKUP(D96,'TPMS-auto'!A:D, 4,0),"Not-in-TPMS") -> 0008228 | Q96: =IFERROR(VLOOKUP(Table2[[#This Row],[Unit Number]],Ops,3,0),"Not-in-TPMS") -> Carol & Tasha | R96: =IFERROR(VLOOKUP(Table2[[#This Row],[Enterprise ID]], 'ExistingRental-12.11'!A:H, 3, 0), "Not Open On 12.11") -> 46000 | S96: =IF(Table2[[#This Row],[Start Rental Date]]="New Rental", "New Rental", "Rental Extension Request") -> New Rental | T96: =IFERROR(IF(Table2[[#This Row],[Date of this request]]-Table2[[#This Row],[Tech Service Date]]<60, "New Hire Rental", "Truck Breakdown"), "New Hire Rental") -> Truck Breakdown | U96: =IFERROR(VLOOKUP(Table2[[#This Row],[Enterprise ID]], 'ExistingRental-12.11'!A:H, 7, 0), "Not Open On 12.11") -> MARK HIGGINS | V96: =IFERROR(VLOOKUP(Table2[[#This Row],[Enterprise ID]],'Tech-ServiceDate'!A:B,2,0), "EitherNewHire or Termed") -> 44462
A97: 45923 | B97: 36056 | C97: MUSTAFA EBADI | D97: MEBADI | E97: =TRIM(B97) -> 36056 | F97: =IFERROR(VLOOKUP(D97,'TPMS-auto'!A:J, 10,0), "Not-in-TPMS") -> 3017930671 | G97: =IFERROR(VLOOKUP(D97,'TPMS-auto'!A:J,6,0),"Not-in-TPMS") -> 036056 | H97: 45855 | I97: MEBADI - in rental since 7/17 -- PEP BOYS 1641 WIGGLESWORTH WAY WOODBRIDGE VA 22191 - last repair approved for engine diagnostics - 9/22 - was repaired on another PO at the same Pep Boys for $574 - brakes | K97: Stop the insanity - get this van repaired and to the technician this week - Rob Anderson | L97: Yes | N97: Yes | O97: Yes | P97: =IFERROR(VLOOKUP(D97,'TPMS-auto'!A:D, 4,0),"Not-in-TPMS") -> 0007084 | Q97: =IFERROR(VLOOKUP(Table2[[#This Row],[Unit Number]],Ops,3,0),"Not-in-TPMS") -> Monica, Cheryl & Machell | R97: =IFERROR(VLOOKUP(Table2[[#This Row],[Enterprise ID]], 'ExistingRental-12.11'!A:H, 3, 0), "Not Open On 12.11") -> 45856 | S97: =IF(Table2[[#This Row],[Start Rental Date]]="New Rental", "New Rental", "Rental Extension Request") -> Rental Extension Request | T97: =IFERROR(IF(Table2[[#This Row],[Date of this request]]-Table2[[#This Row],[Tech Service Date]]<60, "New Hire Rental", "Truck Breakdown"), "New Hire Rental") -> Truck Breakdown | U97: =IFERROR(VLOOKUP(Table2[[#This Row],[Enterprise ID]], 'ExistingRental-12.11'!A:H, 7, 0), "Not Open On 12.11") -> MUSTAFA EBADI | V97: =IFERROR(VLOOKUP(Table2[[#This Row],[Enterprise ID]],'Tech-ServiceDate'!A:B,2,0), "EitherNewHire or Termed") -> 44658
A98: 45923 | B98: 46551 | C98: BLAIR HORNICK | D98: BHORNIC | E98: =TRIM(B98) -> 46551 | F98: =IFERROR(VLOOKUP(D98,'TPMS-auto'!A:J, 10,0), "Not-in-TPMS") -> 7177210063 | G98: =IFERROR(VLOOKUP(D98,'TPMS-auto'!A:J,6,0),"Not-in-TPMS") -> 046527 | H98: 45866 | J98: Declined repair $10,052 | K98: Needs permenant van assigned - John C and Jen - tech needs a van assignment | L98: Yes | N98: Yes | O98: Yes | P98: =IFERROR(VLOOKUP(D98,'TPMS-auto'!A:D, 4,0),"Not-in-TPMS") -> 0006141 | Q98: =IFERROR(VLOOKUP(Table2[[#This Row],[Unit Number]],Ops,3,0),"Not-in-TPMS") -> Monica, Cheryl & Machell | R98: =IFERROR(VLOOKUP(Table2[[#This Row],[Enterprise ID]], 'ExistingRental-12.11'!A:H, 3, 0), "Not Open On 12.11") -> Not Open On 12.11 | S98: =IF(Table2[[#This Row],[Start Rental Date]]="New Rental", "New Rental", "Rental Extension Request") -> Rental Extension Request | T98: =IFERROR(IF(Table2[[#This Row],[Date of this request]]-Table2[[#This Row],[Tech Service Date]]<60, "New Hire Rental", "Truck Breakdown"), "New Hire Rental") -> Truck Breakdown | U98: =IFERROR(VLOOKUP(Table2[[#This Row],[Enterprise ID]], 'ExistingRental-12.11'!A:H, 7, 0), "Not Open On 12.11") -> Not Open On 12.11 | V98: =IFERROR(VLOOKUP(Table2[[#This Row],[Enterprise ID]],'Tech-ServiceDate'!A:B,2,0), "EitherNewHire or Termed") -> 44798
A99: 45923 | B99: 61137 | C99: GOSSELIN, TIMOTHY | D99: TGOSSEL | E99: =TRIM(B99) -> 61137 | F99: =IFERROR(VLOOKUP(D99,'TPMS-auto'!A:J, 10,0), "Not-in-TPMS") -> 2073308276 | G99: =IFERROR(VLOOKUP(D99,'TPMS-auto'!A:J,6,0),"Not-in-TPMS") -> 0 | H99: 45846 | I99: 7/7/25 - Declined repair - $7,010.66 at DARLINGS BRUNSWICK FORD, 262 BATH RD, BRUNSWICK ME 040112619 | J99: Declined repair for $7K but no solution deployed since 7/7 - tech still in the rental since then! | K99: Need a new van for this tech - John C and Jen Dyer | L99: Yes | N99: Yes | O99: Yes | P99: =IFERROR(VLOOKUP(D99,'TPMS-auto'!A:D, 4,0),"Not-in-TPMS") -> 0007670 | Q99: =IFERROR(VLOOKUP(Table2[[#This Row],[Unit Number]],Ops,3,0),"Not-in-TPMS") -> Rob & Andrea | R99: =IFERROR(VLOOKUP(Table2[[#This Row],[Enterprise ID]], 'ExistingRental-12.11'!A:H, 3, 0), "Not Open On 12.11") -> 45997 | S99: =IF(Table2[[#This Row],[Start Rental Date]]="New Rental", "New Rental", "Rental Extension Request") -> Rental Extension Request | T99: =IFERROR(IF(Table2[[#This Row],[Date of this request]]-Table2[[#This Row],[Tech Service Date]]<60, "New Hire Rental", "Truck Breakdown"), "New Hire Rental") -> Truck Breakdown | U99: =IFERROR(VLOOKUP(Table2[[#This Row],[Enterprise ID]], 'ExistingRental-12.11'!A:H, 7, 0), "Not Open On 12.11") -> TIMOTHY GOSSELIN | V99: =IFERROR(VLOOKUP(Table2[[#This Row],[Enterprise ID]],'Tech-ServiceDate'!A:B,2,0), "EitherNewHire or Termed") -> 42885
A100: 45923 | B100: 36777 | C100: BRUNT, TIMOTHY | D100: TBRUNT | E100: =TRIM(B100) -> 36777 | F100: =IFERROR(VLOOKUP(D100,'TPMS-auto'!A:J, 10,0), "Not-in-TPMS") -> 3372300429 | G100: =IFERROR(VLOOKUP(D100,'TPMS-auto'!A:J,6,0),"Not-in-TPMS") -> 036636 | H100: 45917 | I100: ROGERS TRUCK REPAIR, LLC, 900 S ROBERTS ST, AMARILLO TX 79102 | J100: TBRUNT assigned van in TPMS on 9/19 ; TBRUNT in rental since 9/17 - van repair was approved on 8/27 and what is the status of the repair? | K100: Truck assigned to TBRUNT on 9/19 - what is the solution to get van to technician? John Childres, Jen Dyer | L100: Yes | N100: Yes | O100: Yes | P100: =IFERROR(VLOOKUP(D100,'TPMS-auto'!A:D, 4,0),"Not-in-TPMS") -> 0008107 | Q100: =IFERROR(VLOOKUP(Table2[[#This Row],[Unit Number]],Ops,3,0),"Not-in-TPMS") -> Carol & Tasha | R100: =IFERROR(VLOOKUP(Table2[[#This Row],[Enterprise ID]], 'ExistingRental-12.11'!A:H, 3, 0), "Not Open On 12.11") -> 45959 | S100: =IF(Table2[[#This Row],[Start Rental Date]]="New Rental", "New Rental", "Rental Extension Request") -> Rental Extension Request | T100: =IFERROR(IF(Table2[[#This Row],[Date of this request]]-Table2[[#This Row],[Tech Service Date]]<60, "New Hire Rental", "Truck Breakdown"), "New Hire Rental") -> Truck Breakdown | U100: =IFERROR(VLOOKUP(Table2[[#This Row],[Enterprise ID]], 'ExistingRental-12.11'!A:H, 7, 0), "Not Open On 12.11") -> TIMOTHY BRUNT | V100: =IFERROR(VLOOKUP(Table2[[#This Row],[Enterprise ID]],'Tech-ServiceDate'!A:B,2,0), "EitherNewHire or Termed") -> 45837
...

Sheet Ops Team
A1: Unit | B1: Group | C1: Assigned Team
A2: 0004766 | B2: 1 | C2: Rob & Andrea
A3: 0007435 | B3: 1 | C3: Rob & Andrea
A4: 0007670 | B4: 1 | C4: Rob & Andrea
A5: 0007744 | B5: 1 | C5: Rob & Andrea
A6: 0007983 | B6: 1 | C6: Rob & Andrea
A7: 0008035 | B7: 1 | C7: Rob & Andrea
A8: 0008175 | B8: 1 | C8: Rob & Andrea
A9: 0008420 | B9: 1 | C9: Rob & Andrea
A10: 0008380 | B10: 1 | C10: Rob & Andrea
A11: 0006141 | B11: 2 | C11: Monica, Cheryl & Machell
A12: 0007084 | B12: 2 | C12: Monica, Cheryl & Machell
A13: 0007323 | B13: 2 | C13: Monica, Cheryl & Machell
... A30: 0008366 | B30: 3 | C30: Carol & Tasha

Sheet ExistingRental-12.11
A1: Rental Tech Enterprise ID | B1: Truck Listed for Rental | C1: Rental Start Date | D1: Rental Days | E1: Rental under Name: | F1: Rental Tech Enterprise ID | G1: Truck Assigned to in TPMS | H1: Truck assigned to in TPMS Enterprise ID | I1: LU Employment Service Date
A2: =H2 -> AARNOLD | B2: 46863 | C2: 45992 | D2: Less than 14 days | E2: ANTHONY ARNOLD | F2: AARNOLD | G2: ANTHONY ARNOLD | H2: AARNOLD | I2: 45935
A3: =H3 -> ABEHLE | B3: 61432 | C3: 45980 | D3: 21 plus days | E3: ADAM BEHLER | F3: ABEHLE | G3: ADAM BEHLER | H3: ABEHLE | I3: 37137
A4: =H4 -> ABIBLEJ | B4: 61222 | C4: 45980 | D4: 21 plus days | E4: ARTHUR BIBLE | F4: RESEARCH!! | G4: ARTHUR BIBLE JR | H4: ABIBLEJ | I4: 42038
A5: =H5 -> ABLAND | B5: 46689 | C5: 45846 | D5: 28 plus days | E5: JONATHAN MCMEINS | F5: JMCMEIN | G5: AMIR BLAND | H5: ABLAND | I5: 45851
A6: =H6 -> ABLAND | B6: 46689 | C6: 45861 | D6: 28 plus days | E6: AMIR BLAND-ASWAD | F6: RESEARCH!! | G6: AMIR BLAND | H6: ABLAND | I6: 45851
A7: =H7 -> ABRAVAR | B7: 46957 | C7: 45992 | D7: Less than 14 days | E7: ALEX BRAVAR | F7: ABRAVAR | G7: ALEX BRAVAR | H7: ABRAVAR | I7: 44250
A8: =H8 -> ACHRI10 | B8: 47163 | C8: 45861 | D8: 28 plus days | E8: ALEX CHRISTIAN | F8: ACHRI10 | G8: ALEX CHRISTIAN | H8: ACHRI10 | I8: 35723
A9: =H9 -> AEMERSO | B9: 36295 | C9: 45908 | D9: 28 plus days | E9: ALLAN EMERSON | F9: AEMERSO | G9: ALLAN EMERSON | H9: AEMERSO | I9: 44539
A10: =H10 -> AENGEN | B10: 23254 | C10: 45989 | D10: Less than 14 days | E10: ALLEN ENGEN | F10: AENGEN | G10: ALLEN ENGEN | H10: AENGEN | I10: 42499
A11: =H11 -> AESPOSI | B11: 46977 | C11: 45995 | D11: Less than 14 days | E11: ANTHONY ESPOSITO | F11: AESPOSI | G11: ANTHONY ESPOSITO | H11: AESPOSI | I11: 39181
A12: =H12 -> AFELIX | B12: 46598 | C12: 45880 | D12: 28 plus days | E12: ASCHBEA FELIX | F12: AFELIX | G12: ASCHBEA FELIX | H12: AFELIX | I12: 45865
A13: =H13 -> AFRELIC | B13: 46972 | C13: 45868 | D13: 28 plus days | E13: ADAM FRELICK | F13: AFRELIC | G13: ADAM FRELICK | H13: AFRELIC | I13: 43747
... A225: =H225 -> NCRNALI | B225: 21704 | C225: 45978 | D225: 21 plus days | E225: NEDZAD CRNALIC | F225: NCRNALI | G225: NEDZAD CRNALIC | H225: NCRNALI | I225: 38488
A226: =H226 -> Not Assigned in TPMS!! | B226: 06611 | C226: 45866 | D226: 28 plus days | E226: WARREN BURTON | F226: WBURTO | G226: Not Assigned in TPMS!! | H226: Not Assigned in TPMS!! | I226: Not Assigned in TPMS!!
A227: =H227 -> Not Assigned in TPMS!! | B227: 21187 | C227: 45817 | D227: 28 plus days | E227: LONDON WILLIAMS | F227: LWILLI3 | G227: Not Assigned in TPMS!! | H227: Not Assigned in TPMS!! | I227: Not Assigned in TPMS!!
A228: =H228 -> Not Assigned in TPMS!! | B228: 21239 | C228: 45968 | D228: 28 plus days | E228: SHAWN BLOUNT | F228: SBLOUNT | G228: Not Assigned in TPMS!! | H228: Not Assigned in TPMS!! | I228: Not Assigned in TPMS!!
A229: =H229 -> Not Assigned in TPMS!! | B229: 21547 | C229: 45848 | D229: 28 plus days | E229: ERIC CONSUEGRA | F229: ECONSUE | G229: Not Assigned in TPMS!! | H229: Not Assigned in TPMS!! | I229: Not Assigned in TPMS!!
A230: =H230 -> Not Assigned in TPMS!! | B230: 23061 | C230: 45855 | D230: 28 plus days | E230: DARYL WILLIAMS | F230: RESEARCH!! | G230: Not Assigned in TPMS!! | H230: Not Assigned in TPMS!! | I230: Not Assigned in TPMS!!
A231: =H231 -> Not Assigned in TPMS!! | B231: 23150 | C231: 45883 | D231: 28 plus days | E231: DAVIDW JACKSON | F231: RESEARCH!! | G231: Not Assigned in TPMS!! | H231: Not Assigned in TPMS!! | I231: Not Assigned in TPMS!!
A232: =H232 -> Not Assigned in TPMS!! | B232: 23548 | C232: 45939 | D232: 28 plus days | E232: KYLEN HARRIS | F232: KHARRI3 | G232: Not Assigned in TPMS!! | H232: Not Assigned in TPMS!! | I232: Not Assigned in TPMS!!
A233: =H233 -> Not Assigned in TPMS!! | B233: 23921 | C233: 45965 | D233: 28 plus days | E233: MICHAEL COLLINS | F233: RESEARCH!! | G233: Not Assigned in TPMS!! | H233: Not Assigned in TPMS!! | I233: Not Assigned in TPMS!!
A234: =H234 -> Not Assigned in TPMS!! | B234: 24021 | C234: 45946 | D234: 28 plus days | E234: BENITO MONTIEL | F234: RESEARCH!! | G234: Not Assigned in TPMS!! | H234: Not Assigned in TPMS!! | I234: Not Assigned in TPMS!!
A235: =H235 -> Not Assigned in TPMS!! | B235: 24072 | C235: 45943 | D235: 28 plus days | E235: PHILLIP WILLIAMS | F235: RESEARCH!! | G235: Not Assigned in TPMS!! | H235: Not Assigned in TPMS!! | I235: Not Assigned in TPMS!!
A236: =H236 -> Not Assigned in TPMS!! | B236: 24090 | C236: 45909 | D236: 28 plus days | E236: ADLER CADET | F236: ACADET | G236: Not Assigned in TPMS!! | H236: Not Assigned in TPMS!! | I236: Not Assigned in TPMS!!
A237: =H237 -> Not Assigned in TPMS!! | B237: 24118 | C237: 45972 | D237: 28 plus days | E237: CARLOS BARNES | F237: CBARNES | G237: Not Assigned in TPMS!! | H237: Not Assigned in TPMS!! | I237: Not Assigned in TPMS!!
... A276: =H276 -> Not assigned in TPMS!! | B276: 37049 | C276: 45912 | D276: 28 plus days | E276: FRANK VELA | F276: FVELA | G276: Not assigned in TPMS!! | H276: Not assigned in TPMS!! | I276: Not assigned in TPMS!!
A277: =H277 -> OBLEUS | B277: 36675 | C277: 45939 | D277: 28 plus days | E277: OJ BLEUS | F277: OBLEUS | G277: OJ BLEUS | H277: OBLEUS | I277: 45592
A278: =H278 -> PBRADY | B278: 61316 | C278: 45946 | D278: 28 plus days | E278: PAUL BRADY | F278: PBRADY | G278: PAUL BRADY | H278: PBRADY | I278: 45739
A279: =H279 -> PCAMPBE | B279: 37230 | C279: 45852 | D279: 28 plus days | E279: PHILIP CAMPBELL | F279: PCAMPBE | G279: PHILIP CAMPBELL | H279: PCAMPBE | I279: 45207
A280: =H280 -> PKANTZA | B280: 36402 | C280: 45966 | D280: 28 plus days | E280: PETER KANTZAS | F280: PKANTZA | G280: PETER KANTZAS | H280: PKANTZA | I280: 45928
A281: =H281 -> PLICAT | B281: 47075 | C281: 45974 | D281: 28 plus days | E281: PATRICK LICATA | F281: PLICAT | G281: PATRICK LICATA | H281: PLICAT | I281: 37255
A282: =H282 -> PSKOCEL | B282: 36655 | C282: 46000 | D282: Less than 14 days | E282: PATRICK SKOCELAS | F282: PSKOCEL | G282: PATRICK SKOCELAS | H282: PSKOCEL | I282: 32400
A283: =H283 -> RAYALAM | B283: 61745 | C283: 45968 | D283: 28 plus days | E283: ROBERTO AYALA | F283: RESEARCH!! | G283: ROBERTO AYALA MERCADO | H283: RAYALAM | I283: 45844
A284: =H284 -> RCORTEZ | B284: 36882 | C284: 45864 | D284: 28 plus days | E284: RENE CORTEZ | F284: RCORTEZ | G284: RENE CORTEZ | H284: RCORTEZ | I284: 45627
A285: =H285 -> RDELEKT | B285: 61577 | C285: 45996 | D285: Less than 14 days | E285: RAYMOND DELEKTA | F285: RDELEKT | G285: RAYMOND DELEKTA | H285: RDELEKT | I285: 36990
A286: =H286 -> RGARCI0 | B286: 46426 | C286: 45937 | D286: 28 plus days | E286: RANCARLOS GARCIA | F286: RGARCI0 | G286: RANCARLOS GARCIA | H286: RGARCI0 | I286: 44034
A287: =H287 -> RGARRE3 | B287: 47159 | C287: 45953 | D287: 28 plus days | E287: RONALD GARRETT | F287: RGARRE3 | G287: RONALD GARRETT | H287: RGARRE3 | I287: 43066
A288: =H288 -> RHIGGIN | B288: 36234 | C288: 45958 | D288: 28 plus days | E288: ROBERT HIGGINS | F288: RHIGGIN | G288: ROBERT HIGGINS | H288: RHIGGIN | I288: 45760
... A314: =H314 -> SWISE0 | B314: 47420 | C314: 45957 | D314: 28 plus days | E314: SHAQUON WISE | F314: SWISE0 | G314: SHAQUON WISE | H314: SWISE0 | I314: 44284
A315: =H315 -> TANGUS | B315: 41000 | C315: 45937 | D315: 28 plus days | E315: TRAVIS ANGUS | F315: TANGUS | G315: TRAVIS ANGUS | H315: TANGUS | I315: Not on HR File
A316: =H316 -> TBOLAN | B316: 47029 | C316: 45992 | D316: Less than 14 days | E316: TIMOTHY BOLAND | F316: TBOLAN | G316: TIMOTHY BOLAND | H316: TBOLAN | I316: 31347
A317: =H317 -> TBRUNT | B317: 36636 | C317: 45959 | D317: 28 plus days | E317: TIMOTHY BRUNT | F317: TBRUNT | G317: TIMOTHY BRUNT | H317: TBRUNT | I317: 45837
A318: =H318 -> TBURDIC | B318: 47252 | C318: 46000 | D318: Less than 14 days | E318: TYLER BURDICK | F318: TBURDIC | G318: TYLER BURDICK | H318: TBURDIC | I318: 43152
A319: =H319 -> TCARNAH | B319: 21207 | C319: 45861 | D319: 28 plus days | E319: COREY NEWELL | F319: CNEWELL | G319: TYLER CARNAHAN | H319: TCARNAH | I319: 45893
A320: =H320 -> TDAILEY | B320: 46880 | C320: 45883 | D320: 28 plus days | E320: AUNDRAY GULLEY | F320: AGULLEY | G320: THEODORE DAILEY | H320: TDAILEY | I320: 45907
A321: =H321 -> TDOHERT | B321: 46976 | C321: 45915 | D321: 28 plus days | E321: THOMAS DOHERTY | F321: TDOHERT | G321: THOMAS DOHERTY | H321: TDOHERT | I321: 39034
A322: =H322 -> TGANN | B322: 21698 | C322: 45943 | D322: 28 plus days | E322: PHILLIP LAWSON | F322: PLAWSON | G322: TIMOTHY GANN | H322: TGANN | I322: Not on HR File
A323: =H323 -> TGOSSEL | B323: 61579 | C323: 45997 | D323: Less than 14 days | E323: ETHAN SULLIVAN | F323: ESULLIV | G323: TIMOTHY GOSSELIN | H323: TGOSSEL | I323: 42885
A324: =H324 -> THOLBRO | B324: 47412 | C324: 45994 | D324: Less than 14 days | E324: TIMOTHY HOLBROOK | F324: THOLBRO | G324: TIMOTHY HOLBROOK | H324: THOLBRO | I324: 32973
A325: =H325 -> TJENKIN | B325: 61094 | C325: 45967 | D325: 28 plus days | E325: TERENCE JENKINS | F325: TJENKIN | G325: TERENCE JENKINS | H325: TJENKIN | I325: 36227
A326: =H326 -> TKIMBER | B326: 47104 | C326: 45992 | D326: Less than 14 days | E326: THEODORE KIMBERLING | F326: TKIMBER | G326: THEODORE KIMBERLING | H326: TKIMBER | I326: 45942
A327: =H327 -> TMATHI1 | B327: 46360 | C327: 45898 | D327: 28 plus days | E327: TADDERICK MATHIS | F327: RESEARCH!! | G327: TADDERICK MATHIS JR | H327: TMATHI1 | I327: 45445
A328: =H328 -> TMATTHE | B328: 37057 | C328: 45993 | D328: Less than 14 days | E328: TRENT MATTHEWS | F328: TMATTHE | G328: TRENT MATTHEWS | H328: TMATTHE | I328: 45935
A329: =H329 -> TRAI0 | B329: 47040 | C329: 45981 | D329: 21 plus days | E329: TARA RAI | F329: TRAI0 | G329: TARA RAI | H329: TRAI0 | I329: 44700
A330: =H330 -> TWEBER2 | B330: 21365 | C330: 45974 | D330: 28 plus days | E330: VINCE ROSADO | F330: RESEARCH!! | G330: TOM WEBER | H330: TWEBER2 | I330: 36929
A331: =H331 -> VBEST1 | B331: 47026 | C331: 45967 | D331: 28 plus days | E331: VONZELL BEST | F331: VBEST1 | G331: VONZELL BEST | H331: VBEST1 | I331: 35647
A332: =H332 -> VCOUCH | B332: 23862 | C332: 45905 | D332: 28 plus days | E332: VAN COUCH | F332: VCOUCH | G332: VAN COUCH | H332: VCOUCH | I332: 44273
A333: =H333 -> VHAWKI3 | B333: 46276 | C333: 45992 | D333: Less than 14 days | E333: VICTOR HAWKINS | F333: VHAWKI3 | G333: VICTOR HAWKINS | H333: VHAWKI3 | I333: 41162
A334: =H334 -> VHOWARD | B334: 61661 | C334: 45999 | D334: Less than 14 days | E334: VAUGHN HOWARD | F334: VHOWARD | G334: VAUGHN HOWARD | H334: VHOWARD | I334: 45970
... A343: =H343 -> WROBERS | B343: 23456 | C343: 45821 | D343: 28 plus days | E343: WILLIE ROBERSON | F343: WROBERS | G343: WILLIE ROBERSON | H343: WROBERS | I343: 45137

Sheet Summary Report
A2: Rental PO Requests by Reason
B6: Column Labels
B7: New Rental | D7: Rental Extension Request | F7: Total Rental POs | G7: Total % to total
A8: Row Labels | B8: Rental POs | C8: % to total | D8: Rental POs | E8: % to total
A9: New Hire Rental | B9: 12 | C9: 0.17910448 | D9: 6 | E9: 0.26086957 | F9: 18 | G9: 0.2
A10: Truck Breakdown | B10: 55 | C10: 0.82089552 | D10: 17 | E10: 0.73913043 | F10: 72 | G10: 0.8
A11: Total | B11: 67 | C11: 1 | D11: 23 | E11: 1 | F11: 90 | G11: 1
B16: Column Labels
B17: New Rental | F17: New Rental Rental POs | G17: New Rental % to Total | H17: Rental Extension Request | L17: Rental Extension Request Rental POs | M17: Rental Extension Request % to Total | N17: Total Rental POs | O17: Total % to Total
B18: New Hire Rental | D18: Truck Breakdown | H18: New Hire Rental | J18: Truck Breakdown
A19: Row Labels | B19: Rental POs | C19: % to Total | D19: Rental POs | E19: % to Total | H19: Rental POs | I19: % to Total | J19: Rental POs | K19: % to Total
A20: 45978 | B20: 5 | C20: 0.22727273 | D20: 14 | E20: 0.63636364 | F20: 19 | G20: 0.86363636 | H20: 1 | I20: 0.045454545 | J20: 2 | K20: 0.090909091 | L20: 3 | M20: 0.13636364 | N20: 22 | O20: 1
A21: 45979 | B21: 1 | C21: 0.0625 | D21: 13 | E21: 0.8125 | F21: 14 | G21: 0.875 | H21: 1 | I21: 0.0625 | J21: 1 | K21: 0.0625 | L21: 2 | M21: 0.125 | N21: 16 | O21: 1
A22: 45980 | B22: 1 | C22: 0.047619048 | D22: 11 | E22: 0.52380952 | F22: 12 | G22: 0.57142857 | H22: 1 | I22: 0.047619048 | J22: 8 | K22: 0.38095238 | L22: 9 | M22: 0.42857143 | N22: 21 | O22: 1
A23: 45981 | B23: 3 | C23: 0.21428571 | D23: 9 | E23: 0.64285714 | F23: 12 | G23: 0.85714286 | H23: 1 | I23: 0.071428571 | J23: 1 | K23: 0.071428571 | L23: 2 | M23: 0.14285714 | N23: 14 | O23: 1
A24: 45982 | B24: 2 | C24: 0.11764706 | D24: 8 | E24: 0.47058824 | F24: 10 | G24: 0.58823529 | H24: 2 | I24: 0.11764706 | J24: 5 | K24: 0.29411765 | L24: 7 | M24: 0.41176471 | N24: 17 | O24: 1
A25: Grand Total | B25: 12 | C25: 0.13333333 | D25: 55 | E25: 0.61111111 | F25: 67 | G25: 0.74444444 | H25: 6 | I25: 0.066666667 | J25: 17 | K25: 0.18888889 | L25: 23 | M25: 0.25555556 | N25: 90 | O25: 1
A122: Date of this request | B122: (Multiple Items)
B124: Column Labels
B125: New Rental | F125: New Rental Rental POs | G125: New Rental % to Total | H125: Rental Extension Request | L125: Rental Extension Request Rental POs | M125: Rental Extension Request % to Total | N125: Total Rental POs | O125: Total % to Total
B126: New Hire Rental | D126: Truck Breakdown | H126: New Hire Rental | J126: Truck Breakdown
A127: Row Labels | B127: Rental POs | C127: % to Total | D127: Rental POs | E127: % to Total | H127: Rental POs | I127: % to Total | J127: Rental POs | K127: % to Total
A128: 0004766 | B128: 0 | C128: 0 | D128: 5 | E128: 0.625 | F128: 5 | G128: 0.625 | H128: 1 | I128: 0.125 | J128: 2 | K128: 0.25 | L128: 3 | M128: 0.375 | N128: 8 | O128: 1
A129: 0006141 | B129: 0 | C129: 0 | D129: 1 | E129: 1 | F129: 1 | G129: 1 | H129: 0 | I129: 0 | J129: 0 | K129: 0 | L129: 0 | M129: 0 | N129: 1 | O129: 1
A130: 0007084 | B130: 0 | C130: 0 | D130: 5 | E130: 0.71428571 | F130: 5 | G130: 0.71428571 | H130: 0 | I130: 0 | J130: 2 | K130: 0.28571429 | L130: 2 | M130: 0.28571429 | N130: 7 | O130: 1
A131: 0007088 | B131: 0 | C131: 0 | D131: 2 | E131: 1 | F131: 2 | G131: 1 | H131: 0 | I131: 0 | J131: 0 | K131: 0 | L131: 0 | M131: 0 | N131: 2 | O131: 1
A132: 0007108 | B132: 0 | C132: 0 | D132: 1 | E132: 1 | F132: 1 | G132: 1 | H132: 0 | I132: 0 | J132: 0 | K132: 0 | L132: 0 | M132: 0 | N132: 1 | O132: 1
A133: 0007435 | B133: 0 | C133: 0 | D133: 8 | E133: 0.72727273 | F133: 8 | G133: 0.72727273 | H133: 0 | I133: 0 | J133: 3 | K133: 0.27272727 | L133: 3 | M133: 0.27272727 | N133: 11 | O133: 1
A134: 0007670 | B134: 3 | C134: 0.3 | D134: 6 | E134: 0.6 | F134: 9 | G134: 0.9 | H134: 1 | I134: 0.1 | J134: 0 | K134: 0 | L134: 1 | M134: 0.1 | N134: 10 | O134: 1
A135: 0007744 | B135: 1 | C135: 0.33333333 | D135: 2 | E135: 0.66666667 | F135: 3 | G135: 1 | H135: 0 | I135: 0 | J135: 0 | K135: 0 | L135: 0 | M135: 0 | N135: 3 | O135: 1
A136: 0007995 | B136: 0 | C136: 0 | D136: 1 | E136: 0.5 | F136: 1 | G136: 0.5 | H136: 0 | I136: 0 | J136: 1 | K136: 0.5 | L136: 1 | M136: 0.5 | N136: 2 | O136: 1
A137: 0008035 | B137: 1 | C137: 0.33333333 | D137: 1 | E137: 0.33333333 | F137: 2 | G137: 0.66666667 | H137: 1 | I137: 0.33333333 | J137: 0 | K137: 0 | L137: 1 | M137: 0.33333333 | N137: 3 | O137: 1
A138: 0008096 | B138: 0 | C138: 0 | D138: 1 | E138: 0.5 | F138: 1 | G138: 0.5 | H138: 0 | I138: 0 | J138: 1 | K138: 0.5 | L138: 1 | M138: 0.5 | N138: 2 | O138: 1
A139: 0008107 | B139: 0 | C139: 0 | D139: 4 | E139: 0.8 | F139: 4 | G139: 0.8 | H139: 0 | I139: 0 | J139: 1 | K139: 0.2 | L139: 1 | M139: 0.2 | N139: 5 | O139: 1
... A150: 0008555 | B150: 0 | C150: 0 | D150: 2 | E150: 1 | F150: 2 | G150: 1 | H150: 0 | I150: 0 | J150: 0 | K150: 0 | L150: 0 | M150: 0 | N150: 2 | O150: 1
A151: Not-in-TPMS | B151: 0 | C151: #DIV/0! | D151: 0 | E151: #DIV/0! | F151: 0 | G151: #DIV/0! | H151: 0 | I151: #DIV/0! | J151: 0 | K151: #DIV/0! | L151: 0 | M151: #DIV/0! | N151: 0 | O151: #DIV/0!
A152: Grand Total | B152: 12 | C152: 0.13333333 | D152: 55 | E152: 0.61111111 | F152: 67 | G152: 0.74444444 | H152: 6 | I152: 0.066666667 | J152: 17 | K152: 0.18888889 | L152: 23 | M152: 0.25555556 | N152: 90 | O152: 1

Sheet Tech-ServiceDate
A1: Trim ENT ID: | B1: Service Dt
A2: aacuna | B2: 45123
A3: aaguil0 | B3: 44770
A4: aalexa5 | B4: 41736
A5: AALVARA | B5: 32656
A6: aander2 | B6: 45676
A7: aaprim | B7: 45914
A8: AARELLA | B8: 40018
A9: aarnold | B9: 45935
A10: aasghar | B10: 45165
A11: AATRISC | B11: 36836
A12: aatta | B12: 44111
A13: abalice | B13: 44785
... A1776: zwilson | B1776: 45410

Sheet TPMS-auto
A1: Trim ENT ID | B1: TRUCK_LU | C1: FULL_NAME | D1: DISTRICT | E1: TECH_NO | F1: TRUCK_NO | G1: ENTERPRISE_ID | H1: LAST_NAME | I1: FIRST_NAME | J1: MOBILEPHONENUMBER | K1: STATUS | L1: PRIMARYADDR1 | M1: PRIMARYADDR2 | N1: PRIMARYCITY | O1: PRIMARYSTATE | P1: PRIMARYZIP | Q1: SHIPPING_SCHEDULE | R1: PDC_NO | S1: MANAGER_ENT_ID | T1: MANAGER_NAME | U1: EMAIL_ADDRESS | V1: FILE_DATE
A2: =TRIM(Query1[[#This Row],[ENTERPRISE_ID]]) -> SFESSHA | B2: 06121 | C2: SOLOMON FESSHAYE | D2: 0007084 | E2: 0016329 | F2: 006121 | G2: SFESSHA | H2: FESSHAYE | I2: SOLOMON | J2: 7038435717 | K2: A | L2: 7830 Lewis Chapel Cir | M2: Unit 103 | N2: Lorton | O2: VA | P2: 22079 | Q2: NNYNNNN | R2: 8998 | S2: EGONZA9 | T2: GONZALEZ, ELIO | U2: 7038435717@tmomail.net | V2: 45993
A3: =TRIM(Query1[[#This Row],[ENTERPRISE_ID]]) -> KROGER3 | B3: 06135 | C3: KENNETH ROGERS | D3: 0007983 | E3: 0538454 | F3: 006135 | G3: KROGER3 | H3: ROGERS | I3: KENNETH | J3: 8562035565 | K3: A | L3: 514 Bancroft Road | N3: Cherry Hill | O3: NJ | P3: 08034 | Q3: NNNYNNN | R3: 8998 | S3: MDOWNE0 | T3: DOWNEY, MICHAEL | U3: 8562035565@tmomail.net | V3: 45993
A4: =TRIM(Query1[[#This Row],[ENTERPRISE_ID]]) -> PHEMMI0 | B4: 06206 | C4: PETER HEMMINGS | D4: 0008035 | E4: 0002771 | F4: 006206 | G4: PHEMMI0 | H4: HEMMINGS | I4: PETER | J4: 4782600632 | K4: A | L4: 215 Kingsbury Cir | N4: Warner Robins | O4: GA | P4: 31088 | Q4: NNNNNYN | R4: 8998 | S4: WTAYL21 | T4: TAYLOR, WILLIAM | U4: 4782600632@vtext.com | V4: 45993
A5: =TRIM(Query1[[#This Row],[ENTERPRISE_ID]]) -> RSCOTT5 | B5: 06401 | C5: ROBERT SCOTT | D5: 0008096 | E5: 0301671 | F5: 006401 | G5: RSCOTT5 | H5: SCOTT | I5: ROBERT | J5: 2709553019 | K5: A | L5: 386 INGRAM LANE | N5: Almo | O5: KY | P5: 42020 | Q5: NNNYNNN | R5: 8998 | S5: KHOKA01 | T5: HOKANSON, KENNETH | U5: 2709553019@tmomail.net | V5: 45993
A6: =TRIM(Query1[[#This Row],[ENTERPRISE_ID]]) -> CFLETC1 | B6: 06568 | C6: CORTEZ FLETCHER | D6: 0008035 | E6: 0000687 | F6: 006568 | G6: CFLETC1 | H6: FLETCHER | I6: CORTEZ | J6: 2148920567 | K6: A | L6: 12060 COUNTY LINE RD | M6: STE J ADL/SHS-C FLETCHER | N6: MADISON | O6: AL | P6: 35756 | Q6: NNNNNYN | R6: 8998 | S6: JJACKS4 | T6: JACKSON, JIMMY | U6: 2148920567@tmomail.net | V6: 45993
A7: =TRIM(Query1[[#This Row],[ENTERPRISE_ID]]) -> PCARRIN | B7: 06581 | C7: PAUL CARRINGTON | D7: 0008175 | E7: 0021287 | F7: 006581 | G7: PCARRIN | H7: CARRINGTON | I7: PAUL | J7: 9108573163 | K7: A | L7: 6535 TAREYTON RD | N7: FAYETTEVILLE | O7: NC | P7: 28314 | Q7: NNNYNNN | R7: 8998 | S7: AWILLI3 | T7: WILLIAMS, ANTHONY | U7: 9108573163@vtext.com | V7: 45993
A8: =TRIM(Query1[[#This Row],[ENTERPRISE_ID]]) -> GPAULSE | B8: 06585 | C8: GREGG PAULSEN | D8: 0008096 | E8: 0846741 | F8: 006585 | G8: GPAULSE | H8: PAULSEN | I8: GREGG | J8: 5635790302 | K8: A | L8: 204 W FRANKLIN ST | N8: ELDRIDGE | O8: IA | P8: 52748 | Q8: NNNYNNN | R8: 8998 | S8: MMETELK | T8: METELKO, MATTHEW | U8: 5635790302@tmomail.net | V8: 45993
A9: =TRIM(Query1[[#This Row],[ENTERPRISE_ID]]) -> TSETEYE | B9: 06595 | C9: TESFAYE SETEYE | D9: 0008184 | E9: 0496315 | F9: 006595 | G9: TSETEYE | H9: SETEYE | I9: TESFAYE | J9: 5104353678 | K9: A | L9: 433 ADAMS ST | M9: 2G | N9: OAKLAND | O9: CA | P9: 94610 | Q9: NNNYNNN | R9: 8998 | S9: CRODR18 | T9: RODRIGUEZ, CLAUDIO | U9: 5104353678@tmomail.net | V9: 45993
A10: =TRIM(Query1[[#This Row],[ENTERPRISE_ID]]) -> VDUTTA | B10: 06606 | C10: VIKRAM DUTTA | D10: 0008184 | E10: 0021261 | F10: 006606 | G10: VDUTTA | H10: DUTTA | I10: VIKRAM | J10: 5106960173 | K10: A | L10: 530 Napa Ave | N10: Radeo | O10: CA | P10: 94572 | Q10: NNNYNNN | R10: 8998 | S10: DPARK28 | T10: PARKER, DESMOND | U10: 5106960173@tmomail.net | V10: 45993
