Workbook

Sheet Running Progress
A1: Technicians in Rentals - Holman Reporting
CW2: ** Change in Rental Reporting
A3: Rental Update-8/29-Benchmark | D3: Rental Update - 9/2 | H3: Rental Update - 9/3 | L3: Rental Update - 9/5 | P3: Rental Update - 9/16 | T3: Rental Update - 9/17 | X3: Rental Update - 9/18 | AB3: Rental Update - 9/19 | AF3: Rental Update - 9/20 | AJ3: Rental Update - 9/21 | AN3: Rental Update - 9/22 | AR3: Rental Update - 9/23 | AV3: Rental Update - 9/24 | AZ3: Rental Update - 9/29 | BD3: Rental Update - 9/30 | BH3: Rental Update - 10/1 | BL3: Rental Update - 10/2 | BP3: Rental Update - 10/3 | BT3: Rental Update - 10/6 | BX3: Rental Update - 10/7 | CB3: Rental Update - 10/9 | CF3: Rental Update - 10/10 | CJ3: Rental Update - 10/13 | CN3: Rental Update - 10/14 | CR3: Rental Update - 10/15 | CV3: Rental Update - 10/16 | CZ3: Rental Update - 10/17 | DD3: Rental Update - 10/20 | DH3: Rental Update - 10/21 | DL3: Rental Update - 10/22 | DP3: Rental Update - 10/23 | DT3: Rental Update - 10/24 | DX3: Rental Update - 10/27 | EB3: Rental Update - 10/28 | EF3: Rental Update - 10/29 | EJ3: Rental Update - 10/30 | EN3: Rental Update - 10/31 | ER3: Rental Update - 11/3 | EV3: Rental Update - 11/4 | EZ3: Rental Update - 11/5 | FD3: Rental Update - 11/6 | FH3: Rental Update - 11/7 | FL3: Rental Update - 11/10 | FP3: Rental Update - 11/11 | FT3: Rental Update - 11/12 | FX3: Rental Update - 11/13 | GB3: Rental Update - 11/17 | GF3: Rental Update - 11/18 | GJ3: Rental Update - 11/19 | GN3: Rental Update - 11/20 | GR3: Rental Update - 11/21 | GV3: Rental Update - 11/24 | GZ3: Rental Update - 11/25 | HD3: Rental Update - 11/26 | HH3: Rental Update - 12/1 | HL3: Rental Update - 12/2 | HP3: Rental Update - 12/3 | HT3: Rental Update - 12/4 | HX3: Rental Update - 12/5 | IB3: Rental Update - 12/8 | IF3: Rental Update - 12/9 | IJ3: Rental Update - 12/10 | IN3: Rental Update - 12/11 | IR3: Rental Update - 12/12 | IV3: Rental Update - 12/15 | IZ3: Rental Update - 12/16 | JD3: Rental Update - 12/17 | JH3: Rental Update - 12/18 | JL3: Rental Update - 12/19 | JP3: Rental Update - 12/22 | JT3: Rental Update - 12/23 | JX3: Rental Update - 12/24 | KB3: Rental Update - 12/25 | KF3: Rental Update - 12/26 | KJ3: Rental Update - 12/29 | KN3: Rental Update - 12/30 | KR3: Rental Update - 12/31 | KV3: Rental Update - 1/01 New Years Day Holiday | KZ3: Rental Update - 1/02 | LD3: Rental Update - 1/05 | LH3: Rental Update - 1/06 | LL3: Rental Update - 1/07 | LP3: Rental Update - 1/08 | LT3: Rental Update - 1/09 | LX3: Rental Update - 1/12 | MB3: Rental Update - 1/13 | MF3: Rental Update - 1/14 | MJ3: Rental Update - 1/15 | MN3: Rental Update - 1/16 | MR3: Rental Update - 1/19 | MV3: Rental Update - 1/20 | MZ3: Rental Update - 1/21 | ND3: Rental Update - 1/22 | NH3: Rental Update - 1/23 | NL3: Rental Update - 1/26 | NP3: Rental Update - 1/27 | NT3: Rental Update - 1/28 | NX3: Rental Update - 1/29 | OB3: Rental Update - 1/30 | OF3: Rental Update - 2/2 | OJ3: Rental Update - 2/3 | ON3: Rental Update - 2/4 | OR3: Rental Update - 2/5 | OV3: Rental Update - 2/6 | OZ3: Rental Update - 2/9 | PD3: Rental Update - 2/10 | PH3: Rental Update - 2/11 | PL3: Rental Update - 2/12 | PP3: Rental Update - 2/13 | PT3: Rental Update - 2/16 | PX3: Rental Update - 2/17 | QB3: Rental Update - 2/18 | QF3: Rental Update - 2/19 | QJ3: Rental Update - 2/20 | QN3: Rental Update - 2/23 | QR3: Rental Update - 2/24 | QV3: Rental Update - 2/25 | QZ3: Rental Update - 2/26 | RD3: Rental Update - 2/27 | RH3: Rental Update - 3/2 | RL3: Rental Update - 3/3 | RP3: Rental Update -3/4 | RT3: Rental Update - 3/5 | RX3: Rental Update - 3/6
A5: Row Labels | B5: Rentals Open | C5: % to all Rentals | D5: Row Labels | E5: Rentals Open | F5: % to all Rentals | G5: Change MTD | H5: Row Labels | I5: Rentals Open | J5: % to all Rentals | K5: Change MTD | L5: Row Labels | M5: Rentals Open | N5: % to all Rentals | O5: Change MTD | P5: Row Labels | Q5: Rentals Open | R5: % to all Rentals | S5: Change MTD | T5: Row Labels | U5: Rentals Open | V5: % to all Rentals | W5: Change MTD | X5: Row Labels | Y5: Rentals Open | Z5: % to all Rentals | AA5: Change MTD | AB5: Row Labels | AC5: Rentals Open | AD5: % to all Rentals | AE5: Change MTD | AF5: Row Labels | AG5: Rentals Open | AH5: % to all Rentals | AI5: Change MTD | AJ5: Row Labels | AK5: Rentals Open | AL5: % to all Rentals | AM5: Change MTD | AN5: Row Labels | AO5: Rentals Open | AP5: % to all Rentals | AQ5: Change MTD | AR5: Row Labels | AS5: Rentals Open | AT5: % to all Rentals | AU5: Change MTD | AV5: Row Labels | AW5: Rentals Open | AX5: % to all Rentals | AY5: Change MTD | AZ5: Row Labels | BA5: Rentals Open | BB5: % to all Rentals | BC5: Change MTD | BD5: Row Labels | BE5: Rentals Open | BF5: % to all Rentals | BG5: Change MTD | BH5: Row Labels | BI5: Rentals Open | BJ5: % to all Rentals | BK5: Change MTD | BL5: Row Labels | BM5: Rentals Open | BN5: % to all Rentals | BO5: Change MTD | BP5: Row Labels | BQ5: Rentals Open | BR5: % to all Rentals | BS5: Change MTD | BT5: Row Labels | BU5: Rentals Open | BV5: % to all Rentals | BW5: Change MTD | BX5: Row Labels | BY5: Rentals Open | BZ5: % to all Rentals | CA5: Change MTD | CB5: Row Labels | CC5: Rentals Open | CD5: % to all Rentals | CE5: Change MTD | CF5: Row Labels | CG5: Rentals Open | CH5: % to all Rentals | CI5: Change MTD | CJ5: Row Labels | CK5: Rentals Open | CL5: % to all Rentals | CM5: Change MTD | CN5: Row Labels | CO5: Rentals Open | CP5: % to all Rentals | CQ5: Change MTD | CR5: Row Labels | CS5: Rentals Open | CT5: % to all Rentals | CU5: Change MTD | CV5: Row Labels | CW5: Rentals Open | CX5: % to all Rentals | CY5: Change MTD | CZ5: Row Labels | DA5: Rentals Open | DB5: % to all Rentals | DC5: Change MTD | DD5: Row Labels | DE5: Rentals Open | DF5: % to all Rentals | DG5: Change MTD | DH5: Row Labels | DI5: Rentals Open | DJ5: % to all Rentals | DK5: Change MTD | DL5: Row Labels | DM5: Rentals Open | DN5: % to all Rentals | DO5: Change MTD | DP5: Row Labels | DQ5: Rentals Open | DR5: % to all Rentals | DS5: Change MTD | DT5: Row Labels | DU5: Rentals Open | DV5: % to all Rentals | DW5: Change MTD | DX5: Row Labels | DY5: Rentals Open | DZ5: % to all Rentals | EA5: Change MTD | EB5: Row Labels | EC5: Rentals Open | ED5: % to all Rentals | EE5: Change MTD | EF5: Row Labels | EG5: Rentals Open | EH5: % to all Rentals | EI5: Change MTD | EJ5: Row Labels | EK5: Rentals Open | EL5: % to all Rentals | EM5: Change MTD | EN5: Row Labels | EO5: Rentals Open | EP5: % to all Rentals | EQ5: Change MTD | ER5: Row Labels | ES5: Rentals Open | ET5: % to all Rentals | EU5: Change MTD | EV5: Row Labels | EW5: Rentals Open | EX5: % to all Rentals | EY5: Change MTD | EZ5: Row Labels | FA5: Rentals Open | FB5: % to all Rentals | FC5: Change MTD | FD5: Row Labels | FE5: Rentals Open | FF5: % to all Rentals | FG5: Change MTD | FH5: Row Labels | FI5: Rentals Open | FJ5: % to all Rentals | FK5: Change MTD | FL5: Row Labels | FM5: Rentals Open | FN5: % to all Rentals | FO5: Change MTD | FP5: Row Labels | FQ5: Rentals Open | FR5: % to all Rentals | FS5: Change MTD | FT5: Row Labels | FU5: Rentals Open | FV5: % to all Rentals | FW5: Change MTD | FX5: Row Labels | FY5: Rentals Open | FZ5: % to all Rentals | GA5: Change MTD | GB5: Row Labels | GC5: Rentals Open | GD5: % to all Rentals | GE5: Change MTD | GF5: Row Labels | GG5: Rentals Open | GH5: % to all Rentals | GI5: Change MTD | GJ5: Row Labels | GK5: Rentals Open | GL5: % to all Rentals | GM5: Change MTD | GN5: Row Labels | GO5: Rentals Open | GP5: % to all Rentals | GQ5: Change MTD | GR5: Row Labels | GS5: Rentals Open | GT5: % to all Rentals | GU5: Change MTD | GV5: Row Labels | GW5: Rentals Open | GX5: % to all Rentals | GY5: Change MTD | GZ5: Row Labels | HA5: Rentals Open | HB5: % to all Rentals | HC5: Change MTD | HD5: Row Labels | HE5: Rentals Open | HF5: % to all Rentals | HG5: Change MTD | HH5: Row Labels | HI5: Rentals Open | HJ5: % to all Rentals | HK5: Change MTD | HL5: Row Labels | HM5: Rentals Open | HN5: % to all Rentals | HO5: Change MTD | HP5: Row Labels | HQ5: Rentals Open | HR5: % to all Rentals | HS5: Change MTD | HT5: Row Labels | HU5: Rentals Open | HV5: % to all Rentals | HW5: Change MTD | HX5: Row Labels | HY5: Rentals Open | HZ5: % to all Rentals | IA5: Change MTD | IB5: Row Labels | IC5: Rentals Open | ID5: % to all Rentals | IE5: Change MTD | IF5: Row Labels | IG5: Rentals Open | IH5: % to all Rentals | II5: Change MTD | IJ5: Row Labels | IK5: Rentals Open | IL5: % to all Rentals | IM5: Change MTD | IN5: Row Labels | IO5: Rentals Open | IP5: % to all Rentals | IQ5: Change MTD | IR5: Row Labels | IS5: Rentals Open | IT5: % to all Rentals | IU5: Change MTD | IV5: Row Labels | IW5: Rentals Open | IX5: % to all Rentals | IY5: Change MTD | IZ5: Row Labels | JA5: Rentals Open | JB5: % to all Rentals | JC5: Change MTD | JD5: Row Labels | JE5: Rentals Open | JF5: % to all Rentals | JG5: Change MTD | JH5: Row Labels | JI5: Rentals Open | JJ5: % to all Rentals | JK5: Change MTD | JL5: Row Labels | JM5: Rentals Open | JN5: % to all Rentals | JO5: Change MTD | JP5: Row Labels | JQ5: Rentals Open | JR5: % to all Rentals | JS5: Change MTD | JT5: Row Labels | JU5: Rentals Open | JV5: % to all Rentals | JW5: Change MTD | JX5: Row Labels | JY5: Rentals Open | JZ5: % to all Rentals | KA5: Change MTD | KB5: Row Labels | KC5: Rentals Open | KD5: % to all Rentals | KE5: Change MTD | KF5: Row Labels | KG5: Rentals Open | KH5: % to all Rentals | KI5: Change MTD | KJ5: Row Labels | KK5: Rentals Open | KL5: % to all Rentals | KM5: Change MTD | KN5: Row Labels | KO5: Rentals Open | KP5: % to all Rentals | KQ5: Change MTD | KR5: Row Labels | KS5: Rentals Open | KT5: % to all Rentals | KU5: Change MTD | KV5: Row Labels | KW5: Rentals Open | KX5: % to all Rentals | KY5: Change MTD | KZ5: Row Labels | LA5: Rentals Open | LB5: % to all Rentals | LC5: Change MTD | LD5: Row Labels | LE5: Rentals Open | LF5: % to all Rentals | LG5: Change MTD | LH5: Row Labels | LI5: Rentals Open | LJ5: % to all Rentals | LK5: Change MTD | LL5: Row Labels | LM5: Rentals Open | LN5: % to all Rentals | LO5: Change MTD | LP5: Row Labels | LQ5: Rentals Open | LR5: % to all Rentals | LS5: Change MTD | LT5: Row Labels | LU5: Rentals Open | LV5: % to all Rentals | LW5: Change MTD | LX5: Row Labels | LY5: Rentals Open | LZ5: % to all Rentals | MA5: Change MTD | MB5: Row Labels | MC5: Rentals Open | MD5: % to all Rentals | ME5: Change MTD | MF5: Row Labels | MG5: Rentals Open | MH5: % to all Rentals | MI5: Change MTD | MJ5: Row Labels | MK5: Rentals Open | ML5: % to all Rentals | MM5: Change MTD | MN5: Row Labels | MO5: Rentals Open | MP5: % to all Rentals | MQ5: Change MTD | MR5: Row Labels | MS5: Rentals Open | MT5: % to all Rentals | MU5: Change MTD | MV5: Row Labels | MW5: Rentals Open | MX5: % to all Rentals | MY5: Change MTD | MZ5: Row Labels | NA5: Rentals Open | NB5: % to all Rentals | NC5: Change MTD | ND5: Row Labels | NE5: Rentals Open | NF5: % to all Rentals | NG5: Change MTD | NH5: Row Labels | NI5: Rentals Open | NJ5: % to all Rentals | NK5: Change MTD | NL5: Row Labels | NM5: Rentals Open | NN5: % to all Rentals | NO5: Change MTD | NP5: Row Labels | NQ5: Rentals Open | NR5: % to all Rentals | NS5: Change MTD | NT5: Row Labels | NU5: Rentals Open | NV5: % to all Rentals | NW5: Change MTD | NX5: Row Labels | NY5: Rentals Open | NZ5: % to all Rentals | OA5: Change MTD | OB5: Row Labels | OC5: Rentals Open | OD5: % to all Rentals | OE5: Change MTD | OF5: Row Labels | OG5: Rentals Open | OH5: % to all Rentals | OI5: Change MTD | OJ5: Row Labels | OK5: Rentals Open | OL5: % to all Rentals | OM5: Change MTD | ON5: Row Labels | OO5: Rentals Open | OP5: % to all Rentals | OQ5: Change MTD | OR5: Row Labels | OS5: Rentals Open | OT5: % to all Rentals | OU5: Change MTD | OV5: Row Labels | OW5: Rentals Open | OX5: % to all Rentals | OY5: Change MTD | OZ5: Row Labels | PA5: Rentals Open | PB5: % to all Rentals | PC5: Change MTD | PD5: Row Labels | PE5: Rentals Open | PF5: % to all Rentals | PG5: Change MTD | PH5: Row Labels | PI5: Rentals Open | PJ5: % to all Rentals | PK5: Change MTD | PL5: Row Labels | PM5: Rentals Open | PN5: % to all Rentals | PO5: Change MTD | PP5: Row Labels | PQ5: Rentals Open | PR5: % to all Rentals | PS5: Change MTD | PT5: Row Labels | PU5: Rentals Open | PV5: % to all Rentals | PW5: Change MTD | PX5: Row Labels | PY5: Rentals Open | PZ5: % to all Rentals | QA5: Change MTD | QB5: Row Labels | QC5: Rentals Open | QD5: % to all Rentals | QE5: Change MTD | QF5: Row Labels | QG5: Rentals Open | QH5: % to all Rentals | QI5: Change MTD | QJ5: Row Labels | QK5: Rentals Open | QL5: % to all Rentals | QM5: Change MTD | QN5: Row Labels | QO5: Rentals Open | QP5: % to all Rentals | QQ5: Change MTD | QR5: Row Labels | QS5: Rentals Open | QT5: % to all Rentals | QU5: Change MTD | QV5: Row Labels | QW5: Rentals Open | QX5: % to all Rentals | QY5: Change MTD | QZ5: Row Labels | RA5: Rentals Open | RB5: % to all Rentals | RC5: Change MTD | RD5: Row Labels | RE5: Rentals Open | RF5: % to all Rentals | RG5: Change MTD | RH5: Row Labels | RI5: Rentals Open | RJ5: % to all Rentals | RK5: Change MTD | RL5: Row Labels | RM5: Rentals Open | RN5: % to all Rentals | RO5: Change MTD | RP5: Row Labels | RQ5: Rentals Open | RR5: % to all Rentals | RS5: Change MTD | RT5: Row Labels | RU5: Rentals Open | RV5: % to all Rentals | RW5: Change MTD | RX5: Row Labels | RY5: Rentals Open | RZ5: % to all Rentals | SA5: Change MTD
A6: 28 plus days | B6: 172 | C6: 0.43107769 | D6: 28 plus days | E6: 217 | F6: 0.51421801 | G6: =E6-$B6 -> 45 | H6: 28 plus days | I6: 217 | J6: 0.51421801 | K6: =I6-$B6 -> 45 | L6: 28 plus days | M6: 214 | N6: 0.54591837 | O6: =M6-$B6 -> 42 | P6: 28 plus days | Q6: 109 | R6: 0.33641975 | S6: =Q6-$B6 -> -63 | T6: 28 plus days | U6: 194 | V6: 0.55428571 | W6: =U6-$B6 -> 22 | X6: 28 plus days | Y6: 196 | Z6: 0.56321839 | AA6: =Y6-$B6 -> 24 | AB6: 28 plus days | AC6: 189 | AD6: 0.54 | AE6: =AC6-$B6 -> 17 | AF6: 28 plus days | AG6: 184 | AH6: 0.52571429 | AI6: =AG6-$B6 -> 12 | AJ6: 28 plus days | AK6: 183 | AL6: 0.52285714 | AM6: =AK6-$B6 -> 11 | AO6: 190 | AP6: 0.55718475 | AQ6: =AO6-$B6 -> 18 | AR6: 28 plus days | AS6: 196 | AT6: 0.56647399 | AU6: =AS6-$B6 -> 24 | AW6: 185 | AX6: 0.56923077 | AY6: =AW6-$B6 -> 13 | BA6: 183 | BB6: 0.56656347 | BC6: =BA6-$B6 -> 11 | BD6: 28 plus days | BE6: 95 | BF6: 0.29503106 | BG6: =BE6-$B6 -> -77 | BH6: 28 plus days | BI6: 83 | BJ6: 0.26948052 | BK6: =BI6-$B6 -> -89 | BL6: 28 plus days | BM6: 88 | BN6: 0.275 | BO6: =BM6-$B6 -> -84 | BP6: 28 plus days | BQ6: 83 | BR6: 0.27302632 | BS6: =BQ6-$B6 -> -89 | BT6: 28 plus days | BU6: 100 | BV6: 0.33112583 | BW6: =BU6-$B6 -> -72 | BX6: 28 plus days | BY6: 86 | BZ6: 0.29553265 | CA6: =BY6-$B6 -> -86 | CB6: 28 plus days | CC6: 126 | CD6: 0.48837209 | CE6: =CC6-$B6 -> -46 | CF6: 28 plus days | CG6: 129 | CH6: 0.48134328 | CI6: =CG6-$B6 -> -43 | CJ6: 28 plus days | CK6: 136 | CL6: 0.49635036 | CM6: =CK6-$B6 -> -36 | CN6: 28 plus days | CO6: 145 | CP6: 0.50699301 | CQ6: =CO6-$B6 -> -27 | CR6: 28 plus days | CS6: 165 | CT6: 0.56701031 | CU6: =CS6-$B6 -> -7 | CV6: 28 plus days | CW6: 196 | CX6: 0.61442006 | CY6: =CW6-$B6 -> 24 | CZ6: 28 plus days | DA6: 196 | DB6: 0.61442006 | DC6: =DA6-$BQ6 -> 113 | DD6: 28 plus days | DE6: 193 | DF6: 0.61858974 | DG6: =DE6-$BQ6 -> 110 | DH6: 28 plus days | DI6: 191 | DJ6: 0.61612903 | DK6: =DI6-$BQ6 -> 108 | DL6: 28 plus days | DM6: 187 | DN6: 0.61513158 | DO6: =DM6-$BQ6 -> 104 | DP6: 28 plus days | DQ6: 189 | DR6: 0.60771704 | DS6: =DQ6-$BQ6 -> 106 | DT6: 28 plus days | DU6: 187 | DV6: 0.59365079 | DW6: =DU6-$BQ6 -> 104 | DX6: 28 plus days | DY6: 184 | DZ6: 0.5974026 | EA6: =DY6-$BQ6 -> 101 | EB6: 28 plus days | EC6: 188 | ED6: 0.61038961 | EE6: =EC6-$BQ6 -> 105 | EF6: 28 plus days | EG6: 175 | EH6: 0.56451613 | EI6: =EG6-$BQ6 -> 92 | EJ6: 28 plus days | EK6: 175 | EL6: 0.55031447 | EM6: =EK6-$BQ6 -> 92 | EN6: 28 plus days | EO6: 175 | EP6: 0.54858934 | EQ6: =EO6-$BQ6 -> 92 | ER6: 28 plus days | ES6: 176 | ET6: 0.56957929 | EU6: =ES6-$EO6 -> 1 | EV6: 28 plus days | EW6: 171 | EX6: 0.57 | EY6: =EW6-$EO6 -> -4 | EZ6: 28 plus days | FA6: 176 | FB6: 0.58085809 | FC6: =FA6-$EO6 -> 1 | FD6: 28 plus days | FE6: 179 | FF6: 0.57928803 | FG6: =FE6-$EO6 -> 4 | FH6: 28 plus days | FI6: 181 | FJ6: 0.58766234 | FK6: =FI6-$EO6 -> 6 | FL6: 28 plus days | FM6: 176 | FN6: 0.58278146 | FO6: =FM6-$EO6 -> 1 | FP6: 28 plus days | FQ6: 175 | FR6: 0.57755776 | FS6: =FQ6-$EO6 -> 0 | FT6: 28 plus days | FU6: 176 | FV6: 0.5751634 | FW6: =FU6-$EO6 -> 1 | FX6: 28 plus days | FY6: 177 | FZ6: 0.58223684 | GA6: =FY6-$EO6 -> 2 | GB6: 28 plus days | GC6: 168 | GD6: 0.52830189 | GE6: =GC6-$EO6 -> -7 | GF6: 28 plus days | GG6: 170 | GH6: 0.53459119 | GI6: =GG6-$EO6 -> -5 | GJ6: 28 plus days | GK6: 168 | GL6: 0.525 | GM6: =GK6-$EO6 -> -7 | GN6: 28 plus days | GO6: 172 | GP6: 0.53250774 | GQ6: =GO6-$EO6 -> -3 | GR6: 28 plus days | GS6: 173 | GT6: 0.54746835 | GU6: =GS6-$EO6 -> -2 | GV6: 28 plus days | GW6: 173 | GX6: 0.56351792 | GY6: =GW6-$EO6 -> -2 | GZ6: 28 plus days | HA6: 179 | HB6: 0.58496732 | HC6: =HA6-$EO6 -> 4 | HD6: 28 plus days | HE6: 178 | HF6: 0.58745875 | HG6: =HE6-$EO6 -> 3 | HH6: 28 plus days | HI6: 179 | HJ6: 0.58496732 | HK6: =HI6-$HE6 -> 1 | HL6: 28 plus days | HM6: 185 | HN6: 0.56402439 | HO6: =HM6-$HE6 -> 7 | HP6: 28 plus days | HQ6: 185 | HR6: 0.55555556 | HS6: =HQ6-$HE6 -> 7 | HT6: 28 plus days | HU6: 190 | HV6: 0.55393586 | HW6: =HU6-$HE6 -> 12 | HX6: 28 plus days | HY6: 189 | HZ6: 0.5494186 | IA6: =HY6-$HE6 -> 11 | IB6: 28 plus days | IC6: 186 | ID6: 0.55192878 | IE6: =IC6-$HE6 -> 8 | IF6: 28 plus days | IG6: 181 | IH6: 0.54848485 | II6: =IG6-$HE6 -> 3 | IJ6: 28 plus days | IK6: 181 | IL6: 0.5339233 | IM6: =IK6-$HE6 -> 3 | IN6: 28 plus days | IO6: 183 | IP6: 0.53508772 | IQ6: =IO6-$HE6 -> 5 | IR6: 28 plus days | IS6: 187 | IT6: 0.53581662 | IU6: =IS6-$HE6 -> 9 | IV6: 28 plus days | IW6: 184 | IX6: 0.5508982 | IY6: =IW6-$HE6 -> 6 | IZ6: 28 plus days | JA6: 187 | JB6: 0.54202899 | JC6: =JA6-$HE6 -> 9 | JD6: 28 plus days | JE6: 193 | JF6: 0.56764706 | JG6: =JE6-$HE6 -> 15 | JH6: 28 plus days | JI6: 199 | JJ6: 0.584 | JK6: =JI6-$HE6 -> 21 | JL6: 28 plus days | JM6: 194 | JN6: 0.57227139 | JO6: =JM6-$HE6 -> 16 | JP6: 28 plus days | JQ6: 191 | JR6: 0.57014925 | JS6: =JQ6-$HE6 -> 13 | JT6: 28 plus days | JU6: 188 | JV6: 0.56626506 | JW6: =JU6-$HE6 -> 10 | JX6: 28 plus days | JY6: 188 | JZ6: 0.56626506 | KA6: =JY6-$HE6 -> 10 | KB6: 28 plus days | KC6: 188 | KD6: 0.56626506 | KE6: =KC6-$HE6 -> 10 | KF6: 28 plus days | KG6: 194 | KH6: 0.59876543 | KI6: =KG6-$HE6 -> 16 | KJ6: 28 plus days | KK6: 199 | KL6: 0.61042945 | KM6: =KK6-$HE6 -> 21 | KN6: 28 plus days | KO6: 206 | KP6: 0.62424242 | KQ6: =KO6-$HE6 -> 28 | KR6: 28 plus days | KS6: 206 | KT6: 0.62804878 | KU6: =KS6-$HE6 -> 28 | KV6: 28 plus days | KW6: 206 | KX6: 0.62804878 | KY6: =KW6-$HE6 -> 28 | KZ6: 28 plus days | LA6: 213 | LB6: 0.64156627 | LC6: =LA6-$HE6 -> 35 | LD6: 28 plus days | LE6: 211 | LF6: 0.64329268 | LG6: =LE6-$LA6 -> -2 | LH6: 28 plus days | LI6: 210 | LJ6: 0.63444109 | LK6: =LI6-$LA6 -> -3 | LL6: 28 plus days | LM6: 209 | LN6: 0.6183432 | LO6: =LM6-$LA6 -> -4 | LP6: 28 plus days | LQ6: 214 | LR6: 0.63126844 | LS6: =LQ6-$LA6 -> 1 | LT6: 28 plus days | LU6: 211 | LV6: 0.61337209 | LW6: =LU6-$LA6 -> -2 | LX6: 28 plus days | LY6: 210 | LZ6: 0.61403509 | MA6: =LY6-$LA6 -> -3 | MB6: 28 plus days | MC6: 200 | MD6: 0.5899705 | ME6: =MC6-$LA6 -> -13 | MF6: 28 plus days | MG6: 200 | MH6: 0.58651026 | MI6: =MG6-$LA6 -> -13 | MJ6: 28 plus days | MK6: 200 | ML6: 0.5952381 | MM6: =MK6-$LA6 -> -13 | MN6: 28 plus days | MO6: 205 | MP6: 0.60650888 | MQ6: =MO6-$LA6 -> -8 | MR6: 28 plus days | MS6: 209 | MT6: 0.62202381 | MU6: =MS6-$LA6 -> -4 | MV6: 28 plus days | MW6: 206 | MX6: 0.60766962 | MY6: =MW6-$LA6 -> -7 | MZ6: 28 plus days | NA6: 204 | NB6: 0.6 | NC6: =NA6-$LA6 -> -9 | ND6: 28 plus days | NE6: 201 | NF6: 0.59467456 | NG6: =NE6-$LA6 -> -12 | NH6: 28 plus days | NI6: 193 | NJ6: 0.58484848 | NK6: =NI6-$LA6 -> -20 | NL6: 28 plus days | NM6: 201 | NN6: 0.61846154 | NO6: =NM6-$LA6 -> -12 | NP6: 28 plus days | NQ6: 201 | NR6: 0.6036036 | NS6: =NQ6-$LA6 -> -12 | NT6: 28 plus days | NU6: 200 | NV6: 0.58139535 | NW6: =NU6-$LA6 -> -13 | NX6: 28 plus days | NY6: 196 | NZ6: 0.5648415 | OA6: =NY6-$LA6 -> -17 | OB6: 28 plus days | OC6: 196 | OD6: 0.58333333 | OE6: =OC6-$LA6 -> -17 | OF6: 28 plus days | OG6: 195 | OH6: 0.58383234 | OI6: =OG6-$OC6 -> -1 | OJ6: 28 plus days | OK6: 196 | OL6: 0.57478006 | OM6: =OK6-$OC6 -> 0 | ON6: 28 plus days | OO6: 198 | OP6: 0.58579882 | OQ6: =OO6-$OC6 -> 2 | OR6: 28 plus days | OS6: 203 | OT6: 0.59705882 | OU6: =OS6-$OC6 -> 7 | OV6: 28 plus days | OW6: 201 | OX6: 0.60179641 | OY6: =OW6-$OC6 -> 5 | OZ6: 28 plus days | PA6: 204 | PB6: 0.61077844 | PC6: =PA6-$OC6 -> 8 | PD6: 28 plus days | PE6: 204 | PF6: 0.60176991 | PG6: =PE6-$OC6 -> 8 | PH6: 28 plus days | PI6: 199 | PJ6: 0.5887574 | PK6: =PI6-$OC6 -> 3 | PL6: 28 plus days | PM6: 203 | PN6: 0.60597015 | PO6: =PM6-$OC6 -> 7 | PP6: 28 plus days | PQ6: 207 | PR6: 0.61424332 | PS6: =PQ6-$OC6 -> 11 | PT6: 28 plus days | PU6: 205 | PV6: 0.625 | PW6: =PU6-$OC6 -> 9 | PX6: 28 plus days | PY6: 208 | PZ6: 0.62650602 | QA6: =PY6-$OC6 -> 12 | QB6: 28 plus days | QC6: 199 | QD6: 0.63174603 | QE6: =QC6-$OC6 -> 3 | QF6: 28 plus days | QG6: 198 | QH6: 0.64705882 | QI6: =QG6-$OC6 -> 2 | QJ6: 28 plus days | QK6: 191 | QL6: 0.65635739 | QM6: =QK6-$OC6 -> -5 | QN6: 28 plus days | QO6: 187 | QP6: 0.67266187 | QQ6: =QO6-$OC6 -> -9 | QR6: 28 plus days | QS6: 175 | QT6: 0.67307692 | QU6: =QS6-$OC6 -> -21 | QV6: 28 plus days | QW6: 200 | QX6: 0.59171598 | QY6: =QW6-$OC6 -> 4 | QZ6: 28 plus days | RA6: 198 | RB6: 0.59104478 | RC6: =RA6-$OC6 -> 2 | RD6: 28 plus days | RE6: 193 | RF6: 0.5659824 | RG6: =RE6-$OC6 -> -3 | RH6: 28 plus days | RI6: 192 | RJ6: 0.58006042 | RK6: =RI6-$RE6 -> -1 | RL6: 28 plus days | RM6: 192 | RN6: 0.58006042 | RO6: =RM6-$RE6 -> -1 | RP6: 28 plus days | RQ6: 192 | RR6: 0.57657658 | RS6: =RQ6-$RE6 -> -1 | RT6: 28 plus days | RU6: 192 | RV6: 0.57831325 | RW6: =RU6-$RE6 -> -1 | RX6: 28 plus days | SA6: =RY6-$RE6 -> -193
A7: 21 plus days | B7: 55 | C7: 0.13784461 | D7: 21 plus days | E7: 55 | F7: 0.13033175 | G7: =E7-$B7 -> 0 | H7: 21 plus days | I7: 55 | J7: 0.13033175 | K7: =I7-$B7 -> 0 | L7: 21 plus days | M7: 27 | N7: 0.068877551 | O7: =M7-$B7 -> -28 | P7: 21 plus days | Q7: 39 | R7: 0.12037037 | S7: =Q7-$B7 -> -16 | T7: 21 plus days | U7: 42 | V7: 0.12 | W7: =U7-$B7 -> -13 | X7: 21 plus days | Y7: 38 | Z7: 0.1091954 | AA7: =Y7-$B7 -> -17 | AB7: 21 plus days | AC7: 33 | AD7: 0.094285714 | AE7: =AC7-$B7 -> -22 | AF7: 21 plus days | AG7: 36 | AH7: 0.10285714 | AI7: =AG7-$B7 -> -19 | AJ7: 21 plus days | AK7: 37 | AL7: 0.10571429 | AM7: =AK7-$B7 -> -18 | AO7: 27 | AP7: 0.079178886 | AQ7: =AO7-$B7 -> -28 | AR7: 21 plus days | AS7: 19 | AT7: 0.054913295 | AU7: =AS7-$B7 -> -36 | AW7: 18 | AX7: 0.055384615 | AY7: =AW7-$B7 -> -37 | BA7: 17 | BB7: 0.052631579 | BC7: =BA7-$B7 -> -38 | BD7: 21 plus days | BE7: 52 | BF7: 0.16149068 | BG7: =BE7-$B7 -> -3 | BH7: 21 plus days | BI7: 69 | BJ7: 0.22402597 | BK7: =BI7-$B7 -> 14 | BL7: 21 plus days | BM7: 70 | BN7: 0.21875 | BO7: =BM7-$B7 -> 15 | BP7: 21 plus days | BQ7: 61 | BR7: 0.20065789 | BS7: =BQ7-$B7 -> 6 | BT7: 21 plus days | BU7: 65 | BV7: 0.21523179 | BW7: =BU7-$B7 -> 10 | BX7: 21 plus days | BY7: 61 | BZ7: 0.20962199 | CA7: =BY7-$B7 -> 6 | CB7: 21 plus days | CC7: 27 | CD7: 0.10465116 | CE7: =CC7-$B7 -> -28 | CF7: 21 plus days | CG7: 21 | CH7: 0.078358209 | CI7: =CG7-$B7 -> -34 | CJ7: 21 plus days | CK7: 22 | CL7: 0.080291971 | CM7: =CK7-$B7 -> -33 | CN7: 21 plus days | CO7: 23 | CP7: 0.08041958 | CQ7: =CO7-$B7 -> -32 | CR7: 21 plus days | CS7: 19 | CT7: 0.065292096 | CU7: =CS7-$B7 -> -36 | CV7: 21 plus days | CW7: 13 | CX7: 0.040752351 | CY7: =CW7-$B7 -> -42 | CZ7: 21 plus days | DA7: 11 | DB7: 0.034482759 | DC7: =DA7-$BQ7 -> -50 | DD7: 21 plus days | DE7: 13 | DF7: 0.041666667 | DG7: =DE7-$BQ7 -> -48 | DH7: 21 plus days | DI7: 19 | DJ7: 0.061290323 | DK7: =DI7-$BQ7 -> -42 | DL7: 21 plus days | DM7: 19 | DN7: 0.0625 | DO7: =DM7-$BQ7 -> -42 | DP7: 21 plus days | DQ7: 18 | DR7: 0.057877814 | DS7: =DQ7-$BQ7 -> -43 | DT7: 21 plus days | DU7: 18 | DV7: 0.057142857 | DW7: =DU7-$BQ7 -> -43 | DX7: 21 plus days | DY7: 20 | DZ7: 0.064935065 | EA7: =DY7-$BQ7 -> -41 | EB7: 21 plus days | EC7: 16 | ED7: 0.051948052 | EE7: =EC7-$BQ7 -> -45 | EF7: 21 plus days | EG7: 19 | EH7: 0.061290323 | EI7: =EG7-$BQ7 -> -42 | EJ7: 21 plus days | EK7: 22 | EL7: 0.06918239 | EM7: =EK7-$BQ7 -> -39 | EN7: 21 plus days | EO7: 24 | EP7: 0.07523511 | EQ7: =EO7-$BQ7 -> -37 | ER7: 21 plus days | ES7: 26 | ET7: 0.084142395 | EU7: =ES7-$EO7 -> 2 | EV7: 21 plus days | EW7: 25 | EX7: 0.083333333 | EY7: =EW7-$EO7 -> 1 | EZ7: 21 plus days | FA7: 21 | FB7: 0.069306931 | FC7: =FA7-$EO7 -> -3 | FD7: 21 plus days | FE7: 25 | FF7: 0.080906149 | FG7: =FE7-$EO7 -> 1 | FH7: 21 plus days | FI7: 20 | FJ7: 0.064935065 | FK7: =FI7-$EO7 -> -4 | FL7: 21 plus days | FM7: 17 | FN7: 0.056291391 | FO7: =FM7-$EO7 -> -7 | FP7: 21 plus days | FQ7: 18 | FR7: 0.059405941 | FS7: =FQ7-$EO7 -> -6 | FT7: 21 plus days | FU7: 17 | FV7: 0.055555556 | FW7: =FU7-$EO7 -> -7 | FX7: 21 plus days | FY7: 19 | FZ7: 0.0625 | GA7: =FY7-$EO7 -> -5 | GB7: 21 plus days | GC7: 24 | GD7: 0.075471698 | GE7: =GC7-$EO7 -> 0 | GF7: 21 plus days | GG7: 29 | GH7: 0.091194969 | GI7: =GG7-$EO7 -> 5 | GJ7: 21 plus days | GK7: 34 | GL7: 0.10625 | GM7: =GK7-$EO7 -> 10 | GN7: 21 plus days | GO7: 34 | GP7: 0.10526316 | GQ7: =GO7-$EO7 -> 10 | GR7: 21 plus days | GS7: 28 | GT7: 0.088607595 | GU7: =GS7-$EO7 -> 4 | GV7: 21 plus days | GW7: 26 | GX7: 0.084690554 | GY7: =GW7-$EO7 -> 2 | GZ7: 21 plus days | HA7: 21 | HB7: 0.068627451 | HC7: =HA7-$EO7 -> -3 | HD7: 21 plus days | HE7: 18 | HF7: 0.059405941 | HG7: =HE7-$EO7 -> -6 | HH7: 21 plus days | HI7: 22 | HJ7: 0.071895425 | HK7: =HI7-$HE7 -> 4 | HL7: 21 plus days | HM7: 19 | HN7: 0.057926829 | HO7: =HM7-$HE7 -> 1 | HP7: 21 plus days | HQ7: 18 | HR7: 0.054054054 | HS7: =HQ7-$HE7 -> 0 | HT7: 21 plus days | HU7: 20 | HV7: 0.058309038 | HW7: =HU7-$HE7 -> 2 | HX7: 21 plus days | HY7: 25 | HZ7: 0.072674419 | IA7: =HY7-$HE7 -> 7 | IB7: 21 plus days | IC7: 26 | ID7: 0.077151335 | IE7: =IC7-$HE7 -> 8 | IF7: 21 plus days | IG7: 29 | IH7: 0.087878788 | II7: =IG7-$HE7 -> 11 | IJ7: 21 plus days | IK7: 36 | IL7: 0.10619469 | IM7: =IK7-$HE7 -> 18 | IN7: 21 plus days | IO7: 35 | IP7: 0.10233918 | IQ7: =IO7-$HE7 -> 17 | IR7: 21 plus days | IS7: 33 | IT7: 0.094555874 | IU7: =IS7-$HE7 -> 15 | IV7: 21 plus days | IW7: 26 | IX7: 0.077844311 | IY7: =IW7-$HE7 -> 8 | IZ7: 21 plus days | JA7: 24 | JB7: 0.069565217 | JC7: =JA7-$HE7 -> 6 | JD7: 21 plus days | JE7: 21 | JF7: 0.061764706 | JG7: =JE7-$HE7 -> 3 | JH7: 21 plus days | JI7: 17 | JJ7: 0.05 | JK7: =JI7-$HE7 -> -1 | JL7: 21 plus days | JM7: 16 | JN7: 0.04719764 | JO7: =JM7-$HE7 -> -2 | JP7: 21 plus days | JQ7: 25 | JR7: 0.074626866 | JS7: =JQ7-$HE7 -> 7 | JT7: 21 plus days | JU7: 28 | JV7: 0.084337349 | JW7: =JU7-$HE7 -> 10 | JX7: 21 plus days | JY7: 28 | JZ7: 0.084337349 | KA7: =JY7-$HE7 -> 10 | KB7: 21 plus days | KC7: 28 | KD7: 0.084337349 | KE7: =KC7-$HE7 -> 10 | KF7: 21 plus days | KG7: 28 | KH7: 0.086419753 | KI7: =KG7-$HE7 -> 10 | KJ7: 21 plus days | KK7: 23 | KL7: 0.070552147 | KM7: =KK7-$HE7 -> 5 | KN7: 21 plus days | KO7: 19 | KP7: 0.057575758 | KQ7: =KO7-$HE7 -> 1 | KR7: 21 plus days | KS7: 19 | KT7: 0.057926829 | KU7: =KS7-$HE7 -> 1 | KV7: 21 plus days | KW7: 19 | KX7: 0.057926829 | KY7: =KW7-$HE7 -> 1 | KZ7: 21 plus days | LA7: 25 | LB7: 0.075301205 | LC7: =LA7-$HE7 -> 7 | LD7: 21 plus days | LE7: 30 | LF7: 0.091463415 | LG7: =LE7-$LA7 -> 5 | LH7: 21 plus days | LI7: 30 | LJ7: 0.090634441 | LK7: =LI7-$LA7 -> 5 | LL7: 21 plus days | LM7: 34 | LN7: 0.10059172 | LO7: =LM7-$LA7 -> 9 | LP7: 21 plus days | LQ7: 27 | LR7: 0.079646018 | LS7: =LQ7-$LA7 -> 2 | LT7: 21 plus days | LU7: 30 | LV7: 0.087209302 | LW7: =LU7-$LA7 -> 5 | LX7: 21 plus days | LY7: 30 | LZ7: 0.087719298 | MA7: =LY7-$LA7 -> 5 | MB7: 21 plus days | MC7: 28 | MD7: 0.08259587 | ME7: =MC7-$LA7 -> 3 | MF7: 21 plus days | MG7: 21 | MH7: 0.061583578 | MI7: =MG7-$LA7 -> -4 | MJ7: 21 plus days | MK7: 16 | ML7: 0.047619048 | MM7: =MK7-$LA7 -> -9 | MN7: 21 plus days | MO7: 15 | MP7: 0.044378698 | MQ7: =MO7-$LA7 -> -10 | MR7: 21 plus days | MS7: 18 | MT7: 0.053571429 | MU7: =MS7-$LA7 -> -7 | MV7: 21 plus days | MW7: 18 | MX7: 0.053097345 | MY7: =MW7-$LA7 -> -7 | MZ7: 21 plus days | NA7: 17 | NB7: 0.05 | NC7: =NA7-$LA7 -> -8 | ND7: 21 plus days | NE7: 15 | NF7: 0.044378698 | NG7: =NE7-$LA7 -> -10 | NH7: 21 plus days | NI7: 18 | NJ7: 0.054545455 | NK7: =NI7-$LA7 -> -7 | NL7: 21 plus days | NM7: 28 | NN7: 0.086153846 | NO7: =NM7-$LA7 -> 3 | NP7: 21 plus days | NQ7: 27 | NR7: 0.081081081 | NS7: =NQ7-$LA7 -> 2 | NT7: 21 plus days | NU7: 25 | NV7: 0.072674419 | NW7: =NU7-$LA7 -> 0 | NX7: 21 plus days | NY7: 31 | NZ7: 0.089337176 | OA7: =NY7-$LA7 -> 6 | OB7: 21 plus days | OC7: 28 | OD7: 0.083333333 | OE7: =OC7-$LA7 -> 3 | OF7: 21 plus days | OG7: 30 | OH7: 0.089820359 | OI7: =OG7-$OC7 -> 2 | OJ7: 21 plus days | OK7: 27 | OL7: 0.079178886 | OM7: =OK7-$OC7 -> -1 | ON7: 21 plus days | OO7: 22 | OP7: 0.065088757 | OQ7: =OO7-$OC7 -> -6 | OR7: 21 plus days | OS7: 20 | OT7: 0.058823529 | OU7: =OS7-$OC7 -> -8 | OV7: 21 plus days | OW7: 23 | OX7: 0.068862275 | OY7: =OW7-$OC7 -> -5 | OZ7: 21 plus days | PA7: 23 | PB7: 0.068862275 | PC7: =PA7-$OC7 -> -5 | PD7: 21 plus days | PE7: 22 | PF7: 0.064896755 | PG7: =PE7-$OC7 -> -6 | PH7: 21 plus days | PI7: 28 | PJ7: 0.082840237 | PK7: =PI7-$OC7 -> 0 | PL7: 21 plus days | PM7: 28 | PN7: 0.08358209 | PO7: =PM7-$OC7 -> 0 | PP7: 21 plus days | PQ7: 23 | PR7: 0.068249258 | PS7: =PQ7-$OC7 -> -5 | PT7: 21 plus days | PU7: 22 | PV7: 0.067073171 | PW7: =PU7-$OC7 -> -6 | PX7: 21 plus days | PY7: 22 | PZ7: 0.06626506 | QA7: =PY7-$OC7 -> -6 | QB7: 21 plus days | QC7: 20 | QD7: 0.063492063 | QE7: =QC7-$OC7 -> -8 | QF7: 21 plus days | QG7: 18 | QH7: 0.058823529 | QI7: =QG7-$OC7 -> -10 | QJ7: 21 plus days | QK7: 19 | QL7: 0.065292096 | QM7: =QK7-$OC7 -> -9 | QN7: 21 plus days | QO7: 20 | QP7: 0.071942446 | QQ7: =QO7-$OC7 -> -8 | QR7: 21 plus days | QS7: 18 | QT7: 0.069230769 | QU7: =QS7-$OC7 -> -10 | QV7: 21 plus days | QW7: 19 | QX7: 0.056213018 | QY7: =QW7-$OC7 -> -9 | QZ7: 21 plus days | RA7: 22 | RB7: 0.065671642 | RC7: =RA7-$OC7 -> -6 | RD7: 21 plus days | RE7: 22 | RF7: 0.064516129 | RG7: =RE7-$OC7 -> -6 | RH7: 21 plus days | RI7: 25 | RJ7: 0.075528701 | RK7: =RI7-$RE7 -> 3 | RL7: 21 plus days | RM7: 21 | RN7: 0.063444109 | RO7: =RM7-$RE7 -> -1 | RP7: 21 plus days | RQ7: 22 | RR7: 0.066066066 | RS7: =RQ7-$RE7 -> 0 | RT7: 21 plus days | RU7: 22 | RV7: 0.06626506 | RW7: =RU7-$RE7 -> 0 | RX7: 21 plus days | SA7: =RY7-$RE7 -> -22
A8: 14 plus days | B8: 40 | C8: 0.10025063 | D8: 14 plus days | E8: 46 | F8: 0.10900474 | G8: =E8-$B8 -> 6 | H8: 14 plus days | I8: 46 | J8: 0.10900474 | K8: =I8-$B8 -> 6 | L8: 14 plus days | M8: 56 | N8: 0.14285714 | O8: =M8-$B8 -> 16 | P8: 14 plus days | Q8: 37 | R8: 0.11419753 | S8: =Q8-$B8 -> -3 | T8: 14 plus days | U8: 27 | V8: 0.077142857 | W8: =U8-$B8 -> -13 | X8: 14 plus days | Y8: 30 | Z8: 0.086206897 | AA8: =Y8-$B8 -> -10 | AB8: 14 plus days | AC8: 28 | AD8: 0.08 | AE8: =AC8-$B8 -> -12 | AF8: 14 plus days | AG8: 29 | AH8: 0.082857143 | AI8: =AG8-$B8 -> -11 | AJ8: 14 plus days | AK8: 29 | AL8: 0.082857143 | AM8: =AK8-$B8 -> -11 | AO8: 38 | AP8: 0.11143695 | AQ8: =AO8-$B8 -> -2 | AR8: 14 plus days | AS8: 43 | AT8: 0.12427746 | AU8: =AS8-$B8 -> 3 | AW8: 48 | AX8: 0.14769231 | AY8: =AW8-$B8 -> 8 | BA8: 46 | BB8: 0.14241486 | BC8: =BA8-$B8 -> 6 | BD8: 14 plus days | BE8: 71 | BF8: 0.22049689 | BG8: =BE8-$B8 -> 31 | BH8: 14 plus days | BI8: 63 | BJ8: 0.20454545 | BK8: =BI8-$B8 -> 23 | BL8: 14 plus days | BM8: 62 | BN8: 0.19375 | BO8: =BM8-$B8 -> 22 | BP8: 14 plus days | BQ8: 55 | BR8: 0.18092105 | BS8: =BQ8-$B8 -> 15 | BT8: 14 plus days | BU8: 52 | BV8: 0.17218543 | BW8: =BU8-$B8 -> 12 | BX8: 14 plus days | BY8: 49 | BZ8: 0.16838488 | CA8: =BY8-$B8 -> 9 | CB8: 14 plus days | CC8: 27 | CD8: 0.10465116 | CE8: =CC8-$B8 -> -13 | CF8: 14 plus days | CG8: 34 | CH8: 0.12686567 | CI8: =CG8-$B8 -> -6 | CJ8: 14 plus days | CK8: 38 | CL8: 0.13868613 | CM8: =CK8-$B8 -> -2 | CN8: 14 plus days | CO8: 42 | CP8: 0.14685315 | CQ8: =CO8-$B8 -> 2 | CR8: 14 plus days | CS8: 28 | CT8: 0.096219931 | CU8: =CS8-$B8 -> -12 | CV8: 14 plus days | CW8: 21 | CX8: 0.065830721 | CY8: =CW8-$B8 -> -19 | CZ8: 14 plus days | DA8: 23 | DB8: 0.072100313 | DC8: =DA8-$BQ8 -> -32 | DD8: 14 plus days | DE8: 24 | DF8: 0.076923077 | DG8: =DE8-$BQ8 -> -31 | DH8: 14 plus days | DI8: 21 | DJ8: 0.067741935 | DK8: =DI8-$BQ8 -> -34 | DL8: 14 plus days | DM8: 23 | DN8: 0.075657895 | DO8: =DM8-$BQ8 -> -32 | DP8: 14 plus days | DQ8: 32 | DR8: 0.10289389 | DS8: =DQ8-$BQ8 -> -23 | DT8: 14 plus days | DU8: 35 | DV8: 0.11111111 | DW8: =DU8-$BQ8 -> -20 | DX8: 14 plus days | DY8: 38 | DZ8: 0.12337662 | EA8: =DY8-$BQ8 -> -17 | EB8: 14 plus days | EC8: 35 | ED8: 0.11363636 | EE8: =EC8-$BQ8 -> -20 | EF8: 14 plus days | EG8: 29 | EH8: 0.093548387 | EI8: =EG8-$BQ8 -> -26 | EJ8: 14 plus days | EK8: 30 | EL8: 0.094339623 | EM8: =EK8-$BQ8 -> -25 | EN8: 14 plus days | EO8: 26 | EP8: 0.081504702 | EQ8: =EO8-$BQ8 -> -29 | ER8: 14 plus days | ES8: 26 | ET8: 0.084142395 | EU8: =ES8-$EO8 -> 0 | EV8: 14 plus days | EW8: 23 | EX8: 0.076666667 | EY8: =EW8-$EO8 -> -3 | EZ8: 14 plus days | FA8: 24 | FB8: 0.079207921 | FC8: =FA8-$EO8 -> -2 | FD8: 14 plus days | FE8: 23 | FF8: 0.074433657 | FG8: =FE8-$EO8 -> -3 | FH8: 14 plus days | FI8: 31 | FJ8: 0.10064935 | FK8: =FI8-$EO8 -> 5 | FL8: 14 plus days | FM8: 32 | FN8: 0.10596026 | FO8: =FM8-$EO8 -> 6 | FP8: 14 plus days | FQ8: 32 | FR8: 0.10561056 | FS8: =FQ8-$EO8 -> 6 | FT8: 14 plus days | FU8: 37 | FV8: 0.12091503 | FW8: =FU8-$EO8 -> 11 | FX8: 14 plus days | FY8: 35 | FZ8: 0.11513158 | GA8: =FY8-$EO8 -> 9 | GB8: 14 plus days | GC8: 33 | GD8: 0.10377358 | GE8: =GC8-$EO8 -> 7 | GF8: 14 plus days | GG8: 31 | GH8: 0.097484277 | GI8: =GG8-$EO8 -> 5 | GJ8: 14 plus days | GK8: 26 | GL8: 0.08125 | GM8: =GK8-$EO8 -> 0 | GN8: 14 plus days | GO8: 25 | GP8: 0.077399381 | GQ8: =GO8-$EO8 -> -1 | GR8: 14 plus days | GS8: 26 | GT8: 0.082278481 | GU8: =GS8-$EO8 -> 0 | GV8: 14 plus days | GW8: 26 | GX8: 0.084690554 | GY8: =GW8-$EO8 -> 0 | GZ8: 14 plus days | HA8: 23 | HB8: 0.075163399 | HC8: =HA8-$EO8 -> -3 | HD8: 14 plus days | HE8: 21 | HF8: 0.069306931 | HG8: =HE8-$EO8 -> -5 | HH8: 14 plus days | HI8: 31 | HJ8: 0.10130719 | HK8: =HI8-$HE8 -> 10 | HL8: 14 plus days | HM8: 38 | HN8: 0.11585366 | HO8: =HM8-$HE8 -> 17 | HP8: 14 plus days | HQ8: 41 | HR8: 0.12312312 | HS8: =HQ8-$HE8 -> 20 | HT8: 14 plus days | HU8: 38 | HV8: 0.11078717 | HW8: =HU8-$HE8 -> 17 | HX8: 14 plus days | HY8: 35 | HZ8: 0.10174419 | IA8: =HY8-$HE8 -> 14 | IB8: 14 plus days | IC8: 33 | ID8: 0.097922849 | IE8: =IC8-$HE8 -> 12 | IF8: 14 plus days | IG8: 31 | IH8: 0.093939394 | II8: =IG8-$HE8 -> 10 | IJ8: 14 plus days | IK8: 25 | IL8: 0.073746313 | IM8: =IK8-$HE8 -> 4 | IN8: 14 plus days | IO8: 20 | IP8: 0.058479532 | IQ8: =IO8-$HE8 -> -1 | IR8: 14 plus days | IS8: 19 | IT8: 0.054441261 | IU8: =IS8-$HE8 -> -2 | IV8: 14 plus days | IW8: 33 | IX8: 0.098802395 | IY8: =IW8-$HE8 -> 12 | IZ8: 14 plus days | JA8: 36 | JB8: 0.10434783 | JC8: =JA8-$HE8 -> 15 | JD8: 14 plus days | JE8: 34 | JF8: 0.1 | JG8: =JE8-$HE8 -> 13 | JH8: 14 plus days | JI8: 41 | JJ8: 0.12 | JK8: =JI8-$HE8 -> 20 | JL8: 14 plus days | JM8: 38 | JN8: 0.1120944 | JO8: =JM8-$HE8 -> 17 | JP8: 14 plus days | JQ8: 30 | JR8: 0.089552239 | JS8: =JQ8-$HE8 -> 9 | JT8: 14 plus days | JU8: 23 | JV8: 0.069277108 | JW8: =JU8-$HE8 -> 2 | JX8: 14 plus days | JY8: 23 | JZ8: 0.069277108 | KA8: =JY8-$HE8 -> 2 | KB8: 14 plus days | KC8: 23 | KD8: 0.069277108 | KE8: =KC8-$HE8 -> 2 | KF8: 14 plus days | KG8: 33 | KH8: 0.10185185 | KI8: =KG8-$HE8 -> 12 | KJ8: 14 plus days | KK8: 39 | KL8: 0.1196319 | KM8: =KK8-$HE8 -> 18 | KN8: 14 plus days | KO8: 37 | KP8: 0.11212121 | KQ8: =KO8-$HE8 -> 16 | KR8: 14 plus days | KS8: 38 | KT8: 0.11585366 | KU8: =KS8-$HE8 -> 17 | KV8: 14 plus days | KW8: 38 | KX8: 0.11585366 | KY8: =KW8-$HE8 -> 17 | KZ8: 14 plus days | LA8: 34 | LB8: 0.10240964 | LC8: =LA8-$HE8 -> 13 | LD8: 14 plus days | LE8: 34 | LF8: 0.10365854 | LG8: =LE8-$LA8 -> 0 | LH8: 14 plus days | LI8: 32 | LJ8: 0.096676737 | LK8: =LI8-$LA8 -> -2 | LL8: 14 plus days | LM8: 26 | LN8: 0.076923077 | LO8: =LM8-$LA8 -> -8 | LP8: 14 plus days | LQ8: 21 | LR8: 0.061946903 | LS8: =LQ8-$LA8 -> -13 | LT8: 14 plus days | LU8: 20 | LV8: 0.058139535 | LW8: =LU8-$LA8 -> -14 | LX8: 14 plus days | LY8: 17 | LZ8: 0.049707602 | MA8: =LY8-$LA8 -> -17 | MB8: 14 plus days | MC8: 19 | MD8: 0.056047198 | ME8: =MC8-$LA8 -> -15 | MF8: 14 plus days | MG8: 19 | MH8: 0.055718475 | MI8: =MG8-$LA8 -> -15 | MJ8: 14 plus days | MK8: 19 | ML8: 0.056547619 | MM8: =MK8-$LA8 -> -15 | MN8: 14 plus days | MO8: 22 | MP8: 0.065088757 | MQ8: =MO8-$LA8 -> -12 | MR8: 14 plus days | MS8: 29 | MT8: 0.086309524 | MU8: =MS8-$LA8 -> -5 | MV8: 14 plus days | MW8: 27 | MX8: 0.079646018 | MY8: =MW8-$LA8 -> -7 | MZ8: 14 plus days | NA8: 31 | NB8: 0.091176471 | NC8: =NA8-$LA8 -> -3 | ND8: 14 plus days | NE8: 37 | NF8: 0.10946746 | NG8: =NE8-$LA8 -> 3 | NH8: 14 plus days | NI8: 34 | NJ8: 0.1030303 | NK8: =NI8-$LA8 -> 0 | NL8: 14 plus days | NM8: 32 | NN8: 0.098461538 | NO8: =NM8-$LA8 -> -2 | NP8: 14 plus days | NQ8: 32 | NR8: 0.096096096 | NS8: =NQ8-$LA8 -> -2 | NT8: 14 plus days | NU8: 30 | NV8: 0.087209302 | NW8: =NU8-$LA8 -> -4 | NX8: 14 plus days | NY8: 30 | NZ8: 0.086455331 | OA8: =NY8-$LA8 -> -4 | OB8: 14 plus days | OC8: 28 | OD8: 0.083333333 | OE8: =OC8-$LA8 -> -6 | OF8: 14 plus days | OG8: 27 | OH8: 0.080838323 | OI8: =OG8-$OC8 -> -1 | OJ8: 14 plus days | OK8: 27 | OL8: 0.079178886 | OM8: =OK8-$OC8 -> -1 | ON8: 14 plus days | OO8: 31 | OP8: 0.091715976 | OQ8: =OO8-$OC8 -> 3 | OR8: 14 plus days | OS8: 36 | OT8: 0.10588235 | OU8: =OS8-$OC8 -> 8 | OV8: 14 plus days | OW8: 35 | OX8: 0.10479042 | OY8: =OW8-$OC8 -> 7 | OZ8: 14 plus days | PA8: 31 | PB8: 0.092814371 | PC8: =PA8-$OC8 -> 3 | PD8: 14 plus days | PE8: 28 | PF8: 0.08259587 | PG8: =PE8-$OC8 -> 0 | PH8: 14 plus days | PI8: 29 | PJ8: 0.085798817 | PK8: =PI8-$OC8 -> 1 | PL8: 14 plus days | PM8: 21 | PN8: 0.062686567 | PO8: =PM8-$OC8 -> -7 | PP8: 14 plus days | PQ8: 22 | PR8: 0.065281899 | PS8: =PQ8-$OC8 -> -6 | PT8: 14 plus days | PU8: 26 | PV8: 0.079268293 | PW8: =PU8-$OC8 -> -2 | PX8: 14 plus days | PY8: 24 | PZ8: 0.072289157 | QA8: =PY8-$OC8 -> -4 | QB8: 14 plus days | QC8: 23 | QD8: 0.073015873 | QE8: =QC8-$OC8 -> -5 | QF8: 14 plus days | QG8: 23 | QH8: 0.075163399 | QI8: =QG8-$OC8 -> -5 | QJ8: 14 plus days | QK8: 25 | QL8: 0.085910653 | QM8: =QK8-$OC8 -> -3 | QN8: 14 plus days | QO8: 30 | QP8: 0.10791367 | QQ8: =QO8-$OC8 -> 2 | QR8: 14 plus days | QS8: 29 | QT8: 0.11153846 | QU8: =QS8-$OC8 -> 1 | QV8: 14 plus days | QW8: 27 | QX8: 0.079881657 | QY8: =QW8-$OC8 -> -1 | QZ8: 14 plus days | RA8: 34 | RB8: 0.10149254 | RC8: =RA8-$OC8 -> 6 | RD8: 14 plus days | RE8: 34 | RF8: 0.099706745 | RG8: =RE8-$OC8 -> 6 | RH8: 14 plus days | RI8: 36 | RJ8: 0.10876133 | RK8: =RI8-$RE8 -> 2 | RL8: 14 plus days | RM8: 33 | RN8: 0.099697885 | RO8: =RM8-$RE8 -> -1 | RP8: 14 plus days | RQ8: 28 | RR8: 0.084084084 | RS8: =RQ8-$RE8 -> -6 | RT8: 14 plus days | RU8: 28 | RV8: 0.084337349 | RW8: =RU8-$RE8 -> -6 | RX8: 14 plus days | SA8: =RY8-$RE8 -> -34
A9: Less than 14 days | B9: 132 | C9: 0.33082707 | D9: Less than 14 days | E9: 104 | F9: 0.2464455 | G9: =E9-$B9 -> -28 | H9: Less than 14 days | I9: 104 | J9: 0.2464455 | K9: =I9-$B9 -> -28 | L9: Less than 14 days | M9: 95 | N9: 0.24234694 | O9: =M9-$B9 -> -37 | P9: Less than 14 days | Q9: 139 | R9: 0.42901235 | S9: =Q9-$B9 -> 7 | T9: Less than 14 days | U9: 87 | V9: 0.24857143 | W9: =U9-$B9 -> -45 | X9: Less than 14 days | Y9: 84 | Z9: 0.24137931 | AA9: =Y9-$B9 -> -48 | AB9: Less than 14 days | AC9: 100 | AD9: 0.28571429 | AE9: =AC9-$B9 -> -32 | AF9: Less than 14 days | AG9: 101 | AH9: 0.28857143 | AI9: =AG9-$B9 -> -31 | AJ9: Less than 14 days | AK9: 101 | AL9: 0.28857143 | AM9: =AK9-$B9 -> -31 | AO9: 86 | AP9: 0.25219941 | AQ9: =AO9-$B9 -> -46 | AR9: Less than 14 days | AS9: 88 | AT9: 0.25433526 | AU9: =AS9-$B9 -> -44 | AW9: 74 | AX9: 0.22769231 | AY9: =AW9-$B9 -> -58 | BA9: 77 | BB9: 0.23839009 | BC9: =BA9-$B9 -> -55 | BD9: Less than 14 days | BE9: 104 | BF9: 0.32298137 | BG9: =BE9-$B9 -> -28 | BH9: Less than 14 days | BI9: 93 | BJ9: 0.30194805 | BK9: =BI9-$B9 -> -39 | BL9: Less than 14 days | BM9: 100 | BN9: 0.3125 | BO9: =BM9-$B9 -> -32 | BP9: Less than 14 days | BQ9: 105 | BR9: 0.34539474 | BS9: =BQ9-$B9 -> -27 | BT9: Less than 14 days | BU9: 85 | BV9: 0.28145695 | BW9: =BU9-$B9 -> -47 | BX9: Less than 14 days | BY9: 95 | BZ9: 0.32646048 | CA9: =BY9-$B9 -> -37 | CB9: Less than 14 days | CC9: 78 | CD9: 0.30232558 | CE9: =CC9-$B9 -> -54 | CF9: Less than 14 days | CG9: 84 | CH9: 0.31343284 | CI9: =CG9-$B9 -> -48 | CJ9: Less than 14 days | CK9: 78 | CL9: 0.28467153 | CM9: =CK9-$B9 -> -54 | CN9: Less than 14 days | CO9: 76 | CP9: 0.26573427 | CQ9: =CO9-$B9 -> -56 | CR9: Less than 14 days | CS9: 79 | CT9: 0.27147766 | CU9: =CS9-$B9 -> -53 | CV9: Less than 14 days | CW9: 89 | CX9: 0.27899687 | CY9: =CW9-$B9 -> -43 | CZ9: Less than 14 days | DA9: 89 | DB9: 0.27899687 | DC9: =DA9-$BQ9 -> -16 | DD9: Less than 14 days | DE9: 82 | DF9: 0.26282051 | DG9: =DE9-$BQ9 -> -23 | DH9: Less than 14 days | DI9: 79 | DJ9: 0.25483871 | DK9: =DI9-$BQ9 -> -26 | DL9: Less than 14 days | DM9: 75 | DN9: 0.24671053 | DO9: =DM9-$BQ9 -> -30 | DP9: Less than 14 days | DQ9: 72 | DR9: 0.23151125 | DS9: =DQ9-$BQ9 -> -33 | DT9: Less than 14 days | DU9: 75 | DV9: 0.23809524 | DW9: =DU9-$BQ9 -> -30 | DX9: Less than 14 days | DY9: 66 | DZ9: 0.21428571 | EA9: =DY9-$BQ9 -> -39 | EB9: Less than 14 days | EC9: 69 | ED9: 0.22402597 | EE9: =EC9-$BQ9 -> -36 | EF9: Less than 14 days | EG9: 87 | EH9: 0.28064516 | EI9: =EG9-$BQ9 -> -18 | EJ9: Less than 14 days | EK9: 91 | EL9: 0.28616352 | EM9: =EK9-$BQ9 -> -14 | EN9: Less than 14 days | EO9: 94 | EP9: 0.29467085 | EQ9: =EO9-$BQ9 -> -11 | ER9: Less than 14 days | ES9: 81 | ET9: 0.26213592 | EU9: =ES9-$EO9 -> -13 | EV9: Less than 14 days | EW9: 81 | EX9: 0.27 | EY9: =EW9-$EO9 -> -13 | EZ9: Less than 14 days | FA9: 82 | FB9: 0.27062706 | FC9: =FA9-$EO9 -> -12 | FD9: Less than 14 days | FE9: 82 | FF9: 0.26537217 | FG9: =FE9-$EO9 -> -12 | FH9: Less than 14 days | FI9: 76 | FJ9: 0.24675325 | FK9: =FI9-$EO9 -> -18 | FL9: Less than 14 days | FM9: 77 | FN9: 0.25496689 | FO9: =FM9-$EO9 -> -17 | FP9: Less than 14 days | FQ9: 78 | FR9: 0.25742574 | FS9: =FQ9-$EO9 -> -16 | FT9: Less than 14 days | FU9: 76 | FV9: 0.24836601 | FW9: =FU9-$EO9 -> -18 | FX9: Less than 14 days | FY9: 73 | FZ9: 0.24013158 | GA9: =FY9-$EO9 -> -21 | GB9: Less than 14 days | GC9: 93 | GD9: 0.29245283 | GE9: =GC9-$EO9 -> -1 | GF9: Less than 14 days | GG9: 88 | GH9: 0.27672956 | GI9: =GG9-$EO9 -> -6 | GJ9: Less than 14 days | GK9: 92 | GL9: 0.2875 | GM9: =GK9-$EO9 -> -2 | GN9: Less than 14 days | GO9: 92 | GP9: 0.28482972 | GQ9: =GO9-$EO9 -> -2 | GR9: Less than 14 days | GS9: 89 | GT9: 0.28164557 | GU9: =GS9-$EO9 -> -5 | GV9: Less than 14 days | GW9: 82 | GX9: 0.26710098 | GY9: =GW9-$EO9 -> -12 | GZ9: Less than 14 days | HA9: 83 | HB9: 0.27124183 | HC9: =HA9-$EO9 -> -11 | HD9: Less than 14 days | HE9: 86 | HF9: 0.28382838 | HG9: =HE9-$EO9 -> -8 | HH9: Less than 14 days | HI9: 74 | HJ9: 0.24183007 | HK9: =HI9-$HE9 -> -12 | HL9: Less than 14 days | HM9: 86 | HN9: 0.26219512 | HO9: =HM9-$HE9 -> 0 | HP9: Less than 14 days | HQ9: 89 | HR9: 0.26726727 | HS9: =HQ9-$HE9 -> 3 | HT9: Less than 14 days | HU9: 95 | HV9: 0.27696793 | HW9: =HU9-$HE9 -> 9 | HX9: Less than 14 days | HY9: 95 | HZ9: 0.27616279 | IA9: =HY9-$HE9 -> 9 | IB9: Less than 14 days | IC9: 92 | ID9: 0.27299703 | IE9: =IC9-$HE9 -> 6 | IF9: Less than 14 days | IG9: 89 | IH9: 0.26969697 | II9: =IG9-$HE9 -> 3 | IJ9: Less than 14 days | IK9: 97 | IL9: 0.28613569 | IM9: =IK9-$HE9 -> 11 | IN9: Less than 14 days | IO9: 104 | IP9: 0.30409357 | IQ9: =IO9-$HE9 -> 18 | IR9: Less than 14 days | IS9: 110 | IT9: 0.31518625 | IU9: =IS9-$HE9 -> 24 | IV9: Less than 14 days | IW9: 91 | IX9: 0.27245509 | IY9: =IW9-$HE9 -> 5 | IZ9: Less than 14 days | JA9: 98 | JB9: 0.28405797 | JC9: =JA9-$HE9 -> 12 | JD9: Less than 14 days | JE9: 92 | JF9: 0.27058824 | JG9: =JE9-$HE9 -> 6 | JH9: Less than 14 days | JI9: 84 | JJ9: 0.246 | JK9: =JI9-$HE9 -> -2 | JL9: Less than 14 days | JM9: 91 | JN9: 0.26843658 | JO9: =JM9-$HE9 -> 5 | JP9: Less than 14 days | JQ9: 89 | JR9: 0.26567164 | JS9: =JQ9-$HE9 -> 3 | JT9: Less than 14 days | JU9: 93 | JV9: 0.28012048 | JW9: =JU9-$HE9 -> 7 | JX9: Less than 14 days | JY9: 93 | JZ9: 0.28012048 | KA9: =JY9-$HE9 -> 7 | KB9: Less than 14 days | KC9: 93 | KD9: 0.28012048 | KE9: =KC9-$HE9 -> 7 | KF9: Less than 14 days | KG9: 69 | KH9: 0.21296296 | KI9: =KG9-$HE9 -> -17 | KJ9: Less than 14 days | KK9: 65 | KL9: 0.1993865 | KM9: =KK9-$HE9 -> -21 | KN9: Less than 14 days | KO9: 68 | KP9: 0.20606061 | KQ9: =KO9-$HE9 -> -18 | KR9: Less than 14 days | KS9: 65 | KT9: 0.19817073 | KU9: =KS9-$HE9 -> -21 | KV9: Less than 14 days | KW9: 65 | KX9: 0.19817073 | KY9: =KW9-$HE9 -> -21 | KZ9: Less than 14 days | LA9: 60 | LB9: 0.18072289 | LC9: =LA9-$HE9 -> -26 | LD9: Less than 14 days | LE9: 53 | LF9: 0.16158537 | LG9: =LE9-$LA9 -> -7 | LH9: Less than 14 days | LI9: 59 | LJ9: 0.17824773 | LK9: =LI9-$LA9 -> -1 | LL9: Less than 14 days | LM9: 69 | LN9: 0.20414201 | LO9: =LM9-$LA9 -> 9 | LP9: Less than 14 days | LQ9: 77 | LR9: 0.22713864 | LS9: =LQ9-$LA9 -> 17 | LT9: Less than 14 days | LU9: 83 | LV9: 0.24127907 | LW9: =LU9-$LA9 -> 23 | LX9: Less than 14 days | LY9: 85 | LZ9: 0.24853801 | MA9: =LY9-$LA9 -> 25 | MB9: Less than 14 days | MC9: 92 | MD9: 0.27138643 | ME9: =MC9-$LA9 -> 32 | MF9: Less than 14 days | MG9: 101 | MH9: 0.29618768 | MI9: =MG9-$LA9 -> 41 | MJ9: Less than 14 days | MK9: 101 | ML9: 0.30059524 | MM9: =MK9-$LA9 -> 41 | MN9: Less than 14 days | MO9: 96 | MP9: 0.28402367 | MQ9: =MO9-$LA9 -> 36 | MR9: Less than 14 days | MS9: 80 | MT9: 0.23809524 | MU9: =MS9-$LA9 -> 20 | MV9: Less than 14 days | MW9: 88 | MX9: 0.25958702 | MY9: =MW9-$LA9 -> 28 | MZ9: Less than 14 days | NA9: 88 | NB9: 0.25882353 | NC9: =NA9-$LA9 -> 28 | ND9: Less than 14 days | NE9: 85 | NF9: 0.25147929 | NG9: =NE9-$LA9 -> 25 | NH9: Less than 14 days | NI9: 85 | NJ9: 0.25757576 | NK9: =NI9-$LA9 -> 25 | NL9: Less than 14 days | NM9: 64 | NN9: 0.19692308 | NO9: =NM9-$LA9 -> 4 | NP9: Less than 14 days | NQ9: 73 | NR9: 0.21921922 | NS9: =NQ9-$LA9 -> 13 | NT9: Less than 14 days | NU9: 89 | NV9: 0.25872093 | NW9: =NU9-$LA9 -> 29 | NX9: Less than 14 days | NY9: 90 | NZ9: 0.25936599 | OA9: =NY9-$LA9 -> 30 | OB9: Less than 14 days | OC9: 84 | OD9: 0.25 | OE9: =OC9-$LA9 -> 24 | OF9: Less than 14 days | OG9: 82 | OH9: 0.24550898 | OI9: =OG9-$OC9 -> -2 | OJ9: Less than 14 days | OK9: 91 | OL9: 0.26686217 | OM9: =OK9-$OC9 -> 7 | ON9: Less than 14 days | OO9: 87 | OP9: 0.25739645 | OQ9: =OO9-$OC9 -> 3 | OR9: Less than 14 days | OS9: 81 | OT9: 0.23823529 | OU9: =OS9-$OC9 -> -3 | OV9: Less than 14 days | OW9: 75 | OX9: 0.2245509 | OY9: =OW9-$OC9 -> -9 | OZ9: Less than 14 days | PA9: 76 | PB9: 0.22754491 | PC9: =PA9-$OC9 -> -8 | PD9: Less than 14 days | PE9: 85 | PF9: 0.25073746 | PG9: =PE9-$OC9 -> 1 | PH9: Less than 14 days | PI9: 82 | PJ9: 0.24260355 | PK9: =PI9-$OC9 -> -2 | PL9: Less than 14 days | PM9: 83 | PN9: 0.24776119 | PO9: =PM9-$OC9 -> -1 | PP9: Less than 14 days | PQ9: 85 | PR9: 0.25222552 | PS9: =PQ9-$OC9 -> 1 | PT9: Less than 14 days | PU9: 75 | PV9: 0.22865854 | PW9: =PU9-$OC9 -> -9 | PX9: Less than 14 days | PY9: 78 | PZ9: 0.23493976 | QA9: =PY9-$OC9 -> -6 | QB9: Less than 14 days | QC9: 73 | QD9: 0.23174603 | QE9: =QC9-$OC9 -> -11 | QF9: Less than 14 days | QG9: 67 | QH9: 0.21895425 | QI9: =QG9-$OC9 -> -17 | QJ9: Less than 14 days | QK9: 56 | QL9: 0.19243986 | QM9: =QK9-$OC9 -> -28 | QN9: Less than 14 days | QO9: 41 | QP9: 0.14748201 | QQ9: =QO9-$OC9 -> -43 | QR9: Less than 14 days | QS9: 38 | QT9: 0.14615385 | QU9: =QS9-$OC9 -> -46 | QV9: Less than 14 days | QW9: 92 | QX9: 0.27218935 | QY9: =QW9-$OC9 -> 8 | QZ9: Less than 14 days | RA9: 81 | RB9: 0.24179104 | RC9: =RA9-$OC9 -> -3 | RD9: Less than 14 days | RE9: 92 | RF9: 0.26979472 | RG9: =RE9-$OC9 -> 8 | RH9: Less than 14 days | RI9: 78 | RJ9: 0.23564955 | RK9: =RI9-$RE9 -> -14 | RL9: Less than 14 days | RM9: 85 | RN9: 0.25679758 | RO9: =RM9-$RE9 -> -7 | RP9: Less than 14 days | RQ9: 91 | RR9: 0.27327327 | RS9: =RQ9-$RE9 -> -1 | RT9: Less than 14 days | RU9: 90 | RV9: 0.27108434 | RW9: =RU9-$RE9 -> -2 | RX9: Less than 14 days | SA9: =RY9-$RE9 -> -92
A10: Grand Total | B10: 399 | C10: 1 | D10: Grand Total | E10: 422 | F10: 1 | G10: =E10-$B10 -> 23 | H10: Grand Total | I10: 422 | J10: 1 | K10: =I10-$B10 -> 23 | L10: Grand Total | M10: 392 | N10: 1 | O10: =M10-$B10 -> -7 | P10: Grand Total | Q10: 324 | R10: 1 | S10: =Q10-$B10 -> -75 | T10: Grand Total | U10: 350 | V10: 1 | W10: =U10-$B10 -> -49 | X10: Grand Total | Y10: 348 | Z10: 1 | AA10: =Y10-$B10 -> -51 | AB10: Grand Total | AC10: 350 | AD10: 1 | AE10: =AC10-$B10 -> -49 | AF10: Grand Total | AG10: 350 | AH10: 1 | AI10: =AG10-$B10 -> -49 | AJ10: Grand Total | AK10: 350 | AL10: 1 | AM10: =AK10-$B10 -> -49 | AO10: 341 | AP10: 1 | AQ10: =AO10-$B10 -> -58 | AR10: Grand Total | AS10: 346 | AT10: 1 | AU10: =AS10-$B10 -> -53 | AW10: 325 | AX10: 1 | AY10: =AW10-$B10 -> -74 | BA10: 323 | BB10: 1 | BC10: =BA10-$B10 -> -76 | BD10: Grand Total | BE10: 322 | BF10: 1 | BG10: =BE10-$B10 -> -77 | BH10: Grand Total | BI10: 308 | BJ10: 1 | BK10: =BI10-$B10 -> -91 | BL10: Grand Total | BM10: 320 | BN10: 1 | BO10: =BM10-$B10 -> -79 | BP10: Grand Total | BQ10: 304 | BR10: 1 | BS10: =BQ10-$B10 -> -95 | BT10: Grand Total | BU10: 302 | BV10: 1 | BW10: =BU10-$B10 -> -97 | BX10: Grand Total | BY10: 291 | BZ10: 1 | CA10: =BY10-$B10 -> -108 | CB10: Grand Total | CC10: 258 | CD10: 1 | CE10: =CC10-$B10 -> -141 | CF10: Grand Total | CG10: 268 | CH10: 1 | CI10: =CG10-$B10 -> -131 | CJ10: Grand Total | CK10: 274 | CL10: 1 | CM10: =CK10-$B10 -> -125 | CN10: Grand Total | CO10: 286 | CP10: 1 | CQ10: =CO10-$B10 -> -113 | CR10: Grand Total | CS10: 291 | CT10: 1 | CU10: =CS10-$B10 -> -108 | CV10: Grand Total | CW10: 319 | CX10: 1 | CY10: =CW10-$B10 -> -80 | CZ10: Grand Total | DA10: 319 | DB10: 1 | DC10: =DA10-$BQ10 -> 15 | DD10: Grand Total | DE10: 312 | DF10: 1 | DG10: =DE10-$BQ10 -> 8 | DH10: Grand Total | DI10: 310 | DJ10: 1 | DK10: =DI10-$BQ10 -> 6 | DL10: Grand Total | DM10: 304 | DN10: 1 | DO10: =DM10-$BQ10 -> 0 | DP10: Grand Total | DQ10: 311 | DR10: 1 | DS10: =DQ10-$BQ10 -> 7 | DT10: Grand Total | DU10: 315 | DV10: 1 | DW10: =DU10-$BQ10 -> 11 | DX10: Grand Total | DY10: 308 | DZ10: 1 | EA10: =DY10-$BQ10 -> 4 | EB10: Grand Total | EC10: 308 | ED10: 1 | EE10: =EC10-$BQ10 -> 4 | EF10: Grand Total | EG10: 310 | EH10: 1 | EI10: =EG10-$BQ10 -> 6 | EJ10: Grand Total | EK10: 318 | EL10: 1 | EM10: =EK10-$BQ10 -> 14 | EN10: Grand Total | EO10: 319 | EP10: 1 | EQ10: =EO10-$BQ10 -> 15 | ER10: Grand Total | ES10: 309 | ET10: 1 | EU10: =ES10-$EO10 -> -10 | EV10: Grand Total | EW10: 300 | EX10: 1 | EY10: =EW10-$EO10 -> -19 | EZ10: Grand Total | FA10: 303 | FB10: 1 | FC10: =FA10-$EO10 -> -16 | FD10: Grand Total | FE10: 309 | FF10: 1 | FG10: =FE10-$EO10 -> -10 | FH10: Grand Total | FI10: 308 | FJ10: 1 | FK10: =FI10-$EO10 -> -11 | FL10: Grand Total | FM10: 302 | FN10: 1 | FO10: =FM10-$EO10 -> -17 | FP10: Grand Total | FQ10: 303 | FR10: 1 | FS10: =FQ10-$EO10 -> -16 | FT10: Grand Total | FU10: 306 | FV10: 1 | FW10: =FU10-$EO10 -> -13 | FX10: Grand Total | FY10: 304 | FZ10: 1 | GA10: =FY10-$EO10 -> -15 | GB10: Grand Total | GC10: 318 | GD10: 1 | GE10: =GC10-$EO10 -> -1 | GF10: Grand Total | GG10: 318 | GH10: 1 | GI10: =GG10-$EO10 -> -1 | GJ10: Grand Total | GK10: 320 | GL10: 1 | GM10: =GK10-$EO10 -> 1 | GN10: Grand Total | GO10: 323 | GP10: 1 | GQ10: =GO10-$EO10 -> 4 | GR10: Grand Total | GS10: 316 | GT10: 1 | GU10: =GS10-$EO10 -> -3 | GV10: Grand Total | GW10: 307 | GX10: 1 | GY10: =GW10-$EO10 -> -12 | GZ10: Grand Total | HA10: 306 | HB10: 1 | HC10: =HA10-$EO10 -> -13 | HD10: Grand Total | HE10: 303 | HF10: 1 | HG10: =HE10-$EO10 -> -16 | HH10: Grand Total | HI10: 306 | HJ10: 1 | HK10: =HI10-$HE10 -> 3 | HL10: Grand Total | HM10: 328 | HN10: 1 | HO10: =HM10-$HE10 -> 25 | HP10: Grand Total | HQ10: 333 | HR10: 1 | HS10: =HQ10-$HE10 -> 30 | HT10: Grand Total | HU10: 343 | HV10: 1 | HW10: =HU10-$HE10 -> 40 | HX10: Grand Total | HY10: 344 | HZ10: 1 | IA10: =HY10-$HE10 -> 41 | IB10: Grand Total | IC10: 337 | ID10: 1 | IE10: =IC10-$HE10 -> 34 | IF10: Grand Total | IG10: 330 | IH10: 1 | II10: =IG10-$HE10 -> 27 | IJ10: Grand Total | IK10: 339 | IL10: 1 | IM10: =IK10-$HE10 -> 36 | IN10: Grand Total | IO10: 342 | IP10: 1 | IQ10: =IO10-$HE10 -> 39 | IR10: Grand Total | IS10: 349 | IT10: 1 | IU10: =IS10-$HE10 -> 46 | IV10: Grand Total | IW10: 334 | IX10: 1 | IY10: =IW10-$HE10 -> 31 | IZ10: Grand Total | JA10: 345 | JB10: 1 | JC10: =JA10-$HE10 -> 42 | JD10: Grand Total | JE10: 340 | JF10: 1 | JG10: =JE10-$HE10 -> 37 | JH10: Grand Total | JI10: 341 | JJ10: 1 | JK10: =JI10-$HE10 -> 38 | JL10: Grand Total | JM10: 339 | JN10: 1 | JO10: =JM10-$HE10 -> 36 | JP10: Grand Total | JQ10: 335 | JR10: 1 | JS10: =JQ10-$HE10 -> 32 | JT10: Grand Total | JU10: 332 | JV10: 1 | JW10: =JU10-$HE10 -> 29 | JX10: Grand Total | JY10: 332 | JZ10: 1 | KA10: =JY10-$HE10 -> 29 | KB10: Grand Total | KC10: 332 | KD10: 1 | KE10: =KC10-$HE10 -> 29 | KF10: Grand Total | KG10: 324 | KH10: 1 | KI10: =KG10-$HE10 -> 21 | KJ10: Grand Total | KK10: 326 | KL10: 1 | KM10: =KK10-$HE10 -> 23 | KN10: Grand Total | KO10: 330 | KP10: 1 | KQ10: =KO10-$HE10 -> 27 | KR10: Grand Total | KS10: 328 | KT10: 1 | KU10: =KS10-$HE10 -> 25 | KV10: Grand Total | KW10: 328 | KX10: 1 | KY10: =KW10-$HE10 -> 25 | KZ10: Grand Total | LA10: 332 | LB10: 1 | LC10: =LA10-$HE10 -> 29 | LD10: Grand Total | LE10: 328 | LF10: 1 | LG10: =LE10-$LA10 -> -4 | LH10: Grand Total | LI10: 331 | LJ10: 1 | LK10: =LI10-$LA10 -> -1 | LL10: Grand Total | LM10: 338 | LN10: 1 | LO10: =LM10-$LA10 -> 6 | LP10: Grand Total | LQ10: 339 | LR10: 1 | LS10: =LQ10-$LA10 -> 7 | LT10: Grand Total | LU10: 344 | LV10: 1 | LW10: =LU10-$LA10 -> 12 | LX10: Grand Total | LY10: 342 | LZ10: 1 | MA10: =LY10-$LA10 -> 10 | MB10: Grand Total | MC10: 339 | MD10: 1 | ME10: =MC10-$LA10 -> 7 | MF10: Grand Total | MG10: 341 | MH10: 1 | MI10: =MG10-$LA10 -> 9 | MJ10: Grand Total | MK10: 336 | ML10: 1 | MM10: =MK10-$LA10 -> 4 | MN10: Grand Total | MO10: 338 | MP10: 1 | MQ10: =MO10-$LA10 -> 6 | MR10: Grand Total | MS10: 336 | MT10: 1 | MU10: =MS10-$LA10 -> 4 | MV10: Grand Total | MW10: 339 | MX10: 1 | MY10: =MW10-$LA10 -> 7 | MZ10: Grand Total | NA10: 340 | NB10: 1 | NC10: =NA10-$LA10 -> 8 | ND10: Grand Total | NE10: 338 | NF10: 1 | NG10: =NE10-$LA10 -> 6 | NH10: Grand Total | NI10: 330 | NJ10: 1 | NK10: =NI10-$LA10 -> -2 | NL10: Grand Total | NM10: 325 | NN10: 1 | NO10: =NM10-$LA10 -> -7 | NP10: Grand Total | NQ10: 333 | NR10: 1 | NS10: =NQ10-$LA10 -> 1 | NT10: Grand Total | NU10: 344 | NV10: 1 | NW10: =NU10-$LA10 -> 12 | NX10: Grand Total | NY10: 347 | NZ10: 1 | OA10: =NY10-$LA10 -> 15 | OB10: Grand Total | OC10: 336 | OD10: 1 | OE10: =OC10-$LA10 -> 4 | OF10: Grand Total | OG10: 334 | OH10: 1 | OI10: =OG10-$OC10 -> -2 | OJ10: Grand Total | OK10: 341 | OL10: 1 | OM10: =OK10-$OC10 -> 5 | ON10: Grand Total | OO10: 338 | OP10: 1 | OQ10: =OO10-$OC10 -> 2 | OR10: Grand Total | OS10: 340 | OT10: 1 | OU10: =OS10-$OC10 -> 4 | OV10: Grand Total | OW10: 334 | OX10: 1 | OY10: =OW10-$OC10 -> -2 | OZ10: Grand Total | PA10: 334 | PB10: 1 | PC10: =PA10-$OC10 -> -2 | PD10: Grand Total | PE10: 339 | PF10: 1 | PG10: =PE10-$OC10 -> 3 | PH10: Grand Total | PI10: 338 | PJ10: 1 | PK10: =PI10-$OC10 -> 2 | PL10: Grand Total | PM10: 335 | PN10: 1 | PO10: =PM10-$OC10 -> -1 | PP10: Grand Total | PQ10: 337 | PR10: 1 | PS10: =PQ10-$OC10 -> 1 | PT10: Grand Total | PU10: 328 | PV10: 1 | PW10: =PU10-$OC10 -> -8 | PX10: Grand Total | PY10: 332 | PZ10: 1 | QA10: =PY10-$OC10 -> -4 | QB10: Grand Total | QC10: 315 | QD10: 1 | QE10: =QC10-$OC10 -> -21 | QF10: Grand Total | QG10: 306 | QH10: 1 | QI10: =QG10-$OC10 -> -30 | QJ10: Grand Total | QK10: 291 | QL10: 1 | QM10: =QK10-$OC10 -> -45 | QN10: Grand Total | QO10: 278 | QP10: 1 | QQ10: =QO10-$OC10 -> -58 | QR10: Grand Total | QS10: 260 | QT10: 1 | QU10: =QS10-$OC10 -> -76 | QV10: Grand Total | QW10: 338 | QX10: 1 | QY10: =QW10-$OC10 -> 2 | QZ10: Grand Total | RA10: 335 | RB10: 1 | RC10: =RA10-$OC10 -> -1 | RD10: Grand Total | RE10: 341 | RF10: 1 | RG10: =RE10-$OC10 -> 5 | RH10: Grand Total | RI10: 331 | RJ10: 1 | RK10: =RI10-$RE10 -> -10 | RL10: Grand Total | RM10: 331 | RN10: 1 | RO10: =RM10-$RE10 -> -10 | RP10: Grand Total | RQ10: 333 | RR10: 1 | RS10: =RQ10-$RE10 -> -8 | RT10: Grand Total | RU10: 332 | RV10: 1 | RW10: =RU10-$RE10 -> -9 | RX10: Grand Total | SA10: =RY10-$RE10 -> -341
A11: Total >14 Days | B11: =SUM(B6+B7+B8) -> 267 | C11: =B11/B10 -> 0.66917293 | D11: Total >14 Days | E11: =SUM(E6+E7+E8) -> 318 | F11: =E11/E10 -> 0.7535545 | G11: =E11-$B11 -> 51 | H11: Total >14 Days | I11: =SUM(I6+I7+I8) -> 318 | J11: =I11/I10 -> 0.7535545 | K11: =I11-$B11 -> 51 | L11: Total >14 Days | M11: =SUM(M6+M7+M8) -> 297 | N11: =M11/M10 -> 0.75765306 | O11: =M11-$B11 -> 30 | P11: Total >14 Days | Q11: =SUM(Q6+Q7+Q8) -> 185 | R11: =Q11/Q10 -> 0.57098765 | S11: =Q11-$B11 -> -82 | T11: Total >14 Days | U11: =SUM(U6+U7+U8) -> 263 | V11: =U11/U10 -> 0.75142857 | W11: =U11-$B11 -> -4 | X11: Total >14 Days | Y11: =SUM(Y6+Y7+Y8) -> 264 | Z11: =Y11/Y10 -> 0.75862069 | AA11: =Y11-$B11 -> -3 | AB11: Total >14 Days | AC11: =SUM(AC6+AC7+AC8) -> 250 | AD11: =AC11/AC10 -> 0.71428571 | AE11: =AC11-$B11 -> -17 | AF11: Total >14 Days | AG11: =SUM(AG6+AG7+AG8) -> 249 | AH11: =AG11/AG10 -> 0.71142857 | AI11: =AG11-$B11 -> -18 | AJ11: Total >14 Days | AK11: =SUM(AK6+AK7+AK8) -> 249 | AL11: =AK11/AK10 -> 0.71142857 | AM11: =AK11-$B11 -> -18 | AN11: Total >14 Days | AO11: =SUM(AO6+AO7+AO8) -> 255 | AP11: =AO11/AO10 -> 0.74780059 | AQ11: =AO11-$B11 -> -12 | AR11: Total >14 Days | AS11: =SUM(AS6+AS7+AS8) -> 258 | AT11: =AS11/AS10 -> 0.74566474 | AU11: =AS11-$B11 -> -9 | AV11: Total >14 Days | AW11: =SUM(AW6+AW7+AW8) -> 251 | AX11: =AW11/AW10 -> 0.77230769 | AY11: =AW11-$B11 -> -16 | AZ11: Total >14 Days | BA11: =SUM(BA6+BA7+BA8) -> 246 | BB11: =BA11/BA10 -> 0.76160991 | BC11: =BA11-$B11 -> -21 | BD11: Total >14 Days | BE11: =SUM(BE6+BE7+BE8) -> 218 | BF11: =BE11/BE10 -> 0.67701863 | BG11: =BE11-$B11 -> -49 | BH11: Total >14 Days | BI11: =SUM(BI6+BI7+BI8) -> 215 | BJ11: =BI11/BI10 -> 0.69805195 | BK11: =BI11-$B11 -> -52 | BL11: Total >14 Days | BM11: =SUM(BM6+BM7+BM8) -> 220 | BN11: =BM11/BM10 -> 0.6875 | BO11: =BM11-$B11 -> -47 | BP11: Total >14 Days | BQ11: =SUM(BQ6+BQ7+BQ8) -> 199 | BR11: =BQ11/BQ10 -> 0.65460526 | BS11: =BQ11-$B11 -> -68 | BT11: Total >14 Days | BU11: =SUM(BU6+BU7+BU8) -> 217 | BV11: =BU11/BU10 -> 0.71854305 | BW11: =BU11-$B11 -> -50 | BX11: Total >14 Days | BY11: =SUM(BY6+BY7+BY8) -> 196 | BZ11: =BY11/BY10 -> 0.67353952 | CA11: =BY11-$B11 -> -71 | CB11: Total >14 Days | CC11: =SUM(CC6+CC7+CC8) -> 180 | CD11: =CC11/CC10 -> 0.69767442 | CE11: =CC11-$B11 -> -87 | CF11: Total >14 Days | CG11: =SUM(CG6+CG7+CG8) -> 184 | CH11: =CG11/CG10 -> 0.68656716 | CI11: =CG11-$B11 -> -83 | CJ11: Total >14 Days | CK11: =SUM(CK6+CK7+CK8) -> 196 | CL11: =CK11/CK10 -> 0.71532847 | CM11: =CK11-$B11 -> -71 | CN11: Total >14 Days | CO11: =SUM(CO6+CO7+CO8) -> 210 | CP11: =CO11/CO10 -> 0.73426573 | CQ11: =CO11-$B11 -> -57 | CR11: Total >14 Days | CS11: =SUM(CS6+CS7+CS8) -> 212 | CT11: =CS11/CS10 -> 0.72852234 | CU11: =CS11-$B11 -> -55 | CV11: Total >14 Days | CW11: =SUM(CW6+CW7+CW8) -> 230 | CX11: =CW11/CW10 -> 0.72100313 | CY11: =CW11-$B11 -> -37 | CZ11: Total >14 Days | DA11: =SUM(DA6+DA7+DA8) -> 230 | DB11: =DA11/DA10 -> 0.72100313 | DC11: =DA11-$BQ11 -> 31 | DD11: Total >14 Days | DE11: =SUM(DE6+DE7+DE8) -> 230 | DF11: =DE11/DE10 -> 0.73717949 | DG11: =DE11-$BQ11 -> 31 | DH11: Total >14 Days | DI11: =SUM(DI6+DI7+DI8) -> 231 | DJ11: =DI11/DI10 -> 0.74516129 | DK11: =DI11-$BQ11 -> 32 | DL11: Total >14 Days | DM11: =SUM(DM6+DM7+DM8) -> 229 | DN11: =DM11/DM10 -> 0.75328947 | DO11: =DM11-$BQ11 -> 30 | DP11: Total >14 Days | DQ11: =SUM(DQ6+DQ7+DQ8) -> 239 | DR11: =DQ11/DQ10 -> 0.76848875 | DS11: =DQ11-$BQ11 -> 40 | DT11: Total >14 Days | DU11: =SUM(DU6+DU7+DU8) -> 240 | DV11: =DU11/DU10 -> 0.76190476 | DW11: =DU11-$BQ11 -> 41 | DX11: Total >14 Days | DY11: =SUM(DY6+DY7+DY8) -> 242 | DZ11: =DY11/DY10 -> 0.78571429 | EA11: =DY11-$BQ11 -> 43 | EB11: Total >14 Days | EC11: =SUM(EC6+EC7+EC8) -> 239 | ED11: =EC11/EC10 -> 0.77597403 | EE11: =EC11-$BQ11 -> 40 | EF11: Total >14 Days | EG11: =SUM(EG6+EG7+EG8) -> 223 | EH11: =EG11/EG10 -> 0.71935484 | EI11: =EG11-$BQ11 -> 24 | EJ11: Total >14 Days | EK11: 227 | EL11: 0.71383648 | EM11: =EK11-$BQ11 -> 28 | EN11: Total >14 Days | EO11: =SUM(EO6+EO7+EO8) -> 225 | EP11: =EO11/EO10 -> 0.70532915 | EQ11: =EO11-$BQ11 -> 26 | ER11: Total >14 Days | ES11: =SUM(ES6+ES7+ES8) -> 228 | ET11: =ES11/ES10 -> 0.73786408 | EU11: =ES11-$EO11 -> 3 | EV11: Total >14 Days | EW11: =SUM(EW6+EW7+EW8) -> 219 | EX11: =EW11/EW10 -> 0.73 | EY11: =EW11-$EO11 -> -6 | EZ11: Total >14 Days | FA11: =SUM(FA6+FA7+FA8) -> 221 | FB11: =FA11/FA10 -> 0.72937294 | FC11: =FA11-$EO11 -> -4 | FD11: Total >14 Days | FE11: =SUM(FE6+FE7+FE8) -> 227 | FF11: =FE11/FE10 -> 0.73462783 | FG11: =FE11-$EO11 -> 2 | FH11: Total >14 Days | FI11: =SUM(FI6+FI7+FI8) -> 232 | FJ11: =FI11/FI10 -> 0.75324675 | FK11: =FI11-$EO11 -> 7 | FL11: Total >14 Days | FM11: =SUM(FM6+FM7+FM8) -> 225 | FN11: =FM11/FM10 -> 0.74503311 | FO11: =FM11-$EO11 -> 0 | FP11: Total >14 Days | FQ11: =SUM(FQ6+FQ7+FQ8) -> 225 | FR11: =FQ11/FQ10 -> 0.74257426 | FS11: =FQ11-$EO11 -> 0 | FT11: Total >14 Days | FU11: =SUM(FU6+FU7+FU8) -> 230 | FV11: =FU11/FU10 -> 0.75163399 | FW11: =FU11-$EO11 -> 5 | FX11: Total >14 Days | FY11: =SUM(FY6+FY7+FY8) -> 231 | FZ11: =FY11/FY10 -> 0.75986842 | GA11: =FY11-$EO11 -> 6 | GB11: Total >14 Days | GC11: =SUM(GC6+GC7+GC8) -> 225 | GD11: =GC11/GC10 -> 0.70754717 | GE11: =GC11-$EO11 -> 0 | GF11: Total >14 Days | GG11: =SUM(GG6+GG7+GG8) -> 230 | GH11: =GG11/GG10 -> 0.72327044 | GI11: =GG11-$EO11 -> 5 | GJ11: Total >14 Days | GK11: =SUM(GK6+GK7+GK8) -> 228 | GL11: =GK11/GK10 -> 0.7125 | GM11: =GK11-$EO11 -> 3 | GN11: Total >14 Days | GO11: =SUM(GO6+GO7+GO8) -> 231 | GP11: =GO11/GO10 -> 0.71517028 | GQ11: =GO11-$EO11 -> 6 | GR11: Total >14 Days | GS11: =SUM(GS6+GS7+GS8) -> 227 | GT11: =GS11/GS10 -> 0.71835443 | GU11: =GS11-$EO11 -> 2 | GV11: Total >14 Days | GW11: =SUM(GW6+GW7+GW8) -> 225 | GX11: =GW11/GW10 -> 0.73289902 | GY11: =GW11-$EO11 -> 0 | GZ11: Total >14 Days | HA11: =SUM(HA6+HA7+HA8) -> 223 | HB11: =HA11/HA10 -> 0.72875817 | HC11: =HA11-$EO11 -> -2 | HD11: Total >14 Days | HE11: =SUM(HE6+HE7+HE8) -> 217 | HF11: =HE11/HE10 -> 0.71617162 | HG11: =HE11-$EO11 -> -8 | HH11: Total >14 Days | HI11: =SUM(HI6+HI7+HI8) -> 232 | HJ11: =HI11/HI10 -> 0.75816993 | HK11: =HI11-$HE11 -> 15 | HL11: Total >14 Days | HM11: =SUM(HM6+HM7+HM8) -> 242 | HN11: =HM11/HM10 -> 0.73780488 | HO11: =HM11-$HE11 -> 25 | HP11: Total >14 Days | HQ11: =SUM(HQ6+HQ7+HQ8) -> 244 | HR11: =HQ11/HQ10 -> 0.73273273 | HS11: =HQ11-$HE11 -> 27 | HT11: Total >14 Days | HU11: =SUM(HU6+HU7+HU8) -> 248 | HV11: =HU11/HU10 -> 0.72303207 | HW11: =HU11-$HE11 -> 31 | HX11: Total >14 Days | HY11: =SUM(HY6+HY7+HY8) -> 249 | HZ11: =HY11/HY10 -> 0.72383721 | IA11: =HY11-$HE11 -> 32 | IB11: Total >14 Days | IC11: =SUM(IC6+IC7+IC8) -> 245 | ID11: =IC11/IC10 -> 0.72700297 | IE11: =IC11-$HE11 -> 28 | IF11: Total >14 Days | IG11: =SUM(IG6+IG7+IG8) -> 241 | IH11: =IG11/IG10 -> 0.73030303 | II11: =IG11-$HE11 -> 24 | IJ11: Total >14 Days | IK11: =SUM(IK6+IK7+IK8) -> 242 | IL11: =IK11/IK10 -> 0.71386431 | IM11: =IK11-$HE11 -> 25 | IN11: Total >14 Days | IO11: =SUM(IO6+IO7+IO8) -> 238 | IP11: =IO11/IO10 -> 0.69590643 | IQ11: =IO11-$HE11 -> 21 | IR11: Total >14 Days | IS11: =SUM(IS6+IS7+IS8) -> 239 | IT11: =IS11/IS10 -> 0.68481375 | IU11: =IS11-$HE11 -> 22 | IV11: Total >14 Days | IW11: =SUM(IW6+IW7+IW8) -> 243 | IX11: =IW11/IW10 -> 0.72754491 | IY11: =IW11-$HE11 -> 26 | IZ11: Total >14 Days | JA11: =SUM(JA6+JA7+JA8) -> 247 | JB11: =JA11/JA10 -> 0.71594203 | JC11: =JA11-$HE11 -> 30 | JD11: Total >14 Days | JE11: =SUM(JE6+JE7+JE8) -> 248 | JF11: =JE11/JE10 -> 0.72941176 | JG11: =JE11-$HE11 -> 31 | JH11: Total >14 Days | JI11: =SUM(JI6+JI7+JI8) -> 257 | JJ11: =JI11/JI10 -> 0.75366569 | JK11: =JI11-$HE11 -> 40 | JL11: Total >14 Days | JM11: =SUM(JM6+JM7+JM8) -> 248 | JN11: =JM11/JM10 -> 0.73156342 | JO11: =JM11-$HE11 -> 31 | JP11: Total >14 Days | JQ11: =SUM(JQ6+JQ7+JQ8) -> 246 | JR11: =JQ11/JQ10 -> 0.73432836 | JS11: =JQ11-$HE11 -> 29 | JT11: Total >14 Days | JU11: =SUM(JU6+JU7+JU8) -> 239 | JV11: =JU11/JU10 -> 0.71987952 | JW11: =JU11-$HE11 -> 22 | JX11: Total >14 Days | JY11: =SUM(JY6+JY7+JY8) -> 239 | JZ11: =JY11/JY10 -> 0.71987952 | KA11: =JY11-$HE11 -> 22 | KB11: Total >14 Days | KC11: =SUM(KC6+KC7+KC8) -> 239 | KD11: =KC11/KC10 -> 0.71987952 | KE11: =KC11-$HE11 -> 22 | KF11: Total >14 Days | KG11: =SUM(KG6+KG7+KG8) -> 255 | KH11: =KG11/KG10 -> 0.78703704 | KI11: =KG11-$HE11 -> 38 | KJ11: Total >14 Days | KK11: =SUM(KK6+KK7+KK8) -> 261 | KL11: =KK11/KK10 -> 0.8006135 | KM11: =KK11-$HE11 -> 44 | KN11: Total >14 Days | KO11: =SUM(KO6+KO7+KO8) -> 262 | KP11: =KO11/KO10 -> 0.79393939 | KQ11: =KO11-$HE11 -> 45 | KR11: Total >14 Days | KS11: =SUM(KS6+KS7+KS8) -> 263 | KT11: =KS11/KS10 -> 0.80182927 | KU11: =KS11-$HE11 -> 46 | KV11: Total >14 Days | KW11: =SUM(KW6+KW7+KW8) -> 263 | KX11: =KW11/KW10 -> 0.80182927 | KY11: =KW11-$HE11 -> 46 | KZ11: Total >14 Days | LA11: =SUM(LA6+LA7+LA8) -> 272 | LB11: =LA11/LA10 -> 0.81927711 | LC11: =LA11-$HE11 -> 55 | LD11: Total >14 Days | LE11: =SUM(LE6+LE7+LE8) -> 275 | LF11: =LE11/LE10 -> 0.83841463 | LG11: =LE11-$LA11 -> 3 | LH11: Total >14 Days | LI11: =SUM(LI6+LI7+LI8) -> 272 | LJ11: =LI11/LI10 -> 0.82175227 | LK11: =LI11-$LA11 -> 0 | LL11: Total >14 Days | LM11: =SUM(LM6+LM7+LM8) -> 269 | LN11: =LM11/LM10 -> 0.79585799 | LO11: =LM11-$LA11 -> -3 | LP11: Total >14 Days | LQ11: =SUM(LQ6+LQ7+LQ8) -> 262 | LR11: =LQ11/LQ10 -> 0.77286136 | LS11: =LQ11-$LA11 -> -10 | LT11: Total >14 Days | LU11: =SUM(LU6+LU7+LU8) -> 261 | LV11: =LU11/LU10 -> 0.75872093 | LW11: =LU11-$LA11 -> -11 | LX11: Total >14 Days | LY11: =SUM(LY6+LY7+LY8) -> 257 | LZ11: =LY11/LY10 -> 0.75146199 | MA11: =LY11-$LA11 -> -15 | MB11: Total >14 Days | MC11: =SUM(MC6+MC7+MC8) -> 247 | MD11: =MC11/MC10 -> 0.72861357 | ME11: =MC11-$LA11 -> -25 | MF11: Total >14 Days | MG11: =SUM(MG6+MG7+MG8) -> 240 | MH11: =MG11/MG10 -> 0.70381232 | MI11: =MG11-$LA11 -> -32 | MJ11: Total >14 Days | MK11: =SUM(MK6+MK7+MK8) -> 235 | ML11: =MK11/MK10 -> 0.69940476 | MM11: =MK11-$LA11 -> -37 | MN11: Total >14 Days | MO11: =SUM(MO6+MO7+MO8) -> 242 | MP11: =MO11/MO10 -> 0.71597633 | MQ11: =MO11-$LA11 -> -30 | MR11: Total >14 Days | MS11: =SUM(MS6+MS7+MS8) -> 256 | MT11: =MS11/MS10 -> 0.76190476 | MU11: =MS11-$LA11 -> -16 | MV11: Total >14 Days | MW11: =SUM(MW6+MW7+MW8) -> 251 | MX11: =MW11/MW10 -> 0.74041298 | MY11: =MW11-$LA11 -> -21 | MZ11: Total >14 Days | NA11: =SUM(NA6+NA7+NA8) -> 252 | NB11: =NA11/NA10 -> 0.74117647 | NC11: =NA11-$LA11 -> -20 | ND11: Total >14 Days | NE11: =SUM(NE6+NE7+NE8) -> 253 | NF11: =NE11/NE10 -> 0.74852071 | NG11: =NE11-$LA11 -> -19 | NH11: Total >14 Days | NI11: =SUM(NI6+NI7+NI8) -> 245 | NJ11: =NI11/NI10 -> 0.74242424 | NK11: =NI11-$LA11 -> -27 | NL11: Total >14 Days | NM11: =SUM(NM6+NM7+NM8) -> 261 | NN11: =NM11/NM10 -> 0.80307692 | NO11: =NM11-$LA11 -> -11 | NP11: Total >14 Days | NQ11: =SUM(NQ6+NQ7+NQ8) -> 260 | NR11: =NQ11/NQ10 -> 0.78078078 | NS11: =NQ11-$LA11 -> -12 | NT11: Total >14 Days | NU11: =SUM(NU6+NU7+NU8) -> 255 | NV11: =NU11/NU10 -> 0.74127907 | NW11: =NU11-$LA11 -> -17 | NX11: Total >14 Days | NY11: =SUM(NY6+NY7+NY8) -> 257 | NZ11: =NY11/NY10 -> 0.74063401 | OA11: =NY11-$LA11 -> -15 | OB11: Total >14 Days | OC11: =SUM(OC6+OC7+OC8) -> 252 | OD11: =OC11/OC10 -> 0.75 | OE11: =OC11-$LA11 -> -20 | OF11: Total >14 Days | OG11: =SUM(OG6+OG7+OG8) -> 252 | OH11: =OG11/OG10 -> 0.75449102 | OI11: =OG11-$OC11 -> 0 | OJ11: Total >14 Days | OK11: =SUM(OK6+OK7+OK8) -> 250 | OL11: =OK11/OK10 -> 0.73313783 | OM11: =OK11-$OC11 -> -2 | ON11: Total >14 Days | OO11: =SUM(OO6+OO7+OO8) -> 251 | OP11: =OO11/OO10 -> 0.74260355 | OQ11: =OO11-$OC11 -> -1 | OR11: Total >14 Days | OS11: =SUM(OS6+OS7+OS8) -> 259 | OT11: =OS11/OS10 -> 0.76176471 | OU11: =OS11-$OC11 -> 7 | OV11: Total >14 Days | OW11: =SUM(OW6+OW7+OW8) -> 259 | OX11: =OW11/OW10 -> 0.7754491 | OY11: =OW11-$OC11 -> 7 | OZ11: Total >14 Days | PA11: =SUM(PA6+PA7+PA8) -> 258 | PB11: =PA11/PA10 -> 0.77245509 | PC11: =PA11-$OC11 -> 6 | PD11: Total >14 Days | PE11: =SUM(PE6+PE7+PE8) -> 254 | PF11: =PE11/PE10 -> 0.74926254 | PG11: =PE11-$OC11 -> 2 | PH11: Total >14 Days | PI11: =SUM(PI6+PI7+PI8) -> 256 | PJ11: =PI11/PI10 -> 0.75739645 | PK11: =PI11-$OC11 -> 4 | PL11: Total >14 Days | PM11: =SUM(PM6+PM7+PM8) -> 252 | PN11: =PM11/PM10 -> 0.75223881 | PO11: =PM11-$OC11 -> 0 | PP11: Total >14 Days | PQ11: =SUM(PQ6+PQ7+PQ8) -> 252 | PR11: =PQ11/PQ10 -> 0.74777448 | PS11: =PQ11-$OC11 -> 0 | PT11: Total >14 Days | PU11: =SUM(PU6+PU7+PU8) -> 253 | PV11: =PU11/PU10 -> 0.77134146 | PW11: =PU11-$OC11 -> 1 | PX11: Total >14 Days | PY11: =SUM(PY6+PY7+PY8) -> 254 | PZ11: =PY11/PY10 -> 0.76506024 | QA11: =PY11-$OC11 -> 2 | QB11: Total >14 Days | QC11: =SUM(QC6+QC7+QC8) -> 242 | QD11: =QC11/QC10 -> 0.76825397 | QE11: =QC11-$OC11 -> -10 | QF11: Total >14 Days | QG11: =SUM(QG6+QG7+QG8) -> 239 | QH11: =QG11/QG10 -> 0.78104575 | QI11: =QG11-$OC11 -> -13 | QJ11: Total >14 Days | QK11: =SUM(QK6+QK7+QK8) -> 235 | QL11: =QK11/QK10 -> 0.80756014 | QM11: =QK11-$OC11 -> -17 | QN11: Total >14 Days | QO11: =SUM(QO6+QO7+QO8) -> 237 | QP11: =QO11/QO10 -> 0.85251799 | QQ11: =QO11-$OC11 -> -15 | QR11: Total >14 Days | QS11: =SUM(QS6+QS7+QS8) -> 222 | QT11: =QS11/QS10 -> 0.85384615 | QU11: =QS11-$OC11 -> -30 | QV11: Total >14 Days | QW11: =SUM(QW6+QW7+QW8) -> 246 | QX11: =QW11/QW10 -> 0.72781065 | QY11: =QW11-$OC11 -> -6 | QZ11: Total >14 Days | RA11: =SUM(RA6+RA7+RA8) -> 254 | RB11: =RA11/RA10 -> 0.75820896 | RC11: =RA11-$OC11 -> 2 | RD11: Total >14 Days | RE11: =SUM(RE6+RE7+RE8) -> 249 | RF11: =RE11/RE10 -> 0.73020528 | RG11: =RE11-$OC11 -> -3 | RH11: Total >14 Days | RI11: =SUM(RI6+RI7+RI8) -> 253 | RJ11: =RI11/RI10 -> 0.76435045 | RK11: =RI11-$RE11 -> 4 | RL11: Total >14 Days | RM11: =SUM(RM6+RM7+RM8) -> 246 | RN11: =RM11/RM10 -> 0.74320242 | RO11: =RM11-$RE11 -> -3 | RP11: Total >14 Days | RQ11: =SUM(RQ6+RQ7+RQ8) -> 242 | RR11: =RQ11/RQ10 -> 0.72672673 | RS11: =RQ11-$RE11 -> -7 | RT11: Total >14 Days | RU11: =SUM(RU6+RU7+RU8) -> 242 | RV11: =RU11/RU10 -> 0.72891566 | RW11: =RU11-$RE11 -> -7 | RX11: Total >14 Days | RY11: =SUM(RY6+RY7+RY8) -> 0 | RZ11: =RY11/RY10 -> #DIV/0! | SA11: =RY11-$RE11 -> -249
U12: Day Improvement (>14 day rentals) | W12: =U11-Q11 -> 78 | Y12: Day Improvement (>14 day rentals) | AA12: =Y11-U11 -> 1 | AC12: Day Improvement (>14 day rentals) | AE12: =AC11-Y11 -> -14 | AG12: Day Improvement (>14 day rentals) | AI12: =AG11-AC11 -> -1 | AK12: Day Improvement (>14 day rentals) | AM12: =AK11-AG11 -> 0 | AO12: Day Improvement (>14 day rentals) | AQ12: =AO11-AK11 -> 6 | AS12: Day Improvement (>14 day rentals) | AU12: =AS11-AO11 -> 3 | AW12: Day Improvement (>14 day rentals) | AY12: =AW11-AS11 -> -7 | BA12: Day Improvement (>14 day rentals) | BC12: =BA11-AW11 -> -5 | BE12: Day Improvement (>14 day rentals) | BG12: =BE11-BA11 -> -28 | BI12: Day Improvement (>14 day rentals) | BK12: =BI11-BE11 -> -3 | BM12: Day Improvement (>14 day rentals) | BO12: =BM11-BI11 -> 5 | BQ12: Day Improvement (>14 day rentals) | BS12: =BQ11-BM11 -> -21 | BU12: Day Improvement (>14 day rentals) | BW12: =BU11-BQ11 -> 18 | BY12: Day Improvement (>14 day rentals) | CA12: =BY11-BU11 -> -21 | CC12: Day Improvement (>14 day rentals) | CE12: =CC11-BY11 -> -16 | CG12: Day Improvement (>14 day rentals) | CI12: =CG11-CC11 -> 4 | CK12: Day Improvement (>14 day rentals) | CM12: =CK11-CG11 -> 12 | CO12: Day Improvement (>14 day rentals) | CQ12: =CO11-CK11 -> 14 | CS12: Day Improvement (>14 day rentals) | CU12: =CS11-CO11 -> 2 | CW12: Day Improvement (>14 day rentals) | CY12: =CW11-CS11 -> 18 | DA12: Day Improvement (>14 day rentals) | DC12: =DA11-CW11 -> 0 | DE12: Day Improvement (>14 day rentals) | DG12: =DE11-DA11 -> 0 | DI12: Day Improvement (>14 day rentals) | DK12: =DI11-DE11 -> 1 | DM12: Day Improvement (>14 day rentals) | DO12: =DM11-DI11 -> -2 | DQ12: Day Improvement (>14 day rentals) | DS12: =DQ11-DM11 -> 10 | DU12: Day Improvement (>14 day rentals) | DW12: =DU11-DQ11 -> 1 | DY12: Day Improvement (>14 day rentals) | EA12: =DY11-DU11 -> 2 | EC12: Day Improvement (>14 day rentals) | EE12: =EC11-DY11 -> -3 | EG12: Day Improvement (>14 day rentals) | EI12: =EG11-EC11 -> -16 | EK12: Day Improvement (>14 day rentals) | EM12: =EK11-EG11 -> 4 | EO12: Day Improvement (>14 day rentals) | EQ12: =EO11-EK11 -> -2 | ES12: Day Improvement (>14 day rentals) | EU12: =ES11-EO11 -> 3 | EW12: Day Improvement (>14 day rentals) | EY12: =EW11-ES11 -> -9 | FA12: Day Improvement (>14 day rentals) | FC12: =FA11-EW11 -> 2 | FE12: Day Improvement (>14 day rentals) | FG12: =FE11-FA11 -> 6 | FI12: Day Improvement (>14 day rentals) | FK12: =FI11-FE11 -> 5 | FM12: Day Improvement (>14 day rentals) | FO12: =FM11-FI11 -> -7 | FQ12: Day Improvement (>14 day rentals) | FS12: =FQ11-FM11 -> 0 | FU12: Day Improvement (>14 day rentals) | FW12: =FU11-FQ11 -> 5 | FY12: Day Improvement (>14 day rentals) | GA12: =FY11-FU11 -> 1 | GC12: Day Improvement (>14 day rentals) | GE12: =GC11-FY11 -> -6 | GG12: Day Improvement (>14 day rentals) | GI12: =GG11-GC11 -> 5 | GK12: Day Improvement (>14 day rentals) | GM12: =GK11-GG11 -> -2 | GO12: Day Improvement (>14 day rentals) | GQ12: =GO11-GK11 -> 3 | GS12: Day Improvement (>14 day rentals) | GU12: =GS11-GO11 -> -4 | GW12: Day Improvement (>14 day rentals) | GY12: =GW11-GS11 -> -2 | HA12: Day Improvement (>14 day rentals) | HC12: =HA11-GW11 -> -2 | HE12: Day Improvement (>14 day rentals) | HG12: =HE11-HA11 -> -6 | HI12: Day Improvement (>14-day rentals) | HK12: =HI11-HE11 -> 15 | HM12: Day Improvement (>14-day rentals) | HO12: =HM11-HI11 -> 10 | HQ12: Day Improvement (>14-day rentals) | HS12: =HQ11-HM11 -> 2 | HU12: Day Improvement (>14-day rentals) | HW12: =HU11-HQ11 -> 4 | HY12: Day Improvement (>14-day rentals) | IA12: =HY11-HU11 -> 1 | IC12: Day Improvement (>14-day rentals) | IE12: =IC11-HY11 -> -4 | IG12: Day Improvement (>14-day rentals) | II12: =IG11-IC11 -> -4 | IK12: Day Improvement (>14-day rentals) | IM12: =IK11-IG11 -> 1 | IO12: Day Improvement (>14-day rentals) | IQ12: =IO11-IK11 -> -4 | IS12: Day Improvement (>14-day rentals) | IU12: =IS11-IO11 -> 1 | IW12: Day Improvement (>14-day rentals) | IY12: =IW11-IS11 -> 4 | JA12: Day Improvement (>14-day rentals) | JC12: =JA11-IW11 -> 4 | JE12: Day Improvement (>14-day rentals) | JG12: =JE11-JA11 -> 1 | JI12: Day Improvement (>14-day rentals) | JK12: =JI11-JE11 -> 9 | JM12: Day Improvement (>14-day rentals) | JO12: =JM11-JI11 -> -9 | JQ12: Day Improvement (>14-day rentals) | JS12: =JQ11-JM11 -> -2 | JU12: Day Improvement (>14-day rentals) | JW12: =JU11-JQ11 -> -7 | JY12: Day Improvement (>14-day rentals) | KA12: =JY11-JU11 -> 0 | KC12: Day Improvement (>14-day rentals) | KE12: =KC11-JY11 -> 0 | KG12: Day Improvement (>14-day rentals) | KI12: =KG11-KC11 -> 16 | KK12: Day Improvement (>14-day rentals) | KM12: =KK11-KG11 -> 6 | KO12: Day Improvement (>14-day rentals) | KQ12: =KO11-KK11 -> 1 | KS12: Day Improvement (>14-day rentals) | KU12: =KS11-KO11 -> 1 | KW12: Day Improvement (>14-day rentals) | KY12: =KW11-KS11 -> 0 | LA12: Day Improvement (>14-day rentals) | LC12: =LA11-KW11 -> 9 | LE12: Day Improvement (>14-day rentals) | LG12: =LE11-LA11 -> 3 | LI12: Day Improvement (>14-day rentals) | LK12: =LI11-LE11 -> -3 | LM12: Day Improvement (>14-day rentals) | LO12: =LM11-LI11 -> -3 | LQ12: Day Improvement (>14-day rentals) | LS12: =LQ11-LM11 -> -7 | LU12: Day Improvement (>14-day rentals) | LW12: =LU11-LQ11 -> -1 | LY12: Day Improvement (>14-day rentals) | MA12: =LY11-LU11 -> -4 | MC12: Day Improvement (>14-day rentals) | ME12: =MC11-LY11 -> -10 | MG12: Day Improvement (>14-day rentals) | MI12: =MG11-MC11 -> -7 | MK12: Day Improvement (>14-day rentals) | MM12: =MK11-MG11 -> -5 | MO12: Day Improvement (>14-day rentals) | MQ12: =MO11-MK11 -> 7 | MS12: Day Improvement (>14-day rentals) | MU12: =MS11-MO11 -> 14 | MW12: Day Improvement (>14-day rentals) | MY12: =MW11-MS11 -> -5 | NA12: Day Improvement (>14-day rentals) | NC12: =NA11-MW11 -> 1 | NE12: Day Improvement (>14-day rentals) | NG12: =NE11-NA11 -> 1 | NI12: Day Improvement (>14-day rentals) | NK12: =NI11-NE11 -> -8 | NM12: Day Improvement (>14-day rentals) | NO12: =NM11-NI11 -> 16 | NQ12: Day Improvement (>14-day rentals) | NS12: =NQ11-NM11 -> -1 | NU12: Day Improvement (>14-day rentals) | NW12: =NU11-NQ11 -> -5 | NY12: Day Improvement (>14-day rentals) | OA12: =NY11-NU11 -> 2 | OC12: Day Improvement (>14-day rentals) | OE12: =OC11-NY11 -> -5 | OG12: Day Improvement (>14-day rentals) | OI12: =OG11-OC11 -> 0 | OK12: Day Improvement (>14-day rentals) | OM12: =OK11-OG11 -> -2 | OO12: Day Improvement (>14-day rentals) | OQ12: =OO11-OK11 -> 1 | OS12: Day Improvement (>14-day rentals) | OU12: =OS11-OO11 -> 8 | OW12: Day Improvement (>14-day rentals) | OY12: =OW11-OS11 -> 0 | PA12: Day Improvement (>14-day rentals) | PC12: =PA11-OW11 -> -1 | PE12: Day Improvement (>14-day rentals) | PG12: =PE11-PA11 -> -4 | PI12: Day Improvement (>14-day rentals) | PK12: =PI11-PE11 -> 2 | PM12: Day Improvement (>14-day rentals) | PO12: =PM11-PI11 -> -4 | PQ12: Day Improvement (>14-day rentals) | PS12: =PQ11-PM11 -> 0 | PU12: Day Improvement (>14-day rentals) | PW12: =PU11-PQ11 -> 1 | PY12: Day Improvement (>14-day rentals) | QA12: =PY11-PU11 -> 1 | QC12: Day Improvement (>14-day rentals) | QE12: =QC11-PY11 -> -12 | QG12: Day Improvement (>14-day rentals) | QI12: =QG11-QC11 -> -3 | QK12: Day Improvement (>14-day rentals) | QM12: =QK11-QG11 -> -4 | QO12: Day Improvement (>14-day rentals) | QQ12: =QO11-QK11 -> 2 | QS12: Day Improvement (>14-day rentals) | QU12: =QS11-QO11 -> -15 | QW12: Day Improvement (>14-day rentals) | QY12: =QW11-QS11 -> 24 | RA12: Day Improvement (>14-day rentals) | RC12: =RA11-QW11 -> 8 | RE12: Day Improvement (>14-day rentals) | RG12: =RE11-RA11 -> -5 | RI12: Day Improvement (>14-day rentals) | RK12: =RI11-RE11 -> 4 | RM12: Day Improvement (>14-day rentals) | RO12: =RM11-RI11 -> -7 | RQ12: Day Improvement (>14-day rentals) | RS12: =RQ11-RM11 -> -4 | RU12: Day Improvement (>14-day rentals) | RW12: =RU11-RQ11 -> 0 | RY12: Day Improvement (>14-day rentals) | SA12: =RY11-RU11 -> -242
U13: WTD Improvement of >14 day Rentals: | W13: =U11-$M11 -> -34 | Y13: WTD Improvement of >14 day Rentals: | AA13: =Y11-$M11 -> -33 | AC13: WTD Improvement of >14 day Rentals: | AE13: =AC11-$M11 -> -47 | AG13: WTD Improvement of >14 day Rentals: | AI13: =AG11-$M11 -> -48 | AK13: WTD Improvement of >14 day Rentals: | AM13: =AK11-$AG11 -> 0 | AO13: WTD Improvement of >14 day Rentals: | AQ13: =AO11-$AG11 -> 6 | AS13: WTD Improvement of >14 day Rentals: | AU13: =AS11-$AG11 -> 9 | AW13: WTD Improvement of >14 day Rentals: | AY13: =AW11-$AG11 -> 2 | BA13: WTD Improvement of >14 day Rentals: | BC13: =BA11-$AW11 -> -5 | BE13: WTD Improvement of >14 day Rentals: | BG13: =BE11-$AW11 -> -33 | BI13: WTD Improvement of >14 day Rentals: | BK13: =BI11-$AW11 -> -36 | BM13: WTD Improvement of >14 day Rentals: | BO13: =BM11-$AW11 -> -31 | BQ13: WTD Improvement of >14 day Rentals: | BS13: =BQ11-$AW11 -> -52 | BU13: WTD Improvement of >14 day Rentals: | BW13: =BU11-$BQ11 -> 18 | BY13: WTD Improvement of >14 day Rentals: | CA13: =BY11-$BQ11 -> -3 | CC13: WTD Improvement of >14 day Rentals: | CE13: =CC11-$BQ11 -> -19 | CG13: WTD Improvement of >14 day Rentals: | CI13: =CG11-$BQ11 -> -15 | CK13: WTD Improvement of >14 day Rentals: | CM13: =CK11-$CG11 -> 12 | CO13: WTD Improvement of >14 day Rentals: | CQ13: =CO11-$CG11 -> 26 | CS13: WTD Improvement of >14 day Rentals: | CU13: =CS11-$CG11 -> 28 | CW13: WTD Improvement of >14 day Rentals: | CY13: =CW11-$CG11 -> 46 | DA13: WTD Improvement of >14 day Rentals: | DC13: =DA11-$CG11 -> 46 | DE13: WTD Improvement of >14 day Rentals: | DG13: =DE11-$DA11 -> 0 | DI13: WTD Improvement of >14 day Rentals: | DK13: =DI11-$DA11 -> 1 | DM13: WTD Improvement of >14 day Rentals: | DO13: =DM11-$DA11 -> -1 | DQ13: WTD Improvement of >14 day Rentals: | DS13: =DQ11-$DA11 -> 9 | DU13: WTD Improvement of >14 day Rentals: | DW13: =DU11-$DA11 -> 10 | DY13: WTD Improvement of >14 day Rentals: | EA13: =DY11-$DU11 -> 2 | EC13: WTD Improvement of >14 day Rentals: | EE13: =EC11-$DU11 -> -1 | EG13: WTD Improvement of >14 day Rentals: | EI13: =EG11-$DU11 -> -17 | EK13: WTD Improvement of >14 day Rentals: | EM13: =EK11-$DU11 -> -13 | EO13: WTD Improvement of >14 day Rentals: | EQ13: =EO11-$DU11 -> -15 | ES13: WTD Improvement of >14 day Rentals: | EU13: =ES11-$EO11 -> 3 | EW13: WTD Improvement of >14 day Rentals: | EY13: =EW11-$EO11 -> -6 | FA13: WTD Improvement of >14 day Rentals: | FC13: =FA11-$EO11 -> -4 | FE13: WTD Improvement of >14 day Rentals: | FG13: =FE11-$EO11 -> 2 | FI13: WTD Improvement of >14 day Rentals: | FK13: =FI11-$EO11 -> 7 | FM13: WTD Improvement of >14 day Rentals: | FO13: =FM11-$FI11 -> -7 | FQ13: WTD Improvement of >14 day Rentals: | FS13: =FQ11-$FI11 -> -7 | FU13: WTD Improvement of >14 day Rentals: | FW13: =FU11-$FI11 -> -2 | FY13: WTD Improvement of >14 day Rentals: | GA13: =FY11-$FI11 -> -1 | GC13: WTD Improvement of >14 day Rentals: | GE13: =GC11-$FY11 -> -6 | GG13: WTD Improvement of >14 day Rentals: | GI13: =GG11-$FY11 -> -1 | GK13: WTD Improvement of >14 day Rentals: | GM13: =GK11-$FY11 -> -3 | GO13: WTD Improvement of >14 day Rentals: | GQ13: =GO11-$FY11 -> 0 | GS13: WTD Improvement of >14 day Rentals: | GU13: =GS11-$FY11 -> -4 | GW13: WTD Improvement of >14 day Rentals: | GY13: =GW11-$GS11 -> -2 | HA13: WTD Improvement of >14 day Rentals: | HC13: =HA11-$GS11 -> -4 | HE13: WTD Improvement of >14 day Rentals: | HG13: =HE11-$GS11 -> -10 | HI13: WTD Improvement (>14-day rentals) | HK13: =HI11-$HE11 -> 15 | HM13: WTD Improvement (>14-day rentals) | HO13: =HM11-$HE11 -> 25 | HQ13: WTD Improvement (>14-day rentals) | HS13: =HQ11-$HE11 -> 27 | HU13: WTD Improvement (>14-day rentals) | HW13: =HU11-$HE11 -> 31 | HY13: WTD Improvement (>14-day rentals) | IA13: =HY11-$HE11 -> 32 | IC13: WTD Improvement (>14-day rentals) | IE13: =IC11-$HE11 -> 28 | IG13: WTD Improvement (>14-day rentals) | II13: =IG11-$HE11 -> 24 | IK13: WTD Improvement (>14-day rentals) | IM13: =IK11-$HE11 -> 25 | IO13: WTD Improvement (>14-day rentals) | IQ13: =IO11-$HE11 -> 21 | IS13: WTD Improvement (>14-day rentals) | IU13: =IS11-$HE11 -> 22 | IW13: WTD Improvement (>14-day rentals) | IY13: =IW11-$HE11 -> 26 | JA13: WTD Improvement (>14-day rentals) | JC13: =JA11-$HE11 -> 30 | JE13: WTD Improvement (>14-day rentals) | JG13: =JE11-$HE11 -> 31 | JI13: WTD Improvement (>14-day rentals) | JK13: =JI11-$HE11 -> 40 | JM13: WTD Improvement (>14-day rentals) | JO13: =JM11-$HE11 -> 31 | JQ13: WTD Improvement (>14-day rentals) | JS13: =JQ11-$HE11 -> 29 | JU13: WTD Improvement (>14-day rentals) | JW13: =JU11-$HE11 -> 22 | JY13: WTD Improvement (>14-day rentals) | KA13: =JY11-$HE11 -> 22 | KC13: WTD Improvement (>14-day rentals) | KE13: =KC11-$HE11 -> 22 | KG13: WTD Improvement (>14-day rentals) | KI13: =KG11-$HE11 -> 38 | KK13: WTD Improvement (>14-day rentals) | KM13: =KK11-$HE11 -> 44 | KO13: WTD Improvement (>14-day rentals) | KQ13: =KO11-$HE11 -> 45 | KS13: WTD Improvement (>14-day rentals) | KU13: =KS11-$HE11 -> 46 | KW13: WTD Improvement (>14-day rentals) | KY13: =KW11-$HE11 -> 46 | LA13: WTD Improvement (>14-day rentals) | LC13: =LA11-$HE11 -> 55 | LE13: WTD Improvement (>14-day rentals) | LG13: =LE11-$LA11 -> 3 | LI13: WTD Improvement (>14-day rentals) | LK13: =LI11-$LA11 -> 0 | LM13: WTD Improvement (>14-day rentals) | LO13: =LM11-$LA11 -> -3 | LQ13: WTD Improvement (>14-day rentals) | LS13: =LQ11-$LA11 -> -10 | LU13: WTD Improvement (>14-day rentals) | LW13: =LU11-$LA11 -> -11 | LY13: WTD Improvement (>14-day rentals) | MA13: =LY11-$LA11 -> -15 | MC13: WTD Improvement (>14-day rentals) | ME13: =MC11-$LA11 -> -25 | MG13: WTD Improvement (>14-day rentals) | MI13: =MG11-$LA11 -> -32 | MK13: WTD Improvement (>14-day rentals) | MM13: =MK11-$LA11 -> -37 | MO13: WTD Improvement (>14-day rentals) | MQ13: =MO11-$LA11 -> -30 | MS13: WTD Improvement (>14-day rentals) | MU13: =MS11-$LA11 -> -16 | MW13: WTD Improvement (>14-day rentals) | MY13: =MW11-$LA11 -> -21 | NA13: WTD Improvement (>14-day rentals) | NC13: =NA11-$LA11 -> -20 | NE13: WTD Improvement (>14-day rentals) | NG13: =NE11-$LA11 -> -19 | NI13: WTD Improvement (>14-day rentals) | NK13: =NI11-$LA11 -> -27 | NM13: WTD Improvement (>14-day rentals) | NO13: =NM11-$LA11 -> -11 | NQ13: WTD Improvement (>14-day rentals) | NS13: =NQ11-$LA11 -> -12 | NU13: WTD Improvement (>14-day rentals) | NW13: =NU11-$LA11 -> -17 | NY13: WTD Improvement (>14-day rentals) | OA13: =NY11-$LA11 -> -15 | OC13: WTD Improvement (>14-day rentals) | OE13: =OC11-$LA11 -> -20 | OG13: WTD Improvement (>14-day rentals) | OI13: =OG11-$OC11 -> 0 | OK13: WTD Improvement (>14-day rentals) | OM13: =OK11-$OC11 -> -2 | OO13: WTD Improvement (>14-day rentals) | OQ13: =OO11-$OC11 -> -1 | OS13: WTD Improvement (>14-day rentals) | OU13: =OS11-$OC11 -> 7 | OW13: WTD Improvement (>14-day rentals) | OY13: =OW11-$OC11 -> 7 | PA13: WTD Improvement (>14-day rentals) | PC13: =PA11-$OW11 -> -1 | PE13: WTD Improvement (>14-day rentals) | PG13: =PE11-$OW11 -> -5 | PI13: WTD Improvement (>14-day rentals) | PK13: =PI11-$OW11 -> -3 | PM13: WTD Improvement (>14-day rentals) | PO13: =PM11-$OW11 -> -7 | PQ13: WTD Improvement (>14-day rentals) | PS13: =PQ11-$OW11 -> -7 | PU13: WTD Improvement (>14-day rentals) | PW13: =PU11-$PQ11 -> 1 | PY13: WTD Improvement (>14-day rentals) | QA13: =PY11-$PQ11 -> 2 | QC13: WTD Improvement (>14-day rentals) | QE13: =QC11-$PQ11 -> -10 | QG13: WTD Improvement (>14-day rentals) | QI13: =QG11-$PQ11 -> -13 | QK13: WTD Improvement (>14-day rentals) | QM13: =QK11-$PQ11 -> -17 | QO13: WTD Improvement (>14-day rentals) | QQ13: =QO11-$QK11 -> 2 | QS13: WTD Improvement (>14-day rentals) | QU13: =QS11-$QK11 -> -13 | QW13: WTD Improvement (>14-day rentals) | QY13: =QW11-$QK11 -> 11 | RA13: WTD Improvement (>14-day rentals) | RC13: =RA11-$QK11 -> 19 | RE13: WTD Improvement (>14-day rentals) | RG13: =RE11-$QK11 -> 14 | RI13: WTD Improvement (>14-day rentals) | RK13: =RI11-$RE11 -> 4 | RM13: WTD Improvement (>14-day rentals) | RO13: =RM11-$RE11 -> -3 | RQ13: WTD Improvement (>14-day rentals) | RS13: =RQ11-$RE11 -> -7 | RU13: WTD Improvement (>14-day rentals) | RW13: =RU11-$RE11 -> -7 | RY13: WTD Improvement (>14-day rentals) | SA13: =RY11-$RE11 -> -249
RT15: Total Technicians in TPMS (Active Techs) | RW15: 1630
RT16: Service Tech - Modified Duty | RW16: 13
RT17: Active Routable Technicians (excluding Modified Duty): | RW17: 1617
RT18: BYOV Technicians: | RW18: 118
RT19: Total Techs requiring a truck assignment: | RW19: 1499
RT20: Trucks Assigned in TPMS (including assigned to modified duty): | RW20: 1577
RT21: Trucks Assigned in TPMS (excl BYOV): | RW21: 1449
RT22: No Truck Assigned (All Techs) | RW22: 53
RT23: Truck not assigned for a modified duty tech (excluded) | RW23: 3
RT24: Active techs needing a truck assignment (excl. mod duty): | RW24: 50
RT25: Techs assigned to trucks that have a declined estimate for repair: | RW25: 157
RT26: Total Spares (not "declined repair" and not "sent to auction"): | RW26: 423
... RT32: Total Spares (not declined repairs and not sent to auctions): | RW32: 423

Sheet Detail2
A1: Details for Rentals Open - Is on Holman Rental: Research w.Holman, Ticket Status: OPEN, Duplicate: No (+)
A3: Truck Number | B3: Is on Holman Rental | C3: Days Open Category | D3: Days Open | E3: Rental under Name: | F3: Rental Tech Enterprise ID | G3: Truck Assigned to in TPMS | H3: Truck assigned to in TPMS Enterprise ID | I3: LU Employment Start Date in TPMS | J3: Duplicate | K3: ECARS 2.0 Tkt Nbr | L3: Renter Name | M3: Claims Office Name | N3: Claim Number | O3: Rental Start Date | P3: Renting Branch | Q3: Renting City Name | R3: Renting State | S3: Car Class Authorized Description | T3: Days Authorized | U3: Initial Days Authorized | V3: Rate Authorized | W3: Number of Extensions | X3: Rental Days | Y3: Ticket Status | Z3: Vehicle Number | AA3: PO Number | AB3: Client Company Name | AC3: Client Company | AD3: Days Behind | AE3: Rate Level | AF3: Rented Veh Year | AG3: Rented Veh Make | AH3: Rented Veh Model | AI3: ARI20 Client Number | AJ3: Number of Rewrites | AK3: Original Start Date | AL3: Repairs Complete
A4: 06585 | B4: Research w.Holman | C4: 28 plus days | D4: 73 | E4: GREGG PAULSEN | F4: GPAULSE | G4: GREGG PAULSEN | H4: GPAULSE | I4: 45844 | J4: No | K4: 1TWDKC | L4: GREGG PAULSEN | M4: HOLMAN FLEET (ARI) US MAINT | N4: 114771300 -B/R | O4: 46016 | P4: 623G | Q4: DAVENPORT | R4: IA | S4: MINIVAN 7 SEATS | T4: 21 | U4: 4 | V4: 69 | W4: 2 | X4: 16 | Y4: OPEN | Z4: 06585 | AB4: TRANSFORM SEARS HOME SERVICES | AC4: ZLevel 4 Clients Only | AD4: 0 | AE4: F | AF4: 25 | AG4: CHRY | AH4: PACI | AI4: 2B56 | AJ4: 2 | AK4: 45958 | AL4: No
A5: 06611 | B5: Research w.Holman | C5: 28 plus days | D5: 165 | E5: WARREN BURTON | F5: WBURTO | G5: Not Assigned in TPMS!! | H5: Not Assigned in TPMS!! | I5: Not Assigned in TPMS!! | J5: No | K5: 1W33GW | L5: WARREN BURTON | M5: HOLMAN FLEET (ARI) US INTERIM | N5: 113148831 -E/R | O5: 46016 | P5: 32A2 | Q5: SANTA MARIA | R5: CA | S5: SUV STANDARD | T5: 30 | U5: 30 | V5: 72 | W5: 0 | X5: 16 | Y5: OPEN | Z5: 06611 | AB5: TRANSFORM SEARS HOME SERVICES | AC5: ZLevel 4 Clients Only | AD5: 0 | AE5: F | AF5: 23 | AG5: HYUN | AH5: TUCS | AI5: 2B56 | AJ5: 5 | AK5: 45866 | AL5: Yes
A6: 06633 | B6: Research w.Holman | C6: 28 plus days | D6: 91 | E6: ANTHONY EDUARDO SALVADOR | F6: RESEARCH!! | G6: ANTHONY SALVADOR | H6: ASALVAD | I6: 45830 | J6: No | K6: 1ZC53F | L6: ANTHONY EDUARDO SALVADOR | M6: HOLMAN FLEET (ARI) US MAINT | N6: 114510327 -C/R | O6: 46030 | P6: 32VG | Q6: GLENDALE | R6: CA | S6: SUV STANDARD | T6: 1 | U6: 1 | V6: 72 | W6: 0 | X6: 2 | Y6: OPEN | Z6: 06633 | AB6: TRANSFORM SEARS HOME SERVICES | AC6: ZLevel 4 Clients Only | AD6: 1 | AE6: F | AF6: 26 | AG6: CHEV | AH6: S15C | AI6: 2B56 | AJ6: 3 | AK6: 45940 | AL6: No
A7: 21016 | B7: Research w.Holman | C7: 28 plus days | D7: 72 | E7: KEITH GRIFFIN | F7: KGRIFF0 | G7: KEITH GRIFFIN | H7: KGRIFF0 | I7: 44602 | J7: No | K7: 1Y8KNH | L7: KEITH GRIFFIN | M7: HOLMAN FLEET (ARI) US MAINT | N7: 114793133 -B/R | O7: 46019 | P7: 3068 | Q7: ELK GROVE | R7: CA | S7: MINIVAN 7 SEATS | T7: 18 | U7: 3 | V7: 73 | W7: 1 | X7: 13 | Y7: OPEN | Z7: 21016 | AB7: TRANSFORM SEARS HOME SERVICES | AC7: ZLevel 4 Clients Only | AD7: 0 | AE7: F | AF7: 24 | AG7: CHRY | AH7: PACH | AI7: 2B56 | AJ7: 2 | AK7: 45959 | AL7: No
A8: 21160 | B8: 21160 | C8: 28 plus days | D8: 29 | E8: JERMARVIUS YOUNG | F8: JYOUNG0 | G8: JERMARVIUS YOUNG | H8: JYOUNG0 | I8: 45977 | J8: No | K8: 1PLCKY | L8: JERMARVIUS YOUNG | M8: HOLMAN FLEET (ARI) US INTERIM | N8: 115562519 | O8: 46002 | P8: 15AO | Q8: OSWEGO | R8: IL | S8: SUV STANDARD | T8: 30 | U8: 14 | V8: 69 | W8: 1 | X8: 30 | Y8: OPEN | Z8: 21160 | AB8: TRANSFORM SEARS HOME SERVICES | AC8: ZLevel 4 Clients Only | AD8: 0 | AE8: F | AF8: 24 | AG8: MITS | AH8: MIRA | AI8: 2B56 | AJ8: 0 | AK8: 46002 | AL8: No
A9: 21162 | B9: Research w.Holman | C9: 28 plus days | D9: 91 | E9: ILJIR ZULFIU | F9: IZULFIU | G9: ILJIR ZULFIU | H9: IZULFIU | I9: 45809 | J9: No | K9: 1Y12YK | L9: ILJIR ZULFIU | M9: HOLMAN FLEET (ARI) US MAINT | N9: 114972432 -B/R | O9: 46025 | P9: 3902 | Q9: BROOK PARK | R9: OH | S9: MINIVAN 7 SEATS | T9: 13 | U9: 3 | V9: 68 | W9: 1 | X9: 7 | Y9: OPEN | Z9: 21162 | AB9: TRANSFORM SEARS HOME SERVICES | AC9: ZLevel 4 Clients Only | AD9: 0 | AE9: F | AF9: 25 | AG9: CHRY | AH9: PACI | AI9: 2B56 | AJ9: 2 | AK9: 45940 | AL9: No
A10: 21174 | B10: Research w.Holman | C10: 28 plus days | D10: 128 | E10: ALEXANDER SMITH | F10: ASMITH2 | G10: ALEXANDER SMITH | H10: ASMITH2 | I10: 45326 | J10: No | K10: 1YZ698 | L10: ALEXANDER SMITH | M10: HOLMAN FLEET (ARI) US MAINT | N10: 113796397 -D/R | O10: 46027 | P10: 5572 | Q10: PRATTVILLE | R10: AL | S10: MINIVAN 7 SEATS | T10: 11 | U10: 1 | V10: 68 | W10: 1 | X10: 5 | Y10: OPEN | Z10: 21174 | AB10: TRANSFORM SEARS | AC10: ZLevel 4 Clients Only | AD10: 0 | AE10: F | AF10: 25 | AG10: FORD | AH10: F15C | AI10: 2B56 | AJ10: 4 | AK10: 45903 | AL10: No
A11: 21175 | B11: Research w.Holman | C11: 28 plus days | D11: 106 | E11: KYLE TATUM | F11: KTATUM3 | G11: KYLE TATUM | H11: KTATUM3 | I11: 45655 | J11: No | K11: 1YG54M | L11: KYLE TATUM | M11: HOLMAN FLEET (ARI) US INTERIM | N11: 114224652 -C/R | O11: 46022 | P11: 0917 | Q11: BURLESON | R11: TX | S11: MINIVAN 7 SEATS | T11: 30 | U11: 30 | V11: 69 | W11: 0 | X11: 10 | Y11: OPEN | Z11: 21175 | AB11: TRANSFORM SEARS HOME SERVICES | AC11: ZLevel 4 Clients Only | AD11: 0 | AE11: F | AF11: 25 | AG11: CHRY | AH11: PACI | AI11: 2B56 | AJ11: 3 | AK11: 45925 | AL11: Yes
A12: 21187 | B12: 21187 | C12: 28 plus days | D12: 214 | E12: LONDON WILLIAMS | F12: LWILLI3 | G12: Not Assigned in TPMS!! | H12: Not Assigned in TPMS!! | I12: Not Assigned in TPMS!! | J12: No | K12: 1N4DMF | L12: LONDON WILLIAMS | M12: HOLMAN FLEET (ARI) US INTERIM | N12: 112355336 -F/R | O12: 45997 | P12: 1412 | Q12: BAKER | R12: LA | S12: MINIVAN 7 SEATS | T12: 30 | U12: 4 | V12: 68 | W12: 3 | X12: 35 | Y12: OPEN | Z12: 21187 | AB12: TRANSFORM SEARS HOME SERVICES | AC12: ZLevel 4 Clients Only | AD12: 0 | AE12: F | AF12: 26 | AG12: DODG | AH12: DURA | AI12: 2B56 | AJ12: 6 | AK12: 45817 | AL12: Yes
A13: 21190 | B13: Research w.Holman | C13: 28 plus days | D13: 136 | E13: BRAD JONES | F13: BJONES1 | G13: BRAD JONES | H13: BJONES1 | I13: 45242 | J13: No | K13: 1VLDV3 | L13: BRAD JONES | M13: HOLMAN FLEET (ARI) US INTERIM | N13: 113664603 -E/R | O13: 46015 | P13: 5551 | Q13: PENSACOLA | R13: FL | S13: MINIVAN 7 SEATS | T13: 30 | U13: 30 | V13: 68 | W13: 0 | X13: 17 | Y13: OPEN | Z13: 21190 | AB13: TRANSFORM SEARS HOME SERVICES | AC13: ZLevel 4 Clients Only | AD13: 0 | AE13: F | AF13: 24 | AG13: NISN | AH13: ARMA | AI13: 2B56 | AJ13: 5 | AK13: 45895 | AL13: Yes
A14: 21207 | B14: 21207 | C14: 28 plus days | D14: 170 | E14: COREY NEWELL | F14: CNEWELL | G14: TYLER CARNAHAN | H14: TCARNAH | I14: 45893 | J14: No | K14: 1SQ5Z2 | L14: COREY NEWELL | M14: HOLMAN FLEET (ARI) US INTERIM | N14: 113073769 -E/R | O14: 46010 | P14: 552G | Q14: DAPHNE | R14: AL | S14: SUV STANDARD | T14: 30 | U14: 30 | V14: 68 | W14: 0 | X14: 22 | Y14: OPEN | Z14: 21207 | AB14: TRANSFORM SEARS HOME SERVICES | AC14: ZLevel 4 Clients Only | AD14: 0 | AE14: F | AF14: 24 | AG14: SUBU | AH14: OUTB | AI14: 2B56 | AJ14: 5 | AK14: 45861 | AL14: Yes
A15: 21237 | B15: 21237 | C15: 28 plus days | D15: 171 | E15: ARTHUR HARRIS | F15: AHARRIS | G15: ARTHUR HARRIS | H15: AHARRIS | I15: 45858 | J15: No | K15: 1TN6CM | L15: ARTHUR HARRIS | M15: HOLMAN FLEET (ARI) US INTERIM | N15: 113066947 -E/R | O15: 46010 | P15: 24C6 | Q15: BRONX | R15: NY | S15: MINIVAN 7 SEATS | T15: 30 | U15: 30 | V15: 86 | W15: 0 | X15: 22 | Y15: OPEN | Z15: 21237 | AB15: TRANSFORM SEARS HOME SERVICES | AC15: ZLevel 4 Clients Only | AD15: 0 | AE15: F | AF15: 24 | AG15: JEEP | AH15: COMP | AI15: 2B56 | AJ15: 5 | AK15: 45860 | AL15: Yes
A16: 21239 | B16: Research w.Holman | C16: 28 plus days | D16: 63 | E16: SHAWN BLOUNT | F16: SBLOUNT | G16: Not Assigned in TPMS!! | H16: Not Assigned in TPMS!! | I16: Not Assigned in TPMS!! | J16: No | K16: 1PQTVS | L16: SHAWN BLOUNT | M16: HOLMAN FLEET (ARI) US INTERIM | N16: 114937855 -A/R | O16: 46001 | P16: 21C7 | Q16: NORFOLK | R16: VA | S16: MINIVAN 7 SEATS | T16: 30 | U16: 30 | V16: 69 | W16: 0 | X16: 31 | Y16: OPEN | Z16: 21239 | AB16: TRANSFORM SEARS HOME SERVICES | AC16: ZLevel 4 Clients Only | AD16: 1 | AE16: F | AF16: 25 | AG16: CHRY | AH16: PACI | AI16: 2B56 | AJ16: 1 | AK16: 45968 | AL16: No
A17: 21264 | B17: Research w.Holman | C17: 28 plus days | D17: 156 | E17: JOSE LOPEZ | F17: JLOPEZ0 | G17: JOSE LOPEZ | H17: JLOPEZ0 | I17: 45592 | J17: No | K17: 1YFYR5 | L17: JOSE LOPEZ | M17: HOLMAN FLEET (ARI) US MAINT | N17: 113313532 -A/R | O17: 46025 | P17: 522L | Q17: SAN ANTONIO | R17: TX | S17: CARGO VAN | T17: 10 | U17: 10 | V17: 76.29 | W17: 0 | X17: 7 | Y17: OPEN | Z17: 21264 | AB17: TRANSFORM SEARS HOME SERVICES | AC17: ZLevel 4 Clients Only | AD17: 0 | AE17: F | AF17: 24 | AG17: FORD | AH17: EXEL | AI17: 2B56 | AJ17: 5 | AK17: 45875 | AL17: No
A18: 21281 | B18: 21281 | C18: 28 plus days | D18: 29 | E18: JOSHUA LEONARD | F18: JLEONAR | G18: JOSHUA LEONARD | H18: JLEONAR | I18: 45613 | J18: No | K18: 1PM3PK | L18: JOSHUA LEONARD | M18: HOLMAN FLEET (ARI) US MAINT | N18: 115521261 | O18: 46002 | P18: 09LX | Q18: DALLAS | R18: TX | S18: MINIVAN 7 SEATS | T18: 30 | U18: 14 | V18: 69 | W18: 2 | X18: 30 | Y18: OPEN | Z18: 21281 | AB18: TRANSFORM SEARS HOME SERVICES | AC18: ZLevel 4 Clients Only | AD18: 0 | AE18: F | AF18: 24 | AG18: GMC | AH18: TERR | AI18: 2B56 | AJ18: 0 | AK18: 46002 | AL18: No
A19: 21285 | B19: Research w.Holman | C19: 28 plus days | D19: 72 | E19: JORGE SORIANO | F19: JSORIAN | G19: JORGE SORIANO | H19: JSORIAN | I19: 45928 | J19: No | K19: 1VSB7B | L19: JORGE SORIANO | M19: HOLMAN FLEET (ARI) US MAINT | N19: 114791910 -B/R | O19: 46019 | P19: 0743 | Q19: ST. CLOUD | R19: FL | S19: MINIVAN 7 SEATS | T19: 12 | U19: 3 | V19: 69 | W19: 1 | X19: 13 | Y19: OPEN | Z19: 21285 | AB19: TRANSFORM SEARS HOME SERVICES | AC19: ZLevel 4 Clients Only | AD19: 1 | AE19: F | AF19: 25 | AG19: CHRY | AH19: PACI | AI19: 2B56 | AJ19: 2 | AK19: 45959 | AL19: No
A20: 21365 | B20: 21365 | C20: 28 plus days | D20: 57 | E20: VINCE ROSADO | F20: RESEARCH!! | G20: Not Assigned in TPMS!! | H20: Not Assigned in TPMS!! | I20: Not Assigned in TPMS!! | J20: No | K20: 1RJKDG | L20: VINCE ROSADO | M20: HOLMAN FLEET (ARI) US MAINT | N20: 115029941 -A/R | O20: 46004 | P20: 510A | Q20: TEXARKANA | R20: TX | S20: MINIVAN 7 SEATS | T20: 30 | U20: 5 | V20: 69 | W20: 2 | X20: 28 | Y20: OPEN | Z20: 21365 | AB20: TRANSFORM SEARS HOME SERVICES | AC20: ZLevel 4 Clients Only | AD20: 0 | AE20: F | AF20: 26 | AG20: CHRY | AH20: PACI | AI20: 2B56 | AJ20: 1 | AK20: 45974 | AL20: No
A21: 21526 | B21: Research w.Holman | C21: 28 plus days | D21: 93 | E21: BRIC BRADLEY | F21: RESEARCH!! | G21: Not Assigned in TPMS!! | H21: Not Assigned in TPMS!! | I21: Not Assigned in TPMS!! | J21: No | K21: 1NJR8N | L21: BRIC BRADLEY | M21: HOLMAN FLEET (ARI) US MAINT | N21: 114450280 -B/R | O21: 45998 | P21: 5845 | Q21: PADUCAH | R21: KY | S21: SUV INTERMEDIATE | T21: 30 | U21: 9 | V21: 68 | W21: 2 | X21: 34 | Y21: OPEN | Z21: 21526 | AB21: TRANSFORM SEARS HOME SERVICES | AC21: ZLevel 4 Clients Only | AD21: 0 | AE21: F | AF21: 24 | AG21: GMC | AH21: TERR | AI21: 2B56 | AJ21: 2 | AK21: 45938 | AL21: No
A22: 21547 | B22: Research w.Holman | C22: 28 plus days | D22: 183 | E22: ERIC CONSUEGRA | F22: ECONSUE | G22: Not Assigned in TPMS!! | H22: Not Assigned in TPMS!! | I22: Not Assigned in TPMS!! | J22: No | K22: 1Z6S4V | L22: ERIC CONSUEGRA | M22: HOLMAN FLEET (ARI) US MAINT | N22: 112882181 -F/R | O22: 46028 | P22: 2644 | Q22: FLORENCE | R22: SC | S22: MINIVAN 7 SEATS | T22: 7 | U22: 7 | V22: 69 | W22: 0 | X22: 4 | Y22: OPEN | Z22: 21547 | AB22: TRANSFORM SEARS HOME SERVICES | AC22: ZLevel 4 Clients Only | AD22: 0 | AE22: F | AF22: 25 | AG22: CHRY | AH22: PACI | AI22: 2B56 | AJ22: 6 | AK22: 45848 | AL22: No
A23: 21660 | B23: 21660 | C23: 28 plus days | D23: 38 | E23: MAURY CAMARA | F23: RESEARCH!! | G23: Not Assigned in TPMS!! | H23: Not Assigned in TPMS!! | I23: Not Assigned in TPMS!! | J23: No | K23: 1X38YF | L23: MAURY CAMARA | M23: HOLMAN FLEET (ARI) US MAINT | N23: 115419904 -A/R | O23: 46023 | P23: 10L3 | Q23: MARLBOROUGH | R23: MA | S23: MINI-CARGO VANS | T23: 6 | U23: 6 | V23: 79.29 | W23: 0 | X23: 9 | Y23: OPEN | Z23: 21660 | AB23: TRANSFORM SEARS HOME SERVICES | AC23: ZLevel 4 Clients Only | AD23: 3 | AE23: F | AF23: 25 | AG23: RAM | AH23: B15C | AI23: 2B56 | AJ23: 1 | AK23: 45993 | AL23: Yes
A24: 22101 | B24: 22101 | C24: 28 plus days | D24: 205 | E24: JAMSHID HABIBI | F24: JHABIBI | G24: MUJEEB KHAN | H24: MKHAN1 | I24: 45886 | J24: No | K24: 1R9VP5 | L24: JAMSHID HABIBI | M24: HOLMAN FLEET (ARI) US INTERIM | N24: 112526444 -F/R | O24: 46006 | P24: 167F | Q24: DALE CITY | R24: VA | S24: SUV INTERMEDIATE | T24: 30 | U24: 30 | V24: 72 | W24: 0 | X24: 26 | Y24: OPEN | Z24: 22101 | AB24: TRANSFORM SEARS HOME SERVICES | AC24: ZLevel 4 Clients Only | AD24: 0 | AE24: F | AF24: 25 | AG24: MITS | AH24: ECLX | AI24: 2B56 | AJ24: 6 | AK24: 45826 | AL24: No
A25: 22101 | B25: 22101 | C25: 28 plus days | D25: 135 | E25: MUJEEB KHAN | F25: MKHAN1 | G25: MUJEEB KHAN | H25: MKHAN1 | I25: 45886 | J25: No | K25: 1Y73N9 | L25: MUJEEB KHAN | M25: HOLMAN FLEET (ARI) US INTERIM | N25: 113677180 -D/R | O25: 46016 | P25: 1692 | Q25: ALEXANDRIA | R25: VA | S25: SUV INTERMEDIATE | T25: 30 | U25: 30 | V25: 72 | W25: 0 | X25: 16 | Y25: OPEN | Z25: 22101 | AB25: TRANSFORM SEARS HOME SERVICES | AC25: ZLevel 4 Clients Only | AD25: 0 | AE25: F | AF25: 25 | AG25: GMC | AH25: K15C | AI25: 2B56 | AJ25: 4 | AK25: 45896 | AL25: No
A26: 22161 | B26: Research w.Holman | C26: 28 plus days | D26: 93 | E26: MARK JR | F26: RESEARCH!! | G26: Not Assigned in TPMS!! | H26: Not Assigned in TPMS!! | I26: Not Assigned in TPMS!! | J26: No | K26: 1NYQRZ | L26: MARK JR | M26: HOLMAN FLEET (ARI) US MAINT | N26: 114447522 -B/R | O26: 45998 | P26: 5622 | Q26: KNOXVILLE | R26: TN | S26: SUV STANDARD | T26: 30 | U26: 10 | V26: 68 | W26: 2 | X26: 34 | Y26: OPEN | Z26: 22161 | AB26: TRANSFORM SEARS HOME SERVICES | AC26: ZLevel 4 Clients Only | AD26: 0 | AE26: F | AF26: 24 | AG26: FORD | AH26: MUSC | AI26: 2B56 | AJ26: 2 | AK26: 45938 | AL26: Yes
A27: 22186 | B27: 22186 | C27: 28 plus days | D27: 137 | E27: WILLIAM PRICE | F27: WPRICE1 | G27: WILLIAM PRICE | H27: WPRICE1 | I27: 42422 | J27: No | K27: 1WG5BD | L27: WILLIAM PRICE | M27: HOLMAN FLEET (ARI) US MAINT | N27: 113644415 -D/R | O27: 46014 | P27: 5313 | Q27: GASTONIA | R27: NC | S27: MINIVAN 7 SEATS | T27: 30 | U27: 8 | V27: 68 | W27: 1 | X27: 18 | Y27: OPEN | Z27: 22186 | AB27: TRANSFORM SEARS HOME SERVICES | AC27: ZLevel 4 Clients Only | AD27: 0 | AE27: F | AF27: 25 | AG27: CHRY | AH27: PACI | AI27: 2B56 | AJ27: 4 | AK27: 45894 | AL27: Yes
A28: 22201 | B28: 22201 | C28: 28 plus days | D28: 172 | E28: NIGEL POWELL | F28: NPOWELL | G28: ERIN TIPTON | H28: ETIPTON | I28: 45956 | J28: No | K28: 1YZ3H9 | L28: NIGEL POWELL | M28: HOLMAN FLEET (ARI) US INTERIM | N28: 113009651 -E/R | O28: 46029 | P28: 2160 | Q28: CHESAPEAKE | R28: VA | S28: SUV INTERMEDIATE | T28: 30 | U28: 30 | V28: 69 | W28: 0 | X28: 3 | Y28: OPEN | Z28: 22201 | AB28: TRANSFORM SEARS HOME SERVICES | AC28: ZLevel 4 Clients Only | AD28: 0 | AE28: F | AF28: 24 | AG28: MAZD | AH28: CX5 | AI28: 2B56 | AJ28: 5 | AK28: 45859 | AL28: No
A29: 22249 | B29: Research w.Holman | C29: 28 plus days | D29: 51 | E29: GEORGE JOHNSON | F29: GJOHNS7 | G29: GEORGE JOHNSON | H29: GJOHNS7 | I29: 41414 | J29: No | K29: 1S1LRK | L29: GEORGE JOHNSON | M29: HOLMAN FLEET (ARI) US INTERIM | N29: 115212270 -A/R | O29: 46010 | P29: 5731 | Q29: SCRANTON | R29: PA | S29: MINIVAN 7 SEATS | T29: 30 | U29: 1 | V29: 69 | W29: 2 | X29: 22 | Y29: OPEN | Z29: 22249 | AB29: TRANSFORM SEARS HOME SERVICES | AC29: ZLevel 4 Clients Only | AD29: 0 | AE29: F | AF29: 25 | AG29: GMC | AH29: K15C | AI29: 2B56 | AJ29: 1 | AK29: 45980 | AL29: Yes
A30: 22334 | B30: Research w.Holman | C30: 28 plus days | D30: 72 | E30: DORIAN WADE | F30: DWADE | G30: RICHARD PAULSON | H30: RPAULS0 | I30: 45998 | J30: No | K30: 1WJHSK | L30: DORIAN WADE | M30: HOLMAN FLEET (ARI) US MAINT | N30: 114809438 -B/R | O30: 46019 | P30: 6285 | Q30: SIOUX FALLS | R30: SD | S30: MINIVAN 7 SEATS | T30: 18 | U30: 6 | V30: 69 | W30: 1 | X30: 13 | Y30: OPEN | Z30: 22334 | AB30: TRANSFORM SEARS HOME SERVICES | AD30: 0 | AE30: F | AF30: 26 | AG30: RAM | AH30: B15C | AI30: 2B56 | AJ30: 2 | AK30: 45959 | AL30: Yes
A31: 22380 | B31: Research w.Holman | C31: 28 plus days | D31: 78 | E31: GARRETT OMARA | F31: GOMARA | G31: GARRETT OMARA | H31: GOMARA | I31: 45837 | J31: No | K31: 1YV81X | L31: GARRETT OMARA | M31: HOLMAN FLEET (ARI) US MAINT | N31: 114680572 -B/R | O31: 46013 | P31: 4447 | Q31: LA CROSSE | R31: WI | S31: MINIVAN 7 SEATS | T31: 8 | U31: 8 | V31: 69 | W31: 0 | X31: 19 | Y31: OPEN | Z31: 22380 | AB31: TRANSFORM SEARS HOME SERVICES | AC31: ZLevel 4 Clients Only | AD31: 11 | AE31: F | AF31: 26 | AG31: MAZD | AH31: CX90 | AI31: 2B56 | AJ31: 2 | AK31: 45953 | AL31: No
A32: 23061 | B32: Research w.Holman | C32: 28 plus days | D32: 176 | E32: DARYL WILLIAMS | F32: RESEARCH!! | G32: Not Assigned in TPMS!! | H32: Not Assigned in TPMS!! | I32: Not Assigned in TPMS!! | J32: No | K32: 1R364N | L32: DARYL WILLIAMS | M32: HOLMAN FLEET (ARI) US INTERIM | N32: 112971632 -E/R | O32: 46005 | P32: 3826 | Q32: COVINGTON | R32: KY | S32: MINIVAN 7 SEATS | T32: 30 | U32: 30 | V32: 68 | W32: 0 | X32: 27 | Y32: OPEN | Z32: 23061 | AB32: TRANSFORM SEARS HOME SERVICES | AC32: ZLevel 4 Clients Only | AD32: 0 | AE32: F | AF32: 25 | AG32: HOND | AH32: ODYS | AI32: 2B56 | AJ32: 5 | AK32: 45855 | AL32: Yes
A33: 23147 | B33: Research w.Holman | C33: 28 plus days | D33: 118 | E33: SIDNEY GREEN | F33: SGREEN | G33: SIDNEY GREEN | H33: SGREEN | I33: 45900 | J33: No | K33: 1QTJ7V | L33: SIDNEY GREEN | M33: HOLMAN FLEET (ARI) US INTERIM | N33: 113942590 -C/R | O33: 46003 | P33: 5596 | Q33: IRONDALE | R33: AL | S33: SUV STANDARD | T33: 30 | U33: 30 | V33: 68 | W33: 0 | X33: 29 | Y33: OPEN | Z33: 23147 | AB33: TRANSFORM SEARS HOME SERVICES | AC33: ZLevel 4 Clients Only | AD33: 0 | AE33: F | AF33: 25 | AG33: FORD | AH33: ESCA | AI33: 2B56 | AJ33: 3 | AK33: 45913 | AL33: No
A34: 23150 | B34: Research w.Holman | C34: 28 plus days | D34: 148 | E34: DAVIDW JACKSON | F34: RESEARCH!! | G34: Not Assigned in TPMS!! | H34: Not Assigned in TPMS!! | I34: Not Assigned in TPMS!! | J34: No | K34: 1R52MJ | L34: DAVIDW JACKSON | M34: HOLMAN FLEET (ARI) US INTERIM | N34: 113470233 -D/R | O34: 46003 | P34: 55J3 | Q34: RIDGELAND | R34: MS | S34: SUV STANDARD | T34: 30 | U34: 30 | V34: 68 | W34: 0 | X34: 29 | Y34: OPEN | Z34: 23150 | AB34: TRANSFORM SEARS HOME SERVICES | AC34: ZLevel 4 Clients Only | AD34: 0 | AE34: F | AF34: 25 | AG34: JEEP | AH34: WRAU | AI34: 2B56 | AJ34: 4 | AK34: 45883 | AL34: No
A35: 23221 | B35: Research w.Holman | C35: 28 plus days | D35: 66 | E35: ROBERT URQUHART | F35: RURQUH | G35: ROBERT URQUHART | H35: RURQUH | I35: 36927 | J35: No | K35: 1XM7SC | L35: ROBERT URQUHART | M35: HOLMAN FLEET (ARI) US MAINT | N35: 114882853 -B/R | O35: 46025 | P35: 0913 | Q35: MESQUITE | R35: TX | S35: MINIVAN 7 SEATS | T35: 13 | U35: 3 | V35: 69 | W35: 1 | X35: 7 | Y35: OPEN | Z35: 23221 | AB35: TRANSFORM SEARS HOME SERVICES | AD35: 0 | AE35: F | AF35: 24 | AG35: CHRY | AH35: PACI | AI35: 2B56 | AJ35: 2 | AK35: 45965 | AL35: No
A36: 23254 | B36: 23254 | C36: 28 plus days | D36: 42 | E36: ALLEN ENGEN | F36: AENGEN | G36: ALLEN ENGEN | H36: AENGEN | I36: 42499 | J36: No | K36: 1W5X7P | L36: ALLEN ENGEN | M36: HOLMAN FLEET (ARI) US INTERIM | N36: 115356614 -A/R | O36: 46019 | P36: 2307 | Q36: CONCORD | R36: CA | S36: MINIVAN 7 SEATS | T36: 30 | U36: 9 | V36: 73 | W36: 2 | X36: 13 | Y36: OPEN | Z36: 23254 | AB36: TRANSFORM SEARS HOME SERVICES | AC36: ZLevel 4 Clients Only | AD36: 0 | AE36: F | AF36: 25 | AG36: MAZD | AH36: CX50 | AI36: 2B56 | AJ36: 1 | AK36: 45989 | AL36: No
A37: 23302 | B37: 23302 | C37: 28 plus days | D37: 123 | E37: KOREY MINNERD | F37: RESEARCH!! | G37: Not Assigned in TPMS!! | H37: Not Assigned in TPMS!! | I37: Not Assigned in TPMS!! | J37: No | K37: 1NCQJF | L37: KOREY MINNERD | M37: HOLMAN FLEET (ARI) US INTERIM | N37: 113854278 -C/R | O37: 45998 | P37: 65B6 | Q37: AUSTIN | R37: TX | S37: MINIVAN 7 SEATS | T37: 30 | U37: 30 | V37: 69 | W37: 1 | X37: 34 | Y37: OPEN | Z37: 23302 | AB37: TRANSFORM SEARS HOME SERVICES | AC37: ZLevel 4 Clients Only | AD37: 0 | AE37: F | AF37: 25 | AG37: FORD | AH37: F15C | AI37: 2B56 | AJ37: 3 | AK37: 45908 | AL37: No
A38: 23340 | B38: Research w.Holman | C38: 28 plus days | D38: 147 | E38: ABDUL SALAM | F38: ASALAM | G38: ABDUL SALAM | H38: ASALAM | I38: 44455 | J38: No | K38: 1QQDJ4 | L38: ABDUL SALAM | M38: HOLMAN FLEET (ARI) US INTERIM | N38: 113484720 -D/R | O38: 46004 | P38: 1692 | Q38: ALEXANDRIA | R38: VA | S38: MINIVAN 7 SEATS | T38: 30 | U38: 30 | V38: 72 | W38: 0 | X38: 28 | Y38: OPEN | Z38: 23340 | AB38: TRANSFORM SEARS HOME SERVICES | AC38: ZLevel 4 Clients Only | AD38: 0 | AE38: F | AF38: 25 | AG38: NISN | AH38: ROGU | AI38: 2B56 | AJ38: 4 | AK38: 45884 | AL38: No
A39: 23571 | B39: 23571 | C39: 28 plus days | D39: 49 | E39: SEAN JOHNSON | F39: RESEARCH!! | G39: Not Assigned in TPMS!! | H39: Not Assigned in TPMS!! | I39: Not Assigned in TPMS!! | J39: No | K39: 1W7YGV | L39: SEAN JOHNSON | M39: HOLMAN FLEET (ARI) US INTERIM | N39: 115114402 -A/R | O39: 46012 | P39: 6255 | Q39: GALESBURG | R39: IL | S39: SUV STANDARD | T39: 30 | U39: 30 | V39: 69 | W39: 0 | X39: 20 | Y39: OPEN | Z39: 23571 | AB39: TRANSFORM SEARS HOME SERVICES | AC39: ZLevel 4 Clients Only | AD39: 0 | AE39: F | AF39: 25 | AG39: MAZD | AH39: CX5 | AI39: 2B56 | AJ39: 1 | AK39: 45982 | AL39: No
A40: 23798 | B40: Research w.Holman | C40: 28 plus days | D40: 119 | E40: ROBERT POMNITZ | F40: RPOMNIT | G40: ROBERT POMNITZ | H40: RPOMNIT | I40: 45564 | J40: No | K40: 1182JN | L40: ROBERT POMNITZ | M40: HOLMAN FLEET (ARI) US MAINT | N40: 113983045 -A/R | O40: 45942 | P40: 2384 | Q40: WALNUT CREEK | R40: CA | S40: MINIVAN 7 SEATS | T40: 30 | U40: 2 | V40: 73 | W40: 3 | X40: 90 | Y40: OPEN | Z40: 23798 | AB40: TRANSFORM SEARS HOME SERVICES | AC40: ZLevel 4 Clients Only | AD40: 0 | AE40: F | AF40: 25 | AG40: CHRY | AH40: PACI | AI40: 2B56 | AJ40: 1 | AK40: 45912 | AL40: No
A41: 23844 | B41: 23844 | C41: 28 plus days | D41: 44 | E41: VINCENT WHALEY | F41: VWHALEY | G41: VINCENT WHALEY | H41: VWHALEY | I41: 45340 | J41: No | K41: 1XVC5C | L41: VINCENT WHALEY | M41: HOLMAN FLEET (ARI) US MAINT | N41: 115350058 -A/R | O41: 46017 | P41: 2666 | Q41: SUMMERVILLE | R41: SC | S41: SUV STANDARD | T41: 20 | U41: 8 | V41: 69 | W41: 1 | X41: 15 | Y41: OPEN | Z41: 23844 | AB41: TRANSFORM SEARS HOME SERVICES | AC41: ZLevel 4 Clients Only | AD41: 0 | AE41: F | AF41: 24 | AG41: FORD | AH41: EDGE | AI41: 2B56 | AJ41: 1 | AK41: 45987 | AL41: Yes
A42: 23874 | B42: 23874 | C42: 28 plus days | D42: 101 | E42: LETWAN HAND | F42: LHAND0 | G42: LETWAN HAND | H42: LHAND0 | I42: 42954 | J42: No | K42: 1VXDBR | L42: LETWAN HAND | M42: HOLMAN FLEET (ARI) US MAINT | N42: 114330605 -C/R | O42: 46020 | P42: 1517 | Q42: CALUMET CITY | R42: IL | S42: SUV STANDARD | T42: 17 | U42: 3 | V42: 69 | W42: 1 | X42: 12 | Y42: OPEN | Z42: 23874 | AB42: TRANSFORM SEARS HOME SERVICES | AC42: ZLevel 4 Clients Only | AD42: 0 | AE42: F | AF42: 24 | AG42: MITS | AH42: OUTL | AI42: 2B56 | AJ42: 3 | AK42: 45930 | AL42: No
A43: 23921 | B43: Research w.Holman | C43: 28 plus days | D43: 66 | E43: MICHAEL COLLINS | F43: RESEARCH!! | G43: Not Assigned in TPMS!! | H43: Not Assigned in TPMS!! | I43: Not Assigned in TPMS!! | J43: No | K43: 1YB2GH | L43: MICHAEL COLLINS | M43: HOLMAN FLEET (ARI) US INTERIM | N43: 114880694 -B/R | O43: 46025 | P43: 167L | Q43: WALDORF | R43: MD | S43: MINIVAN 7 SEATS | T43: 30 | U43: 30 | V43: 72 | W43: 0 | X43: 7 | Y43: OPEN | Z43: 23921 | AB43: TRANSFORM SEARS HOME SERVICES | AC43: ZLevel 4 Clients Only | AD43: 0 | AE43: F | AF43: 25 | AG43: CHEV | AH43: S15C | AI43: 2B56 | AJ43: 2 | AK43: 45965 | AL43: No
A44: 23966 | B44: 23966 | C44: 28 plus days | D44: 39 | E44: ERIC KELLY | F44: EKELLY | G44: ERIC KELLY | H44: EKELLY | I44: 44018 | J44: No | K44: 1XCFSB | L44: ERIC KELLY | M44: HOLMAN FLEET (ARI) US MAINT | N44: 115382159 | O44: 46021 | P44: 516H | Q44: WICHITA | R44: KS | S44: SUV LARGE | T44: 16 | V44: 101.54 | W44: 1 | X44: 11 | Y44: OPEN | Z44: 23966 | AB44: TRANSFORM SEARS HOME SERVICES | AD44: 0 | AE44: F | AF44: 25 | AG44: CHEV | AH44: TAHO | AI44: 2B56 | AJ44: 0 | AK44: 45992 | AL44: No
A45: 24021 | B45: 24021 | C45: 28 plus days | D45: 85 | E45: BENITO MONTIEL | F45: RESEARCH!! | G45: ALEJANDRO ZAMBRANO ARREOLA | H45: AZAMBRA | I45: 46012 | J45: No | K45: 1QYQ9X | L45: BENITO MONTIEL | M45: HOLMAN FLEET (ARI) US MAINT | N45: 114611789 -B/R | O45: 46006 | P45: 305P | Q45: BAKERSFIELD | R45: CA | S45: SUV STANDARD | T45: 25 | U45: 1 | V45: 73 | W45: 2 | X45: 26 | Y45: OPEN | Z45: 24021 | AB45: TRANSFORM SEARS HOME SERVICES | AC45: ZLevel 4 Clients Only | AD45: 1 | AE45: F | AF45: 24 | AG45: NISN | AH45: PATH | AI45: 2B56 | AJ45: 2 | AK45: 45946 | AL45: Yes
A46: 24067 | B46: Research w.Holman | C46: 28 plus days | D46: 113 | E46: BRIAN KIRK | F46: BKIRK | G46: BRIAN KIRK | H46: BKIRK | I46: 44777 | J46: No | K46: 1SFR8H | L46: BRIAN KIRK | M46: HOLMAN FLEET (ARI) US MAINT | N46: 114119303 -C/R | O46: 46008 | P46: 32KH | Q46: OXNARD | R46: CA | S46: MINIVAN 7 SEATS | T46: 30 | U46: 2 | V46: 72 | W46: 2 | X46: 24 | Y46: OPEN | Z46: 24067 | AB46: TRANSFORM SEARS HOME SERVICES | AC46: ZLevel 4 Clients Only | AD46: 0 | AE46: F | AF46: 25 | AG46: CHRY | AH46: PACI | AI46: 2B56 | AJ46: 3 | AK46: 45918 | AL46: Yes
A47: 24070 | B47: 24070 | C47: 28 plus days | D47: 65 | E47: IAN LACY | F47: ILACY | G47: IAN LACY | H47: ILACY | I47: 42534 | J47: No | K47: 1YX541 | L47: IAN LACY | M47: HOLMAN FLEET (ARI) US INTERIM | N47: 114880169 -B/R | O47: 46026 | P47: 03G9 | Q47: DECATUR | R47: GA | S47: MINIVAN 7 SEATS | T47: 30 | U47: 30 | V47: 68 | W47: 0 | X47: 6 | Y47: OPEN | Z47: 24070 | AB47: TRANSFORM SEARS HOME SERVICES | AC47: ZLevel 4 Clients Only | AD47: 0 | AE47: F | AF47: 25 | AG47: CHRY | AH47: PACI | AI47: 2B56 | AJ47: 2 | AK47: 45966 | AL47: Yes
A48: 24072 | B48: Research w.Holman | C48: 28 plus days | D48: 88 | E48: PHILLIP WILLIAMS | F48: PWILLI0 | G48: Not Assigned in TPMS!! | H48: Not Assigned in TPMS!! | I48: Not Assigned in TPMS!! | J48: No | K48: 1RK9D2 | L48: PHILLIP WILLIAMS | M48: HOLMAN FLEET (ARI) US MAINT | N48: 114540439 -B/R | O48: 46003 | P48: 2641 | Q48: COLUMBIA | R48: SC | S48: SUV STANDARD | T48: 28 | U48: 8 | V48: 69 | W48: 2 | X48: 29 | Y48: OPEN | Z48: 24072 | AB48: TRANSFORM SEARS HOME SERVICES | AD48: 1 | AE48: F | AF48: 25 | AG48: MITS | AH48: ECLX | AI48: 2B56 | AJ48: 2 | AK48: 45943 | AL48: No
A49: 24090 | B49: Research w.Holman | C49: 28 plus days | D49: 122 | E49: ADLER CADET | F49: ACADET | G49: Not Assigned in TPMS!! | H49: Not Assigned in TPMS!! | I49: Not Assigned in TPMS!! | J49: No | K49: 1Q1BWG | L49: ADLER CADET | M49: HOLMAN FLEET (ARI) US INTERIM | N49: 113910081 -C/R | O49: 46002 | P49: 2487 | Q49: JAMAICA | R49: NY | S49: MINIVAN 7 SEATS | T49: 30 | U49: 30 | V49: 86 | W49: 0 | X49: 30 | Y49: OPEN | Z49: 24090 | AB49: TRANSFORM SEARS HOME SERVICES | AC49: ZLevel 4 Clients Only | AD49: 0 | AE49: F | AF49: 24 | AG49: JEEP | AH49: WAGO | AI49: 2B56 | AJ49: 3 | AK49: 45909 | AL49: No
A50: 24114 | B50: Research w.Holman | C50: 28 plus days | D50: 56 | E50: SEAN KELLY | F50: SKELLY0 | G50: SEAN KELLY | H50: SKELLY0 | I50: 44699 | J50: No | K50: 1QPZ83 | L50: SEAN KELLY | M50: HOLMAN FLEET (ARI) US MAINT | N50: 115121449 -A/R | O50: 46005 | P50: 3801 | Q50: CINCINNATI | R50: OH | S50: SUV STANDARD | T50: 27 | U50: 5 | V50: 68 | W50: 2 | X50: 27 | Y50: OPEN | Z50: 24114 | AB50: TRANSFORM SEARS HOME SERVICES | AD50: 0 | AE50: F | AF50: 26 | AG50: CHEV | AH50: S15C | AI50: 2B56 | AJ50: 1 | AK50: 45975 | AL50: No
A51: 36020 | B51: Research w.Holman | C51: 28 plus days | D51: 58 | E51: CEDRIC ANDERSON | F51: CANDER4 | G51: CEDRIC ANDERSON | H51: CANDER4 | I51: 31574 | J51: No | K51: 1Q4Z0Z | L51: CEDRIC ANDERSON | M51: HOLMAN FLEET (ARI) US MAINT | N51: 115023135 -A/R | O51: 46003 | P51: 1677 | Q51: PRINCE FREDERICK | R51: MD | S51: SUV STANDARD | T51: 30 | U51: 4 | V51: 72 | W51: 4 | X51: 29 | Y51: OPEN | Z51: 36020 | AB51: TRANSFORM SEARS HOME SERVICES | AC51: ZLevel 4 Clients Only | AD51: 0 | AE51: F | AF51: 24 | AG51: NISN | AH51: ROGU | AI51: 2B56 | AJ51: 1 | AK51: 45973 | AL51: Yes
A52: 36024 | B52: Research w.Holman | C52: 28 plus days | D52: 101 | E52: WALTON EDWARDS | F52: WEDWAR3 | G52: WALTON EDWARDS | H52: WEDWAR3 | I52: 39538 | J52: No | K52: 1X5C8M | L52: WALTON EDWARDS | M52: HOLMAN FLEET (ARI) US MAINT | N52: 114286182 -C/R | O52: 46020 | P52: 1623 | Q52: SILVER SPRING | R52: MD | S52: SUV STANDARD | T52: 10 | U52: 10 | V52: 72 | W52: 0 | X52: 12 | Y52: OPEN | Z52: 36024 | AB52: TRANSFORM SEARS HOME SERVICES | AD52: 2 | AE52: F | AF52: 24 | AG52: HYUN | AH52: TUCS | AI52: 2B56 | AJ52: 3 | AK52: 45930 | AL52: Yes
A53: 36031 | B53: 36031 | C53: 28 plus days | D53: 39 | E53: HAROLD WHEELER | F53: HWHEELE | G53: HAROLD WHEELER | H53: HWHEELE | I53: 44658 | J53: No | K53: 1X5SLY | L53: HAROLD WHEELER | M53: HOLMAN FLEET (ARI) US MAINT | N53: 115388050 -A/R | O53: 46022 | P53: 1735 | Q53: DOVER | R53: DE | S53: MINIVAN 7 SEATS | T53: 10 | U53: 10 | V53: 72 | W53: 0 | X53: 10 | Y53: OPEN | Z53: 36031 | AB53: TRANSFORM SEARS HOME SERVICES | AC53: ZLevel 4 Clients Only | AD53: 0 | AE53: F | AF53: 26 | AG53: CHRY | AH53: PACI | AI53: 2B56 | AJ53: 1 | AK53: 45992 | AL53: No
A54: 36040 | B54: 36040 | C54: 28 plus days | D54: 60 | E54: ELISHA PEAKE | F54: EPEAKE | G54: ELISHA PEAKE | H54: EPEAKE | I54: 45914 | J54: No | K54: 1Z5YNW | L54: ELISHA PEAKE | M54: HOLMAN FLEET (ARI) US MAINT | N54: 114989138 -B/R | O54: 46030 | P54: 164U | Q54: BOWIE | R54: MD | S54: CARGO VAN | T54: 9 | U54: 9 | V54: 79.29 | W54: 0 | X54: 2 | Y54: OPEN | Z54: 36040 | AB54: TRANSFORM SEARS HOME SERVICES | AC54: ZLevel 4 Clients Only | AD54: 0 | AE54: F | AF54: 24 | AG54: FORD | AH54: EXEL | AI54: 2B56 | AJ54: 2 | AK54: 45971 | AL54: Yes
A55: 36056 | B55: 36056 | C55: 28 plus days | D55: 175 | E55: MUSTAFA EBADI | F55: MEBADI | G55: MUSTAFA EBADI | H55: MEBADI | I55: 44658 | J55: No | K55: 1QCJK7 | L55: MUSTAFA EBADI | M55: HOLMAN FLEET (ARI) US MAINT | N55: 113004417 -E/R | O55: 46004 | P55: 1610 | Q55: WOODBRIDGE | R55: VA | S55: MINIVAN 7 SEATS | T55: 30 | U55: 6 | V55: 72 | W55: 3 | X55: 28 | Y55: OPEN | Z55: 36056 | AB55: TRANSFORM SEARS HOME SERVICES | AC55: ZLevel 4 Clients Only | AD55: 0 | AE55: F | AF55: 26 | AG55: CHRY | AH55: PACI | AI55: 2B56 | AJ55: 5 | AK55: 45856 | AL55: No
A56: 36185 | B56: Research w.Holman | C56: 28 plus days | D56: 157 | E56: BRIAN TURNER | F56: BTURNER | G56: BRIAN TURNER | H56: BTURNER | I56: 45865 | J56: No | K56: 1Y22HN | L56: BRIAN TURNER | M56: HOLMAN FLEET (ARI) US INTERIM | N56: 113290586 -E/R | O56: 46023 | P56: 3838 | Q56: NEWARK | R56: OH | S56: CARGO VAN | T56: 30 | U56: 30 | V56: 75.29 | W56: 0 | X56: 9 | Y56: OPEN | Z56: 36185 | AB56: TRANSFORM SEARS HOME SERVICES | AC56: ZLevel 4 Clients Only | AD56: 0 | AE56: F | AF56: 24 | AG56: FORD | AH56: EDGE | AI56: 2B56 | AJ56: 5 | AK56: 45874 | AL56: No
A57: 36189 | B57: Research w.Holman | C57: 28 plus days | D57: 163 | E57: DUANE SOWARDF | F57: RESEARCH!! | G57: DUANE SOWARDS | H57: DSOWARD | I57: 45858 | J57: No | K57: 1YBLB5 | L57: DUANE SOWARDF | M57: HOLMAN FLEET (ARI) US INTERIM | N57: 113179642 -E/R | O57: 46023 | P57: 38B1 | Q57: CINCINNATI | R57: OH | S57: MINIVAN 7 SEATS | T57: 30 | U57: 30 | V57: 68 | W57: 0 | X57: 9 | Y57: OPEN | Z57: 36189 | AB57: TRANSFORM SEARS HOME SERVICES | AC57: ZLevel 4 Clients Only | AD57: 0 | AE57: F | AF57: 24 | AG57: MITS | AH57: OUTL | AI57: 2B56 | AJ57: 5 | AK57: 45868 | AL57: No
A58: 36215 | B58: 36215 | C58: 28 plus days | D58: 35 | E58: GEARY JORDAN | F58: GJORDAN | G58: Not Assigned in TPMS!! | H58: Not Assigned in TPMS!! | I58: Not Assigned in TPMS!! | J58: No | K58: 1YD11D | L58: GEARY JORDAN | M58: HOLMAN FLEET (ARI) US INTERIM | N58: 115447484 -A/R | O58: 46026 | P58: 2425 | Q58: NORWALK | R58: CT | S58: SUV STANDARD | T58: 30 | U58: 30 | V58: 72 | W58: 0 | X58: 6 | Y58: OPEN | Z58: 36215 | AB58: TRANSFORM SEARS HOME SERVICES | AC58: ZLevel 4 Clients Only | AD58: 0 | AE58: F | AF58: 24 | AG58: CHRY | AH58: PACI | AI58: 2B56 | AJ58: 1 | AK58: 45996 | AL58: No
A59: 36269 | B59: 36269 | C59: 28 plus days | D59: 51 | E59: WILLIAM BROWN | F59: WBROWN | G59: WILLIAM BROWN | H59: WBROWN | I59: 45319 | J59: No | K59: 1TQSDM | L59: WILLIAM BROWN | M59: HOLMAN FLEET (ARI) US MAINT | N59: 115222014 -A/R | O59: 46010 | P59: 5334 | Q59: ROCKY MOUNT | R59: NC | S59: SUV STANDARD | T59: 22 | U59: 4 | V59: 68 | W59: 3 | X59: 22 | Y59: OPEN | Z59: 36269 | AB59: TRANSFORM SEARS HOME SERVICES | AD59: 0 | AE59: F | AF59: 25 | AG59: RAM | AH59: B15C | AI59: 2B56 | AJ59: 1 | AK59: 45980 | AL59: No
A60: 36295 | B60: Research w.Holman | C60: 28 plus days | D60: 123 | E60: ALLAN EMERSON | F60: AEMERSO | G60: ALLAN EMERSON | H60: AEMERSO | I60: 44539 | J60: No | K60: 1YD022 | L60: ALLAN EMERSON | M60: HOLMAN FLEET (ARI) US MAINT | N60: 113878964-C/R -A/R | O60: 46028 | P60: 38H1 | Q60: WEST CHESTER | R60: OH | S60: SUV STANDARD | T60: 7 | U60: 7 | V60: 68 | W60: 0 | X60: 4 | Y60: OPEN | Z60: 36295 | AB60: TRANSFORM SEARS HOME SERVICES | AC60: ZLevel 4 Clients Only | AD60: 0 | AE60: F | AF60: 24 | AG60: BMW | AH60: 740I | AI60: 2B56 | AJ60: 4 | AK60: 45908 | AL60: Yes
A61: 36315 | B61: 36315 | C61: 28 plus days | D61: 56 | E61: LUIS PEREZ | F61: LPEREZ | G61: LUIS PEREZ | H61: LPEREZ | I61: 44931 | J61: No | K61: 1TYTVJ | L61: LUIS PEREZ | M61: HOLMAN FLEET (ARI) US MAINT | N61: 115117587 -A/R | O61: 46005 | P61: 3503 | Q61: BRADENTON | R61: FL | S61: MINIVAN 7 SEATS | T61: 30 | U61: 4 | V61: 69 | W61: 2 | X61: 27 | Y61: OPEN | Z61: 36315 | AB61: TRANSFORM SEARS HOME SERVICES | AC61: ZLevel 4 Clients Only | AD61: 0 | AE61: F | AF61: 25 | AG61: CHRY | AH61: PACI | AI61: 2B56 | AJ61: 1 | AK61: 45975 | AL61: Yes
A62: 36376 | B62: 36376 | C62: 28 plus days | D62: 31 | E62: JAIME QUINONES | F62: JQUINON | G62: JAIME QUINONES | H62: JQUINON | I62: 45291 | J62: No | K62: 1NQC79 | L62: JAIME QUINONES | M62: HOLMAN FLEET (ARI) US MAINT | N62: 115510370 | O62: 46000 | P62: 10M2 | Q62: SALEM | R62: NH | S62: SUV STANDARD | T62: 30 | U62: 14 | V62: 69 | W62: 2 | X62: 32 | Y62: OPEN | Z62: 36376 | AB62: TRANSFORM SEARS HOME SERVICES | AC62: ZLevel 4 Clients Only | AD62: 2 | AE62: F | AF62: 24 | AG62: NISN | AH62: ROGU | AI62: 2B56 | AJ62: 0 | AK62: 46000 | AL62: No
A63: 36386 | B63: 36386 | C63: 28 plus days | D63: 30 | E63: V DAL TUIOFU | F63: RESEARCH!! | G63: Not Assigned in TPMS!! | H63: Not Assigned in TPMS!! | I63: Not Assigned in TPMS!! | J63: No | K63: 1P44C4 | L63: V DAL TUIOFU | M63: HOLMAN FLEET (ARI) US MAINT | N63: 115519777 | O63: 46001 | P63: 48P2 | Q63: NORTH PROVIDENCE | R63: RI | S63: SUV INTERMEDIATE | T63: 30 | U63: 14 | V63: 72 | W63: 2 | X63: 31 | Y63: OPEN | Z63: 36386 | AB63: TRANSFORM SEARS HOME SERVICES | AD63: 0 | AE63: F | AF63: 23 | AG63: NISN | AH63: ROGU | AI63: 2B56 | AJ63: 0 | AK63: 46001 | AL63: Yes
A64: 36402 | B64: Research w.Holman | C64: 28 plus days | D64: 65 | E64: PETER KANTZAS | F64: PKANTZA | G64: DEWARREN GATES | H64: DGATES | I64: 46019 | J64: No | K64: 1MBDC4 | L64: PETER KANTZAS | M64: HOLMAN FLEET (ARI) US INTERIM | N64: 114934958 -A/R | O64: 45996 | P64: 2434 | Q64: SHELTON | R64: CT | S64: SUV STANDARD | T64: 30 | U64: 6 | V64: 72 | W64: 3 | X64: 36 | Y64: OPEN | Z64: 36402 | AB64: TRANSFORM SEARS HOME SERVICES | AC64: ZLevel 4 Clients Only | AD64: 0 | AE64: F | AF64: 25 | AG64: GMC | AH64: K15C | AI64: 2B56 | AJ64: 1 | AK64: 45966 | AL64: Yes
A65: 36417 | B65: Research w.Holman | C65: 28 plus days | D65: 80 | E65: MICHAEL BONOMI | F65: MBONOM | G65: KEVIN COLEMAN | H65: KCOLE17 | I65: 41526 | J65: No | K65: 1W60S6 | L65: MICHAEL BONOMI | M65: HOLMAN FLEET (ARI) US INTERIM | N65: 114667537 -B/R | O65: 46011 | P65: 4830 | Q65: NORWICH | R65: CT | S65: MINIVAN 7 SEATS | T65: 30 | U65: 30 | V65: 72 | W65: 0 | X65: 21 | Y65: OPEN | Z65: 36417 | AB65: TRANSFORM SEARS HOME SERVICES | AD65: 0 | AE65: F | AF65: 24 | AG65: NISN | AH65: ROGU | AI65: 2B56 | AJ65: 2 | AK65: 45951 | AL65: No
A66: 36438 | B66: Research w.Holman | C66: 28 plus days | D66: 73 | E66: BRIAN POWERS | F66: BPOWER8 | G66: BRIAN POWERS | H66: BPOWER8 | I66: 31432 | J66: No | K66: 1WDR16 | L66: BRIAN POWERS | M66: HOLMAN FLEET (ARI) US MAINT | N66: 114778896 -B/R | O66: 46018 | P66: 1734 | Q66: VINELAND | R66: NJ | S66: MINIVAN 7 SEATS | T66: 20 | U66: 10 | V66: 72 | W66: 1 | X66: 14 | Y66: OPEN | Z66: 36438 | AB66: TRANSFORM SEARS HOME SERVICES | AC66: ZLevel 4 Clients Only | AD66: 0 | AE66: F | AF66: 24 | AG66: FORD | AH66: EDGE | AI66: 2B56 | AJ66: 2 | AK66: 45958 | AL66: Yes
A67: 36443 | B67: Research w.Holman | C67: 28 plus days | D67: 73 | E67: DANTE EVANS | F67: RESEARCH!! | G67: DONTA EVANS | H67: DEVANS | I67: 45347 | J67: No | K67: 1X5RVP | L67: DANTE EVANS | M67: HOLMAN FLEET (ARI) US MAINT | N67: 114780836 -B/R | O67: 46018 | P67: 1805 | Q67: ELLICOTT CITY | R67: MD | S67: MINIVAN 7 SEATS | T67: 12 | U67: 12 | V67: 72 | W67: 0 | X67: 14 | Y67: OPEN | Z67: 36443 | AB67: TRANSFORM SEARS HOME SERVICES | AC67: ZLevel 4 Clients Only | AD67: 2 | AE67: F | AF67: 24 | AG67: FORD | AH67: EXPE | AI67: 2B56 | AJ67: 2 | AK67: 45958 | AL67: No
A68: 36516 | B68: 36516 | C68: 28 plus days | D68: 45 | E68: GEORGE LLOYD | F68: GLLOYD0 | G68: GEORGE LLOYD | H68: GLLOYD0 | I68: 44258 | J68: No | K68: 1VJHF7 | L68: GEORGE LLOYD | M68: HOLMAN FLEET (ARI) US MAINT | N68: 115311131 -A/R | O68: 46016 | P68: 0748 | Q68: ORANGE CITY | R68: FL | S68: MINIVAN 7 SEATS | T68: 19 | U68: 5 | V68: 69 | W68: 1 | X68: 16 | Y68: OPEN | Z68: 36516 | AB68: TRANSFORM SEARS HOME SERVICES | AC68: ZLevel 4 Clients Only | AD68: 0 | AE68: F | AF68: 25 | AG68: CHEV | AH68: S15C | AI68: 2B56 | AJ68: 1 | AK68: 45986 | AL68: No
A69: 36568 | B69: Research w.Holman | C69: 28 plus days | D69: 57 | E69: LUIS SOTELO | F69: LSOTELO | G69: LUIS SOTELO | H69: LSOTELO | I69: 45900 | J69: No | K69: 1Z91XB | L69: LUIS SOTELO | M69: HOLMAN FLEET (ARI) US MAINT | N69: 115111589 -B/R | O69: 46029 | P69: 3268 | Q69: INDIO | R69: CA | S69: MINIVAN 7 SEATS | T69: 16 | U69: 16 | V69: 72 | W69: 0 | X69: 3 | Y69: OPEN | Z69: 36568 | AB69: TRANSFORM SEARS HOME SERVICES | AC69: ZLevel 4 Clients Only | AD69: 0 | AE69: F | AF69: 24 | AG69: TOYO | AH69: CAMR | AI69: 2B56 | AJ69: 2 | AK69: 45974 | AL69: No
A70: 36597 | B70: Research w.Holman | C70: 28 plus days | D70: 119 | E70: STEPHEN MEAD | F70: SMEAD | G70: STEPHEN MEAD | H70: SMEAD | I70: 44546 | J70: No | K70: 1YC5Z3 | L70: STEPHEN MEAD | M70: HOLMAN FLEET (ARI) US MAINT | N70: 113978116 -C/R | O70: 46028 | P70: 20N7 | Q70: KALAMAZOO | R70: MI | S70: MINIVAN 7 SEATS | T70: 10 | U70: 1 | V70: 69 | W70: 1 | X70: 4 | Y70: OPEN | Z70: 36597 | AB70: TRANSFORM SEARS HOME SERVICES | AC70: ZLevel 4 Clients Only | AD70: 0 | AE70: F | AF70: 26 | AG70: DODG | AH70: DURA | AI70: 2B56 | AJ70: 3 | AK70: 45912 | AL70: No
A71: 36604 | B71: 36604 | C71: 28 plus days | D71: 36 | E71: JEREMY ALVAREZ | F71: JALVARE | G71: JEREMY ALVAREZ | H71: JALVARE | I71: 45949 | J71: No | K71: 1XWQKD | L71: JEREMY ALVAREZ | M71: HOLMAN FLEET (ARI) US MAINT | N71: 115420078 -A/R | O71: 46025 | P71: 1215 | Q71: PUEBLO | R71: CO | S71: SUV STANDARD | T71: 7 | U71: 7 | V71: 72 | W71: 0 | X71: 7 | Y71: OPEN | Z71: 36604 | AB71: TRANSFORM SEARS HOME SERVICES | AC71: ZLevel 4 Clients Only | AD71: 0 | AE71: F | AF71: 25 | AG71: FORD | AH71: F15C | AI71: 2B56 | AJ71: 1 | AK71: 45995 | AL71: No
A72: 36606 | B72: 36606 | C72: 28 plus days | D72: 39 | E72: AHMADPARWIZ SAMADI | F72: RESEARCH!! | G72: AHMAD PARWIZ SAMADI | H72: ASAMAD0 | I72: 45473 | J72: No | K72: 1XY2DQ | L72: AHMADPARWIZ SAMADI | M72: HOLMAN FLEET (ARI) US MAINT | N72: 115395500 -A/R | O72: 46022 | P72: 2384 | Q72: WALNUT CREEK | R72: CA | S72: MINIVAN 7 SEATS | T72: 10 | U72: 10 | V72: 73 | W72: 0 | X72: 10 | Y72: OPEN | Z72: 36606 | AB72: TRANSFORM SEARS HOME SERVICES | AC72: ZLevel 4 Clients Only | AD72: 0 | AE72: F | AF72: 26 | AG72: CHRY | AH72: PACI | AI72: 2B56 | AJ72: 1 | AK72: 45992 | AL72: No
A73: 36637 | B73: Research w.Holman | C73: 28 plus days | D73: 157 | E73: JON WILSON | F73: RESEARCH!! | G73: Not Assigned in TPMS!! | H73: Not Assigned in TPMS!! | I73: Not Assigned in TPMS!! | J73: No | K73: 1Z3TPX | L73: JON WILSON | M73: HOLMAN FLEET (ARI) US INTERIM | N73: 113290808-A/R -A/R | O73: 46024 | P73: 5801 | Q73: MADISON | R73: IN | S73: CARGO VAN | T73: 30 | U73: 30 | V73: 75.29 | W73: 0 | X73: 8 | Y73: OPEN | Z73: 36637 | AB73: TRANSFORM SEARS HOME SERVICES | AC73: ZLevel 4 Clients Only | AD73: 0 | AE73: F | AF73: 25 | AG73: VOLK | AH73: ATLA | AI73: 2B56 | AJ73: 1 | AK73: 45874 | AL73: No
A74: 36675 | B74: Research w.Holman | C74: 28 plus days | D74: 92 | E74: OJ BLEUS | F74: OBLEUS | G74: OJ BLEUS | H74: OBLEUS | I74: 45592 | J74: No | K74: 1P73LW | L74: OJ BLEUS | M74: HOLMAN FLEET (ARI) US INTERIM | N74: 114843951 -B/R | O74: 45999 | P74: 4373 | Q74: JACKSONVILLE | R74: FL | S74: MINIVAN 7 SEATS | T74: 30 | U74: 10 | V74: 68 | W74: 3 | X74: 33 | Y74: OPEN | Z74: 36675 | AB74: TRANSFORM SEARS HOME SERVICES | AC74: ZLevel 4 Clients Only | AD74: 0 | AE74: F | AF74: 25 | AG74: GMC | AH74: K15C | AI74: 2B56 | AJ74: 2 | AK74: 45939 | AL74: Yes
A75: 36770 | B75: 36770 | C75: 28 plus days | D75: 51 | E75: LOUIS SMITH | F75: LSMI314 | G75: LOUIS SMITH | H75: LSMI314 | I75: 39052 | J75: No | K75: 1T8N87 | L75: LOUIS SMITH | M75: HOLMAN FLEET (ARI) US MAINT | N75: 115183625 -A/R | O75: 46010 | P75: 062H | Q75: RICHMOND | R75: TX | S75: SUV STANDARD | T75: 27 | U75: 4 | V75: 69 | W75: 3 | X75: 22 | Y75: OPEN | Z75: 36770 | AB75: TRANSFORM SEARS HOME SERVICES | AC75: ZLevel 4 Clients Only | AD75: 0 | AE75: F | AF75: 23 | AG75: NISN | AH75: ROGU | AI75: 2B56 | AJ75: 1 | AK75: 45980 | AL75: No
A76: 36777 | B76: 36777 | C76: 28 plus days | D76: 86 | E76: ERIC DAVIS | F76: EDAVIS0 | G76: ERIC DAVIS | H76: EDAVIS0 | I76: 44180 | J76: No | K76: 1NHXYN | L76: ERIC DAVIS | M76: HOLMAN FLEET (ARI) US MAINT | N76: 114581168 -B/R | O76: 46000 | P76: 6516 | Q76: AMARILLO | R76: TX | S76: SUV STANDARD | T76: 30 | U76: 2 | V76: 69 | W76: 4 | X76: 32 | Y76: OPEN | Z76: 36777 | AB76: TRANSFORM SEARS HOME SERVICES | AC76: ZLevel 4 Clients Only | AD76: 0 | AE76: F | AF76: 25 | AG76: MAZD | AH76: CX5 | AI76: 2B56 | AJ76: 2 | AK76: 45945 | AL76: No
A77: 36785 | B77: Research w.Holman | C77: 28 plus days | D77: 30 | E77: BEN GEBBERT | F77: BGEBBER | G77: BEN GEBBERT | H77: BGEBBER | I77: 45900 | J77: No | K77: 1P9412 | L77: BEN GEBBERT | M77: HOLMAN FLEET (ARI) US ACCIDENT | N77: 115504386 | O77: 46001 | P77: 6552 | Q77: BASTROP | R77: TX | S77: MINIVAN 7 SEATS | T77: 30 | U77: 7 | V77: 69 | W77: 3 | X77: 31 | Y77: OPEN | Z77: 36785 | AB77: TRANSFORM SEARS HOME SERVICES | AC77: ZLevel 4 Clients Only | AD77: 0 | AE77: F | AF77: 25 | AG77: CHRY | AH77: PACI | AI77: 2B56 | AJ77: 0 | AK77: 46001 | AL77: No
A78: 36845 | B78: 36845 | C78: 28 plus days | D78: 29 | E78: JONATHON DICKSON | F78: JDICKSO | G78: JONATHON DICKSON | H78: JDICKSO | I78: 45424 | J78: No | K78: 1PSRJH | L78: JONATHON DICKSON | M78: HOLMAN FLEET (ARI) US MAINT | N78: 115586848 | O78: 46002 | P78: 4553 | Q78: LEWISTON | R78: ID | S78: CARGO VAN | T78: 30 | U78: 14 | V78: 75.29 | W78: 1 | X78: 30 | Y78: OPEN | Z78: 36845 | AB78: TRANSFORM SEARS HOME SERVICES | AD78: 0 | AE78: F | AF78: 26 | AG78: CHRY | AH78: PACI | AI78: 2B56 | AJ78: 0 | AK78: 46002 | AL78: No
A79: 36882 | B79: Research w.Holman | C79: 28 plus days | D79: 167 | E79: RENE CORTEZ | F79: RCORTEZ | G79: RENE CORTEZ | H79: RCORTEZ | I79: 45627 | J79: No | K79: 1VDSH5 | L79: RENE CORTEZ | M79: HOLMAN FLEET (ARI) US INTERIM | N79: 113155891 -E/R | O79: 46014 | P79: 52H1 | Q79: LAREDO | R79: TX | S79: SUV INTERMEDIATE | T79: 30 | U79: 30 | V79: 69 | W79: 0 | X79: 18 | Y79: OPEN | Z79: 36882 | AB79: TRANSFORM SEARS HOME SERVICES | AC79: ZLevel 4 Clients Only | AD79: 0 | AE79: F | AF79: 25 | AG79: HYUN | AH79: TUCS | AI79: 2B56 | AJ79: 5 | AK79: 45864 | AL79: Yes
A80: 36894 | B80: 36894 | C80: 28 plus days | D80: 51 | E80: CHRISTOPHE FELTS | F80: RESEARCH!! | G80: CHRISTOPHER FELTS | H80: CFELTS | I80: 45725 | J80: No | K80: 1WC60G | L80: CHRISTOPHE FELTS | M80: HOLMAN FLEET (ARI) US MAINT | N80: 115214379 -A/R | O80: 46010 | P80: 5225 | Q80: SAN ANTONIO | R80: TX | S80: MINIVAN 7 SEATS | T80: 22 | U80: 5 | V80: 69 | W80: 1 | X80: 22 | Y80: OPEN | Z80: 36894 | AB80: TRANSFORM SEARS HOME SERVICES | AC80: ZLevel 4 Clients Only | AD80: 0 | AE80: F | AF80: 24 | AG80: NISN | AH80: ALTI | AI80: 2B56 | AJ80: 1 | AK80: 45980 | AL80: No
A81: 36902 | B81: Research w.Holman | C81: 28 plus days | D81: 186 | E81: ROBERT SAUCEDO | F81: RSAUCED | G81: Not Assigned in TPMS!! | H81: Not Assigned in TPMS!! | I81: Not Assigned in TPMS!! | J81: No | K81: 1PY2N5 | L81: ROBERT SAUCEDO | M81: HOLMAN FLEET (ARI) US MAINT | N81: 112795881 -E/R | O81: 46004 | P81: 5220 | Q81: SAN ANTONIO | R81: TX | S81: MINIVAN 7 SEATS | T81: 30 | U81: 9 | V81: 69 | W81: 2 | X81: 28 | Y81: OPEN | Z81: 36902 | AB81: TRANSFORM SEARS HOME SERVICES | AC81: ZLevel 4 Clients Only | AD81: 0 | AE81: F | AF81: 24 | AG81: HYUN | AH81: TUCS | AI81: 2B56 | AJ81: 5 | AK81: 45845 | AL81: No
A82: 36982 | B82: Research w.Holman | C82: 28 plus days | D82: 192 | E82: WILLIAM VOKAL | F82: WVOKAL | G82: Not Assigned in TPMS!! | H82: Not Assigned in TPMS!! | I82: Not Assigned in TPMS!! | J82: No | K82: 1WG4Z0 | L82: WILLIAM VOKAL | M82: HOLMAN FLEET (ARI) US INTERIM | N82: 112736328 -F/R | O82: 46019 | P82: 6351 | Q82: BISMARCK | R82: ND | S82: MINIVAN 7 SEATS | T82: 30 | U82: 30 | V82: 69 | W82: 0 | X82: 13 | Y82: OPEN | Z82: 36982 | AB82: TRANSFORM SEARS HOME SERVICES | AC82: ZLevel 4 Clients Only | AD82: 0 | AE82: F | AF82: 25 | AG82: CHRY | AH82: PACI | AI82: 2B56 | AJ82: 6 | AK82: 45839 | AL82: No
A83: 37032 | B83: 37032 | C83: 28 plus days | D83: 38 | E83: SCOTTY BROWN | F83: SBROWN5 | G83: SCOTTY BROWN | H83: SBROWN5 | I83: 44406 | J83: No | K83: 1XJJCB | L83: SCOTTY BROWN | M83: HOLMAN FLEET (ARI) US MAINT | N83: 115381560 -A/R | O83: 46023 | P83: 2105 | Q83: SUFFOLK | R83: VA | S83: SUV STANDARD | T83: 11 | U83: 11 | V83: 69 | W83: 0 | X83: 9 | Y83: OPEN | Z83: 37032 | AB83: TRANSFORM SEARS HOME SERVICES | AC83: ZLevel 4 Clients Only | AD83: 0 | AE83: F | AF83: 25 | AG83: FORD | AH83: F15C | AI83: 2B56 | AJ83: 1 | AK83: 45993 | AL83: No
A84: 37055 | B84: 37055 | C84: 28 plus days | D84: 44 | E84: JASON FLETCHER | F84: JFLETCH | G84: JASON FLETCHER | H84: JFLETCH | I84: 30426 | J84: No | K84: 1W6Y7H | L84: JASON FLETCHER | M84: HOLMAN FLEET (ARI) US MAINT | N84: 115320249 -A/R | O84: 46017 | P84: 072B | Q84: MERRITT ISLAND | R84: FL | S84: MINIVAN 7 SEATS | T84: 12 | U84: 2 | V84: 69 | W84: 1 | X84: 15 | Y84: OPEN | Z84: 37055 | AB84: TRANSFORM SEARS HOME SERVICES | AC84: ZLevel 4 Clients Only | AD84: 3 | AE84: F | AF84: 26 | AG84: CHEV | AH84: S15C | AI84: 2B56 | AJ84: 1 | AK84: 45987 | AL84: No
A85: 37057 | B85: 37057 | C85: 28 plus days | D85: 38 | E85: TRENT MATTHEWS | F85: TMATTHE | G85: TRENT MATTHEWS | H85: TMATTHE | I85: 45935 | J85: No | K85: 1X3VVX | L85: TRENT MATTHEWS | M85: HOLMAN FLEET (ARI) US MAINT | N85: 115408206 -A/R | O85: 46023 | P85: 5334 | Q85: ROCKY MOUNT | R85: NC | S85: SUV STANDARD | T85: 6 | U85: 6 | V85: 68 | W85: 0 | X85: 9 | Y85: OPEN | Z85: 37057 | AB85: TRANSFORM SEARS HOME SERVICES | AC85: ZLevel 4 Clients Only | AD85: 3 | AE85: F | AF85: 25 | AG85: CHEV | AH85: TRAX | AI85: 2B56 | AJ85: 1 | AK85: 45993 | AL85: No
A86: 37125 | B86: Research w.Holman | C86: 28 plus days | D86: 60 | E86: KAREEM WILLIAMS | F86: KWILLI1 | G86: KAREEM WILLIAMS | H86: KWILLI1 | I86: 45900 | J86: No | K86: 1P4V85 | L86: KAREEM WILLIAMS | M86: HOLMAN FLEET (ARI) US MAINT | N86: 115001014 -A/R | O86: 46001 | P86: 5579 | Q86: GULFPORT | R86: MS | S86: MINIVAN 7 SEATS | T86: 30 | U86: 7 | V86: 68 | W86: 2 | X86: 31 | Y86: OPEN | Z86: 37125 | AB86: TRANSFORM SEARS HOME SERVICES | AC86: ZLevel 4 Clients Only | AD86: 0 | AE86: F | AF86: 25 | AG86: MAZD | AH86: CX5 | AI86: 2B56 | AJ86: 1 | AK86: 45971 | AL86: No
A87: 37139 | B87: 37139 | C87: 28 plus days | D87: 185 | E87: ANTHONY PARSONS | F87: RESEARCH!! | G87: ANTHONY PARSON | H87: APARSO0 | I87: 43782 | J87: No | K87: 1YWQGW | L87: ANTHONY PARSONS | M87: HOLMAN FLEET (ARI) US MAINT | N87: 112794061 -F/R | O87: 46023 | P87: 55C2 | Q87: STARKVILLE | R87: MS | S87: SUV STANDARD | T87: 9 | U87: 9 | V87: 68 | W87: 0 | X87: 9 | Y87: OPEN | Z87: 37139 | AB87: TRANSFORM SEARS HOME SERVICES | AC87: ZLevel 4 Clients Only | AD87: 0 | AE87: F | AF87: 24 | AG87: DODG | AH87: DURA | AI87: 2B56 | AJ87: 6 | AK87: 45846 | AL87: No
A88: 37230 | B88: 37230 | C88: 28 plus days | D88: 179 | E88: PHILIP CAMPBELL | F88: PCAMPBE | G88: PHILIP CAMPBELL | H88: PCAMPBE | I88: 45207 | J88: No | K88: 1P9VT2 | L88: PHILIP CAMPBELL | M88: HOLMAN FLEET (ARI) US MAINT | N88: 112935871 -E/R | O88: 46002 | P88: 0907 | Q88: N RICHLND HLS | R88: TX | S88: SUV STANDARD | T88: 27 | U88: 1 | V88: 69 | W88: 2 | X88: 30 | Y88: OPEN | Z88: 37230 | AB88: TRANSFORM SEARS HOME SERVICES | AC88: ZLevel 4 Clients Only | AD88: 3 | AE88: F | AF88: 24 | AG88: CHEV | AH88: EQUI | AI88: 2B56 | AJ88: 5 | AK88: 45852 | AL88: No
A89: 37241 | B89: 37241 | C89: 28 plus days | D89: 186 | E89: MATTHEW WILLIAMSON | F89: MWILLI1 | G89: MICHAEL JONES | H89: MJONE10 | I89: 46005 | J89: No | K89: 1Y7WGK | L89: MATTHEW WILLIAMSON | M89: HOLMAN FLEET (ARI) US INTERIM | N89: 112775449 -F/R | O89: 46025 | P89: 5586 | Q89: MILTON | R89: FL | S89: MINIVAN 7 SEATS | T89: 30 | U89: 30 | V89: 68 | W89: 0 | X89: 7 | Y89: OPEN | Z89: 37241 | AB89: TRANSFORM SEARS HOME SERVICES | AC89: ZLevel 4 Clients Only | AD89: 0 | AE89: F | AF89: 24 | AG89: CHRY | AH89: PACI | AI89: 2B56 | AJ89: 6 | AK89: 45845 | AL89: No
A90: 37243 | B90: Research w.Holman | C90: 28 plus days | D90: 147 | E90: OMAR HERNANDEZ | F90: RESEARCH!! | G90: Not Assigned in TPMS!! | H90: Not Assigned in TPMS!! | I90: Not Assigned in TPMS!! | J90: No | K90: 1RBH8C | L90: OMAR HERNANDEZ | M90: HOLMAN FLEET (ARI) US INTERIM | N90: 113470092 -D/R | O90: 46004 | P90: 3578 | Q90: ESTERO | R90: FL | S90: SUV STANDARD | T90: 30 | U90: 30 | V90: 69 | W90: 0 | X90: 28 | Y90: OPEN | Z90: 37243 | AB90: TRANSFORM SEARS HOME SERVICES | AC90: ZLevel 4 Clients Only | AD90: 0 | AE90: F | AF90: 25 | AG90: NISN | AH90: ROGU | AI90: 2B56 | AJ90: 4 | AK90: 45884 | AL90: No
A91: 37268 | B91: 37268 | C91: 28 plus days | D91: 42 | E91: JUSTIN WILBER | F91: JWILBER | G91: JUSTIN WILBER | H91: JWILBER | I91: 45907 | J91: No | K91: 1WGZQH | L91: JUSTIN WILBER | M91: HOLMAN FLEET (ARI) US INTERIM | N91: 115353491 -A/R | O91: 46019 | P91: 5585 | Q91: LAGRANGE | R91: GA | S91: SUV STANDARD | T91: 30 | U91: 30 | V91: 68 | W91: 0 | X91: 13 | Y91: OPEN | Z91: 37268 | AB91: TRANSFORM SEARS HOME SERVICES | AC91: ZLevel 4 Clients Only | AD91: 0 | AE91: F | AF91: 24 | AG91: RAM | AH91: C15Q | AI91: 2B56 | AJ91: 1 | AK91: 45989 | AL91: No
A92: 37275 | B92: Research w.Holman | C92: 28 plus days | D92: 57 | E92: LUTHER COOPER | F92: RESEARCH!! | G92: LUTHER ERBY COOPER | H92: LERBYCO | I92: 45032 | J92: No | K92: 1SJGFL | L92: LUTHER COOPER | M92: HOLMAN FLEET (ARI) US MAINT | N92: 115099211 -A/R | O92: 46004 | P92: 5597 | Q92: BIRMINGHAM | R92: AL | S92: CARGO VAN | T92: 30 | U92: 7 | V92: 75.29 | W92: 2 | X92: 28 | Y92: OPEN | Z92: 37275 | AB92: TRANSFORM SEARS HOME SERVICES | AC92: ZLevel 4 Clients Only | AD92: 0 | AE92: F | AF92: 24 | AG92: MITS | AH92: OUTL | AI92: 2B56 | AJ92: 1 | AK92: 45974 | AL92: No
A93: 37309 | B93: 37309 | C93: 28 plus days | D93: 29 | E93: BRANDON DRAZIC | F93: BDRAZIC | G93: BRANDON DRAZIC | H93: BDRAZIC | I93: 45928 | J93: No | K93: 1PPSRH | L93: BRANDON DRAZIC | M93: HOLMAN FLEET (ARI) US MAINT | N93: 115572245 | O93: 46002 | P93: 24C2 | Q93: ALBANY | R93: NY | S93: MINIVAN 7 SEATS | T93: 30 | U93: 14 | V93: 73 | W93: 1 | X93: 30 | Y93: OPEN | Z93: 37309 | AB93: TRANSFORM SEARS HOME SERVICES | AC93: ZLevel 4 Clients Only | AD93: 0 | AE93: F | AF93: 24 | AG93: GMC | AH93: TERR | AI93: 2B56 | AJ93: 0 | AK93: 46002 | AL93: No
A94: 37359 | B94: Research w.Holman | C94: 28 plus days | D94: 148 | E94: JOSHUA JACOBS | F94: JJACOBS | G94: Not Assigned in TPMS!! | H94: Not Assigned in TPMS!! | I94: Not Assigned in TPMS!! | J94: No | K94: 1Q4YQD | L94: JOSHUA JACOBS | M94: HOLMAN FLEET (ARI) US INTERIM | N94: 113470133 -D/R | O94: 46003 | P94: 06C6 | Q94: NEDERLAND | R94: TX | S94: SUV STANDARD | T94: 30 | U94: 30 | V94: 69 | W94: 0 | X94: 29 | Y94: OPEN | Z94: 37359 | AB94: TRANSFORM SEARS HOME SERVICES | AC94: ZLevel 4 Clients Only | AD94: 0 | AE94: F | AF94: 25 | AG94: HYUN | AH94: TUCS | AI94: 2B56 | AJ94: 4 | AK94: 45883 | AL94: No
A95: 46017 | B95: 46017 | C95: 28 plus days | D95: 53 | E95: JAVEN MITT | F95: JMITT | G95: STERLING SZULWACH | H95: SSZULWA | I95: 45767 | J95: No | K95: 1RXSSG | L95: JAVEN MITT | M95: HOLMAN FLEET (ARI) US INTERIM | N95: 115162008 -A/R | O95: 46008 | P95: 1435 | Q95: THIBODAUX | R95: LA | S95: MINIVAN 7 SEATS | T95: 30 | U95: 30 | V95: 68 | W95: 0 | X95: 24 | Y95: OPEN | Z95: 46017 | AB95: TRANSFORM SEARS HOME SERVICES | AC95: ZLevel 4 Clients Only | AD95: 0 | AE95: F | AF95: 25 | AG95: NISN | AH95: ROGU | AI95: 2B56 | AJ95: 1 | AK95: 45978 | AL95: No
A96: 46071 | B96: 46071 | C96: 28 plus days | D96: 29 | E96: RAUL CERVANTES | F96: RCERVAN | G96: RAUL CERVANTES | H96: RCERVAN | I96: 45984 | J96: No | K96: 1PNGMK | L96: RAUL CERVANTES | M96: HOLMAN FLEET (ARI) US MAINT | N96: 115562612 | O96: 46002 | P96: 2392 | Q96: RICHMOND | R96: CA | S96: SUV STANDARD | T96: 30 | U96: 14 | V96: 73 | W96: 2 | X96: 30 | Y96: OPEN | Z96: 46071 | AB96: TRANSFORM SEARS HOME SERVICES | AD96: 0 | AE96: F | AF96: 25 | AG96: CHEV | AH96: TBLZ | AI96: 2B56 | AJ96: 0 | AK96: 46002 | AL96: No
A97: 46141 | B97: Research w.Holman | C97: 28 plus days | D97: 125 | E97: WILLIE HYNES | F97: WHYNES | G97: MANUEL VIVEROS | H97: MVIVERO | I97: 45963 | J97: No | K97: 1NS2HK | L97: WILLIE HYNES | M97: HOLMAN FLEET (ARI) US INTERIM | N97: 113854159 -C/R | O97: 45996 | P97: 19P7 | Q97: PLYMOUTH | R97: MN | S97: MINIVAN 7 SEATS | T97: 30 | U97: 30 | V97: 69 | W97: 1 | X97: 36 | Y97: OPEN | Z97: 46141 | AB97: TRANSFORM SEARS HOME SERVICES | AC97: ZLevel 4 Clients Only | AD97: 0 | AE97: F | AF97: 25 | AG97: CHEV | AH97: TRAX | AI97: 2B56 | AJ97: 3 | AK97: 45906 | AL97: No
A98: 46174 | B98: 46174 | C98: 28 plus days | D98: 112 | E98: VLADISLAV TAVYANSKYY | F98: VTAVYAN | G98: Not Assigned in TPMS!! | H98: Not Assigned in TPMS!! | I98: Not Assigned in TPMS!! | J98: No | K98: 1RW4Y3 | L98: VLADISLAV TAVYANSKYY | M98: HOLMAN FLEET (ARI) US INTERIM | N98: 113540670 -D/R | O98: 46008 | P98: 4447 | Q98: LA CROSSE | R98: WI | S98: SUV INTERMEDIATE | T98: 30 | U98: 30 | V98: 69 | W98: 0 | X98: 24 | Y98: OPEN | Z98: 46174 | AB98: TRANSFORM SEARS HOME SERVICES | AC98: ZLevel 4 Clients Only | AD98: 0 | AE98: F | AF98: 25 | AG98: FORD | AH98: ESCA | AI98: 2B56 | AJ98: 4 | AK98: 45919 | AL98: No
A99: 46205 | B99: Research w.Holman | C99: 28 plus days | D99: 147 | E99: NICHOLAS ALMARAZ | F99: NALMARA | G99: NICHOLAS ALMARAZ | H99: NALMARA | I99: 45067 | J99: No | K99: 1Q8NHC | L99: NICHOLAS ALMARAZ | M99: HOLMAN FLEET (ARI) US MAINT | N99: 113490416 -D/R | O99: 46004 | P99: 5290 | Q99: VICTORIA | R99: TX | S99: SUV STANDARD | T99: 30 | U99: 3 | V99: 69 | W99: 6 | X99: 28 | Y99: OPEN | Z99: 46205 | AB99: TRANSFORM SEARS HOME SERVICES | AC99: ZLevel 4 Clients Only | AD99: 0 | AE99: F | AF99: 24 | AG99: FORD | AH99: EDGE | AI99: 2B56 | AJ99: 4 | AK99: 45884 | AL99: No
A100: 46227 | B100: 46227 | C100: 28 plus days | D100: 45 | E100: HILARIO GONZALES | F100: RESEARCH!! | G100: HILARIO GONZALES JR | H100: HGONZA0 | I100: 44336 | J100: No | K100: 1WLY98 | L100: HILARIO GONZALES | M100: HOLMAN FLEET (ARI) US MAINT | N100: 115312601 -A/R | O100: 46016 | P100: 5281 | Q100: CORPUS CHRISTI | R100: TX | S100: SUV STANDARD | T100: 21 | U100: 9 | V100: 69 | W100: 1 | X100: 16 | Y100: OPEN | Z100: 46227 | AB100: TRANSFORM SEARS HOME SERVICES | AC100: ZLevel 4 Clients Only | AD100: 0 | AE100: F | AF100: 25 | AG100: CHRY | AH100: PACI | AI100: 2B56 | AJ100: 1 | AK100: 45986 | AL100: No
A101: 46245 | B101: Research w.Holman | C101: 28 plus days | D101: 77 | E101: ELI SOCKEY | F101: ESOCKEY | G101: ELI SOCKEY | H101: ESOCKEY | I101: 43284 | J101: No | K101: 1J4LFY | L101: ELI SOCKEY | M101: HOLMAN FLEET (ARI) US MAINT | N101: 114736181 -A/R | O101: 45983 | P101: 5175 | Q101: FAYETTEVILLE | R101: AR | S101: MINIVAN 7 SEATS | T101: 30 | U101: 9 | V101: 68 | W101: 2 | X101: 49 | Y101: OPEN | Z101: 46245 | AB101: TRANSFORM SEARS HOME SERVICES | AC101: ZLevel 4 Clients Only | AD101: 0 | AE101: F | AF101: 24 | AG101: HYUN | AH101: TUCS | AI101: 2B56 | AJ101: 1 | AK101: 45954 | AL101: No
...

Sheet Summary
A1: Holman Rental Reporting - primarily used for non-Enterprise rentals
A3: Is Enterprise | B3: NotEnterprise | C3: Not Enterprise
A4: Duplicate? | B4: No | C4: Not a Duplicate
A5: Check Enterprise Open anyway | B5: NotonEnterpriseReporting | C5: Not on Enterprise Reporting
A7: Row Labels | B7: Rentals Open | C7: % to all Rentals | D7: Average of Days PO is open
A8: 28 plus days | B8: 12 | C8: 0.8 | D8: 66.583333
A9: Less than 14 days | B9: 3 | C9: 0.2 | D9: 6
A10: Grand Total | B10: 15 | C10: 1 | D10: 54.466667
A27: Enterprise Rentals - OPEN
A30: Is on Holman Rental | B30: (All)
A31: Ticket Status | B31: OPEN | C31: Enterprise OPEN
A32: Duplicate | B32: No | C32: Not a Duplicate
A34: Row Labels | B34: Rentals Open | C34: % to all Rentals | D34: Average of Days Open
A35: 28 plus days | B35: 180 | C35: 0.56782334 | D35: 112.37778
A36: 21 plus days | B36: 22 | C36: 0.069400631 | D36: 23.909091
A37: 14 plus days | B37: 28 | C37: 0.088328076 | D37: 16.25
A38: Less than 14 days | B38: 87 | C38: 0.27444795 | D38: 5.6781609
A39: Grand Total | B39: 317 | C39: 1 | D39: 68.463722
A69: TOTAL RENTALS OPEN
A71: Category | B71: Rentals Open | C71: % to all Rentals
A72: 28 plus days | B72: =IFERROR(GETPIVOTDATA("Rentals Open",$A$7,"Category of Days Open",A72),0)+IFERROR(GETPIVOTDATA("Rentals Open",$A$34,"Days Open Category",A72),0) -> 192 | C72: =B72/$B$76 -> 0.57831325
A73: 21 plus days | B73: =IFERROR(GETPIVOTDATA("Rentals Open",$A$7,"Category of Days Open",A73),0)+IFERROR(GETPIVOTDATA("Rentals Open",$A$34,"Days Open Category",A73),0) -> 22 | C73: =B73/$B$76 -> 0.06626506
A74: 14 plus days | B74: =IFERROR(GETPIVOTDATA("Rentals Open",$A$7,"Category of Days Open",A74),0)+IFERROR(GETPIVOTDATA("Rentals Open",$A$34,"Days Open Category",A74),0) -> 28 | C74: =B74/$B$76 -> 0.084337349
A75: Less than 14 days | B75: =IFERROR(GETPIVOTDATA("Rentals Open",$A$7,"Category of Days Open",A75),0)+IFERROR(GETPIVOTDATA("Rentals Open",$A$34,"Days Open Category",A75),0) -> 90 | C75: =B75/$B$76 -> 0.27108434
A76: Grand Total | B76: =SUM(B72:B75) -> 332 | C76: =B76/$B$76 -> 1

Sheet Enterprise
A1: Truck Number | B1: Is on Holman Rental | C1: Days Open Category | D1: Days Open | E1: Rental under Name: | F1: Rental Tech Enterprise ID | G1: Truck Assigned to in TPMS | H1: Truck assigned to in TPMS Enterprise ID | I1: LU Employment Start Date in TPMS | J1: Duplicate | K1: ECARS 2.0 Tkt Nbr | L1: Renter Name | M1: Claims Office Name | N1: Claim Number | O1: Rental Start Date | P1: Renting Branch | Q1: Renting City Name | R1: Renting State | S1: Car Class Authorized Description | T1: Days Authorized | U1: Initial Days Authorized | V1: Rate Authorized | W1: Number of Extensions | X1: Rental Days | Y1: Ticket Status | Z1: Vehicle Number | AA1: PO Number | AB1: Client Company Name | AC1: Client Company | AD1: Days Behind | AE1: Rate Level | AF1: Rented Veh Year | AG1: Rented Veh Make | AH1: Rented Veh Model | AI1: ARI20 Client Number | AJ1: Number of Rewrites | AK1: Original Start Date | AL1: Repairs Complete
A2: =TRIM(Z2) -> 06121 | B2: =IFERROR(VLOOKUP(Table3[[#This Row],[Truck Number]], HolmanReport!C:C,1,0), "Research w.Holman") -> 06121 | C2: =IF(Table3[[#This Row],[Days Open]]>27, "28 plus days", IF(Table3[[#This Row],[Days Open]]>20, "21 plus days", IF(Table3[[#This Row],[Days Open]]>13, "14 plus days", "Less than 14 days"))) -> Less than 14 days | D2: =IF(Table3[[#This Row],[Ticket Status]]="OPEN", SUM((TODAY())-Table3[[#This Row],[Original Start Date]]), "Not Open") -> 9 | E2: =Table3[[#This Row],[Renter Name]] -> SOLOMON FESSHAYE | F2: =IFERROR(VLOOKUP(Table3[[#This Row],[Rental under Name: ]], 'TPMS-Auto'!C:G,5,0), "RESEARCH!!") -> SFESSHA | G2: =IFERROR(VLOOKUP(Table3[[#This Row],[Truck Number]],'TPMS-Auto'!$A:$K,3, 0), "Not Assigned in TPMS!!") -> SOLOMON FESSHAYE | H2: =IFERROR(VLOOKUP(Table3[[#This Row],[Truck Number]],'TPMS-Auto'!$A:$K,7, 0), "Not Assigned in TPMS!!") -> SFESSHA | I2: =IFERROR(VLOOKUP(Table3[[#This Row],[Truck Number]], Query1[[TRUCK_LU]:[Service Date]],25, 0), "Not Assigned in TPMS!!") -> Not Assigned in TPMS!! | J2: =IF(E2=E1, "Yes", "No") -> No | K2: 2GWR6M | L2: SOLOMON FESSHAYE | M2: HOLMAN FLEET (ARI) US MAINT | N2: 116925727 | O2: 46077 | P2: 1610 | Q2: WOODBRIDGE | R2: VA | S2: SUV STANDARD | T2: 7 | U2: 7 | V2: 72 | W2: 0 | X2: 10 | Y2: OPEN | Z2: 06121 | AB2: TRANSFORM SEARS HOME SERVICES | AC2: ZLevel 4 Clients Only | AD2: 3 | AE2: F | AF2: 25 | AG2: MITS | AH2: OUTL | AI2: 2B56 | AJ2: 0 | AK2: 46077 | AL2: No
A3: =TRIM(Z3) -> 06585 | B3: =IFERROR(VLOOKUP(Table3[[#This Row],[Truck Number]], HolmanReport!C:C,1,0), "Research w.Holman") -> Research w.Holman | C3: =IF(Table3[[#This Row],[Days Open]]>27, "28 plus days", IF(Table3[[#This Row],[Days Open]]>20, "21 plus days", IF(Table3[[#This Row],[Days Open]]>13, "14 plus days", "Less than 14 days"))) -> 28 plus days | D3: =IF(Table3[[#This Row],[Ticket Status]]="OPEN", SUM((TODAY())-Table3[[#This Row],[Original Start Date]]), "Not Open") -> 128 | E3: =Table3[[#This Row],[Renter Name]] -> GREGG PAULSEN | F3: =IFERROR(VLOOKUP(Table3[[#This Row],[Rental under Name: ]], 'TPMS-Auto'!C:G,5,0), "RESEARCH!!") -> GPAULSE | G3: =IFERROR(VLOOKUP(Table3[[#This Row],[Truck Number]],'TPMS-Auto'!$A:$K,3, 0), "Not Assigned in TPMS!!") -> GREGG PAULSEN | H3: =IFERROR(VLOOKUP(Table3[[#This Row],[Truck Number]],'TPMS-Auto'!$A:$K,7, 0), "Not Assigned in TPMS!!") -> GPAULSE | I3: =IFERROR(VLOOKUP(Table3[[#This Row],[Truck Number]], Query1[[TRUCK_LU]:[Service Date]],25, 0), "Not Assigned in TPMS!!") -> Not Assigned in TPMS!! | J3: =IF(E3=E2, "Yes", "No") -> No | K3: 2GD4MW | L3: GREGG PAULSEN | M3: HOLMAN FLEET (ARI) US MAINT | N3: 114771300 -D/R | O3: 46076 | P3: 623G | Q3: DAVENPORT | R3: IA | S3: MINIVAN 7 SEATS | T3: 12 | U3: 3 | V3: 69 | W3: 1 | X3: 11 | Y3: OPEN | Z3: 06585 | AB3: TRANSFORM SEARS HOME SERVICES | AC3: ZLevel 4 Clients Only | AD3: 0 | AE3: F | AF3: 25 | AG3: CHRY | AH3: PACI | AI3: 2B56 | AJ3: 4 | AK3: 45958 | AL3: No
A4: =TRIM(Z4) -> 06610 | B4: =IFERROR(VLOOKUP(Table3[[#This Row],[Truck Number]], HolmanReport!C:C,1,0), "Research w.Holman") -> Research w.Holman | C4: =IF(Table3[[#This Row],[Days Open]]>27, "28 plus days", IF(Table3[[#This Row],[Days Open]]>20, "21 plus days", IF(Table3[[#This Row],[Days Open]]>13, "14 plus days", "Less than 14 days"))) -> 28 plus days | D4: =IF(Table3[[#This Row],[Ticket Status]]="OPEN", SUM((TODAY())-Table3[[#This Row],[Original Start Date]]), "Not Open") -> 59 | E4: =Table3[[#This Row],[Renter Name]] -> AUSTIN JOHNSON | F4: =IFERROR(VLOOKUP(Table3[[#This Row],[Rental under Name: ]], 'TPMS-Auto'!C:G,5,0), "RESEARCH!!") -> AJOHNSO | G4: =IFERROR(VLOOKUP(Table3[[#This Row],[Truck Number]],'TPMS-Auto'!$A:$K,3, 0), "Not Assigned in TPMS!!") -> Not Assigned in TPMS!! | H4: =IFERROR(VLOOKUP(Table3[[#This Row],[Truck Number]],'TPMS-Auto'!$A:$K,7, 0), "Not Assigned in TPMS!!") -> Not Assigned in TPMS!! | I4: =IFERROR(VLOOKUP(Table3[[#This Row],[Truck Number]], Query1[[TRUCK_LU]:[Service Date]],25, 0), "Not Assigned in TPMS!!") -> Not Assigned in TPMS!! | J4: =IF(E4=E3, "Yes", "No") -> No | K4: 27YNG7 | L4: AUSTIN JOHNSON | M4: HOLMAN FLEET (ARI) US MAINT | N4: 115877014 -A/R | O4: 46057 | P4: 3007 | Q4: YUBA CITY | R4: CA | S4: SUV STANDARD | T4: 27 | U4: 6 | V4: 73 | W4: 2 | X4: 30 | Y4: OPEN | Z4: 06610 | AB4: TRANSFORM SEARS HOME SERVICES | AC4: ZLevel 4 Clients Only | AD4: 3 | AE4: F | AF4: 24 | AG4: RAM | AH4: C15C | AI4: 2B56 | AJ4: 1 | AK4: 46027 | AL4: No
A5: =TRIM(Z5) -> 21091 | B5: =IFERROR(VLOOKUP(Table3[[#This Row],[Truck Number]], HolmanReport!C:C,1,0), "Research w.Holman") -> 21091 | C5: =IF(Table3[[#This Row],[Days Open]]>27, "28 plus days", IF(Table3[[#This Row],[Days Open]]>20, "21 plus days", IF(Table3[[#This Row],[Days Open]]>13, "14 plus days", "Less than 14 days"))) -> Less than 14 days | D5: =IF(Table3[[#This Row],[Ticket Status]]="OPEN", SUM((TODAY())-Table3[[#This Row],[Original Start Date]]), "Not Open") -> 7 | E5: =Table3[[#This Row],[Renter Name]] -> JOHNNY QUACH | F5: =IFERROR(VLOOKUP(Table3[[#This Row],[Rental under Name: ]], 'TPMS-Auto'!C:G,5,0), "RESEARCH!!") -> JQUACH | G5: =IFERROR(VLOOKUP(Table3[[#This Row],[Truck Number]],'TPMS-Auto'!$A:$K,3, 0), "Not Assigned in TPMS!!") -> JOHNNY QUACH | H5: =IFERROR(VLOOKUP(Table3[[#This Row],[Truck Number]],'TPMS-Auto'!$A:$K,7, 0), "Not Assigned in TPMS!!") -> JQUACH | I5: =IFERROR(VLOOKUP(Table3[[#This Row],[Truck Number]], Query1[[TRUCK_LU]:[Service Date]],25, 0), "Not Assigned in TPMS!!") -> Not Assigned in TPMS!! | J5: =IF(E5=E4, "Yes", "No") -> No | K5: 2HN0SM | L5: JOHNNY QUACH | M5: HOLMAN FLEET (ARI) US MAINT | N5: 116924651 | O5: 46079 | P5: 3257 | Q5: EL MONTE | R5: CA | S5: SUV STANDARD | T5: 13 | U5: 3 | V5: 72 | W5: 1 | X5: 8 | Y5: OPEN | Z5: 21091 | AB5: TRANSFORM SEARS HOME SERVICES | AC5: ZLevel 4 Clients Only | AD5: 0 | AE5: F | AF5: 25 | AG5: MAZD | AH5: CX5 | AI5: 2B56 | AJ5: 0 | AK5: 46079 | AL5: No
A6: =TRIM(Z6) -> 21095 | B6: =IFERROR(VLOOKUP(Table3[[#This Row],[Truck Number]], HolmanReport!C:C,1,0), "Research w.Holman") -> 21095 | C6: =IF(Table3[[#This Row],[Days Open]]>27, "28 plus days", IF(Table3[[#This Row],[Days Open]]>20, "21 plus days", IF(Table3[[#This Row],[Days Open]]>13, "14 plus days", "Less than 14 days"))) -> Less than 14 days | D6: =IF(Table3[[#This Row],[Ticket Status]]="OPEN", SUM((TODAY())-Table3[[#This Row],[Original Start Date]]), "Not Open") -> 3 | E6: =Table3[[#This Row],[Renter Name]] -> JC RODRIGUEZ | F6: =IFERROR(VLOOKUP(Table3[[#This Row],[Rental under Name: ]], 'TPMS-Auto'!C:G,5,0), "RESEARCH!!") -> JRODRI3 | G6: =IFERROR(VLOOKUP(Table3[[#This Row],[Truck Number]],'TPMS-Auto'!$A:$K,3, 0), "Not Assigned in TPMS!!") -> JC RODRIGUEZ | H6: =IFERROR(VLOOKUP(Table3[[#This Row],[Truck Number]],'TPMS-Auto'!$A:$K,7, 0), "Not Assigned in TPMS!!") -> JRODRI3 | I6: =IFERROR(VLOOKUP(Table3[[#This Row],[Truck Number]], Query1[[TRUCK_LU]:[Service Date]],25, 0), "Not Assigned in TPMS!!") -> Not Assigned in TPMS!! | J6: =IF(E6=E5, "Yes", "No") -> No | K6: 2JVJQ4 | L6: JC RODRIGUEZ | M6: HOLMAN FLEET (ARI) US MAINT | N6: 116998272 | O6: 46083 | P6: 32U3 | Q6: VALENCIA | R6: CA | S6: MINIVAN 7 SEATS | T6: 14 | U6: 14 | V6: 72 | W6: 0 | X6: 4 | Y6: OPEN | Z6: 21095 | AB6: TRANSFORM SEARS HOME SERVICES | AC6: ZLevel 4 Clients Only | AD6: 0 | AE6: F | AF6: 25 | AG6: CHRY | AH6: PACI | AI6: 2B56 | AJ6: 0 | AK6: 46083 | AL6: No
A7: =TRIM(Z7) -> 21116 | B7: =IFERROR(VLOOKUP(Table3[[#This Row],[Truck Number]], HolmanReport!C:C,1,0), "Research w.Holman") -> 21116 | C7: =IF(Table3[[#This Row],[Days Open]]>27, "28 plus days", IF(Table3[[#This Row],[Days Open]]>20, "21 plus days", IF(Table3[[#This Row],[Days Open]]>13, "14 plus days", "Less than 14 days"))) -> Less than 14 days | D7: =IF(Table3[[#This Row],[Ticket Status]]="OPEN", SUM((TODAY())-Table3[[#This Row],[Original Start Date]]), "Not Open") -> 1 | E7: =Table3[[#This Row],[Renter Name]] -> BERNARDO ESTRADA | F7: =IFERROR(VLOOKUP(Table3[[#This Row],[Rental under Name: ]], 'TPMS-Auto'!C:G,5,0), "RESEARCH!!") -> BESTRAD | G7: =IFERROR(VLOOKUP(Table3[[#This Row],[Truck Number]],'TPMS-Auto'!$A:$K,3, 0), "Not Assigned in TPMS!!") -> BERNARDO ESTRADA | H7: =IFERROR(VLOOKUP(Table3[[#This Row],[Truck Number]],'TPMS-Auto'!$A:$K,7, 0), "Not Assigned in TPMS!!") -> BESTRAD | I7: =IFERROR(VLOOKUP(Table3[[#This Row],[Truck Number]], Query1[[TRUCK_LU]:[Service Date]],25, 0), "Not Assigned in TPMS!!") -> Not Assigned in TPMS!! | J7: =IF(E7=E6, "Yes", "No") -> No | K7: 2KZBN1 | L7: BERNARDO ESTRADA | M7: HOLMAN FLEET (ARI) US MAINT | N7: 117065614 | O7: 46085 | P7: 3200 | Q7: CANOGA PARK | R7: CA | S7: SUV STANDARD | T7: 14 | U7: 14 | V7: 72 | W7: 0 | X7: 2 | Y7: OPEN | Z7: 21116 | AB7: TRANSFORM SEARS HOME SERVICES | AC7: ZLevel 4 Clients Only | AD7: 0 | AE7: F | AF7: 24 | AG7: DODG | AH7: DURA | AI7: 2B56 | AJ7: 0 | AK7: 46085 | AL7: No
A8: =TRIM(Z8) -> 21159 | B8: =IFERROR(VLOOKUP(Table3[[#This Row],[Truck Number]], HolmanReport!C:C,1,0), "Research w.Holman") -> 21159 | C8: =IF(Table3[[#This Row],[Days Open]]>27, "28 plus days", IF(Table3[[#This Row],[Days Open]]>20, "21 plus days", IF(Table3[[#This Row],[Days Open]]>13, "14 plus days", "Less than 14 days"))) -> 14 plus days | D8: =IF(Table3[[#This Row],[Ticket Status]]="OPEN", SUM((TODAY())-Table3[[#This Row],[Original Start Date]]), "Not Open") -> 17 | E8: =Table3[[#This Row],[Renter Name]] -> DILAN ABREU | F8: =IFERROR(VLOOKUP(Table3[[#This Row],[Rental under Name: ]], 'TPMS-Auto'!C:G,5,0), "RESEARCH!!") -> DABREU | G8: =IFERROR(VLOOKUP(Table3[[#This Row],[Truck Number]],'TPMS-Auto'!$A:$K,3, 0), "Not Assigned in TPMS!!") -> DILAN ABREU | H8: =IFERROR(VLOOKUP(Table3[[#This Row],[Truck Number]],'TPMS-Auto'!$A:$K,7, 0), "Not Assigned in TPMS!!") -> DABREU | I8: =IFERROR(VLOOKUP(Table3[[#This Row],[Truck Number]], Query1[[TRUCK_LU]:[Service Date]],25, 0), "Not Assigned in TPMS!!") -> Not Assigned in TPMS!! | J8: =IF(E8=E7, "Yes", "No") -> No | K8: 2D2NWS | L8: DILAN ABREU | M8: HOLMAN FLEET (ARI) US MAINT | N8: 116741241 | O8: 46069 | P8: 1509 | Q8: OAK PARK | R8: IL | S8: SUV STANDARD | T8: 15 | U8: 5 | V8: 73 | W8: 1 | X8: 18 | Y8: OPEN | Z8: 21159 | AB8: TRANSFORM SEARS HOME SERVICES | AC8: ZLevel 4 Clients Only | AD8: 3 | AE8: F | AF8: 24 | AG8: CHEV | AH8: EQUI | AI8: 2B56 | AJ8: 0 | AK8: 46069 | AL8: Yes
A9: =TRIM(Z9) -> 21162 | B9: =IFERROR(VLOOKUP(Table3[[#This Row],[Truck Number]], HolmanReport!C:C,1,0), "Research w.Holman") -> Research w.Holman | C9: =IF(Table3[[#This Row],[Days Open]]>27, "28 plus days", IF(Table3[[#This Row],[Days Open]]>20, "21 plus days", IF(Table3[[#This Row],[Days Open]]>13, "14 plus days", "Less than 14 days"))) -> 28 plus days | D9: =IF(Table3[[#This Row],[Ticket Status]]="OPEN", SUM((TODAY())-Table3[[#This Row],[Original Start Date]]), "Not Open") -> 146 | E9: =Table3[[#This Row],[Renter Name]] -> ILJIR ZULFIU | F9: =IFERROR(VLOOKUP(Table3[[#This Row],[Rental under Name: ]], 'TPMS-Auto'!C:G,5,0), "RESEARCH!!") -> IZULFIU | G9: =IFERROR(VLOOKUP(Table3[[#This Row],[Truck Number]],'TPMS-Auto'!$A:$K,3, 0), "Not Assigned in TPMS!!") -> ILJIR ZULFIU | H9: =IFERROR(VLOOKUP(Table3[[#This Row],[Truck Number]],'TPMS-Auto'!$A:$K,7, 0), "Not Assigned in TPMS!!") -> IZULFIU | I9: =IFERROR(VLOOKUP(Table3[[#This Row],[Truck Number]], Query1[[TRUCK_LU]:[Service Date]],25, 0), "Not Assigned in TPMS!!") -> Not Assigned in TPMS!! | J9: =IF(E9=E8, "Yes", "No") -> No | K9: 29N2GB | L9: ILJIR ZULFIU | M9: HOLMAN FLEET (ARI) US MAINT | N9: 114972432 -C/R | O9: 46055 | P9: 3902 | Q9: BROOK PARK | R9: OH | S9: MINIVAN 7 SEATS | T9: 29 | U9: 3 | V9: 68 | W9: 2 | X9: 32 | Y9: OPEN | Z9: 21162 | AB9: TRANSFORM SEARS HOME SERVICES | AC9: ZLevel 4 Clients Only | AD9: 3 | AE9: F | AF9: 25 | AG9: CHRY | AH9: PACI | AI9: 2B56 | AJ9: 3 | AK9: 45940 | AL9: No
A10: =TRIM(Z10) -> 21164 | B10: =IFERROR(VLOOKUP(Table3[[#This Row],[Truck Number]], HolmanReport!C:C,1,0), "Research w.Holman") -> 21164 | C10: =IF(Table3[[#This Row],[Days Open]]>27, "28 plus days", IF(Table3[[#This Row],[Days Open]]>20, "21 plus days", IF(Table3[[#This Row],[Days Open]]>13, "14 plus days", "Less than 14 days"))) -> Less than 14 days | D10: =IF(Table3[[#This Row],[Ticket Status]]="OPEN", SUM((TODAY())-Table3[[#This Row],[Original Start Date]]), "Not Open") -> 1 | E10: =Table3[[#This Row],[Renter Name]] -> ADAM APRIM | F10: =IFERROR(VLOOKUP(Table3[[#This Row],[Rental under Name: ]], 'TPMS-Auto'!C:G,5,0), "RESEARCH!!") -> AAPRIM | G10: =IFERROR(VLOOKUP(Table3[[#This Row],[Truck Number]],'TPMS-Auto'!$A:$K,3, 0), "Not Assigned in TPMS!!") -> ADAM APRIM | H10: =IFERROR(VLOOKUP(Table3[[#This Row],[Truck Number]],'TPMS-Auto'!$A:$K,7, 0), "Not Assigned in TPMS!!") -> AAPRIM | I10: =IFERROR(VLOOKUP(Table3[[#This Row],[Truck Number]], Query1[[TRUCK_LU]:[Service Date]],25, 0), "Not Assigned in TPMS!!") -> Not Assigned in TPMS!! | J10: =IF(E10=E9, "Yes", "No") -> No | K10: 2KX3QH | L10: ADAM APRIM | M10: HOLMAN FLEET (ARI) US MAINT TR | N10: 117060442 | O10: 46085 | P10: 382X | Q10: ERLANGER | R10: KY | S10: HI-ROOF CARGO VANS | T10: 14 | U10: 14 | V10: 95.11 | W10: 0 | X10: 2 | Y10: OPEN | Z10: 21164 | AC10: ZLevel 4 Clients Only | AD10: 0 | AE10: F | AF10: 25 | AG10: RAM | AH10: B15C | AI10: 2B56 | AJ10: 0 | AK10: 46085 | AL10: No
A11: =TRIM(Z11) -> 21175 | B11: =IFERROR(VLOOKUP(Table3[[#This Row],[Truck Number]], HolmanReport!C:C,1,0), "Research w.Holman") -> 21175 | C11: =IF(Table3[[#This Row],[Days Open]]>27, "28 plus days", IF(Table3[[#This Row],[Days Open]]>20, "21 plus days", IF(Table3[[#This Row],[Days Open]]>13, "14 plus days", "Less than 14 days"))) -> 28 plus days | D11: =IF(Table3[[#This Row],[Ticket Status]]="OPEN", SUM((TODAY())-Table3[[#This Row],[Original Start Date]]), "Not Open") -> Not Open | E11: =Table3[[#This Row],[Renter Name]] -> KYLE TATUM | F11: =IFERROR(VLOOKUP(Table3[[#This Row],[Rental under Name: ]], 'TPMS-Auto'!C:G,5,0), "RESEARCH!!") -> KTATUM3 | G11: =IFERROR(VLOOKUP(Table3[[#This Row],[Truck Number]],'TPMS-Auto'!$A:$K,3, 0), "Not Assigned in TPMS!!") -> KYLE TATUM | H11: =IFERROR(VLOOKUP(Table3[[#This Row],[Truck Number]],'TPMS-Auto'!$A:$K,7, 0), "Not Assigned in TPMS!!") -> KTATUM3 | I11: =IFERROR(VLOOKUP(Table3[[#This Row],[Truck Number]], Query1[[TRUCK_LU]:[Service Date]],25, 0), "Not Assigned in TPMS!!") -> Not Assigned in TPMS!! | J11: =IF(E11=E10, "Yes", "No") -> No | K11: 2BQM59 | L11: KYLE TATUM | M11: HOLMAN FLEET (ARI) US MAINT | N11: 116353277 | O11: 46065 | P11: 0917 | Q11: BURLESON | R11: TX | S11: MINIVAN 7 SEATS | T11: 16 | U11: 14 | V11: 69 | W11: 1 | X11: 16 | Y11: PENDED | Z11: 21175 | AB11: TRANSFORM SEARS HOME SERVICES | AC11: ZLevel 4 Clients Only | AD11: 0 | AE11: F | AF11: 25 | AG11: CHRY | AH11: PACI | AI11: 2B56 | AJ11: 0 | AK11: 46065 | AL11: Yes
A12: =TRIM(Z12) -> 21187 | B12: =IFERROR(VLOOKUP(Table3[[#This Row],[Truck Number]], HolmanReport!C:C,1,0), "Research w.Holman") -> 21187 | C12: =IF(Table3[[#This Row],[Days Open]]>27, "28 plus days", IF(Table3[[#This Row],[Days Open]]>20, "21 plus days", IF(Table3[[#This Row],[Days Open]]>13, "14 plus days", "Less than 14 days"))) -> 28 plus days | D12: =IF(Table3[[#This Row],[Ticket Status]]="OPEN", SUM((TODAY())-Table3[[#This Row],[Original Start Date]]), "Not Open") -> Not Open | E12: =Table3[[#This Row],[Renter Name]] -> LONDON WILLIAMS | F12: =IFERROR(VLOOKUP(Table3[[#This Row],[Rental under Name: ]], 'TPMS-Auto'!C:G,5,0), "RESEARCH!!") -> LWILLI3 | G12: =IFERROR(VLOOKUP(Table3[[#This Row],[Truck Number]],'TPMS-Auto'!$A:$K,3, 0), "Not Assigned in TPMS!!") -> Not Assigned in TPMS!! | H12: =IFERROR(VLOOKUP(Table3[[#This Row],[Truck Number]],'TPMS-Auto'!$A:$K,7, 0), "Not Assigned in TPMS!!") -> Not Assigned in TPMS!! | I12: =IFERROR(VLOOKUP(Table3[[#This Row],[Truck Number]], Query1[[TRUCK_LU]:[Service Date]],25, 0), "Not Assigned in TPMS!!") -> Not Assigned in TPMS!! | J12: =IF(E12=E11, "Yes", "No") -> No | K12: 1ZSYDC | L12: LONDON WILLIAMS | M12: HOLMAN FLEET (ARI) US INTERIM | N12: 112355336 -G/R | O12: 46027 | P12: 1412 | Q12: BAKER | R12: LA | S12: MINIVAN 7 SEATS | T12: 30 | U12: 30 | V12: 68 | W12: 1 | X12: 31 | Y12: PENDED | Z12: 21187 | AB12: TRANSFORM SEARS HOME SERVICES | AC12: ZLevel 4 Clients Only | AD12: 0 | AE12: F | AF12: 26 | AG12: DODG | AH12: DURA | AI12: 2B56 | AJ12: 7 | AK12: 45817 | AL12: Yes
A13: =TRIM(Z13) -> 21190 | B13: =IFERROR(VLOOKUP(Table3[[#This Row],[Truck Number]], HolmanReport!C:C,1,0), "Research w.Holman") -> Research w.Holman | C13: =IF(Table3[[#This Row],[Days Open]]>27, "28 plus days", IF(Table3[[#This Row],[Days Open]]>20, "21 plus days", IF(Table3[[#This Row],[Days Open]]>13, "14 plus days", "Less than 14 days"))) -> 28 plus days | D13: =IF(Table3[[#This Row],[Ticket Status]]="OPEN", SUM((TODAY())-Table3[[#This Row],[Original Start Date]]), "Not Open") -> 191 | E13: =Table3[[#This Row],[Renter Name]] -> BRAD JONES | F13: =IFERROR(VLOOKUP(Table3[[#This Row],[Rental under Name: ]], 'TPMS-Auto'!C:G,5,0), "RESEARCH!!") -> BJONES1 | G13: =IFERROR(VLOOKUP(Table3[[#This Row],[Truck Number]],'TPMS-Auto'!$A:$K,3, 0), "Not Assigned in TPMS!!") -> BRAD JONES | H13: =IFERROR(VLOOKUP(Table3[[#This Row],[Truck Number]],'TPMS-Auto'!$A:$K,7, 0), "Not Assigned in TPMS!!") -> BJONES1 | I13: =IFERROR(VLOOKUP(Table3[[#This Row],[Truck Number]], Query1[[TRUCK_LU]:[Service Date]],25, 0), "Not Assigned in TPMS!!") -> Not Assigned in TPMS!! | J13: =IF(E13=E12, "Yes", "No") -> No | K13: 2GPSNR | L13: BRAD JONES | M13: HOLMAN FLEET (ARI) US INTERIM | N13: 113664603 -G/R | O13: 46075 | P13: 5551 | Q13: PENSACOLA | R13: FL | S13: MINIVAN 7 SEATS | T13: 30 | U13: 30 | V13: 68 | W13: 0 | X13: 12 | Y13: OPEN | Z13: 21190 | AB13: TRANSFORM SEARS HOME SERVICES | AC13: ZLevel 4 Clients Only | AD13: 0 | AE13: F | AF13: 24 | AG13: NISN | AH13: ARMA | AI13: 2B56 | AJ13: 7 | AK13: 45895 | AL13: Yes
A14: =TRIM(Z14) -> 21222 | B14: =IFERROR(VLOOKUP(Table3[[#This Row],[Truck Number]], HolmanReport!C:C,1,0), "Research w.Holman") -> 21222 | C14: =IF(Table3[[#This Row],[Days Open]]>27, "28 plus days", IF(Table3[[#This Row],[Days Open]]>20, "21 plus days", IF(Table3[[#This Row],[Days Open]]>13, "14 plus days", "Less than 14 days"))) -> 28 plus days | D14: =IF(Table3[[#This Row],[Ticket Status]]="OPEN", SUM((TODAY())-Table3[[#This Row],[Original Start Date]]), "Not Open") -> 58 | E14: =Table3[[#This Row],[Renter Name]] -> WILLIAM VALENTINE | F14: =IFERROR(VLOOKUP(Table3[[#This Row],[Rental under Name: ]], 'TPMS-Auto'!C:G,5,0), "RESEARCH!!") -> WVALENT | G14: =IFERROR(VLOOKUP(Table3[[#This Row],[Truck Number]],'TPMS-Auto'!$A:$K,3, 0), "Not Assigned in TPMS!!") -> WILLIAM VALENTINE | H14: =IFERROR(VLOOKUP(Table3[[#This Row],[Truck Number]],'TPMS-Auto'!$A:$K,7, 0), "Not Assigned in TPMS!!") -> WVALENT | I14: =IFERROR(VLOOKUP(Table3[[#This Row],[Truck Number]], Query1[[TRUCK_LU]:[Service Date]],25, 0), "Not Assigned in TPMS!!") -> Not Assigned in TPMS!! | J14: =IF(E14=E13, "Yes", "No") -> No | K14: 285NP5 | L14: WILLIAM VALENTINE | M14: HOLMAN FLEET (ARI) US MAINT | N14: 115887409 -A/R | O14: 46058 | P14: 2678 | Q14: STATESBORO | R14: GA | S14: STANDARD | T14: 30 | U14: 2 | V14: 53.01 | W14: 5 | X14: 29 | Y14: OPEN | Z14: 21222 | AB14: TRANSFORM SEARS HOME SERVICES | AC14: ZLevel 4 Clients Only | AD14: 0 | AE14: F | AF14: 26 | AG14: HYUN | AH14: ELAH | AI14: 2B56 | AJ14: 1 | AK14: 46028 | AL14: No
A15: =TRIM(Z15) -> 21234 | B15: =IFERROR(VLOOKUP(Table3[[#This Row],[Truck Number]], HolmanReport!C:C,1,0), "Research w.Holman") -> 21234 | C15: =IF(Table3[[#This Row],[Days Open]]>27, "28 plus days", IF(Table3[[#This Row],[Days Open]]>20, "21 plus days", IF(Table3[[#This Row],[Days Open]]>13, "14 plus days", "Less than 14 days"))) -> Less than 14 days | D15: =IF(Table3[[#This Row],[Ticket Status]]="OPEN", SUM((TODAY())-Table3[[#This Row],[Original Start Date]]), "Not Open") -> 9 | E15: =Table3[[#This Row],[Renter Name]] -> TYLER LABORDE | F15: =IFERROR(VLOOKUP(Table3[[#This Row],[Rental under Name: ]], 'TPMS-Auto'!C:G,5,0), "RESEARCH!!") -> TLABORD | G15: =IFERROR(VLOOKUP(Table3[[#This Row],[Truck Number]],'TPMS-Auto'!$A:$K,3, 0), "Not Assigned in TPMS!!") -> TYLER LABORDE | H15: =IFERROR(VLOOKUP(Table3[[#This Row],[Truck Number]],'TPMS-Auto'!$A:$K,7, 0), "Not Assigned in TPMS!!") -> TLABORD | I15: =IFERROR(VLOOKUP(Table3[[#This Row],[Truck Number]], Query1[[TRUCK_LU]:[Service Date]],25, 0), "Not Assigned in TPMS!!") -> Not Assigned in TPMS!! | J15: =IF(E15=E14, "Yes", "No") -> No | K15: 2GX5LB | L15: TYLER LABORDE | M15: HOLMAN FLEET (ARI) US MAINT | N15: 116927243 | O15: 46077 | P15: 072A | Q15: ORLANDO | R15: FL | S15: SUV STANDARD | T15: 14 | U15: 14 | V15: 69 | W15: 0 | X15: 10 | Y15: OPEN | Z15: 21234 | AB15: TRANSFORM SEARS HOME SERVICES | AC15: ZLevel 4 Clients Only | AD15: 0 | AE15: F | AF15: 25 | AG15: CHRY | AH15: PACI | AI15: 2B56 | AJ15: 0 | AK15: 46077 | AL15: No
A16: =TRIM(Z16) -> 21237 | B16: =IFERROR(VLOOKUP(Table3[[#This Row],[Truck Number]], HolmanReport!C:C,1,0), "Research w.Holman") -> 21237 | C16: =IF(Table3[[#This Row],[Days Open]]>27, "28 plus days", IF(Table3[[#This Row],[Days Open]]>20, "21 plus days", IF(Table3[[#This Row],[Days Open]]>13, "14 plus days", "Less than 14 days"))) -> 28 plus days | D16: =IF(Table3[[#This Row],[Ticket Status]]="OPEN", SUM((TODAY())-Table3[[#This Row],[Original Start Date]]), "Not Open") -> 226 | E16: =Table3[[#This Row],[Renter Name]] -> ARTHUR HARRIS | F16: =IFERROR(VLOOKUP(Table3[[#This Row],[Rental under Name: ]], 'TPMS-Auto'!C:G,5,0), "RESEARCH!!") -> AHARRIS | G16: =IFERROR(VLOOKUP(Table3[[#This Row],[Truck Number]],'TPMS-Auto'!$A:$K,3, 0), "Not Assigned in TPMS!!") -> ARTHUR HARRIS | H16: =IFERROR(VLOOKUP(Table3[[#This Row],[Truck Number]],'TPMS-Auto'!$A:$K,7, 0), "Not Assigned in TPMS!!") -> AHARRIS | I16: =IFERROR(VLOOKUP(Table3[[#This Row],[Truck Number]], Query1[[TRUCK_LU]:[Service Date]],25, 0), "Not Assigned in TPMS!!") -> Not Assigned in TPMS!! | J16: =IF(E16=E15, "Yes", "No") -> No | K16: 2DQXV4 | L16: ARTHUR HARRIS | M16: HOLMAN FLEET (ARI) US INTERIM | N16: 113066947 -G/R | O16: 46070 | P16: 24C6 | Q16: BRONX | R16: NY | S16: MINIVAN 7 SEATS | T16: 30 | U16: 30 | V16: 86 | W16: 0 | X16: 17 | Y16: OPEN | Z16: 21237 | AB16: TRANSFORM SEARS HOME SERVICES | AC16: ZLevel 4 Clients Only | AD16: 0 | AE16: F | AF16: 26 | AG16: CHRY | AH16: PACI | AI16: 2B56 | AJ16: 7 | AK16: 45860 | AL16: Yes
A17: =TRIM(Z17) -> 21264 | B17: =IFERROR(VLOOKUP(Table3[[#This Row],[Truck Number]], HolmanReport!C:C,1,0), "Research w.Holman") -> Research w.Holman | C17: =IF(Table3[[#This Row],[Days Open]]>27, "28 plus days", IF(Table3[[#This Row],[Days Open]]>20, "21 plus days", IF(Table3[[#This Row],[Days Open]]>13, "14 plus days", "Less than 14 days"))) -> 28 plus days | D17: =IF(Table3[[#This Row],[Ticket Status]]="OPEN", SUM((TODAY())-Table3[[#This Row],[Original Start Date]]), "Not Open") -> 211 | E17: =Table3[[#This Row],[Renter Name]] -> JOSE LOPEZ | F17: =IFERROR(VLOOKUP(Table3[[#This Row],[Rental under Name: ]], 'TPMS-Auto'!C:G,5,0), "RESEARCH!!") -> JLOPEZ0 | G17: =IFERROR(VLOOKUP(Table3[[#This Row],[Truck Number]],'TPMS-Auto'!$A:$K,3, 0), "Not Assigned in TPMS!!") -> JOSE LOPEZ | H17: =IFERROR(VLOOKUP(Table3[[#This Row],[Truck Number]],'TPMS-Auto'!$A:$K,7, 0), "Not Assigned in TPMS!!") -> JLOPEZ0 | I17: =IFERROR(VLOOKUP(Table3[[#This Row],[Truck Number]], Query1[[TRUCK_LU]:[Service Date]],25, 0), "Not Assigned in TPMS!!") -> Not Assigned in TPMS!! | J17: =IF(E17=E16, "Yes", "No") -> No | K17: 278KCH | L17: JOSE LOPEZ | M17: HOLMAN FLEET (ARI) US MAINT | N17: 113313532 -B/R | O17: 46055 | P17: 522L | Q17: SAN ANTONIO | R17: TX | S17: CARGO VAN | T17: 29 | U17: 1 | V17: 76.29 | W17: 3 | X17: 32 | Y17: OPEN | Z17: 21264 | AB17: TRANSFORM SEARS HOME SERVICES | AC17: ZLevel 4 Clients Only | AD17: 3 | AE17: F | AF17: 24 | AG17: FORD | AH17: EXEL | AI17: 2B56 | AJ17: 6 | AK17: 45875 | AL17: Yes
A18: =TRIM(Z18) -> 21281 | B18: =IFERROR(VLOOKUP(Table3[[#This Row],[Truck Number]], HolmanReport!C:C,1,0), "Research w.Holman") -> Research w.Holman | C18: =IF(Table3[[#This Row],[Days Open]]>27, "28 plus days", IF(Table3[[#This Row],[Days Open]]>20, "21 plus days", IF(Table3[[#This Row],[Days Open]]>13, "14 plus days", "Less than 14 days"))) -> 28 plus days | D18: =IF(Table3[[#This Row],[Ticket Status]]="OPEN", SUM((TODAY())-Table3[[#This Row],[Original Start Date]]), "Not Open") -> 84 | E18: =Table3[[#This Row],[Renter Name]] -> JOSHUA LEONARD | F18: =IFERROR(VLOOKUP(Table3[[#This Row],[Rental under Name: ]], 'TPMS-Auto'!C:G,5,0), "RESEARCH!!") -> JLEONAR | G18: =IFERROR(VLOOKUP(Table3[[#This Row],[Truck Number]],'TPMS-Auto'!$A:$K,3, 0), "Not Assigned in TPMS!!") -> JOSHUA LEONARD | H18: =IFERROR(VLOOKUP(Table3[[#This Row],[Truck Number]],'TPMS-Auto'!$A:$K,7, 0), "Not Assigned in TPMS!!") -> JLEONAR | I18: =IFERROR(VLOOKUP(Table3[[#This Row],[Truck Number]], Query1[[TRUCK_LU]:[Service Date]],25, 0), "Not Assigned in TPMS!!") -> Not Assigned in TPMS!! | J18: =IF(E18=E17, "Yes", "No") -> No | K18: 29KWHX | L18: JOSHUA LEONARD | M18: HOLMAN FLEET (ARI) US MAINT | N18: 115521261 -B/R | O18: 46062 | P18: 09LX | Q18: DALLAS | R18: TX | S18: MINIVAN 7 SEATS | T18: 25 | U18: 3 | V18: 69 | W18: 2 | X18: 25 | Y18: OPEN | Z18: 21281 | AB18: TRANSFORM SEARS HOME SERVICES | AC18: ZLevel 4 Clients Only | AD18: 0 | AE18: F | AF18: 24 | AG18: GMC | AH18: TERR | AI18: 2B56 | AJ18: 2 | AK18: 46002 | AL18: No
A19: =TRIM(Z19) -> 21316 | B19: =IFERROR(VLOOKUP(Table3[[#This Row],[Truck Number]], HolmanReport!C:C,1,0), "Research w.Holman") -> Research w.Holman | C19: =IF(Table3[[#This Row],[Days Open]]>27, "28 plus days", IF(Table3[[#This Row],[Days Open]]>20, "21 plus days", IF(Table3[[#This Row],[Days Open]]>13, "14 plus days", "Less than 14 days"))) -> 28 plus days | D19: =IF(Table3[[#This Row],[Ticket Status]]="OPEN", SUM((TODAY())-Table3[[#This Row],[Original Start Date]]), "Not Open") -> 59 | E19: =Table3[[#This Row],[Renter Name]] -> ZACHARY DYSART | F19: =IFERROR(VLOOKUP(Table3[[#This Row],[Rental under Name: ]], 'TPMS-Auto'!C:G,5,0), "RESEARCH!!") -> ZDYSART | G19: =IFERROR(VLOOKUP(Table3[[#This Row],[Truck Number]],'TPMS-Auto'!$A:$K,3, 0), "Not Assigned in TPMS!!") -> ZACHARY DYSART | H19: =IFERROR(VLOOKUP(Table3[[#This Row],[Truck Number]],'TPMS-Auto'!$A:$K,7, 0), "Not Assigned in TPMS!!") -> ZDYSART | I19: =IFERROR(VLOOKUP(Table3[[#This Row],[Truck Number]], Query1[[TRUCK_LU]:[Service Date]],25, 0), "Not Assigned in TPMS!!") -> Not Assigned in TPMS!! | J19: =IF(E19=E18, "Yes", "No") -> No | K19: 2C9JGM | L19: ZACHARY DYSART | M19: HOLMAN FLEET (ARI) US MAINT | N19: 115850746 -A/R | O19: 46057 | P19: 5860 | Q19: PIKEVILLE | R19: KY | S19: MINIVAN 7 SEATS | T19: 30 | U19: 7 | V19: 68 | W19: 3 | X19: 30 | Y19: OPEN | Z19: 21316 | AB19: TRANSFORM SEARS HOME SERVICES | AC19: ZLevel 4 Clients Only | AD19: 0 | AE19: F | AF19: 25 | AG19: CHRY | AH19: PACI | AI19: 2B56 | AJ19: 1 | AK19: 46027 | AL19: No
A20: =TRIM(Z20) -> 21365 | B20: =IFERROR(VLOOKUP(Table3[[#This Row],[Truck Number]], HolmanReport!C:C,1,0), "Research w.Holman") -> 21365 | C20: =IF(Table3[[#This Row],[Days Open]]>27, "28 plus days", IF(Table3[[#This Row],[Days Open]]>20, "21 plus days", IF(Table3[[#This Row],[Days Open]]>13, "14 plus days", "Less than 14 days"))) -> 28 plus days | D20: =IF(Table3[[#This Row],[Ticket Status]]="OPEN", SUM((TODAY())-Table3[[#This Row],[Original Start Date]]), "Not Open") -> 112 | E20: =Table3[[#This Row],[Renter Name]] -> VINCE ROSADO | F20: =IFERROR(VLOOKUP(Table3[[#This Row],[Rental under Name: ]], 'TPMS-Auto'!C:G,5,0), "RESEARCH!!") -> RESEARCH!! | G20: =IFERROR(VLOOKUP(Table3[[#This Row],[Truck Number]],'TPMS-Auto'!$A:$K,3, 0), "Not Assigned in TPMS!!") -> Not Assigned in TPMS!! | H20: =IFERROR(VLOOKUP(Table3[[#This Row],[Truck Number]],'TPMS-Auto'!$A:$K,7, 0), "Not Assigned in TPMS!!") -> Not Assigned in TPMS!! | I20: =IFERROR(VLOOKUP(Table3[[#This Row],[Truck Number]], Query1[[TRUCK_LU]:[Service Date]],25, 0), "Not Assigned in TPMS!!") -> Not Assigned in TPMS!! | J20: =IF(E20=E19, "Yes", "No") -> No | K20: 2D8MK3 | L20: VINCE ROSADO | M20: HOLMAN FLEET (ARI) US MAINT | N20: 115029941 -C/R | O20: 46064 | P20: 510A | Q20: TEXARKANA | R20: TX | S20: MINIVAN 7 SEATS | T20: 24 | U20: 2 | V20: 69 | W20: 2 | X20: 23 | Y20: OPEN | Z20: 21365 | AB20: TRANSFORM SEARS HOME SERVICES | AC20: ZLevel 4 Clients Only | AD20: 0 | AE20: F | AF20: 25 | AG20: CHRY | AH20: PACI | AI20: 2B56 | AJ20: 3 | AK20: 45974 | AL20: No
A21: =TRIM(Z21) -> 21402 | B21: =IFERROR(VLOOKUP(Table3[[#This Row],[Truck Number]], HolmanReport!C:C,1,0), "Research w.Holman") -> Research w.Holman | C21: =IF(Table3[[#This Row],[Days Open]]>27, "28 plus days", IF(Table3[[#This Row],[Days Open]]>20, "21 plus days", IF(Table3[[#This Row],[Days Open]]>13, "14 plus days", "Less than 14 days"))) -> 28 plus days | D21: =IF(Table3[[#This Row],[Ticket Status]]="OPEN", SUM((TODAY())-Table3[[#This Row],[Original Start Date]]), "Not Open") -> 72 | E21: =Table3[[#This Row],[Renter Name]] -> MOHAMMAD SAHIBZADA | F21: =IFERROR(VLOOKUP(Table3[[#This Row],[Rental under Name: ]], 'TPMS-Auto'!C:G,5,0), "RESEARCH!!") -> MSAHIBZ | G21: =IFERROR(VLOOKUP(Table3[[#This Row],[Truck Number]],'TPMS-Auto'!$A:$K,3, 0), "Not Assigned in TPMS!!") -> MOHAMMAD SAHIBZADA | H21: =IFERROR(VLOOKUP(Table3[[#This Row],[Truck Number]],'TPMS-Auto'!$A:$K,7, 0), "Not Assigned in TPMS!!") -> MSAHIBZ | I21: =IFERROR(VLOOKUP(Table3[[#This Row],[Truck Number]], Query1[[TRUCK_LU]:[Service Date]],25, 0), "Not Assigned in TPMS!!") -> Not Assigned in TPMS!! | J21: =IF(E21=E20, "Yes", "No") -> No | K21: 2FSHTF | L21: MOHAMMAD SAHIBZADA | M21: HOLMAN FLEET (ARI) US MAINT | N21: 115761100 -B/R | O21: 46074 | P21: 165S | Q21: SPRINGFIELD | R21: VA | S21: MINIVAN 7 SEATS | T21: 21 | U21: 7 | V21: 72 | W21: 1 | X21: 13 | Y21: OPEN | Z21: 21402 | AB21: TRANSFORM SEARS HOME SERVICES | AC21: ZLevel 4 Clients Only | AD21: 0 | AE21: F | AF21: 24 | AG21: JEEP | AH21: WRAU | AI21: 2B56 | AJ21: 2 | AK21: 46014 | AL21: Yes
A22: =TRIM(Z22) -> 21535 | B22: =IFERROR(VLOOKUP(Table3[[#This Row],[Truck Number]], HolmanReport!C:C,1,0), "Research w.Holman") -> 21535 | C22: =IF(Table3[[#This Row],[Days Open]]>27, "28 plus days", IF(Table3[[#This Row],[Days Open]]>20, "21 plus days", IF(Table3[[#This Row],[Days Open]]>13, "14 plus days", "Less than 14 days"))) -> Less than 14 days | D22: =IF(Table3[[#This Row],[Ticket Status]]="OPEN", SUM((TODAY())-Table3[[#This Row],[Original Start Date]]), "Not Open") -> 13 | E22: =Table3[[#This Row],[Renter Name]] -> RICHARD MANEGO | F22: =IFERROR(VLOOKUP(Table3[[#This Row],[Rental under Name: ]], 'TPMS-Auto'!C:G,5,0), "RESEARCH!!") -> RMANEGO | G22: =IFERROR(VLOOKUP(Table3[[#This Row],[Truck Number]],'TPMS-Auto'!$A:$K,3, 0), "Not Assigned in TPMS!!") -> RICHARD MANEGO | H22: =IFERROR(VLOOKUP(Table3[[#This Row],[Truck Number]],'TPMS-Auto'!$A:$K,7, 0), "Not Assigned in TPMS!!") -> RMANEGO | I22: =IFERROR(VLOOKUP(Table3[[#This Row],[Truck Number]], Query1[[TRUCK_LU]:[Service Date]],25, 0), "Not Assigned in TPMS!!") -> Not Assigned in TPMS!! | J22: =IF(E22=E21, "Yes", "No") -> No | K22: 2FG5BR | L22: RICHARD MANEGO | M22: HOLMAN FLEET (ARI) US MAINT | N22: 116863027 | O22: 46073 | P22: 5579 | Q22: GULFPORT | R22: MS | S22: MINIVAN 7 SEATS | T22: 15 | U22: 7 | V22: 68 | W22: 1 | X22: 14 | Y22: OPEN | Z22: 21535 | AB22: TRANSFORM SEARS HOME SERVICES | AC22: ZLevel 4 Clients Only | AD22: 0 | AE22: F | AF22: 25 | AG22: NISN | AH22: ROGU | AI22: 2B56 | AJ22: 0 | AK22: 46073 | AL22: No
... A64: =TRIM(Z64) -> 23571 | B64: =IFERROR(VLOOKUP(Table3[[#This Row],[Truck Number]], HolmanReport!C:C,1,0), "Research w.Holman") -> 23571 | C64: =IF(Table3[[#This Row],[Days Open]]>27, "28 plus days", IF(Table3[[#This Row],[Days Open]]>20, "21 plus days", IF(Table3[[#This Row],[Days Open]]>13, "14 plus days", "Less than 14 days"))) -> Less than 14 days | D64: =IF(Table3[[#This Row],[Ticket Status]]="OPEN", SUM((TODAY())-Table3[[#This Row],[Original Start Date]]), "Not Open") -> 9 | E64: =Table3[[#This Row],[Renter Name]] -> COLE PICKFORD | F64: =IFERROR(VLOOKUP(Table3[[#This Row],[Rental under Name: ]], 'TPMS-Auto'!C:G,5,0), "RESEARCH!!") -> CPICKFO | G64: =IFERROR(VLOOKUP(Table3[[#This Row],[Truck Number]],'TPMS-Auto'!$A:$K,3, 0), "Not Assigned in TPMS!!") -> COLE PICKFORD | H64: =IFERROR(VLOOKUP(Table3[[#This Row],[Truck Number]],'TPMS-Auto'!$A:$K,7, 0), "Not Assigned in TPMS!!") -> CPICKFO | I64: =IFERROR(VLOOKUP(Table3[[#This Row],[Truck Number]], Query1[[TRUCK_LU]:[Service Date]],25, 0), "Not Assigned in TPMS!!") -> Not Assigned in TPMS!! | J64: =IF(E64=E63, "Yes", "No") -> No | K64: 2GTW62 | L64: COLE PICKFORD | M64: HOLMAN FLEET (ARI) US MAINT | N64: 116916176 | O64: 46077 | P64: 20Z2 | Q64: CADILLAC | R64: MI | S64: SUV STANDARD | T64: 11 | U64: 4 | V64: 69 | W64: 1 | X64: 10 | Y64: OPEN | Z64: 23571 | AB64: TRANSFORM SEARS HOME SERVICES | AC64: ZLevel 4 Clients Only | AD64: 0 | AE64: F | AF64: 25 | AG64: MITS | AH64: ECLX | AI64: 2B56 | AJ64: 0 | AK64: 46077 | AL64: No
A65: =TRIM(Z65) -> 23597 | B65: =IFERROR(VLOOKUP(Table3[[#This Row],[Truck Number]], HolmanReport!C:C,1,0), "Research w.Holman") -> Research w.Holman | C65: =IF(Table3[[#This Row],[Days Open]]>27, "28 plus days", IF(Table3[[#This Row],[Days Open]]>20, "21 plus days", IF(Table3[[#This Row],[Days Open]]>13, "14 plus days", "Less than 14 days"))) -> 21 plus days | D65: =IF(Table3[[#This Row],[Ticket Status]]="OPEN", SUM((TODAY())-Table3[[#This Row],[Original Start Date]]), "Not Open") -> 26 | E65: =Table3[[#This Row],[Renter Name]] -> VICTOR CMELA | F65: =IFERROR(VLOOKUP(Table3[[#This Row],[Rental under Name: ]], 'TPMS-Auto'!C:G,5,0), "RESEARCH!!") -> VCMELA | G65: =IFERROR(VLOOKUP(Table3[[#This Row],[Truck Number]],'TPMS-Auto'!$A:$K,3, 0), "Not Assigned in TPMS!!") -> VICTOR CMELA | H65: =IFERROR(VLOOKUP(Table3[[#This Row],[Truck Number]],'TPMS-Auto'!$A:$K,7, 0), "Not Assigned in TPMS!!") -> VCMELA | I65: =IFERROR(VLOOKUP(Table3[[#This Row],[Truck Number]], Query1[[TRUCK_LU]:[Service Date]],25, 0), "Not Assigned in TPMS!!") -> Not Assigned in TPMS!! | J65: =IF(E65=E64, "Yes", "No") -> No | K65: 2FH86T | L65: VICTOR CMELA | M65: HOLMAN FLEET (ARI) US INTERIM | N65: 116607015 | O65: 46074 | P65: 58DM | Q65: BOWLING GREEN | R65: KY | S65: SUV INTERMEDIATE | T65: 30 | V65: 68 | W65: 1 | X65: 13 | Y65: OPEN | Z65: 23597 | AB65: TRANSFORM SEARS HOME SERVICES | AC65: ZLevel 4 Clients Only | AD65: 0 | AE65: F | AF65: 25 | AG65: CHEV | AH65: TBLZ | AI65: 2B56 | AJ65: 0 | AK65: 46060 | AL65: No
A66: =TRIM(Z66) -> 23796 | B66: =IFERROR(VLOOKUP(Table3[[#This Row],[Truck Number]], HolmanReport!C:C,1,0), "Research w.Holman") -> Research w.Holman | C66: =IF(Table3[[#This Row],[Days Open]]>27, "28 plus days", IF(Table3[[#This Row],[Days Open]]>20, "21 plus days", IF(Table3[[#This Row],[Days Open]]>13, "14 plus days", "Less than 14 days"))) -> 28 plus days | D66: =IF(Table3[[#This Row],[Ticket Status]]="OPEN", SUM((TODAY())-Table3[[#This Row],[Original Start Date]]), "Not Open") -> 73 | E66: =Table3[[#This Row],[Renter Name]] -> CHARLES DUNCAN | F66: =IFERROR(VLOOKUP(Table3[[#This Row],[Rental under Name: ]], 'TPMS-Auto'!C:G,5,0), "RESEARCH!!") -> CDUNCA3 | G66: =IFERROR(VLOOKUP(Table3[[#This Row],[Truck Number]],'TPMS-Auto'!$A:$K,3, 0), "Not Assigned in TPMS!!") -> Not Assigned in TPMS!! | H66: =IFERROR(VLOOKUP(Table3[[#This Row],[Truck Number]],'TPMS-Auto'!$A:$K,7, 0), "Not Assigned in TPMS!!") -> Not Assigned in TPMS!! | I66: =IFERROR(VLOOKUP(Table3[[#This Row],[Truck Number]], Query1[[TRUCK_LU]:[Service Date]],25, 0), "Not Assigned in TPMS!!") -> Not Assigned in TPMS!! | J66: =IF(E66=E65, "Yes", "No") -> No | K66: 2FQ3RN | L66: CHARLES DUNCAN | M66: HOLMAN FLEET (ARI) US INTERIM | N66: 115723395 -B/R | O66: 46073 | P66: 4545 | Q66: PUYALLUP | R66: WA | S66: SUV STANDARD | T66: 30 | U66: 30 | V66: 72 | W66: 0 | X66: 14 | Y66: OPEN | Z66: 23796 | AB66: TRANSFORM SEARS HOME SERVICES | AC66: ZLevel 4 Clients Only | AD66: 0 | AE66: F | AF66: 24 | AG66: DODG | AH66: DURA | AI66: 2B56 | AJ66: 2 | AK66: 46013 | AL66: No
A67: =TRIM(Z67) -> 23875 | B67: =IFERROR(VLOOKUP(Table3[[#This Row],[Truck Number]], HolmanReport!C:C,1,0), "Research w.Holman") -> 23875 | C67: =IF(Table3[[#This Row],[Days Open]]>27, "28 plus days", IF(Table3[[#This Row],[Days Open]]>20, "21 plus days", IF(Table3[[#This Row],[Days Open]]>13, "14 plus days", "Less than 14 days"))) -> Less than 14 days | D67: =IF(Table3[[#This Row],[Ticket Status]]="OPEN", SUM((TODAY())-Table3[[#This Row],[Original Start Date]]), "Not Open") -> 7 | E67: =Table3[[#This Row],[Renter Name]] -> CHAD JONES | F67: =IFERROR(VLOOKUP(Table3[[#This Row],[Rental under Name: ]], 'TPMS-Auto'!C:G,5,0), "RESEARCH!!") -> CJONES1 | G67: =IFERROR(VLOOKUP(Table3[[#This Row],[Truck Number]],'TPMS-Auto'!$A:$K,3, 0), "Not Assigned in TPMS!!") -> CHAD JONES | H67: =IFERROR(VLOOKUP(Table3[[#This Row],[Truck Number]],'TPMS-Auto'!$A:$K,7, 0), "Not Assigned in TPMS!!") -> CJONES1 | I67: =IFERROR(VLOOKUP(Table3[[#This Row],[Truck Number]], Query1[[TRUCK_LU]:[Service Date]],25, 0), "Not Assigned in TPMS!!") -> Not Assigned in TPMS!! | J67: =IF(E67=E66, "Yes", "No") -> No | K67: 2HQLT2 | L67: CHAD JONES | M67: HOLMAN FLEET (ARI) US MAINT | N67: 116971356 | O67: 46079 | P67: 1518 | Q67: JOLIET | R67: IL | S67: SUV INTERMEDIATE | T67: 14 | U67: 14 | V67: 69 | W67: 0 | X67: 8 | Y67: OPEN | Z67: 23875 | AB67: TRANSFORM SEARS HOME SERVICES | AC67: ZLevel 4 Clients Only | AD67: 0 | AE67: F | AF67: 24 | AG67: RAM | AH67: B15C | AI67: 2B56 | AJ67: 0 | AK67: 46079 | AL67: No
A68: =TRIM(Z68) -> 23895 | B68: =IFERROR(VLOOKUP(Table3[[#This Row],[Truck Number]], HolmanReport!C:C,1,0), "Research w.Holman") -> 23895 | C68: =IF(Table3[[#This Row],[Days Open]]>27, "28 plus days", IF(Table3[[#This Row],[Days Open]]>20, "21 plus days", IF(Table3[[#This Row],[Days Open]]>13, "14 plus days", "Less than 14 days"))) -> 14 plus days | D68: =IF(Table3[[#This Row],[Ticket Status]]="OPEN", SUM((TODAY())-Table3[[#This Row],[Original Start Date]]), "Not Open") -> 16 | E68: =Table3[[#This Row],[Renter Name]] -> ERIC KENNEDY | F68: =IFERROR(VLOOKUP(Table3[[#This Row],[Rental under Name: ]], 'TPMS-Auto'!C:G,5,0), "RESEARCH!!") -> EKENNED | G68: =IFERROR(VLOOKUP(Table3[[#This Row],[Truck Number]],'TPMS-Auto'!$A:$K,3, 0), "Not Assigned in TPMS!!") -> ERIC KENNEDY | H68: =IFERROR(VLOOKUP(Table3[[#This Row],[Truck Number]],'TPMS-Auto'!$A:$K,7, 0), "Not Assigned in TPMS!!") -> EKENNED | I68: =IFERROR(VLOOKUP(Table3[[#This Row],[Truck Number]], Query1[[TRUCK_LU]:[Service Date]],25, 0), "Not Assigned in TPMS!!") -> Not Assigned in TPMS!! | J68: =IF(E68=E67, "Yes", "No") -> No | K68: 2DDHD9 | L68: ERIC KENNEDY | M68: HOLMAN FLEET (ARI) US MAINT | N68: 116758636 | O68: 46070 | P68: 1735 | Q68: DOVER | R68: DE | S68: SUV STANDARD | T68: 23 | U68: 7 | V68: 72 | W68: 1 | X68: 17 | Y68: OPEN | Z68: 23895 | AB68: TRANSFORM SEARS HOME SERVICES | AC68: ZLevel 4 Clients Only | AD68: 0 | AE68: F | AF68: 25 | AG68: RAM | AH68: B15C | AI68: 2B56 | AJ68: 0 | AK68: 46070 | AL68: No
A69: =TRIM(Z69) -> 23905 | B69: =IFERROR(VLOOKUP(Table3[[#This Row],[Truck Number]], HolmanReport!C:C,1,0), "Research w.Holman") -> 23905 | C69: =IF(Table3[[#This Row],[Days Open]]>27, "28 plus days", IF(Table3[[#This Row],[Days Open]]>20, "21 plus days", IF(Table3[[#This Row],[Days Open]]>13, "14 plus days", "Less than 14 days"))) -> Less than 14 days | D69: =IF(Table3[[#This Row],[Ticket Status]]="OPEN", SUM((TODAY())-Table3[[#This Row],[Original Start Date]]), "Not Open") -> 3 | E69: =Table3[[#This Row],[Renter Name]] -> DONALD WILSON | F69: =IFERROR(VLOOKUP(Table3[[#This Row],[Rental under Name: ]], 'TPMS-Auto'!C:G,5,0), "RESEARCH!!") -> DWILS48 | G69: =IFERROR(VLOOKUP(Table3[[#This Row],[Truck Number]],'TPMS-Auto'!$A:$K,3, 0), "Not Assigned in TPMS!!") -> DONALD WILSON | H69: =IFERROR(VLOOKUP(Table3[[#This Row],[Truck Number]],'TPMS-Auto'!$A:$K,7, 0), "Not Assigned in TPMS!!") -> DWILS48 | I69: =IFERROR(VLOOKUP(Table3[[#This Row],[Truck Number]], Query1[[TRUCK_LU]:[Service Date]],25, 0), "Not Assigned in TPMS!!") -> Not Assigned in TPMS!! | J69: =IF(E69=E68, "Yes", "No") -> No | K69: 2JTF52 | L69: DONALD WILSON | M69: HOLMAN FLEET (ARI) US MAINT | N69: 117005916 | O69: 46083 | P69: 1669 | Q69: BELTSVILLE | R69: MD | S69: MINIVAN 7 SEATS | T69: 5 | U69: 5 | V69: 72 | W69: 0 | X69: 4 | Y69: OPEN | Z69: 23905 | AB69: TRANSFORM SEARS HOME SERVICES | AC69: ZLevel 4 Clients Only | AD69: 0 | AE69: F | AF69: 24 | AG69: NISN | AH69: ROGU | AI69: 2B56 | AJ69: 0 | AK69: 46083 | AL69: No
A70: =TRIM(Z70) -> 23921 | B70: =IFERROR(VLOOKUP(Table3[[#This Row],[Truck Number]], HolmanReport!C:C,1,0), "Research w.Holman") -> Research w.Holman | C70: =IF(Table3[[#This Row],[Days Open]]>27, "28 plus days", IF(Table3[[#This Row],[Days Open]]>20, "21 plus days", IF(Table3[[#This Row],[Days Open]]>13, "14 plus days", "Less than 14 days"))) -> 28 plus days | D70: =IF(Table3[[#This Row],[Ticket Status]]="OPEN", SUM((TODAY())-Table3[[#This Row],[Original Start Date]]), "Not Open") -> 121 | E70: =Table3[[#This Row],[Renter Name]] -> MICHAEL COLLINS | F70: =IFERROR(VLOOKUP(Table3[[#This Row],[Rental under Name: ]], 'TPMS-Auto'!C:G,5,0), "RESEARCH!!") -> RESEARCH!! | G70: =IFERROR(VLOOKUP(Table3[[#This Row],[Truck Number]],'TPMS-Auto'!$A:$K,3, 0), "Not Assigned in TPMS!!") -> Not Assigned in TPMS!! | H70: =IFERROR(VLOOKUP(Table3[[#This Row],[Truck Number]],'TPMS-Auto'!$A:$K,7, 0), "Not Assigned in TPMS!!") -> Not Assigned in TPMS!! | I70: =IFERROR(VLOOKUP(Table3[[#This Row],[Truck Number]], Query1[[TRUCK_LU]:[Service Date]],25, 0), "Not Assigned in TPMS!!") -> Not Assigned in TPMS!! | J70: =IF(E70=E69, "Yes", "No") -> No | K70: 288J5G | L70: MICHAEL COLLINS | M70: HOLMAN FLEET (ARI) US INTERIM | N70: 114880694 -C/R | O70: 46055 | P70: 167L | Q70: WALDORF | R70: MD | S70: MINIVAN 7 SEATS | T70: 30 | U70: 30 | V70: 72 | W70: 0 | X70: 32 | Y70: OPEN | Z70: 23921 | AB70: TRANSFORM SEARS HOME SERVICES | AC70: ZLevel 4 Clients Only | AD70: 2 | AE70: F | AF70: 25 | AG70: CHEV | AH70: S15C | AI70: 2B56 | AJ70: 3 | AK70: 45965 | AL70: No
A71: =TRIM(Z71) -> 23966 | B71: =IFERROR(VLOOKUP(Table3[[#This Row],[Truck Number]], HolmanReport!C:C,1,0), "Research w.Holman") -> Research w.Holman | C71: =IF(Table3[[#This Row],[Days Open]]>27, "28 plus days", IF(Table3[[#This Row],[Days Open]]>20, "21 plus days", IF(Table3[[#This Row],[Days Open]]>13, "14 plus days", "Less than 14 days"))) -> 28 plus days | D71: =IF(Table3[[#This Row],[Ticket Status]]="OPEN", SUM((TODAY())-Table3[[#This Row],[Original Start Date]]), "Not Open") -> 94 | E71: =Table3[[#This Row],[Renter Name]] -> ERIC KELLY | F71: =IFERROR(VLOOKUP(Table3[[#This Row],[Rental under Name: ]], 'TPMS-Auto'!C:G,5,0), "RESEARCH!!") -> EKELLY | G71: =IFERROR(VLOOKUP(Table3[[#This Row],[Truck Number]],'TPMS-Auto'!$A:$K,3, 0), "Not Assigned in TPMS!!") -> ERIC KELLY | H71: =IFERROR(VLOOKUP(Table3[[#This Row],[Truck Number]],'TPMS-Auto'!$A:$K,7, 0), "Not Assigned in TPMS!!") -> EKELLY | I71: =IFERROR(VLOOKUP(Table3[[#This Row],[Truck Number]], Query1[[TRUCK_LU]:[Service Date]],25, 0), "Not Assigned in TPMS!!") -> Not Assigned in TPMS!! | J71: =IF(E71=E70, "Yes", "No") -> No | K71: 2J4CGW | L71: ERIC KELLY | M71: HOLMAN FLEET (ARI) US MAINT | N71: 115382159-A/R -B/R | O71: 46081 | P71: 516H | Q71: WICHITA | R71: KS | S71: SUV LARGE | T71: 5 | U71: 5 | V71: 101.54 | W71: 0 | X71: 6 | Y71: OPEN | Z71: 23966 | AB71: TRANSFORM SEARS HOME SERVICES | AD71: 1 | AE71: F | AF71: 25 | AG71: CHEV | AH71: TAHO | AI71: 2B56 | AJ71: 2 | AK71: 45992 | AL71: No
A72: =TRIM(Z72) -> 24021 | B72: =IFERROR(VLOOKUP(Table3[[#This Row],[Truck Number]], HolmanReport!C:C,1,0), "Research w.Holman") -> 24021 | C72: =IF(Table3[[#This Row],[Days Open]]>27, "28 plus days", IF(Table3[[#This Row],[Days Open]]>20, "21 plus days", IF(Table3[[#This Row],[Days Open]]>13, "14 plus days", "Less than 14 days"))) -> Less than 14 days | D72: =IF(Table3[[#This Row],[Ticket Status]]="OPEN", SUM((TODAY())-Table3[[#This Row],[Original Start Date]]), "Not Open") -> 9 | E72: =Table3[[#This Row],[Renter Name]] -> ALEJANDRO ZAMBRANOARREOLA | F72: =IFERROR(VLOOKUP(Table3[[#This Row],[Rental under Name: ]], 'TPMS-Auto'!C:G,5,0), "RESEARCH!!") -> RESEARCH!! | G72: =IFERROR(VLOOKUP(Table3[[#This Row],[Truck Number]],'TPMS-Auto'!$A:$K,3, 0), "Not Assigned in TPMS!!") -> ALEJANDRO ZAMBRANO ARREOLA | H72: =IFERROR(VLOOKUP(Table3[[#This Row],[Truck Number]],'TPMS-Auto'!$A:$K,7, 0), "Not Assigned in TPMS!!") -> AZAMBRA | I72: =IFERROR(VLOOKUP(Table3[[#This Row],[Truck Number]], Query1[[TRUCK_LU]:[Service Date]],25, 0), "Not Assigned in TPMS!!") -> Not Assigned in TPMS!! | J72: =IF(E72=E71, "Yes", "No") -> No | K72: 2GRTQL | L72: ALEJANDRO ZAMBRANOARREOLA | M72: HOLMAN FLEET (ARI) US MAINT | N72: 116879274 | O72: 46077 | P72: 32A6 | Q72: PASO ROBLES | R72: CA | S72: MINIVAN 7 SEATS | T72: 14 | U72: 14 | V72: 72 | W72: 0 | X72: 10 | Y72: OPEN | Z72: 24021 | AB72: TRANSFORM SEARS HOME SERVICES | AC72: ZLevel 4 Clients Only | AD72: 0 | AE72: F | AF72: 24 | AG72: CHRY | AH72: PACH | AI72: 2B56 | AJ72: 0 | AK72: 46077 | AL72: No
A73: =TRIM(Z73) -> 24056 | B73: =IFERROR(VLOOKUP(Table3[[#This Row],[Truck Number]], HolmanReport!C:C,1,0), "Research w.Holman") -> 24056 | C73: =IF(Table3[[#This Row],[Days Open]]>27, "28 plus days", IF(Table3[[#This Row],[Days Open]]>20, "21 plus days", IF(Table3[[#This Row],[Days Open]]>13, "14 plus days", "Less than 14 days"))) -> 28 plus days | D73: =IF(Table3[[#This Row],[Ticket Status]]="OPEN", SUM((TODAY())-Table3[[#This Row],[Original Start Date]]), "Not Open") -> 57 | E73: =Table3[[#This Row],[Renter Name]] -> RALPH VILLELA | F73: =IFERROR(VLOOKUP(Table3[[#This Row],[Rental under Name: ]], 'TPMS-Auto'!C:G,5,0), "RESEARCH!!") -> RVILLEL | G73: =IFERROR(VLOOKUP(Table3[[#This Row],[Truck Number]],'TPMS-Auto'!$A:$K,3, 0), "Not Assigned in TPMS!!") -> Not Assigned in TPMS!! | H73: =IFERROR(VLOOKUP(Table3[[#This Row],[Truck Number]],'TPMS-Auto'!$A:$K,7, 0), "Not Assigned in TPMS!!") -> Not Assigned in TPMS!! | I73: =IFERROR(VLOOKUP(Table3[[#This Row],[Truck Number]], Query1[[TRUCK_LU]:[Service Date]],25, 0), "Not Assigned in TPMS!!") -> Not Assigned in TPMS!! | J73: =IF(E73=E72, "Yes", "No") -> No | K73: 29PGQR | L73: RALPH VILLELA | M73: HOLMAN FLEET (ARI) US MAINT | N73: 115922245 -A/R | O73: 46059 | P73: 32HJ | Q73: RIVERSIDE | R73: CA | S73: P/UP LARGE | T73: 30 | U73: 5 | V73: 73.26 | W73: 3 | X73: 28 | Y73: OPEN | Z73: 24056 | AB73: TRANSFORM SEARS HOME SERVICES | AC73: ZLevel 4 Clients Only | AD73: 0 | AE73: F | AF73: 25 | AG73: FORD | AH73: F15C | AI73: 2B56 | AJ73: 1 | AK73: 46029 | AL73: No
A74: =TRIM(Z74) -> 24067 | B74: =IFERROR(VLOOKUP(Table3[[#This Row],[Truck Number]], HolmanReport!C:C,1,0), "Research w.Holman") -> 24067 | C74: =IF(Table3[[#This Row],[Days Open]]>27, "28 plus days", IF(Table3[[#This Row],[Days Open]]>20, "21 plus days", IF(Table3[[#This Row],[Days Open]]>13, "14 plus days", "Less than 14 days"))) -> Less than 14 days | D74: =IF(Table3[[#This Row],[Ticket Status]]="OPEN", SUM((TODAY())-Table3[[#This Row],[Original Start Date]]), "Not Open") -> 13 | E74: =Table3[[#This Row],[Renter Name]] -> BRIAN KIRK | F74: =IFERROR(VLOOKUP(Table3[[#This Row],[Rental under Name: ]], 'TPMS-Auto'!C:G,5,0), "RESEARCH!!") -> BKIRK | G74: =IFERROR(VLOOKUP(Table3[[#This Row],[Truck Number]],'TPMS-Auto'!$A:$K,3, 0), "Not Assigned in TPMS!!") -> BRIAN KIRK | H74: =IFERROR(VLOOKUP(Table3[[#This Row],[Truck Number]],'TPMS-Auto'!$A:$K,7, 0), "Not Assigned in TPMS!!") -> BKIRK | I74: =IFERROR(VLOOKUP(Table3[[#This Row],[Truck Number]], Query1[[TRUCK_LU]:[Service Date]],25, 0), "Not Assigned in TPMS!!") -> Not Assigned in TPMS!! | J74: =IF(E74=E73, "Yes", "No") -> No | K74: 2FPYY3 | L74: BRIAN KIRK | M74: HOLMAN FLEET (ARI) US MAINT | N74: 116878668 | O74: 46073 | P74: 32KH | Q74: OXNARD | R74: CA | S74: MINIVAN 7 SEATS | T74: 18 | U74: 6 | V74: 72 | W74: 1 | X74: 14 | Y74: OPEN | Z74: 24067 | AB74: TRANSFORM SEARS HOME SERVICES | AC74: ZLevel 4 Clients Only | AD74: 0 | AE74: F | AF74: 25 | AG74: CHRY | AH74: PACI | AI74: 2B56 | AJ74: 0 | AK74: 46073 | AL74: No
A75: =TRIM(Z75) -> 24070 | B75: =IFERROR(VLOOKUP(Table3[[#This Row],[Truck Number]], HolmanReport!C:C,1,0), "Research w.Holman") -> Research w.Holman | C75: =IF(Table3[[#This Row],[Days Open]]>27, "28 plus days", IF(Table3[[#This Row],[Days Open]]>20, "21 plus days", IF(Table3[[#This Row],[Days Open]]>13, "14 plus days", "Less than 14 days"))) -> 28 plus days | D75: =IF(Table3[[#This Row],[Ticket Status]]="OPEN", SUM((TODAY())-Table3[[#This Row],[Original Start Date]]), "Not Open") -> 120 | E75: =Table3[[#This Row],[Renter Name]] -> IAN LACY | F75: =IFERROR(VLOOKUP(Table3[[#This Row],[Rental under Name: ]], 'TPMS-Auto'!C:G,5,0), "RESEARCH!!") -> ILACY | G75: =IFERROR(VLOOKUP(Table3[[#This Row],[Truck Number]],'TPMS-Auto'!$A:$K,3, 0), "Not Assigned in TPMS!!") -> IAN LACY | H75: =IFERROR(VLOOKUP(Table3[[#This Row],[Truck Number]],'TPMS-Auto'!$A:$K,7, 0), "Not Assigned in TPMS!!") -> ILACY | I75: =IFERROR(VLOOKUP(Table3[[#This Row],[Truck Number]], Query1[[TRUCK_LU]:[Service Date]],25, 0), "Not Assigned in TPMS!!") -> Not Assigned in TPMS!! | J75: =IF(E75=E74, "Yes", "No") -> No | K75: 2HJKVV | L75: IAN LACY | M75: HOLMAN FLEET (ARI) US INTERIM | N75: 114880169 -C/R | O75: 46056 | P75: 03G9 | Q75: DECATUR | R75: GA | S75: MINIVAN 7 SEATS | T75: 30 | U75: 30 | V75: 68 | W75: 0 | X75: 31 | Y75: OPEN | Z75: 24070 | AB75: TRANSFORM SEARS HOME SERVICES | AC75: ZLevel 4 Clients Only | AD75: 1 | AE75: F | AF75: 25 | AG75: CHRY | AH75: PACI | AI75: 2B56 | AJ75: 3 | AK75: 45966 | AL75: Yes
A76: =TRIM(Z76) -> 24072 | B76: =IFERROR(VLOOKUP(Table3[[#This Row],[Truck Number]], HolmanReport!C:C,1,0), "Research w.Holman") -> Research w.Holman | C76: =IF(Table3[[#This Row],[Days Open]]>27, "28 plus days", IF(Table3[[#This Row],[Days Open]]>20, "21 plus days", IF(Table3[[#This Row],[Days Open]]>13, "14 plus days", "Less than 14 days"))) -> 28 plus days | D76: =IF(Table3[[#This Row],[Ticket Status]]="OPEN", SUM((TODAY())-Table3[[#This Row],[Original Start Date]]), "Not Open") -> 143 | E76: =Table3[[#This Row],[Renter Name]] -> PHILLIP WILLIAMS | F76: =IFERROR(VLOOKUP(Table3[[#This Row],[Rental under Name: ]], 'TPMS-Auto'!C:G,5,0), "RESEARCH!!") -> PWILLI0 | G76: =IFERROR(VLOOKUP(Table3[[#This Row],[Truck Number]],'TPMS-Auto'!$A:$K,3, 0), "Not Assigned in TPMS!!") -> PHILLIP WILLIAMS | H76: =IFERROR(VLOOKUP(Table3[[#This Row],[Truck Number]],'TPMS-Auto'!$A:$K,7, 0), "Not Assigned in TPMS!!") -> PWILLI0 | I76: =IFERROR(VLOOKUP(Table3[[#This Row],[Truck Number]], Query1[[TRUCK_LU]:[Service Date]],25, 0), "Not Assigned in TPMS!!") -> Not Assigned in TPMS!! | J76: =IF(E76=E75, "Yes", "No") -> No | K76: 27HYMN | L76: PHILLIP WILLIAMS | M76: HOLMAN FLEET (ARI) US MAINT | N76: 114540439 -D/R | O76: 46057 | P76: 2641 | Q76: COLUMBIA | R76: SC | S76: SUV STANDARD | T76: 30 | U76: 7 | V76: 69 | W76: 2 | X76: 30 | Y76: OPEN | Z76: 24072 | AB76: TRANSFORM SEARS HOME SERVICES | AD76: 0 | AE76: F | AF76: 25 | AG76: MITS | AH76: ECLX | AI76: 2B56 | AJ76: 4 | AK76: 45943 | AL76: Yes
